Workbook

Sheet ReadMe
A1: H2-SHIFT Round 2 model: hydrogen retrofit of factory-CNG passenger cars versus continuing on CNG and versus a BEV
A2: Team Wookies, NIT Warangal. SRDI Igniters Innovation Challenge 2026, Engineering Track, Option 2. Research cut-off 14 September 2026.
A4: Purpose: one consistent set of inputs feeding the presentation, annexure and pitch. All outputs are formulas; change inputs only on the Inputs sheet.
A5: Scenario selector: Inputs!C3 (1 = Base, 2 = Downside for the retrofit case, 3 = Upside for the retrofit case). 'Downside' means the retrofit looks worse (for example cheaper CNG, dearer hydrogen).
A6: Colour code: blue text on yellow = input; black = formula; green header = key output.
A7: Evidence classes on the Inputs sheet: A = verified external evidence; B = our calculated estimate; C = explicit assumption or sensitivity range; D = proposed target requiring validation.
A8: Options compared for an owner deciding in the decision year: A = continue operating the CNG donor; B = retrofit the donor to hydrogen (H2-ICE, petrol retained as backup); C = sell the donor and buy a compact fleet BEV.
A9: Fairness rules: the donor's resale value is a cash inflow only in option C (sold at t0); options A and B receive the donor's residual value at the end of the horizon instead. No depreciation is charged in addition to capital cost. Battery replacement is not assumed within the horizon (warranty evidence on Inputs). Charging during idle hours carries no time cost; in-shift charging or refuelling carries a time cost in all three options.
A10: Levelised cost per km = NPV of costs divided by discounted kilometres. Break-even hydrogen price = the year-1 delivered price at which option B has the same NPV as the comparator, holding the same price trajectory shape.
A11: Hydrogen price is the delivered price at the dispenser and is built up on the H2_Supply sheet (production, transport, compression electricity, station capital recovery at a stated utilisation, O&M, losses, margin and taxes). Station capital is recovered through the fuel price only, never allocated twice.
A12: Sheets: Inputs; Donor_Tech (donor and technology comparison); BOM (conversion cost, pilot versus commercial volume); Energy_Range (energy balance, storage, range, mass, power); TCO (cash flows, NPVs, break-even); H2_Supply (fleet demand, station sizing, delivered price, utilisation); Market (bottom-up sizing); Pilot_Budget (phases, budget, rollout); Emissions (per-km and fleet-scale); Sensitivities (grids and one-at-a-time); Sources (register).
A13: Recalculated with LibreOffice Calc (headless) on the build date; open in Excel and press F9 if values do not appear.
A14: Limitations: many external documents were inaccessible through the build environment's network policy; such inputs are flagged in Sources with 'excerpt' or 'summary' status and should be re-verified against originals before publication.

Sheet Inputs
A1: Inputs (single source of truth)
A2: Change values in the Base / Downside / Upside columns only. Active column follows the scenario selector.
B3: Scenario selector (1 Base, 2 Downside, 3 Upside): | C3: 1
A5: Key | B5: Parameter | C5: Base | D5: Downside | E5: Upside | F5: Active | G5: Unit | H5: Class | I5: Source IDs | J5: Notes
A6: General frame
A7: decision_year | B7: Decision year for the owner's choice (first commercial kits after certification) | C7: 2028 | D7: 2028 | E7: 2028 | F7: =CHOOSE($C$3,C7,D7,E7) -> 2028 | G7: year | H7: C | J7: Pilot vehicles run from 2028; owner decision modelled at commercial availability
A8: horizon | B8: Analysis horizon (fixed at 5 years in the cash-flow table) | C8: 5 | D8: 5 | E8: 5 | F8: =CHOOSE($C$3,C8,D8,E8) -> 5 | G8: years | H8: C | J8: Remaining useful life of a 3-year-old fleet sedan
A9: disc | B9: Discount rate (nominal) | C9: 0.12 | D9: 0.14 | E9: 0.1 | F9: =CHOOSE($C$3,C9,D9,E9) -> 0.12 | G9: fraction | H9: A | I9: W4-S29 | J9: NBFC fleet loan rates 10-16 percent
A10: days | B10: Operating days per year | C10: 330 | D10: 330 | E10: 330 | F10: =CHOOSE($C$3,C10,D10,E10) -> 330 | G10: days | H10: C | I10: R1 | J10: Fleet taxi benchmark (Round 1)
A11: km_day | B11: Kilometres per operating day | C11: 167 | D11: 212 | E11: 150 | F11: =CHOOSE($C$3,C11,D11,E11) -> 167 | G11: km/day | H11: A | I11: W4-S30 | J11: 55,000 km/yr base; NITI Aayog Feb 2026 plans 70,000 km/yr for 4W taxis (downside); Round 1 used 150
A12: fuel_esc | B12: Annual escalation of petrol and CNG prices | C12: 0.03 | D12: 0.02 | E12: 0.04 | F12: =CHOOSE($C$3,C12,D12,E12) -> 0.03 | G12: fraction/yr | H12: C | J12: Nominal
A13: elec_esc | B13: Annual escalation of electricity tariffs | C13: 0.02 | D13: 0.01 | E13: 0.03 | F13: =CHOOSE($C$3,C13,D13,E13) -> 0.02 | G13: fraction/yr | H13: C | J13: Nominal
A14: vot | B14: Value of in-shift time lost to refuelling or charging | C14: 150 | D14: 150 | E14: 150 | F14: =CHOOSE($C$3,C14,D14,E14) -> 150 | G14: Rs/hour | H14: C | J14: Approximate contribution margin per hour of a fleet taxi
A15: Donor vehicle (Maruti Suzuki Dzire Tour S CNG, about 3 years old at decision)
A16: donor_value_now | B16: Resale value of donor at decision date (taxi-registered) | C16: 350000 | D16: 400000 | E16: 300000 | F16: =CHOOSE($C$3,C16,D16,E16) -> 350000 | G16: Rs | H16: C | I16: W4-S28 | J16: New Tour S CNG ex-showroom about Rs 7.1 lakh; taxi retention 45-55 percent at 3-4 years; higher value favours selling for a BEV
A17: donor_value_end | B17: Residual value of donor at end of horizon (about 8 years old, high km) | C17: 100000 | D17: 70000 | E17: 130000 | F17: =CHOOSE($C$3,C17,D17,E17) -> 100000 | G17: Rs | H17: C | I17: W4-S28
A18: cng_price | B18: CNG retail price, Delhi (IGL), September 2026 | C18: 87 | D18: 78 | E18: 95 | F18: =CHOOSE($C$3,C18,D18,E18) -> 87 | G18: Rs/kg | H18: A | I18: W4-S16 | J18: Rs 86.98/kg on 14 Sep 2026 (aggregator); Ahmedabad Rs 94; lower CNG price is downside for the retrofit
A19: cng_kmkg | B19: CNG consumption in fleet use (real world, AC, load) | C19: 25 | D19: 27 | E19: 23 | F19: =CHOOSE($C$3,C19,D19,E19) -> 25 | G19: km/kg | H19: C | I19: W1-S3b;W1-S8a | J19: Declared 32.1 km/kg (Tour S); owner reports 24-30; fleet use assumed lower
A20: petrol_price | B20: Petrol retail price, Delhi | C20: 102 | D20: 95 | E20: 111 | F20: =CHOOSE($C$3,C20,D20,E20) -> 102 | G20: Rs/L | H20: A | I20: W4-S19 | J20: Rs 102.12/L verified 25 May 2026; aggregators show Rs 111 in Sep 2026
A21: petrol_kml | B21: Petrol consumption in fleet use (real world, AC) | C21: 15 | D21: 16 | E21: 14 | F21: =CHOOSE($C$3,C21,D21,E21) -> 15 | G21: km/L | H21: C | I21: W1-S3a | J21: Declared 26.1 km/L (Tour S); fleet use assumed lower
A22: petrol_share_cng | B22: Share of km run on petrol by the CNG car (CNG unavailable, queues) | C22: 0.05 | D22: 0.05 | E22: 0.05 | F22: =CHOOSE($C$3,C22,D22,E22) -> 0.05 | G22: fraction | H22: C
A23: maint_cng | B23: Maintenance and tyres, CNG car | C23: 0.9 | D23: 0.7 | E23: 1.2 | F23: =CHOOSE($C$3,C23,D23,E23) -> 0.9 | G23: Rs/km | H23: C | I23: W4-S22 | J23: CEEW 2025 Table 5 to be transcribed; Round 1 value retained
A24: ins_cng | B24: Insurance per year, CNG car | C24: 18000 | D24: 18000 | E24: 18000 | F24: =CHOOSE($C$3,C24,D24,E24) -> 18000 | G24: Rs/yr | H24: C
A25: cng_retest | B25: CNG cylinder hydrostatic test every 3 years | C25: 2000 | D25: 2000 | E25: 2000 | F25: =CHOOSE($C$3,C25,D25,E25) -> 2000 | G25: Rs per test | H25: A | I25: W2-S24 | J25: Gas Cylinder Rules: 3-yearly test
A26: time_cng_h | B26: In-shift time lost refuelling CNG per day (queues) | C26: 0.5 | D26: 0.4 | E26: 0.6 | F26: =CHOOSE($C$3,C26,D26,E26) -> 0.5 | G26: hours/day | H26: C
A27: Hydrogen retrofit (H2-ICE, port injection, 350 bar composite cylinder, petrol retained as automatic backup)
A28: kit_cost | B28: Installed conversion cost at commercial volume, incl. taxes (from BOM sheet) | C28: =BOM!$H$40 -> 322123.48 | D28: =BOM!$H$40*1.25 -> 402654.35 | E28: =BOM!$H$40*0.85 -> 273804.96 | F28: =CHOOSE($C$3,C28,D28,E28) -> 322123.48 | G28: Rs | H28: B | I28: BOM | J28: Linked to BOM volume total
A29: kit_cost_pilot | B29: Installed conversion cost per pilot vehicle (from BOM sheet) | C29: =BOM!$G$40 -> 774375 | D29: =BOM!$G$40 -> 774375 | E29: =BOM!$G$40 -> 774375 | F29: =CHOOSE($C$3,C29,D29,E29) -> 774375 | G29: Rs | H29: B | I29: BOM
A30: salvage_cng | B30: Credit for removed CNG cylinder and kit | C30: 10000 | D30: 0 | E30: 20000 | F30: =CHOOSE($C$3,C30,D30,E30) -> 10000 | G30: Rs | H30: C | J30: Requalified cylinder resale
A31: downtime_days | B31: Conversion downtime | C31: 3 | D31: 4 | E31: 2 | F31: =CHOOSE($C$3,C31,D31,E31) -> 3 | G31: days | H31: C
A32: lost_margin_day | B32: Lost contribution per day of downtime | C32: 1500 | D32: 1500 | E32: 1500 | F32: =CHOOSE($C$3,C32,D32,E32) -> 1500 | G32: Rs/day | H32: C
A33: h2_cons | B33: Hydrogen consumption, H2-ICE mode, fleet use (real world, AC) | C33: 1.85 | D33: 2.3 | E33: 1.6 | F33: =CHOOSE($C$3,C33,D33,E33) -> 1.85 | G33: kg/100 km | H33: B | I33: W1-S12a;W1-S12c;W1-S9a | J33: Energy balance versus CNG (Energy_Range); Ford Focus H2RV 1.4, Mazda RX-8 RE 2.4, HiAce van 3.1 kg/100 km
A34: h2_share | B34: Share of km driven on hydrogen (rest on petrol backup) | C34: 0.65 | D34: 0.5 | E34: 0.85 | F34: =CHOOSE($C$3,C34,D34,E34) -> 0.65 | G34: fraction | H34: C | J34: Two depot fills per day; check Energy_Range max share
A35: h2_price_y1 | B35: Delivered hydrogen price at dispenser, year 1 (2028), unsubsidised, shared hub station | C35: 800 | D35: 1000 | E35: 550 | F35: =CHOOSE($C$3,C35,D35,E35) -> 800 | G35: Rs/kg | H35: B | I35: W4-S22;W4-S46 | J35: CEEW: small-network refuelling today above USD 10/kg; H2_Supply build-up gives the pilot-station price
A36: h2_change | B36: Annual change in delivered hydrogen price | C36: -0.1 | D36: -0.03 | E36: -0.15 | F36: =CHOOSE($C$3,C36,D36,E36) -> -0.1 | G36: fraction/yr | H36: C | I36: W4-S22 | J36: CEEW path to USD 4.2/kg (about Rs 360) delivered in 2030
A37: maint_h2 | B37: Maintenance and tyres, retrofitted car | C37: 1 | D37: 1.2 | E37: 0.85 | F37: =CHOOSE($C$3,C37,D37,E37) -> 1 | G37: Rs/km | H37: C | I37: W4-S22 | J37: Adds injector, sensor, regulator service
A38: ins_h2 | B38: Insurance per year, retrofitted car | C38: 21000 | D38: 24000 | E38: 19000 | F38: =CHOOSE($C$3,C38,D38,E38) -> 21000 | G38: Rs/yr | H38: C | I38: W2-S53 | J38: No IMT endorsement exists for hydrogen kits; assumes insurer accepts endorsed retrofit
A39: h2_inspect_yr | B39: Hydrogen system inspection and 3-yearly cylinder requalification, annualised | C39: 4000 | D39: 6000 | E39: 3000 | F39: =CHOOSE($C$3,C39,D39,E39) -> 4000 | G39: Rs/yr | H39: C | I39: W2-S24
A40: time_h2_h | B40: In-shift time lost for hydrogen refuelling and detour per day | C40: 0.4 | D40: 0.6 | E40: 0.3 | F40: =CHOOSE($C$3,C40,D40,E40) -> 0.4 | G40: hours/day | H40: C | J40: Two short fills at a depot dispenser
A41: mod_resid_factor | B41: Residual value factor for a modified vehicle | C41: 0.9 | D41: 0.8 | E41: 1 | F41: =CHOOSE($C$3,C41,D41,E41) -> 0.9 | G41: fraction | H41: C
A42: kit_resid | B42: Residual value of the kit at end of horizon | C42: 0 | D42: 0 | E42: 20000 | F42: =CHOOSE($C$3,C42,D42,E42) -> 0 | G42: Rs | H42: C
A43: BEV alternative (sell donor, buy compact fleet BEV)
A44: bev_price | B44: BEV ex-showroom price incl. GST (compact fleet BEV, 24-30 kWh) | C44: 1050000 | D44: 900000 | E44: 1300000 | F44: =CHOOSE($C$3,C44,D44,E44) -> 1050000 | G44: Rs | H44: A | I44: W3-S27;W3-S25 | J44: Tata Tiago EV Rs 6.99-10.09 lakh, Punch EV Rs 9.69-12.59 lakh (2026), Xpres-T fleet EV from Rs 13.04 lakh
A45: bev_onroad | B45: Registration and first-year extras beyond ex-showroom | C45: 30000 | D45: 20000 | E45: 40000 | F45: =CHOOSE($C$3,C45,D45,E45) -> 30000 | G45: Rs | H45: A | I45: W4-S25 | J45: Delhi EV Policy 2026 waives road tax and registration fee to March 2030
A46: bev_kwh100 | B46: BEV consumption measured at the meter (incl. charging losses) | C46: 15 | D46: 13 | E46: 17 | F46: =CHOOSE($C$3,C46,D46,E46) -> 15 | G46: kWh/100 km | H46: A | I46: W3-S30;W4-S23 | J46: Real-world tests 12.8-15.3 kWh/100 km at the battery (Tiago EV, Punch EV, Nexon EV) plus 5-15 percent charging losses
A47: depot_tariff | B47: Depot or home charging tariff, landed | C47: 6 | D47: 5 | E47: 8 | F47: =CHOOSE($C$3,C47,D47,E47) -> 6 | G47: Rs/kWh | H47: A | I47: W4-S20;W3-S32 | J47: Delhi DERC EV-charging tariff Rs 4.50/kWh (LT) plus surcharges and taxes
A48: pub_tariff | B48: Public DC fast-charging price | C48: 20 | D48: 16 | E48: 25 | F48: =CHOOSE($C$3,C48,D48,E48) -> 20 | G48: Rs/kWh | H48: A | I48: W4-S21;W3-S33 | J48: 2026 network prices Rs 16-25/kWh incl. GST
A49: pub_share | B49: Share of energy from public fast charging | C49: 0.3 | D49: 0.2 | E49: 0.5 | F49: =CHOOSE($C$3,C49,D49,E49) -> 0.3 | G49: fraction | H49: C
A50: maint_bev | B50: Maintenance and tyres, BEV | C50: 0.5 | D50: 0.4 | E50: 0.8 | F50: =CHOOSE($C$3,C50,D50,E50) -> 0.5 | G50: Rs/km | H50: C | I50: W4-S22
A51: ins_bev | B51: Insurance per year, BEV | C51: 30000 | D51: 28000 | E51: 34000 | F51: =CHOOSE($C$3,C51,D51,E51) -> 30000 | G51: Rs/yr | H51: C
A52: bev_resid | B52: BEV residual value at end of horizon | C52: 420000 | D52: 480000 | E52: 340000 | F52: =CHOOSE($C$3,C52,D52,E52) -> 420000 | G52: Rs | H52: C | I52: W4-S22 | J52: 40 percent of price at 5 years (no Indian fleet-EV residual data found); higher residual is downside for the retrofit
A53: time_bev_h | B53: In-shift time lost for charging per day | C53: 0.5 | D53: 0.3 | E53: 1 | F53: =CHOOSE($C$3,C53,D53,E53) -> 0.5 | G53: hours/day | H53: C | J53: Overnight depot charging is idle time
A54: Energy and storage physics
A55: cng_lhv | B55: Lower heating value of CNG | C55: 48 | D55: 48 | E55: 48 | F55: =CHOOSE($C$3,C55,D55,E55) -> 48 | G55: MJ/kg | H55: A | I55: W4-S62 | J55: IPCC natural gas 48.0 TJ/Gg
A56: petrol_lhv | B56: Lower heating value of petrol | C56: 32.2 | D56: 32.2 | E56: 32.2 | F56: =CHOOSE($C$3,C56,D56,E56) -> 32.2 | G56: MJ/L | H56: A | I56: W4-S62 | J56: 44.3 MJ/kg x 0.74 kg/L
A57: h2_lhv | B57: Lower heating value of hydrogen | C57: 120 | D57: 120 | E57: 120 | F57: =CHOOSE($C$3,C57,D57,E57) -> 120 | G57: MJ/kg | H57: A | I57: W1-S13a
A58: cyl_vol | B58: Hydrogen cylinder internal (water) volume | C58: 60 | D58: 60 | E58: 60 | F58: =CHOOSE($C$3,C58,D58,E58) -> 60 | G58: L | H58: A | I58: W1-S2 | J58: Luxfer G-Stor Pro V060H35 (Type III, 350 bar): 60 L, OD 400 mm, length 767 mm, 36 kg, 1.45 kg H2
A59: h2_density_350 | B59: Hydrogen density at 350 bar, 15 C | C59: 24 | D59: 24 | E59: 24 | F59: =CHOOSE($C$3,C59,D59,E59) -> 24 | G59: kg/m3 | H59: A | I59: W1-S13a | J59: Full-fill density per SAE J2601 definition
A60: h2_density_700 | B60: Hydrogen density at 700 bar, 15 C | C60: 40.2 | D60: 40.2 | E60: 40.2 | F60: =CHOOSE($C$3,C60,D60,E60) -> 40.2 | G60: kg/m3 | H60: A | I60: W1-S13a
A61: fill_soc | B61: State of charge reached in a non-cooled 350 bar fill (hot ambient) | C61: 0.85 | D61: 0.8 | E61: 0.95 | F61: =CHOOSE($C$3,C61,D61,E61) -> 0.85 | G61: fraction | H61: C | I61: W1-S13d | J61: SAE J2601: 95-100 percent needs pre-cooled dispensing; small tanks may fall outside light-duty tables
A62: resid_density | B62: Residual gas density at minimum usable pressure | C62: 1.7 | D62: 2 | E62: 1.5 | F62: =CHOOSE($C$3,C62,D62,E62) -> 1.7 | G62: kg/m3 | H62: C | I62: W1-S13c | J62: About 20 bar residual
A63: fills_day | B63: Depot fills per day available to the driver | C63: 2 | D63: 1.5 | E63: 2.5 | F63: =CHOOSE($C$3,C63,D63,E63) -> 2 | G63: fills/day | H63: C
A64: cyl_mass | B64: Composite cylinder mass (60 L, 350 bar) | C64: 36 | D64: 42 | E64: 32 | F64: =CHOOSE($C$3,C64,D64,E64) -> 36 | G64: kg | H64: A | I64: W1-S2 | J64: Luxfer Type III 36 kg; Type IV similar
A65: kit_other_mass | B65: Valve, frame, regulator, lines, ECU mass | C65: 14 | D65: 16 | E65: 12 | F65: =CHOOSE($C$3,C65,D65,E65) -> 14 | G65: kg | H65: C
A66: cng_cyl_mass | B66: Removed CNG cylinder (55 L Type I) mass | C66: 55 | D66: 55 | E66: 55 | F66: =CHOOSE($C$3,C66,D66,E66) -> 55 | G66: kg | H66: A | I66: W1-S14a;W1-S14b | J66: 50 L steel cylinder 48 kg; 60 L 61-69 kg
A67: cng_kit_mass | B67: Removed CNG regulator, rail, lines mass | C67: 8 | D67: 8 | E67: 8 | F67: =CHOOSE($C$3,C67,D67,E67) -> 8 | G67: kg | H67: C
A68: petrol_ps | B68: Donor engine power on petrol (Tour S 1.2 L) | C68: 81.6 | D68: 81.6 | E68: 81.6 | F68: =CHOOSE($C$3,C68,D68,E68) -> 81.6 | G68: PS | H68: A | I68: W1-S3a | J68: 60 kW at 5,700 rpm
A69: cng_ps | B69: Donor engine power on CNG | C69: 70 | D69: 70 | E69: 70 | F69: =CHOOSE($C$3,C69,D69,E69) -> 70 | G69: PS | H69: C | I69: W1-S6 | J69: Third-party 69 bhp; official CNG rating not captured
A70: h2_power_factor | B70: H2 lean-burn peak power relative to petrol | C70: 0.52 | D70: 0.45 | E70: 0.6 | F70: =CHOOSE($C$3,C70,D70,E70) -> 0.52 | G70: fraction | H70: B | I70: W1-S9a;W1-S9b | J70: About 30 percent air displacement (20 percent loss at stoichiometric) plus 35-40 percent loss at lambda 2; strategy uses lambda 1.6-2.2
A71: petrol_tank | B71: Petrol tank capacity | C71: 37 | D71: 37 | E71: 37 | F71: =CHOOSE($C$3,C71,D71,E71) -> 37 | G71: L | H71: A | I71: W1-S3a
A72: Hydrogen supply and station
A73: pilot_cars | B73: Pilot fleet size | C73: 30 | D73: 30 | E73: 30 | F73: =CHOOSE($C$3,C73,D73,E73) -> 30 | G73: cars | H73: D | J73: Statistical spread across three fleets, one dispensing point
A74: h2_prod_cost | B74: Green hydrogen production cost at plant gate (2026-28) | C74: 400 | D74: 560 | E74: 300 | F74: =CHOOSE($C$3,C74,D74,E74) -> 400 | G74: Rs/kg | H74: A | I74: W4-S33;W4-S34;W4-S38 | J74: CEEW USD 3.5-5/kg; industry Rs 397-560; SIGHT ammonia auctions imply up to Rs 302 for the hydrogen molecule
A75: h2_prod_cost_2030 | B75: Green hydrogen production cost at plant gate (2030) | C75: 240 | D75: 320 | E75: 180 | F75: =CHOOSE($C$3,C75,D75,E75) -> 240 | G75: Rs/kg | H75: A | I75: W4-S22;W4-S57;W4-S36 | J75: CEEW USD 2-2.5; IEA about USD 3; NITI-RMI best case USD 1.6
A76: transport_cost | B76: Tube-trailer transport to station | C76: 45 | D76: 60 | E76: 35 | F76: =CHOOSE($C$3,C76,D76,E76) -> 45 | G76: Rs/kg | H76: B | I76: W4-S44 | J76: About 150 km, 300 kg payload
A77: station_capex_pilot | B77: Dispensing point capex, pilot (compressor, cascade, one dispenser, civil, safety, PESO) | C77: 100000000 | D77: 150000000 | E77: 80000000 | F77: =CHOOSE($C$3,C77,D77,E77) -> 100000000 | G77: Rs | H77: B | I77: W4-S56;W4-S43 | J77: Indian trade source Rs 14-20 crore for 200-500 kg/day; delivered hydrogen, no electrolyser
A78: station_cap_pilot | B78: Dispensing point design capacity, pilot | C78: 150 | D78: 150 | E78: 150 | F78: =CHOOSE($C$3,C78,D78,E78) -> 150 | G78: kg/day | H78: C
A79: station_util_pilot | B79: Station utilisation, pilot | C79: 0.5 | D79: 0.35 | E79: 0.65 | F79: =CHOOSE($C$3,C79,D79,E79) -> 0.5 | G79: fraction | H79: C | I79: W4-S22 | J79: Shared with bus/truck pilot users on the Sahibabad-Faridabad-Delhi route
A80: station_capex_2030 | B80: Station capex, 2030 hub scale (500 kg/day) | C80: 120000000 | D80: 200000000 | E80: 90000000 | F80: =CHOOSE($C$3,C80,D80,E80) -> 120000000 | G80: Rs | H80: B | I80: W4-S56
A81: station_cap_2030 | B81: Station design capacity, 2030 hub | C81: 500 | D81: 500 | E81: 500 | F81: =CHOOSE($C$3,C81,D81,E81) -> 500 | G81: kg/day | H81: C
A82: station_util_2030 | B82: Station utilisation, 2030 hub | C82: 0.7 | D82: 0.5 | E82: 0.85 | F82: =CHOOSE($C$3,C82,D82,E82) -> 0.7 | G82: fraction | H82: C | I82: W4-S22;W4-S46 | J82: CEEW assumes 30 percent in 2030 rising to 80 percent by 2050; ICCT 50-70 percent
A83: station_life | B83: Station capital recovery period | C83: 10 | D83: 10 | E83: 10 | F83: =CHOOSE($C$3,C83,D83,E83) -> 10 | G83: years | H83: C
A84: station_om | B84: Fixed operation and maintenance, share of capex per year | C84: 0.04 | D84: 0.05 | E84: 0.03 | F84: =CHOOSE($C$3,C84,D84,E84) -> 0.04 | G84: fraction/yr | H84: A | I84: W4-S22 | J84: CEEW 5 percent
A85: comp_kwh | B85: Compression and dispensing electricity | C85: 3 | D85: 3.5 | E85: 2.5 | F85: =CHOOSE($C$3,C85,D85,E85) -> 3 | G85: kWh/kg | H85: C | J85: Delivered gas at 200 bar to 450 bar cascade
A86: ind_tariff | B86: Industrial electricity tariff | C86: 9 | D86: 10 | E86: 8 | F86: =CHOOSE($C$3,C86,D86,E86) -> 9 | G86: Rs/kWh | H86: C
A87: h2_loss | B87: Venting, purge and metering losses | C87: 0.03 | D87: 0.05 | E87: 0.02 | F87: =CHOOSE($C$3,C87,D87,E87) -> 0.03 | G87: fraction | H87: C
A88: h2_margin_tax | B88: Retailer margin and taxes on delivered hydrogen | C88: 0.1 | D88: 0.15 | E88: 0.05 | F88: =CHOOSE($C$3,C88,D88,E88) -> 0.1 | G88: fraction | H88: C | J88: GST treatment of hydrogen as automotive fuel to be confirmed
A89: trailer_kg | B89: Tube-trailer payload | C89: 300 | D89: 250 | E89: 350 | F89: =CHOOSE($C$3,C89,D89,E89) -> 300 | G89: kg | H89: C | J89: Typical 200 bar tube trailer
A90: Emissions factors
A91: ef_cng | B91: Tailpipe CO2 per kg CNG | C91: 2.69 | D91: 2.69 | E91: 2.75 | F91: =CHOOSE($C$3,C91,D91,E91) -> 2.69 | G91: kg CO2/kg | H91: A | I91: W4-S62 | J91: IPCC 2006 default 56.1 t/TJ at 48 TJ/Gg
A92: wtt_cng | B92: Well-to-tank uplift for CNG in India | C92: 0.25 | D92: 0.15 | E92: 0.35 | F92: =CHOOSE($C$3,C92,D92,E92) -> 0.25 | G92: fraction | H92: C | I92: W4-S63;W4-S17 | J92: Imported spot LNG share raises upstream emissions; India-specific factor not found
A93: ef_petrol | B93: Tailpipe CO2 per litre petrol | C93: 2.27 | D93: 2.27 | E93: 2.31 | F93: =CHOOSE($C$3,C93,D93,E93) -> 2.27 | G93: kg CO2/L | H93: A | I93: W4-S62 | J93: IPCC 2006 default
A94: wtt_petrol | B94: Well-to-tank uplift for petrol | C94: 0.2 | D94: 0.15 | E94: 0.25 | F94: =CHOOSE($C$3,C94,D94,E94) -> 0.2 | G94: fraction | H94: C | I94: W4-S63
A95: ci_h2_green | B95: Carbon intensity, green hydrogen incl. compression and delivery | C95: 2 | D95: 3.5 | E95: 1.2 | F95: =CHOOSE($C$3,C95,D95,E95) -> 2 | G95: kg CO2e/kg H2 | H95: A | I95: W4-S63;W4-S64;W4-S65 | J95: India green hydrogen standard: 2 kg CO2e/kg well-to-gate
A96: ci_h2_grid | B96: Carbon intensity, grid-electrolysis hydrogen (India grid 2025) | C96: 39 | D96: 43 | E96: 35 | F96: =CHOOSE($C$3,C96,D96,E96) -> 39 | G96: kg CO2e/kg H2 | H96: B | I96: W4-S59 | J96: 0.71 t/MWh x 50-60 kWh/kg
A97: ci_h2_grey | B97: Carbon intensity, grey (SMR) hydrogen | C97: 12 | D97: 14 | E97: 10 | F97: =CHOOSE($C$3,C97,D97,E97) -> 12 | G97: kg CO2e/kg H2 | H97: A | I97: W4-S64
A98: grid_now | B98: Grid emission factor at the meter, 2025 | C98: 0.86 | D98: 0.86 | E98: 0.86 | F98: =CHOOSE($C$3,C98,D98,E98) -> 0.86 | G98: kg CO2/kWh | H98: A | I98: W4-S59 | J98: CEA v21 weighted average 0.710 t/MWh (FY2024-25) adjusted for about 17 percent T&D losses
A99: grid_2030 | B99: Grid emission factor at the meter, 2030 | C99: 0.58 | D99: 0.52 | E99: 0.66 | F99: =CHOOSE($C$3,C99,D99,E99) -> 0.58 | G99: kg CO2/kWh | H99: A | I99: W4-S60 | J99: CEA NEP path 0.548 (2026-27) to 0.430 (2031-32) net, adjusted for T&D losses; lower grid factor is downside for the retrofit
A100: bev_mfg | B100: Manufacturing emissions, compact BEV incl. 27 kWh battery | C100: 7 | D100: 6 | E100: 8.5 | F100: =CHOOSE($C$3,C100,D100,E100) -> 7 | G100: t CO2e | H100: B | I100: W4-S63;W4-S66 | J100: Glider 4-6 t plus 27 kWh x 70 kg CO2e/kWh
A101: bev_life_km | B101: Lifetime km over which BEV manufacturing is amortised | C101: 150000 | D101: 180000 | E101: 120000 | F101: =CHOOSE($C$3,C101,D101,E101) -> 150000 | G101: km | H101: C
...

Sheet BOM
A1: Retrofit bill of materials and conversion cost
A2: Pilot batch (about 30 kits) versus commercial volume (about 10,000 kits per year with localised cylinders). Unit costs are estimates unless a source is given.
A4: # | B4: Component / activity | C4: Qty | D4: Unit cost pilot (Rs) | E4: Unit cost volume (Rs) | F4: Pilot total (Rs) | G4: Volume total (Rs) | H4: Class | I4: Basis / source
B5: Storage and mounting
A6: 1 | B6: Composite hydrogen cylinder, 60 L water volume, 350 bar (Type III or IV), 15-year life | C6: 1 | D6: 250000 | E6: 95000 | F6: =C6*D6 -> 250000 | G6: =C6*E6 -> 95000 | H6: B | I6: Scaled from DOE/Strategic Analysis Type IV system cost records (S-CYLCOST): about $33/kWh at low volume and $21/kWh at 10k/yr for a 5.6 kg 700 bar system, applied to a 1.45 kg (48 kWh) cylinder with a small-size penalty; example product Luxfer G-Stor Pro V060H35 (S-CYL)
A7: 2 | B7: On-tank valve with solenoid, excess-flow, manual shut-off and TPRD (UN R134 class) | C7: 1 | D7: 55000 | E7: 18000 | F7: =C7*D7 -> 55000 | G7: =C7*E7 -> 18000 | H7: C | I7: Production parts exist (S-OTV); no public price; estimate
A8: 3 | B8: Mounting frame, straps, boot bulkhead shield, TPRD vent duct, boot ventilation | C8: 1 | D8: 30000 | E8: 11000 | F8: =C8*D8 -> 30000 | G8: =C8*E8 -> 11000 | H8: C | I8: Fabricated steel frame per UN R110-type 20 g / 8 g loads; estimate
B9: Fuel delivery
A10: 4 | B10: H35 receptacle, check valve, high-pressure filter | C10: 1 | D10: 25000 | E10: 8000 | F10: =C10*D10 -> 25000 | G10: =C10*E10 -> 8000 | H10: C | I10: ISO 17268 H35 receptacle; estimate
A11: 5 | B11: Stainless (316L) high-pressure lines and fittings | C11: 1 | D11: 18000 | E11: 7000 | F11: =C11*D11 -> 18000 | G11: =C11*E11 -> 7000 | H11: C | I11: Estimate
A12: 6 | B12: Two-stage pressure regulator 350 bar to injection pressure, with pressure and temperature sensors | C12: 1 | D12: 55000 | E12: 15000 | F12: =C12*D12 -> 55000 | G12: =C12*E12 -> 15000 | H12: C | I12: Production FCEV regulators exist (S-REG); estimate for ICE outlet pressure
A13: 7 | B13: Hydrogen port-fuel injectors (4) and rail | C13: 1 | D13: 40000 | E13: 12000 | F13: =C13*D13 -> 40000 | G13: =C13*E13 -> 12000 | H13: C | I13: Bosch / PHINIA H2 PFI injectors announced 2024-25 (S-INJ); estimate
A14: 8 | B14: Low-pressure hose, fuel shut-off, pressure relief | C14: 1 | D14: 8000 | E14: 3500 | F14: =C14*D14 -> 8000 | G14: =C14*E14 -> 3500 | H14: C | I14: Estimate
B15: Controls and safety
A16: 9 | B16: Hydrogen ECU (dual-map, CAN, automatic petrol fallback, diagnostics) with harness | C16: 1 | D16: 45000 | E16: 15000 | F16: =C16*D16 -> 45000 | G16: =C16*E16 -> 15000 | H16: C | I16: Analogous to sequential CNG ECU at volume; pilot uses low-volume controller
A17: 10 | B17: Hydrogen leak sensors (boot and engine bay), controller, cabin warning, vent fan | C17: 1 | D17: 22000 | E17: 7000 | F17: =C17*D17 -> 22000 | G17: =C17*E17 -> 7000 | H17: C | I17: Automotive H2 sensors exist (S-SENS); estimate
B18: Engine and emissions
A19: 11 | B19: Cold-grade spark plugs, PCV/oil-separator upgrade, coolant and knock sensor check | C19: 1 | D19: 8000 | E19: 4000 | F19: =C19*D19 -> 8000 | G19: =C19*E19 -> 4000 | H19: C | I19: Backfire and pre-ignition mitigation items (S-H2ICE)
A20: 12 | B20: Lean-NOx aftertreatment provision (lean NOx trap) and lambda sensor | C20: 1 | D20: 35000 | E20: 15000 | F20: =C20*D20 -> 35000 | G20: =C20*E20 -> 15000 | H20: C | I20: Needed if lean calibration alone does not meet BS-VI NOx over the cycle (S-NOX); estimate
B21: Installation and validation
A22: 13 | B22: Removal of CNG kit and cylinder, installation labour (hours) | C22: 40 | D22: 600 | E22: 600 | F22: =C22*D22 -> 24000 | G22: =14*E22 -> 8400 | H22: C | I22: Pilot 40 h; volume 14 h at Rs 600/h (see qty note)
A23: 14 | B23: Per-vehicle leak test, commissioning, road test and documentation | C23: 1 | D23: 10000 | E23: 2500 | F23: =C23*D23 -> 10000 | G23: =C23*E23 -> 2500 | H23: C | I23: Estimate
A24: 15 | B24: Certification and engineering amortisation per kit | C24: 1 | D24: 0 | E24: 8000 | F24: =C24*D24 -> 0 | G24: =C24*E24 -> 8000 | H24: B | I24: Volume: one-time development and type-approval cost (Pilot_Budget) spread over 50,000 kits; pilot carries it in the programme budget
B26: Subtotal parts, labour and validation | F26: =SUM(F6:F24) -> 625000 | G26: =SUM(G6:G24) -> 229400
B27: Warranty provision (share of subtotal) | D27: 0.05 | E27: 0.04 | F27: =F26*D27 -> 31250 | G27: =G26*E27 -> 9176
B28: Installer and kit-maker margin (share of subtotal) | D28: 0 | E28: 0.15 | F28: =F26*D28 -> 0 | G28: =G26*E28 -> 34410
B29: GST on kit and installation (rate assumed; CNG kits attract 28 percent, hydrogen kit classification to be confirmed) | D29: 0.18 | E29: 0.18 | F29: =(F26+F27+F28)*D29 -> 118125 | G29: =(G26+G27+G28)*E29 -> 49137.48
B40: Installed conversion cost per vehicle (incl. taxes) | E40: Pilot (G) / Volume (H): | F40: =F26+F27+F28+F29 -> 774375 | G40: =F40 -> 774375 | H40: =G26+G27+G28+G29 -> 322123.48
B41: Share of cylinder and valve in volume kit cost | F41: =(G6+G7)/G26 -> 0.49258936
B42: Volume kit cost in Rs lakh | F42: =H40/100000 -> 3.2212348
B43: Pilot kit cost in Rs lakh | F43: =G40/100000 -> 7.74375
B44: Reference: Round 1 assumed Rs 1.8 to 2.2 lakh installed. Reference: sequential CNG retrofit kit incl. cylinder and fitting in India about Rs 0.6 to 0.9 lakh (S-CNGKIT).

Sheet Energy_Range
A1: Energy balance, storage, range, mass and power
A2: Column vectors of formulas referencing Inputs. Hydrogen consumption is an input cross-checked against the CNG energy balance.
A4: Quantity | B4: Value | C4: Unit | D4: Formula / note
A5: Energy use per km on CNG (fleet real-world) | B5: =Inputs!$F$55/Inputs!$F$19 -> 1.92 | C5: MJ/km | D5: LHV / km per kg
A6: Energy use per km on petrol (fleet real-world) | B6: =Inputs!$F$56/Inputs!$F$21 -> 2.1466667 | C6: MJ/km
A7: Hydrogen consumption assumed (input) | B7: =Inputs!$F$33 -> 1.85 | C7: kg/100 km | D7: Input h2_cons
A8: Energy use per km on hydrogen | B8: =B7/100*Inputs!$F$57 -> 2.22 | C8: MJ/km
A9: Implied H2-ICE efficiency relative to CNG operation (>1 = better) | B9: =B5/B8 -> 0.86486486 | C9: ratio | D9: Cross-check: lean PFI hydrogen at part load can match or exceed CNG efficiency; retrofit calibration usually loses some of that
A10: Hydrogen economy | B10: =100/B7 -> 54.054054 | C10: km/kg
A11: Cylinder internal volume | B11: =Inputs!$F$58 -> 60 | C11: L
A12: Nominal hydrogen at 350 bar, 15 C | B12: =B11/1000*Inputs!$F$59 -> 1.44 | C12: kg | D12: Density 24.0 kg/m3 (S-DENS)
A13: Nominal hydrogen if 700 bar cylinder of same volume | B13: =B11/1000*Inputs!$F$60 -> 2.412 | C13: kg | D13: Design option; needs 700 bar dispensing
A14: Hydrogen after a non-cooled 350 bar fill | B14: =B12*Inputs!$F$61 -> 1.224 | C14: kg | D14: Fill SOC input; hot ambient, no pre-cooling
A15: Residual hydrogen at minimum usable pressure | B15: =B11/1000*Inputs!$F$62 -> 0.102 | C15: kg | D15: About 20 bar residual
A16: Usable hydrogen per fill | B16: =B14-B15 -> 1.122 | C16: kg | D16: Key output
A17: Range on hydrogen per fill | B17: =B16/(B7/100) -> 60.648649 | C17: km | D17: Key output
A18: Range on hydrogen per fill, 700 bar option | B18: =(B13*Inputs!$F$61-B15)/(B7/100) -> 105.30811 | C18: km
A19: Petrol backup range | B19: =Inputs!$F$71*Inputs!$F$21 -> 555 | C19: km | D19: Existing tank retained
A20: Daily hydrogen need at full hydrogen operation | B20: =Inputs!$F$11*B7/100 -> 3.0895 | C20: kg/day
A21: Fills per day needed for 100 percent hydrogen operation | B21: =B20/B16 -> 2.7535651 | C21: fills/day
A22: Maximum share of km on hydrogen with the available depot fills | B22: =MIN(1,Inputs!$F$63*B16/B20) -> 0.72633112 | C22: fraction | D22: Compare with input h2_share
A23: Share of km on hydrogen used in the model (input) | B23: =Inputs!$F$34 -> 0.65 | C23: fraction
A24: Hydrogen used per operating day in the model | B24: =Inputs!$F$11*B7/100*B23 -> 2.008175 | C24: kg/day
A25: Mass added: cylinder + valve/frame/regulator/lines/ECU | B25: =Inputs!$F$64+Inputs!$F$65 -> 50 | C25: kg
A26: Mass removed: CNG cylinder + CNG kit | B26: =Inputs!$F$66+Inputs!$F$67 -> 63 | C26: kg
A27: Net kerb mass change | B27: =B25-B26 -> -13 | C27: kg | D27: Negative = lighter than CNG configuration
A28: Peak power on petrol | B28: =Inputs!$F$68 -> 81.6 | C28: PS | D28: Donor spec
A29: Peak power on CNG (factory) | B29: =Inputs!$F$69 -> 70 | C29: PS | D29: Third-party figure; official CNG rating not captured
A30: Estimated peak power on hydrogen (lean PFI) | B30: =Inputs!$F$68*Inputs!$F$70 -> 42.432 | C30: PS | D30: About 30 percent air displacement plus lean operation (S-H2PWR)
A31: Power loss versus petrol | B31: =1-Inputs!$F$70 -> 0.48 | C31: fraction
A32: Power loss versus CNG | B32: =1-B30/B29 -> 0.39382857 | C32: fraction
A33: Power-to-mass, hydrogen mode, 4 occupants (kerb 1045 kg + 300 kg) | B33: =B30/((1045+B27+300)/1000) -> 31.855856 | C33: PS per tonne | D33: Urban duty reference: a loaded 800 cc hatchback is about 40 PS per tonne
A34: HCNG 18 vol% blend: hydrogen share of energy | B34: =(18*10.8)/(18*10.8+82*35.8) -> 0.062108626 | C34: fraction | D34: Volumetric LHVs 10.8 and 35.8 MJ/Nm3 (S-HCNG); no vehicle modification

Sheet TCO
A1: Ownership cost comparison for one vehicle: A continue on CNG, B hydrogen retrofit, C sell and buy BEV
A2: Nominal cash costs (Rs). Negative values are inflows (residual values). Years in columns; t0 = decision date.
A3: Year index | C3: 0 | D3: 1 | E3: 2 | F3: 3 | G3: 4 | H3: 5
A4: Calendar year | C4: =Inputs!$F$7+C3 -> 2028 | D4: =Inputs!$F$7+D3 -> 2029 | E4: =Inputs!$F$7+E3 -> 2030 | F4: =Inputs!$F$7+F3 -> 2031 | G4: =Inputs!$F$7+G3 -> 2032 | H4: =Inputs!$F$7+H3 -> 2033
A5: Discount factor | C5: =1/(1+Inputs!$F$9)^C3 -> 1 | D5: =1/(1+Inputs!$F$9)^D3 -> 0.89285714 | E5: =1/(1+Inputs!$F$9)^E3 -> 0.79719388 | F5: =1/(1+Inputs!$F$9)^F3 -> 0.71178025 | G5: =1/(1+Inputs!$F$9)^G3 -> 0.63551808 | H5: =1/(1+Inputs!$F$9)^H3 -> 0.56742686
A6: Annual km | C6: 0 | D6: =Inputs!$F$10*Inputs!$F$11 -> 55110 | E6: =Inputs!$F$10*Inputs!$F$11 -> 55110 | F6: =Inputs!$F$10*Inputs!$F$11 -> 55110 | G6: =Inputs!$F$10*Inputs!$F$11 -> 55110 | H6: =Inputs!$F$10*Inputs!$F$11 -> 55110
A7: Petrol price (Rs/L) | D7: =Inputs!$F$20*(1+Inputs!$F$12)^(D3-1) -> 102 | E7: =Inputs!$F$20*(1+Inputs!$F$12)^(E3-1) -> 105.06 | F7: =Inputs!$F$20*(1+Inputs!$F$12)^(F3-1) -> 108.2118 | G7: =Inputs!$F$20*(1+Inputs!$F$12)^(G3-1) -> 111.45815 | H7: =Inputs!$F$20*(1+Inputs!$F$12)^(H3-1) -> 114.8019
A8: CNG price (Rs/kg) | D8: =Inputs!$F$18*(1+Inputs!$F$12)^(D3-1) -> 87 | E8: =Inputs!$F$18*(1+Inputs!$F$12)^(E3-1) -> 89.61 | F8: =Inputs!$F$18*(1+Inputs!$F$12)^(F3-1) -> 92.2983 | G8: =Inputs!$F$18*(1+Inputs!$F$12)^(G3-1) -> 95.067249 | H8: =Inputs!$F$18*(1+Inputs!$F$12)^(H3-1) -> 97.919266
A9: Delivered hydrogen price (Rs/kg) | D9: =Inputs!$F$35*(1+Inputs!$F$36)^(D3-1) -> 800 | E9: =Inputs!$F$35*(1+Inputs!$F$36)^(E3-1) -> 720 | F9: =Inputs!$F$35*(1+Inputs!$F$36)^(F3-1) -> 648 | G9: =Inputs!$F$35*(1+Inputs!$F$36)^(G3-1) -> 583.2 | H9: =Inputs!$F$35*(1+Inputs!$F$36)^(H3-1) -> 524.88
A10: Hydrogen price trajectory multiplier (relative to year 1) | D10: =(1+Inputs!$F$36)^(D3-1) -> 1 | E10: =(1+Inputs!$F$36)^(E3-1) -> 0.9 | F10: =(1+Inputs!$F$36)^(F3-1) -> 0.81 | G10: =(1+Inputs!$F$36)^(G3-1) -> 0.729 | H10: =(1+Inputs!$F$36)^(H3-1) -> 0.6561
A11: Depot tariff (Rs/kWh) | D11: =Inputs!$F$47*(1+Inputs!$F$13)^(D3-1) -> 6 | E11: =Inputs!$F$47*(1+Inputs!$F$13)^(E3-1) -> 6.12 | F11: =Inputs!$F$47*(1+Inputs!$F$13)^(F3-1) -> 6.2424 | G11: =Inputs!$F$47*(1+Inputs!$F$13)^(G3-1) -> 6.367248 | H11: =Inputs!$F$47*(1+Inputs!$F$13)^(H3-1) -> 6.494593
A12: Public fast-charge price (Rs/kWh) | D12: =Inputs!$F$48*(1+Inputs!$F$13)^(D3-1) -> 20 | E12: =Inputs!$F$48*(1+Inputs!$F$13)^(E3-1) -> 20.4 | F12: =Inputs!$F$48*(1+Inputs!$F$13)^(F3-1) -> 20.808 | G12: =Inputs!$F$48*(1+Inputs!$F$13)^(G3-1) -> 21.22416 | H12: =Inputs!$F$48*(1+Inputs!$F$13)^(H3-1) -> 21.648643
A13: Hydrogen consumed (kg) | D13: =D6*Inputs!$F$34*Inputs!$F$33/100 -> 662.69775 | E13: =E6*Inputs!$F$34*Inputs!$F$33/100 -> 662.69775 | F13: =F6*Inputs!$F$34*Inputs!$F$33/100 -> 662.69775 | G13: =G6*Inputs!$F$34*Inputs!$F$33/100 -> 662.69775 | H13: =H6*Inputs!$F$34*Inputs!$F$33/100 -> 662.69775
A16: Option A: continue operating the CNG donor
A17: Capital / transaction at t0 | C17: =0 -> 0 | D17: 0 | E17: 0 | F17: 0 | G17: 0 | H17: 0
A18: CNG fuel | C18: 0 | D18: =D6*(1-Inputs!$F$22)/Inputs!$F$19*D8 -> 182193.66 | E18: =E6*(1-Inputs!$F$22)/Inputs!$F$19*E8 -> 187659.47 | F18: =F6*(1-Inputs!$F$22)/Inputs!$F$19*F8 -> 193289.25 | G18: =G6*(1-Inputs!$F$22)/Inputs!$F$19*G8 -> 199087.93 | H18: =H6*(1-Inputs!$F$22)/Inputs!$F$19*H8 -> 205060.57
A19: Petrol fuel (share of km) | C19: 0 | D19: =D6*Inputs!$F$22/Inputs!$F$21*D7 -> 18737.4 | E19: =E6*Inputs!$F$22/Inputs!$F$21*E7 -> 19299.522 | F19: =F6*Inputs!$F$22/Inputs!$F$21*F7 -> 19878.508 | G19: =G6*Inputs!$F$22/Inputs!$F$21*G7 -> 20474.863 | H19: =H6*Inputs!$F$22/Inputs!$F$21*H7 -> 21089.109
A20: Maintenance and tyres | C20: 0 | D20: =D6*Inputs!$F$23 -> 49599 | E20: =E6*Inputs!$F$23 -> 49599 | F20: =F6*Inputs!$F$23 -> 49599 | G20: =G6*Inputs!$F$23 -> 49599 | H20: =H6*Inputs!$F$23 -> 49599
A21: Insurance | C21: 0 | D21: =Inputs!$F$24 -> 18000 | E21: =Inputs!$F$24 -> 18000 | F21: =Inputs!$F$24 -> 18000 | G21: =Inputs!$F$24 -> 18000 | H21: =Inputs!$F$24 -> 18000
A22: Cylinder periodic test (annualised) | C22: 0 | D22: =Inputs!$F$25/3 -> 666.66667 | E22: =Inputs!$F$25/3 -> 666.66667 | F22: =Inputs!$F$25/3 -> 666.66667 | G22: =Inputs!$F$25/3 -> 666.66667 | H22: =Inputs!$F$25/3 -> 666.66667
A23: In-shift refuelling time cost | C23: 0 | D23: =Inputs!$F$26*Inputs!$F$10*Inputs!$F$14 -> 24750 | E23: =Inputs!$F$26*Inputs!$F$10*Inputs!$F$14 -> 24750 | F23: =Inputs!$F$26*Inputs!$F$10*Inputs!$F$14 -> 24750 | G23: =Inputs!$F$26*Inputs!$F$10*Inputs!$F$14 -> 24750 | H23: =Inputs!$F$26*Inputs!$F$10*Inputs!$F$14 -> 24750
A24: Residual value at end of horizon (inflow) | C24: 0 | D24: 0 | E24: 0 | F24: 0 | G24: 0 | H24: =-Inputs!$F$17 -> -100000
A25: Total cash cost | C25: =SUM(C17:C24) -> 0 | D25: =SUM(D17:D24) -> 293946.73 | E25: =SUM(E17:E24) -> 299974.66 | F25: =SUM(F17:F24) -> 306183.43 | G25: =SUM(G17:G24) -> 312578.46 | H25: =SUM(H17:H24) -> 219165.34
A26: Present value | C26: =C25*C$5 -> 0 | D26: =D25*D$5 -> 262452.43 | E26: =E25*E$5 -> 239137.96 | F26: =F25*F$5 -> 217935.32 | G26: =G25*G$5 -> 198649.26 | H26: =H25*H$5 -> 124360.3
A27: NPV of costs (Rs) | C27: =SUM(C26:H26) -> 1042535.3
A30: Option B: retrofit the donor to hydrogen (H2-ICE, petrol backup retained)
A31: Capital / transaction at t0 | C31: =Inputs!$F$28-Inputs!$F$30+Inputs!$F$31*Inputs!$F$32 -> 316623.48 | D31: 0 | E31: 0 | F31: 0 | G31: 0 | H31: 0
A32: Hydrogen fuel | C32: 0 | D32: =D13*D9 -> 530158.2 | E32: =E13*E9 -> 477142.38 | F32: =F13*F9 -> 429428.14 | G32: =G13*G9 -> 386485.33 | H32: =H13*H9 -> 347836.8
A33: Petrol fuel (backup share of km) | C33: 0 | D33: =D6*(1-Inputs!$F$34)/Inputs!$F$21*D7 -> 131161.8 | E33: =E6*(1-Inputs!$F$34)/Inputs!$F$21*E7 -> 135096.65 | F33: =F6*(1-Inputs!$F$34)/Inputs!$F$21*F7 -> 139149.55 | G33: =G6*(1-Inputs!$F$34)/Inputs!$F$21*G7 -> 143324.04 | H33: =H6*(1-Inputs!$F$34)/Inputs!$F$21*H7 -> 147623.76
A34: Maintenance and tyres | C34: 0 | D34: =D6*Inputs!$F$37 -> 55110 | E34: =E6*Inputs!$F$37 -> 55110 | F34: =F6*Inputs!$F$37 -> 55110 | G34: =G6*Inputs!$F$37 -> 55110 | H34: =H6*Inputs!$F$37 -> 55110
A35: Insurance | C35: 0 | D35: =Inputs!$F$38 -> 21000 | E35: =Inputs!$F$38 -> 21000 | F35: =Inputs!$F$38 -> 21000 | G35: =Inputs!$F$38 -> 21000 | H35: =Inputs!$F$38 -> 21000
A36: Hydrogen system inspection and cylinder requalification | C36: 0 | D36: =Inputs!$F$39 -> 4000 | E36: =Inputs!$F$39 -> 4000 | F36: =Inputs!$F$39 -> 4000 | G36: =Inputs!$F$39 -> 4000 | H36: =Inputs!$F$39 -> 4000
A37: In-shift refuelling time and detour cost | C37: 0 | D37: =Inputs!$F$40*Inputs!$F$10*Inputs!$F$14 -> 19800 | E37: =Inputs!$F$40*Inputs!$F$10*Inputs!$F$14 -> 19800 | F37: =Inputs!$F$40*Inputs!$F$10*Inputs!$F$14 -> 19800 | G37: =Inputs!$F$40*Inputs!$F$10*Inputs!$F$14 -> 19800 | H37: =Inputs!$F$40*Inputs!$F$10*Inputs!$F$14 -> 19800
A38: Residual value at end of horizon (inflow) | C38: 0 | D38: 0 | E38: 0 | F38: 0 | G38: 0 | H38: =-(Inputs!$F$17*Inputs!$F$41+Inputs!$F$42) -> -90000
A39: Total cash cost | C39: =SUM(C31:C38) -> 316623.48 | D39: =SUM(D31:D38) -> 761230 | E39: =SUM(E31:E38) -> 712149.03 | F39: =SUM(F31:F38) -> 668487.7 | G39: =SUM(G31:G38) -> 629719.37 | H39: =SUM(H31:H38) -> 505370.56
A40: Present value | C40: =C39*C$5 -> 316623.48 | D40: =D39*D$5 -> 679669.64 | E40: =E39*E$5 -> 567720.85 | F40: =F39*F$5 -> 475816.34 | G40: =G39*G$5 -> 400198.04 | H40: =H39*H$5 -> 286760.83
A41: NPV of costs (Rs) | C41: =SUM(C40:H40) -> 2726789.2
A42: NPV of option B excluding hydrogen fuel (Rs) | C42: =C41-SUMPRODUCT(D32:H32,D5:H5) -> 1124409.8
A45: Option C: sell the donor and buy a compact fleet BEV
A46: Capital / transaction at t0 | C46: =Inputs!$F$44+Inputs!$F$45-Inputs!$F$16 -> 730000 | D46: 0 | E46: 0 | F46: 0 | G46: 0 | H46: 0
A47: Electricity (depot and public mix) | C47: 0 | D47: =D6*Inputs!$F$46/100*(Inputs!$F$49*D12+(1-Inputs!$F$49)*D11) -> 84318.3 | E47: =E6*Inputs!$F$46/100*(Inputs!$F$49*E12+(1-Inputs!$F$49)*E11) -> 86004.666 | F47: =F6*Inputs!$F$46/100*(Inputs!$F$49*F12+(1-Inputs!$F$49)*F11) -> 87724.759 | G47: =G6*Inputs!$F$46/100*(Inputs!$F$49*G12+(1-Inputs!$F$49)*G11) -> 89479.255 | H47: =H6*Inputs!$F$46/100*(Inputs!$F$49*H12+(1-Inputs!$F$49)*H11) -> 91268.84
A48: Maintenance and tyres | C48: 0 | D48: =D6*Inputs!$F$50 -> 27555 | E48: =E6*Inputs!$F$50 -> 27555 | F48: =F6*Inputs!$F$50 -> 27555 | G48: =G6*Inputs!$F$50 -> 27555 | H48: =H6*Inputs!$F$50 -> 27555
A49: Insurance | C49: 0 | D49: =Inputs!$F$51 -> 30000 | E49: =Inputs!$F$51 -> 30000 | F49: =Inputs!$F$51 -> 30000 | G49: =Inputs!$F$51 -> 30000 | H49: =Inputs!$F$51 -> 30000
A50: In-shift charging time cost | C50: 0 | D50: =Inputs!$F$53*Inputs!$F$10*Inputs!$F$14 -> 24750 | E50: =Inputs!$F$53*Inputs!$F$10*Inputs!$F$14 -> 24750 | F50: =Inputs!$F$53*Inputs!$F$10*Inputs!$F$14 -> 24750 | G50: =Inputs!$F$53*Inputs!$F$10*Inputs!$F$14 -> 24750 | H50: =Inputs!$F$53*Inputs!$F$10*Inputs!$F$14 -> 24750
A51: Residual value at end of horizon (inflow) | C51: 0 | D51: 0 | E51: 0 | F51: 0 | G51: 0 | H51: =-Inputs!$F$52 -> -420000
A52: Total cash cost | C52: =SUM(C46:C51) -> 730000 | D52: =SUM(D46:D51) -> 166623.3 | E52: =SUM(E46:E51) -> 168309.67 | F52: =SUM(F46:F51) -> 170029.76 | G52: =SUM(G46:G51) -> 171784.25 | H52: =SUM(H46:H51) -> -246426.16
A53: Present value | C53: =C52*C$5 -> 730000 | D53: =D52*D$5 -> 148770.8 | E53: =E52*E$5 -> 134175.44 | F53: =F52*F$5 -> 121023.82 | G53: =G52*G$5 -> 109172 | H53: =H52*H$5 -> -139828.82
A54: NPV of costs (Rs) | C54: =SUM(C53:H53) -> 1103313.2
A57: SUMMARY (active scenario)
A58: Discounted km over horizon | C58: =SUMPRODUCT(D6:H6,D5:H5) -> 198659.22
A59: NPV A: continue CNG (Rs) | C59: =C27 -> 1042535.3
A60: NPV B: hydrogen retrofit (Rs) | C60: =C41 -> 2726789.2
A61: NPV C: sell and buy BEV (Rs) | C61: =C54 -> 1103313.2
A62: Levelised cost per km, A (Rs/km) | C62: =TCO!$C$59/TCO!$C$58 -> 5.2478576
A63: Levelised cost per km, B (Rs/km) | C63: =TCO!$C$60/TCO!$C$58 -> 13.725964
A64: Levelised cost per km, C (Rs/km) | C64: =TCO!$C$61/TCO!$C$58 -> 5.5537984
A65: Extra cost of B versus A over horizon (Rs) | C65: =TCO!$C$60-TCO!$C$59 -> 1684253.9
A66: Extra cost of B versus C over horizon (Rs) | C66: =TCO!$C$60-TCO!$C$61 -> 1623475.9
A67: Extra cost of C versus A over horizon (Rs) | C67: =TCO!$C$61-TCO!$C$59 -> 60777.963
A68: Year-1 fuel cost per km, CNG mode (Rs/km) | C68: =D8/Inputs!$F$19 -> 3.48
A69: Year-1 fuel cost per km, hydrogen mode (Rs/km) | C69: =Inputs!$F$33/100*D9 -> 14.8
A70: Year-1 fuel cost per km, petrol mode (Rs/km) | C70: =D7/Inputs!$F$21 -> 6.8
A71: Year-1 energy cost per km, BEV (Rs/km) | C71: =Inputs!$F$46/100*(Inputs!$F$49*D12+(1-Inputs!$F$49)*D11) -> 1.53
A72: Year-1 blended fuel cost per km, option B (Rs/km) | C72: =Inputs!$F$34*TCO!$C$69+(1-Inputs!$F$34)*TCO!$C$70 -> 12
A73: Year-1 blended fuel cost per km, option A (Rs/km) | C73: =(1-Inputs!$F$22)*TCO!$C$68+Inputs!$F$22*TCO!$C$70 -> 3.646
A74: Year-1 non-fuel operating cost per km, A (Rs/km) | C74: =(D20+D21+D22+D23)/D6 -> 1.6878183
A75: Year-1 non-fuel operating cost per km, B (Rs/km) | C75: =(D34+D35+D36+D37)/D6 -> 1.8129196
A76: Year-1 non-fuel operating cost per km, C (Rs/km) | C76: =(D48+D49+D50)/D6 -> 1.4934676
A77: Discounted hydrogen kg, trajectory-weighted | C77: =SUMPRODUCT(D13:H13,D10:H10,D5:H5) -> 2002.9742
A78: Discounted hydrogen kg, flat | C78: =SUMPRODUCT(D13:H13,D5:H5) -> 2388.8771
A79: Break-even year-1 hydrogen price versus A, same trajectory (Rs/kg) | C79: =(TCO!$C$59-C42)/TCO!$C$77 -> -40.876493
A80: Break-even flat hydrogen price versus A (Rs/kg) | C80: =(TCO!$C$59-C42)/TCO!$C$78 -> -34.273241
A81: Break-even year-1 hydrogen price versus C (BEV), same trajectory (Rs/kg) | C81: =(TCO!$C$61-C42)/TCO!$C$77 -> -10.532636
A82: Fuel-parity hydrogen price versus CNG (fuel cost per km equal) (Rs/kg) | C82: =TCO!$C$68/(Inputs!$F$33/100) -> 188.10811
A83: Fuel-parity hydrogen price versus petrol (Rs/kg) | C83: =TCO!$C$70/(Inputs!$F$33/100) -> 367.56757
A84: Maximum conversion cost for parity with A at the active hydrogen price (Rs) | C84: =MAX(0,Inputs!$F$28+(TCO!$C$59-TCO!$C$60)) -> 0
A85: Maximum conversion cost for parity with C at the active hydrogen price (Rs) | C85: =MAX(0,Inputs!$F$28+(TCO!$C$61-TCO!$C$60)) -> 0
A86: Year-1 operating saving of B versus A (Rs/yr; negative = B costs more) | C86: =D25-D39 -> -467283.27
A87: Simple payback of conversion versus A (years) | C87: =IF(TCO!$C$86>0,C31/TCO!$C$86,"none") -> none
A88: Annuity factor (sum of discount factors, years 1-5) | C88: =SUM(D5:H5) -> 3.6047762
A89: Minimum annual km for payback within horizon (year-1 prices) | C89: =IF((TCO!$C$73+TCO!$C$74-TCO!$C$72-TCO!$C$75)>0,(C31/TCO!$C$88)/(TCO!$C$73+TCO!$C$74-TCO!$C$72-TCO!$C$75),"n/a") -> n/a
A90: Coefficient a (B-A): fixed and capital terms (Rs) | C90: =C31-C17+SUMPRODUCT(D35:H35,D5:H5)+SUMPRODUCT(D36:H36,D5:H5)+SUMPRODUCT(D37:H37,D5:H5)-SUMPRODUCT(D21:H21,D5:H5)-SUMPRODUCT(D22:H22,D5:H5)-SUMPRODUCT(D23:H23,D5:H5)+(H38-H24)*H5 -> 327284.36
A91: Coefficient b (B-A): per-km non-hydrogen terms (Rs per km) | C91: =SUMPRODUCT(D7:H7,D5:H5)*(1-Inputs!$F$34)/Inputs!$F$21+Inputs!$F$37*SUM(D5:H5)-SUMPRODUCT(D8:H8,D5:H5)*(1-Inputs!$F$22)/Inputs!$F$19-SUMPRODUCT(D7:H7,D5:H5)*Inputs!$F$22/Inputs!$F$21-Inputs!$F$23*SUM(D5:H5) -> -4.4530901
A92: Coefficient c: hydrogen term (Rs per km per Rs/kg of year-1 price) | C92: =Inputs!$F$34*Inputs!$F$33/100*SUMPRODUCT(D10:H10,D5:H5) -> 0.036345022
A93: Check: a + b*km + c*km*P reproduces B-A (should be ~0) | C93: =TCO!$C$90+TCO!$C$91*D6+TCO!$C$92*D6*Inputs!$F$35-TCO!$C$65 -> 0
A94: Coefficient a (B-C): fixed and capital terms (Rs) | C94: =C31-C46+SUMPRODUCT(D35:H35,D5:H5)+SUMPRODUCT(D36:H36,D5:H5)+SUMPRODUCT(D37:H37,D5:H5)-SUMPRODUCT(D49:H49,D5:H5)-SUMPRODUCT(D50:H50,D5:H5)+(H38-H51)*H5 -> -261993.18
A95: Coefficient b (B-C): per-km non-hydrogen terms (Rs per km) | C95: =SUMPRODUCT(D7:H7,D5:H5)*(1-Inputs!$F$34)/Inputs!$F$21+Inputs!$F$37*SUM(D5:H5)-Inputs!$F$46/100*(Inputs!$F$49*SUMPRODUCT(D12:H12,D5:H5)+(1-Inputs!$F$49)*SUMPRODUCT(D11:H11,D5:H5))-Inputs!$F$50*SUM(D5:H5) -> 5.1368132
A96: Check: a + b*km + c*km*P reproduces B-C (should be ~0) | C96: =TCO!$C$94+TCO!$C$95*D6+TCO!$C$92*D6*Inputs!$F$35-TCO!$C$66 -> 0

Sheet H2_Supply
A1: Hydrogen supply: fleet demand, station sizing and delivered price build-up
A2: Delivered price = (production + transport + compression electricity + station capital recovery + O&M) x (1 + losses) x (1 + margin and taxes). Capital is recovered only here.
A4: Quantity | B4: Pilot (2028) | C4: Hub (2030) | D4: Unit | E4: Note
A5: Cars served | B5: =Inputs!$F$73 -> 30 | C5: =B27 -> 37.347343 | D5: cars | E5: Hub: cars per station at design utilisation (row 27)
A6: Hydrogen per car per operating day | B6: =Energy_Range!$B$24 -> 2.008175 | C6: =Energy_Range!$B$24 -> 2.008175 | D6: kg/car/day | E6: From Energy_Range
A7: Fleet hydrogen demand per operating day | B7: =B5*B6 -> 60.24525 | C7: =C5*C6 -> 75 | D7: kg/day
A8: Station design capacity | B8: =Inputs!$F$78 -> 150 | C8: =Inputs!$F$81 -> 500 | D8: kg/day
A9: Station utilisation assumed for pricing | B9: =Inputs!$F$79 -> 0.5 | C9: =Inputs!$F$82 -> 0.7 | D9: fraction | E9: Pilot station shared with bus/truck pilot users
A10: Hydrogen dispensed per year at that utilisation | B10: =B8*365*B9 -> 27375 | C10: =C8*365*C9 -> 127750 | D10: kg/yr
A11: Fills per day (cars x fills) | B11: =B5*Inputs!$F$63 -> 60 | C11: =C5*Inputs!$F$63 -> 74.694685 | D11: fills/day
A12: Peak window length | B12: 3 | C12: 3 | D12: hours | E12: Start-of-shift window
A13: Share of fills in the peak window | B13: 0.5 | C13: 0.4 | D13: fraction | E13: Assumption
A14: Fills per hour in the peak window | B14: =B11*B13/B12 -> 10 | C14: =C11*C13/C12 -> 9.9592914 | D14: fills/h
A15: Dispenser positions needed (6 fills per hour each, 1.2 kg fills at 350 bar) | B15: =ROUNDUP(B14/6,0) -> 2 | C15: =ROUNDUP(C14/6,0) -> 2 | D15: dispensers | E15: Assumption 6 fills/h per H35 dispenser incl. connection
A16: Compressor throughput needed (16 operating hours) | B16: =B8/16 -> 9.375 | C16: =C8/16 -> 31.25 | D16: kg/h | E16: Sized on design capacity
A17: On-site storage buffer (1.5 days of demand) | B17: =1.5*B7 -> 90.367875 | C17: =1.5*C7 -> 112.5 | D17: kg | E17: Cascade at 450 bar
A18: Tube-trailer deliveries per week | B18: =B7*7/Inputs!$F$89 -> 1.4057225 | C18: =C7*7/Inputs!$F$89 -> 1.75 | D18: deliveries/week
A19: Production cost at plant gate | B19: =Inputs!$F$74 -> 400 | C19: =Inputs!$F$75 -> 240 | D19: Rs/kg
A20: Transport (tube trailer) | B20: =Inputs!$F$76 -> 45 | C20: =Inputs!$F$76 -> 45 | D20: Rs/kg
A21: Compression and dispensing electricity | B21: =Inputs!$F$85*Inputs!$F$86 -> 27 | C21: =Inputs!$F$85*Inputs!$F$86 -> 27 | D21: Rs/kg
A22: Station capex | B22: =Inputs!$F$77 -> 100000000 | C22: =Inputs!$F$80 -> 120000000 | D22: Rs
A23: Capital recovery factor | B23: =Inputs!$F$9*(1+Inputs!$F$9)^Inputs!$F$83/((1+Inputs!$F$9)^Inputs!$F$83-1) -> 0.17698416 | C23: =Inputs!$F$9*(1+Inputs!$F$9)^Inputs!$F$83/((1+Inputs!$F$9)^Inputs!$F$83-1) -> 0.17698416 | D23: fraction
A24: Station capital recovery per kg | B24: =B22*B23/B10 -> 646.51749 | C24: =C22*C23/C10 -> 166.24736 | D24: Rs/kg | E24: At the assumed utilisation
A25: Station fixed O&M per kg | B25: =B22*Inputs!$F$84/B10 -> 146.11872 | C25: =C22*Inputs!$F$84/C10 -> 37.573386 | D25: Rs/kg
A26: Delivered price at dispenser | B26: =(B19+B20+B21+B24+B25)*(1+Inputs!$F$87)*(1+Inputs!$F$88) -> 1432.8328 | C26: =(C19+C20+C21+C24+C25)*(1+Inputs!$F$87)*(1+Inputs!$F$88) -> 584.4249 | D26: Rs/kg | E26: Key output; compare with Inputs h2_price_y1
A27: Cars a station can serve at design utilisation | B27: =B8*B9/B6 -> 37.347343 | C27: =C8*C9/C6 -> 174.2876 | D27: cars
A28: Utilisation implied by the car fleet alone | B28: =B7/B8 -> 0.401635 | C28: =C7/C8 -> 0.15 | D28: fraction
A31: Delivered price versus station utilisation (Rs/kg)
A32: Utilisation | B32: Pilot station (2028) | C32: Hub station (2030)
A33: 0.2 | B33: =($B$19+$B$20+$B$21+($B$22*$B$23+$B$22*Inputs!$F$84)/($B$8*365*A33))*(1+Inputs!$F$87)*(1+Inputs!$F$88) -> 2779.9181 | C33: =($C$19+$C$20+$C$21+($C$22*$C$23+$C$22*Inputs!$F$84)/($C$8*365*A33))*(1+Inputs!$F$87)*(1+Inputs!$F$88) -> 1161.7471
A34: 0.35 | B34: =($B$19+$B$20+$B$21+($B$22*$B$23+$B$22*Inputs!$F$84)/($B$8*365*A34))*(1+Inputs!$F$87)*(1+Inputs!$F$88) -> 1817.7143 | C34: =($C$19+$C$20+$C$21+($C$22*$C$23+$C$22*Inputs!$F$84)/($C$8*365*A34))*(1+Inputs!$F$87)*(1+Inputs!$F$88) -> 815.3538
A35: 0.5 | B35: =($B$19+$B$20+$B$21+($B$22*$B$23+$B$22*Inputs!$F$84)/($B$8*365*A35))*(1+Inputs!$F$87)*(1+Inputs!$F$88) -> 1432.8328 | C35: =($C$19+$C$20+$C$21+($C$22*$C$23+$C$22*Inputs!$F$84)/($C$8*365*A35))*(1+Inputs!$F$87)*(1+Inputs!$F$88) -> 676.79646
A36: 0.65 | B36: =($B$19+$B$20+$B$21+($B$22*$B$23+$B$22*Inputs!$F$84)/($B$8*365*A36))*(1+Inputs!$F$87)*(1+Inputs!$F$88) -> 1225.5889 | C36: =($C$19+$C$20+$C$21+($C$22*$C$23+$C$22*Inputs!$F$84)/($C$8*365*A36))*(1+Inputs!$F$87)*(1+Inputs!$F$88) -> 602.18866
A37: 0.8 | B37: =($B$19+$B$20+$B$21+($B$22*$B$23+$B$22*Inputs!$F$84)/($B$8*365*A37))*(1+Inputs!$F$87)*(1+Inputs!$F$88) -> 1096.0615 | C37: =($C$19+$C$20+$C$21+($C$22*$C$23+$C$22*Inputs!$F$84)/($C$8*365*A37))*(1+Inputs!$F$87)*(1+Inputs!$F$88) -> 555.55879
A38: 0.95 | B38: =($B$19+$B$20+$B$21+($B$22*$B$23+$B$22*Inputs!$F$84)/($B$8*365*A38))*(1+Inputs!$F$87)*(1+Inputs!$F$88) -> 1007.4375 | C38: =($C$19+$C$20+$C$21+($C$22*$C$23+$C$22*Inputs!$F$84)/($C$8*365*A38))*(1+Inputs!$F$87)*(1+Inputs!$F$88) -> 523.65414
A40: Utilisation needed to reach a target delivered price
A41: Target | B41: Target price (Rs/kg) | C41: Pilot station utilisation needed | D41: Hub station utilisation needed
A42: CNG fuel-parity price (from TCO) | B42: =TCO!$C$82 -> 188.10811 | C42: =IF(B42/((1+Inputs!$F$87)*(1+Inputs!$F$88))-($B$19+$B$20+$B$21)<=0,"not reachable at any utilisation",MIN(9.99,($B$22*$B$23+$B$22*Inputs!$F$84)/($B$8*365)/(B42/((1+Inputs!$F$87)*(1+Inputs!$F$88))-($B$19+$B$20+$B$21)))) -> not reachable at any utilisation | D42: =IF(B42/((1+Inputs!$F$87)*(1+Inputs!$F$88))-($C$19+$C$20+$C$21)<=0,"not reachable at any utilisation",MIN(9.99,($C$22*$C$23+$C$22*Inputs!$F$84)/($C$8*365)/(B42/((1+Inputs!$F$87)*(1+Inputs!$F$88))-($C$19+$C$20+$C$21)))) -> not reachable at any utilisation
A43: Full-TCO break-even versus continuing on CNG (from TCO) | B43: =TCO!$C$79 -> -40.876493 | C43: =IF(B43/((1+Inputs!$F$87)*(1+Inputs!$F$88))-($B$19+$B$20+$B$21)<=0,"not reachable at any utilisation",MIN(9.99,($B$22*$B$23+$B$22*Inputs!$F$84)/($B$8*365)/(B43/((1+Inputs!$F$87)*(1+Inputs!$F$88))-($B$19+$B$20+$B$21)))) -> not reachable at any utilisation | D43: =IF(B43/((1+Inputs!$F$87)*(1+Inputs!$F$88))-($C$19+$C$20+$C$21)<=0,"not reachable at any utilisation",MIN(9.99,($C$22*$C$23+$C$22*Inputs!$F$84)/($C$8*365)/(B43/((1+Inputs!$F$87)*(1+Inputs!$F$88))-($C$19+$C$20+$C$21)))) -> not reachable at any utilisation
A44: Petrol fuel-parity price (from TCO) | B44: =TCO!$C$83 -> 367.56757 | C44: =IF(B44/((1+Inputs!$F$87)*(1+Inputs!$F$88))-($B$19+$B$20+$B$21)<=0,"not reachable at any utilisation",MIN(9.99,($B$22*$B$23+$B$22*Inputs!$F$84)/($B$8*365)/(B44/((1+Inputs!$F$87)*(1+Inputs!$F$88))-($B$19+$B$20+$B$21)))) -> not reachable at any utilisation | D44: =IF(B44/((1+Inputs!$F$87)*(1+Inputs!$F$88))-($C$19+$C$20+$C$21)<=0,"not reachable at any utilisation",MIN(9.99,($C$22*$C$23+$C$22*Inputs!$F$84)/($C$8*365)/(B44/((1+Inputs!$F$87)*(1+Inputs!$F$88))-($C$19+$C$20+$C$21)))) -> 9.99
A45: Full-TCO break-even versus BEV (from TCO) | B45: =TCO!$C$81 -> -10.532636 | C45: =IF(B45/((1+Inputs!$F$87)*(1+Inputs!$F$88))-($B$19+$B$20+$B$21)<=0,"not reachable at any utilisation",MIN(9.99,($B$22*$B$23+$B$22*Inputs!$F$84)/($B$8*365)/(B45/((1+Inputs!$F$87)*(1+Inputs!$F$88))-($B$19+$B$20+$B$21)))) -> not reachable at any utilisation | D45: =IF(B45/((1+Inputs!$F$87)*(1+Inputs!$F$88))-($C$19+$C$20+$C$21)<=0,"not reachable at any utilisation",MIN(9.99,($C$22*$C$23+$C$22*Inputs!$F$84)/($C$8*365)/(B45/((1+Inputs!$F$87)*(1+Inputs!$F$88))-($C$19+$C$20+$C$21)))) -> not reachable at any utilisation
A47: Note: values above 100 percent mean the target cannot be met even at full utilisation; 'not reachable' means production plus transport plus electricity alone exceed the target.

Sheet Market
A1: Bottom-up addressable market and supply-constrained deployment
A2: Funnel from national CNG stock to what stations can actually serve by 2030.
A4: Step | B4: Vehicles | C4: Share applied | D4: Note
A5: CNG vehicles in India, all categories | B5: =Inputs!$F$105 -> 8195000 | D5: Input, class A
A6: Passenger cars among them | B6: =B5*Inputs!$F$106 -> 4507250 | C6: =Inputs!$F$106 -> 0.55 | D6: Share input
A7: Technically eligible: factory-fitted, boot-cylinder layout, under 6 years old at 2028 | B7: =B6*Inputs!$F$107 -> 2253625 | C7: =Inputs!$F$107 -> 0.5 | D7: Excludes older vehicles and layouts without a compatible cylinder bay
A8: In commercial fleets (taxi, aggregator, corporate, institutional) | B8: =B7*Inputs!$F$108 -> 450725 | C8: =Inputs!$F$108 -> 0.2 | D8: Private owners excluded from the first segment
A9: In cities with a hydrogen hub station by 2030 | B9: =B8*Inputs!$F$109 -> 180290 | C9: =Inputs!$F$109 -> 0.4 | D9: Delhi-NCR, Gujarat corridor, Pune-Mumbai, Kochi and similar
A10: Plausible early adopters (return-to-base fleets willing to convert) | B10: =B9*Inputs!$F$110 -> 9014.5 | C10: =Inputs!$F$110 -> 0.05 | D10: Hypothesis to be validated with fleet interviews
A11: Supply-constrained capacity: stations x cars per station | B11: =Inputs!$F$111*H2_Supply!$C$27 -> 1394.3008 | D11: From H2_Supply
A12: Realistic 2030 converted fleet (minimum of demand and supply) | B12: =MIN(B10,B11) -> 1394.3008 | D12: Key output
A13: Round 1 claim for 2030 | B13: 100000 | D13: For comparison

Sheet Pilot_Budget
A1: Programme budget by phase and rollout quantities
A2: Rs. Phases run October 2026 to September 2030. Contingency applied to all phases.
A4: Phase | B4: Line item | C4: Quantity | D4: Unit cost (Rs) | E4: Total (Rs) | F4: Class | G4: Basis
A5: Phase 0: Feasibility and validation (Oct 2026 - Mar 2027)
B6: Regulator and test-agency consultations, route definition (AISC, MoRTH, ARAI/ICAT, PESO) | C6: 1 | D6: 2500000 | E6: =C6*D6 -> 2500000 | F6: C | G6: Engineering time, travel, legal review
B7: Fleet and fuel-partner validation: 30 operator interviews, duty-cycle telematics on 20 cars | C7: 1 | D7: 2500000 | E7: =C7*D7 -> 2500000 | F7: C | G7: Customer demand is a hypothesis; this buys the evidence
B8: Donor inspection, packaging study, CAD and mule vehicle (boot mock-up) | C8: 1 | D8: 4000000 | E8: =C8*D8 -> 4000000 | F8: C
B9: Phase subtotal | E9: =SUM(E6:E8) -> 9000000
A11: Phase 1: Engineering and controlled validation (Apr 2027 - Mar 2028)
B12: Hydrogen engine test-cell time and instrumentation (calibration, NOx, abnormal combustion, 500 h) | C12: 1 | D12: 30000000 | E12: =C12*D12 -> 30000000 | F12: C | G12: Hydrogen test cells exist at ARAI, iCAT and IOCL R&D (S-TEST)
B13: Prototype conversions (3 vehicles) at pilot kit cost | C13: 3 | D13: =BOM!$G$40 -> 774375 | E13: =C13*D13 -> 2323125 | F13: B | G13: BOM pilot cost
B14: Prototype donor vehicles (used Tour S CNG) | C14: 3 | D14: 500000 | E14: =C14*D14 -> 1500000 | F14: C
B15: Storage system qualification samples and tests (burst, cycling, bonfire, drop, permeation) | C15: 1 | D15: 15000000 | E15: =C15*D15 -> 15000000 | F15: C | G15: UN GTR 13 / R134 type tests via supplier and PESO
B16: Vehicle-level safety tests (leak, sled/crash structure, ventilation) at test agency | C16: 1 | D16: 12000000 | E16: =C16*D16 -> 12000000 | F16: C
B17: Engineering team (8 FTE x 12 months) | C17: 96 | D17: 250000 | E17: =C17*D17 -> 24000000 | F17: C | G17: Rs 2.5 lakh per FTE-month fully loaded
B18: Phase subtotal | E18: =SUM(E12:E17) -> 84823125
A20: Phase 2: Certification and pilot build (Apr 2028 - Mar 2029)
B21: Kit type approval and emissions testing at ARAI/ICAT (analogous to CNG kit approval) | C21: 1 | D21: 10000000 | E21: =C21*D21 -> 10000000 | F21: C | G21: Industry reports Rs 40-50 lakh for CNG kit approval (S-TAFEE); hydrogen scope larger
B22: Durability demonstration (2 vehicles x 80,000 km accelerated) | C22: 1 | D22: 8000000 | E22: =C22*D22 -> 8000000 | F22: C
B23: Pilot conversions (30 vehicles) at pilot kit cost | C23: =Inputs!$F$73 -> 30 | D23: =BOM!$G$40 -> 774375 | E23: =C23*D23 -> 23231250 | F23: B | G23: BOM pilot cost
B24: Instrumentation and telematics (30 cars + 20 comparison cars) | C24: 50 | D24: 60000 | E24: =C24*D24 -> 3000000 | F24: C | G24: CAN logger, GPS, hydrogen sensor logging
B25: Hydrogen dispensing point at partner site (compressor, cascade, one dispenser, safety, PESO) | C25: 1 | D25: =Inputs!$F$77 -> 100000000 | E25: =C25*D25 -> 100000000 | F25: B | G25: Input station_capex_pilot; delivered hydrogen, no on-site electrolyser
B26: Workshop upgrade (ventilation, detection, training) at 2 service points | C26: 2 | D26: 4000000 | E26: =C26*D26 -> 8000000 | F26: C | G26: NFPA 2 type ventilation and detection
B27: Phase subtotal | E27: =SUM(E21:E26) -> 152231250
A29: Phase 3: Pilot operation and evaluation (Apr 2029 - Sep 2030)
B30: Hydrogen fuel for 30 cars, 18 months (kg at delivered pilot price) | C30: =Inputs!$F$73*Energy_Range!$B$24*Inputs!$F$10*1.5 -> 29821.399 | D30: =H2_Supply!$B$26 -> 1432.8328 | E30: =C30*D30 -> 42729079 | F30: B | G30: Quantity from Energy_Range and H2_Supply
B31: Operations, safety officer, data analysis and independent evaluation (18 months) | C31: 18 | D31: 1500000 | E31: =C31*D31 -> 27000000 | F31: C | G31: Per month
B32: Quarterly emissions and consumption tests at test agency | C32: 6 | D32: 800000 | E32: =C32*D32 -> 4800000 | F32: C
B33: Insurance, incident reserve and driver training | C33: 1 | D33: 6000000 | E33: =C33*D33 -> 6000000 | F33: C
B34: Phase subtotal | E34: =SUM(E30:E33) -> 80529079
B36: Subtotal all phases | E36: =E9+E18+E27+E34 -> 3.2658345e+08
B37: Contingency (share of subtotal) | C37: 0.15 | E37: =E36*C37 -> 48987518
B38: Total programme budget to September 2030 (Rs) | E38: =E36+E37 -> 3.7557097e+08
B39: Total in Rs crore | E39: =E38/10000000 -> 37.557097
B41: Proposed funding split (shares are proposals, not commitments)
B42: Suzuki R&D Center India / Maruti Suzuki (engineering, prototypes, test cells) | C42: 0.4 | E42: =C42*E38 -> 1.5022839e+08
B43: Public support sought (MNRE NGHM R&D or pilot scheme, state hydrogen policy) | C43: 0.35 | E43: =C43*E38 -> 1.3144984e+08
B44: Fuel and station partner (OMC or gas utility): dispensing point | C44: 0.15 | E44: =C44*E38 -> 56335646
B45: Fleet partner (vehicles, drivers, operations) | C45: 0.1 | E45: =C45*E38 -> 37557097
B47: Rollout quantities (conditional expansion after gates)
B48: Item | C48: 2028 | D48: 2029 | E48: 2030 | G48: Note
B49: Converted cars in operation (cumulative) | C49: 3 | D49: =Inputs!$F$73 -> 30 | E49: =Market!$B$12 -> 1394.3008 | G49: 2030 value from Market sheet (supply-constrained scenario, conditional on gates)
B50: Fleet-hub stations serving cars | C50: 1 | D50: 1 | E50: =Inputs!$F$111 -> 8
B51: Hydrogen demand from cars (t/yr) | C51: =C49*Energy_Range!$B$24*Inputs!$F$10/1000 -> 1.9880932 | D51: =D49*Energy_Range!$B$24*Inputs!$F$10/1000 -> 19.880933 | E51: =E49*Energy_Range!$B$24*Inputs!$F$10/1000 -> 924

Sheet Emissions
A1: Emissions per km and at fleet scale, same service boundary for all options
A2: Tailpipe, well-to-tank and amortised manufacturing. Hydrogen combustion emits NOx (not CO2); see NOx rows.
A4: Quantity | B4: Value | C4: Unit | D4: Note
A5: A: CNG tailpipe CO2 per km (CNG share of km) | B5: =(1-Inputs!$F$22)/Inputs!$F$19*Inputs!$F$91*1000 -> 102.22 | C5: g/km
A6: A: petrol tailpipe CO2 per km (petrol share) | B6: =Inputs!$F$22/Inputs!$F$21*Inputs!$F$93*1000 -> 7.5666667 | C6: g/km
A7: A: well-to-tank CO2e per km | B7: =B5*Inputs!$F$92+B6*Inputs!$F$94 -> 27.068333 | C7: g/km | D7: Uplift factors on tailpipe
A8: A: total well-to-wheel CO2e per km | B8: =B5+B6+B7 -> 136.855 | C8: g/km | D8: Key
A9: B: hydrogen share of km | B9: =Inputs!$F$34 -> 0.65 | C9: fraction
A10: B: hydrogen consumption | B10: =Inputs!$F$33 -> 1.85 | C10: kg/100 km
A11: B: well-to-wheel CO2e per km, green hydrogen | B11: =B9*B10/100*Inputs!$F$95*1000+(1-B9)/Inputs!$F$21*Inputs!$F$93*(1+Inputs!$F$94)*1000 -> 87.61 | C11: g/km | D11: Tailpipe CO2 on hydrogen km is zero; petrol backup km counted
A12: B: well-to-wheel CO2e per km, grid-electrolysis hydrogen | B12: =B9*B10/100*Inputs!$F$96*1000+(1-B9)/Inputs!$F$21*Inputs!$F$93*(1+Inputs!$F$94)*1000 -> 532.535 | C12: g/km | D12: Reversal case
A13: B: well-to-wheel CO2e per km, grey (SMR) hydrogen | B13: =B9*B10/100*Inputs!$F$97*1000+(1-B9)/Inputs!$F$21*Inputs!$F$93*(1+Inputs!$F$94)*1000 -> 207.86 | C13: g/km | D13: Reversal case
A14: B: retrofit kit manufacturing amortised over horizon km | B14: =Inputs!$F$102*1000000/(Inputs!$F$10*Inputs!$F$11*Inputs!$F$8) -> 1.8145527 | C14: g/km
A15: B: total per km incl. kit manufacturing, green hydrogen | B15: =B11+B14 -> 89.424553 | C15: g/km | D15: Key
A16: C: BEV electricity per km at 2025 grid factor | B16: =Inputs!$F$46/100*Inputs!$F$98*1000 -> 129 | C16: g/km | D16: Metered kWh already include charging losses
A17: C: BEV electricity per km at 2030 grid factor | B17: =Inputs!$F$46/100*Inputs!$F$99*1000 -> 87 | C17: g/km
A18: C: BEV manufacturing amortised per km | B18: =Inputs!$F$100*1000000/Inputs!$F$101 -> 46.666667 | C18: g/km | D18: New vehicle and battery; counterfactual is keeping the donor
A19: C: total per km incl. manufacturing, 2025 grid | B19: =B16+B18 -> 175.66667 | C19: g/km | D19: Key
A20: C: total per km incl. manufacturing, 2030 grid | B20: =B17+B18 -> 133.66667 | C20: g/km | D20: Key
A21: Reduction of B (green) versus A | B21: =1-B15/B8 -> 0.34657446 | C21: fraction
A22: Reduction of C (2030 grid) versus A | B22: =1-B20/B8 -> 0.023297164 | C22: fraction | D22: Negative = BEV replacement emits more than continuing on CNG within the horizon
A23: Grid factor at which BEV equals green-hydrogen retrofit per km | B23: =(B15-B18)/(Inputs!$F$46/100)/1000 -> 0.28505257 | C23: kg CO2/kWh | D23: Reversal threshold
A24: Hydrogen carbon intensity at which retrofit equals continuing on CNG | B24: =(B8-(1-B9)/Inputs!$F$21*Inputs!$F$93*(1+Inputs!$F$94)*1000-B14)/(B9*B10/100*1000) -> 5.9443199 | C24: kg CO2e/kg H2 | D24: Retrofit is worse than CNG above this hydrogen carbon intensity
A25: Per-car CO2e avoided over the horizon, B (green) versus A | B25: =(B8-B15)*Inputs!$F$10*Inputs!$F$11*Inputs!$F$8/1000000 -> 13.06946 | C25: t CO2e
A26: Abatement cost of the retrofit versus continuing on CNG (active scenario) | B26: =IF(B25>0,TCO!$C$65/B25,"n/a") -> 128869.44 | C26: Rs per t CO2e | D26: Extra ownership cost divided by CO2e avoided
A27: Pilot fleet (30 cars) CO2e avoided per year, green hydrogen | B27: =Inputs!$F$73*(B8-B15)*Inputs!$F$10*Inputs!$F$11/1000000 -> 78.416759 | C27: t CO2e/yr
A28: 2030 converted fleet CO2e avoided per year, green hydrogen | B28: =Market!$B$12*(B8-B15)*Inputs!$F$10*Inputs!$F$11/1000000 -> 3644.5516 | C28: t CO2e/yr | D28: Supply-constrained fleet from Market
A29: 2030 converted fleet hydrogen demand | B29: =Market!$B$12*Energy_Range!$B$24*Inputs!$F$10/1000 -> 924 | C29: t/yr
A30: NOx: BS-VI limit for M1 petrol | B30: =Inputs!$F$103 -> 60 | C30: mg/km | D30: Applies to the converted vehicle by analogy; test procedure for H2-ICE retrofits does not exist yet
A31: NOx: lean hydrogen combustion engine-out (lambda above 2) reported range | B31: 5 to 20 | C31: mg/km class | D31: Literature indicates near-zero NOx above lambda about 2 (S-NOX); transients and high load exceed it, hence aftertreatment provision

Sheet Sensitivities
A1: When does the recommendation change? Grids use the closed-form decomposition from the TCO sheet (same trajectory shape, active scenario for all other inputs).
A2: Values in Rs lakh over the horizon; negative = the hydrogen retrofit is cheaper than the comparator.
A4: Grid 1: retrofit minus continue-on-CNG (Rs lakh) by year-1 delivered hydrogen price (rows) and annual km (columns)
A5: Rs/kg \ km/yr | B5: 30000 | C5: 40000 | D5: 50000 | E5: 60000 | F5: 70000
A6: 100 | B6: =(TCO!$C$90+TCO!$C$91*B$5+TCO!$C$92*B$5*$A6)/100000 -> 3.0272672 | C6: =(TCO!$C$90+TCO!$C$91*C$5+TCO!$C$92*C$5*$A6)/100000 -> 2.9454084 | D6: =(TCO!$C$90+TCO!$C$91*D$5+TCO!$C$92*D$5*$A6)/100000 -> 2.8635496 | E6: =(TCO!$C$90+TCO!$C$91*E$5+TCO!$C$92*E$5*$A6)/100000 -> 2.7816908 | F6: =(TCO!$C$90+TCO!$C$91*F$5+TCO!$C$92*F$5*$A6)/100000 -> 2.699832
A7: 150 | B7: =(TCO!$C$90+TCO!$C$91*B$5+TCO!$C$92*B$5*$A7)/100000 -> 3.5724425 | C7: =(TCO!$C$90+TCO!$C$91*C$5+TCO!$C$92*C$5*$A7)/100000 -> 3.6723089 | D7: =(TCO!$C$90+TCO!$C$91*D$5+TCO!$C$92*D$5*$A7)/100000 -> 3.7721752 | E7: =(TCO!$C$90+TCO!$C$91*E$5+TCO!$C$92*E$5*$A7)/100000 -> 3.8720415 | F7: =(TCO!$C$90+TCO!$C$91*F$5+TCO!$C$92*F$5*$A7)/100000 -> 3.9719078
A8: 200 | B8: =(TCO!$C$90+TCO!$C$91*B$5+TCO!$C$92*B$5*$A8)/100000 -> 4.1176179 | C8: =(TCO!$C$90+TCO!$C$91*C$5+TCO!$C$92*C$5*$A8)/100000 -> 4.3992093 | D8: =(TCO!$C$90+TCO!$C$91*D$5+TCO!$C$92*D$5*$A8)/100000 -> 4.6808007 | E8: =(TCO!$C$90+TCO!$C$91*E$5+TCO!$C$92*E$5*$A8)/100000 -> 4.9623922 | F8: =(TCO!$C$90+TCO!$C$91*F$5+TCO!$C$92*F$5*$A8)/100000 -> 5.2439836
A9: 250 | B9: =(TCO!$C$90+TCO!$C$91*B$5+TCO!$C$92*B$5*$A9)/100000 -> 4.6627932 | C9: =(TCO!$C$90+TCO!$C$91*C$5+TCO!$C$92*C$5*$A9)/100000 -> 5.1261097 | D9: =(TCO!$C$90+TCO!$C$91*D$5+TCO!$C$92*D$5*$A9)/100000 -> 5.5894263 | E9: =(TCO!$C$90+TCO!$C$91*E$5+TCO!$C$92*E$5*$A9)/100000 -> 6.0527428 | F9: =(TCO!$C$90+TCO!$C$91*F$5+TCO!$C$92*F$5*$A9)/100000 -> 6.5160594
A10: 300 | B10: =(TCO!$C$90+TCO!$C$91*B$5+TCO!$C$92*B$5*$A10)/100000 -> 5.2079685 | C10: =(TCO!$C$90+TCO!$C$91*C$5+TCO!$C$92*C$5*$A10)/100000 -> 5.8530102 | D10: =(TCO!$C$90+TCO!$C$91*D$5+TCO!$C$92*D$5*$A10)/100000 -> 6.4980518 | E10: =(TCO!$C$90+TCO!$C$91*E$5+TCO!$C$92*E$5*$A10)/100000 -> 7.1430935 | F10: =(TCO!$C$90+TCO!$C$91*F$5+TCO!$C$92*F$5*$A10)/100000 -> 7.7881352
A11: 400 | B11: =(TCO!$C$90+TCO!$C$91*B$5+TCO!$C$92*B$5*$A11)/100000 -> 6.2983192 | C11: =(TCO!$C$90+TCO!$C$91*C$5+TCO!$C$92*C$5*$A11)/100000 -> 7.3068111 | D11: =(TCO!$C$90+TCO!$C$91*D$5+TCO!$C$92*D$5*$A11)/100000 -> 8.315303 | E11: =(TCO!$C$90+TCO!$C$91*E$5+TCO!$C$92*E$5*$A11)/100000 -> 9.3237948 | F11: =(TCO!$C$90+TCO!$C$91*F$5+TCO!$C$92*F$5*$A11)/100000 -> 10.332287
A12: 500 | B12: =(TCO!$C$90+TCO!$C$91*B$5+TCO!$C$92*B$5*$A12)/100000 -> 7.3886699 | C12: =(TCO!$C$90+TCO!$C$91*C$5+TCO!$C$92*C$5*$A12)/100000 -> 8.760612 | D12: =(TCO!$C$90+TCO!$C$91*D$5+TCO!$C$92*D$5*$A12)/100000 -> 10.132554 | E12: =(TCO!$C$90+TCO!$C$91*E$5+TCO!$C$92*E$5*$A12)/100000 -> 11.504496 | F12: =(TCO!$C$90+TCO!$C$91*F$5+TCO!$C$92*F$5*$A12)/100000 -> 12.876438
A13: 600 | B13: =(TCO!$C$90+TCO!$C$91*B$5+TCO!$C$92*B$5*$A13)/100000 -> 8.4790205 | C13: =(TCO!$C$90+TCO!$C$91*C$5+TCO!$C$92*C$5*$A13)/100000 -> 10.214413 | D13: =(TCO!$C$90+TCO!$C$91*D$5+TCO!$C$92*D$5*$A13)/100000 -> 11.949805 | E13: =(TCO!$C$90+TCO!$C$91*E$5+TCO!$C$92*E$5*$A13)/100000 -> 13.685198 | F13: =(TCO!$C$90+TCO!$C$91*F$5+TCO!$C$92*F$5*$A13)/100000 -> 15.42059
A14: 800 | B14: =(TCO!$C$90+TCO!$C$91*B$5+TCO!$C$92*B$5*$A14)/100000 -> 10.659722 | C14: =(TCO!$C$90+TCO!$C$91*C$5+TCO!$C$92*C$5*$A14)/100000 -> 13.122015 | D14: =(TCO!$C$90+TCO!$C$91*D$5+TCO!$C$92*D$5*$A14)/100000 -> 15.584307 | E14: =(TCO!$C$90+TCO!$C$91*E$5+TCO!$C$92*E$5*$A14)/100000 -> 18.0466 | F14: =(TCO!$C$90+TCO!$C$91*F$5+TCO!$C$92*F$5*$A14)/100000 -> 20.508893
A17: Grid 2: retrofit minus sell-and-buy-BEV (Rs lakh) by year-1 hydrogen price (rows) and BEV price in Rs lakh (columns)
A18: Rs/kg \ BEV price | B18: 9 | C18: 10 | D18: 11 | E18: 12 | F18: 13 | G18: 14
A19: 100 | B19: =(TCO!$C$94-(B$18*100000-Inputs!$F$44)+TCO!$C$95*TCO!$D$6+TCO!$C$92*TCO!$D$6*$A19)/100000 -> 3.7139401 | C19: =(TCO!$C$94-(C$18*100000-Inputs!$F$44)+TCO!$C$95*TCO!$D$6+TCO!$C$92*TCO!$D$6*$A19)/100000 -> 2.7139401 | D19: =(TCO!$C$94-(D$18*100000-Inputs!$F$44)+TCO!$C$95*TCO!$D$6+TCO!$C$92*TCO!$D$6*$A19)/100000 -> 1.7139401 | E19: =(TCO!$C$94-(E$18*100000-Inputs!$F$44)+TCO!$C$95*TCO!$D$6+TCO!$C$92*TCO!$D$6*$A19)/100000 -> 0.71394015 | F19: =(TCO!$C$94-(F$18*100000-Inputs!$F$44)+TCO!$C$95*TCO!$D$6+TCO!$C$92*TCO!$D$6*$A19)/100000 -> -0.28605985 | G19: =(TCO!$C$94-(G$18*100000-Inputs!$F$44)+TCO!$C$95*TCO!$D$6+TCO!$C$92*TCO!$D$6*$A19)/100000 -> -1.2860599
A20: 150 | B20: =(TCO!$C$94-(B$18*100000-Inputs!$F$44)+TCO!$C$95*TCO!$D$6+TCO!$C$92*TCO!$D$6*$A20)/100000 -> 4.7154272 | C20: =(TCO!$C$94-(C$18*100000-Inputs!$F$44)+TCO!$C$95*TCO!$D$6+TCO!$C$92*TCO!$D$6*$A20)/100000 -> 3.7154272 | D20: =(TCO!$C$94-(D$18*100000-Inputs!$F$44)+TCO!$C$95*TCO!$D$6+TCO!$C$92*TCO!$D$6*$A20)/100000 -> 2.7154272 | E20: =(TCO!$C$94-(E$18*100000-Inputs!$F$44)+TCO!$C$95*TCO!$D$6+TCO!$C$92*TCO!$D$6*$A20)/100000 -> 1.7154272 | F20: =(TCO!$C$94-(F$18*100000-Inputs!$F$44)+TCO!$C$95*TCO!$D$6+TCO!$C$92*TCO!$D$6*$A20)/100000 -> 0.71542723 | G20: =(TCO!$C$94-(G$18*100000-Inputs!$F$44)+TCO!$C$95*TCO!$D$6+TCO!$C$92*TCO!$D$6*$A20)/100000 -> -0.28457277
A21: 200 | B21: =(TCO!$C$94-(B$18*100000-Inputs!$F$44)+TCO!$C$95*TCO!$D$6+TCO!$C$92*TCO!$D$6*$A21)/100000 -> 5.7169143 | C21: =(TCO!$C$94-(C$18*100000-Inputs!$F$44)+TCO!$C$95*TCO!$D$6+TCO!$C$92*TCO!$D$6*$A21)/100000 -> 4.7169143 | D21: =(TCO!$C$94-(D$18*100000-Inputs!$F$44)+TCO!$C$95*TCO!$D$6+TCO!$C$92*TCO!$D$6*$A21)/100000 -> 3.7169143 | E21: =(TCO!$C$94-(E$18*100000-Inputs!$F$44)+TCO!$C$95*TCO!$D$6+TCO!$C$92*TCO!$D$6*$A21)/100000 -> 2.7169143 | F21: =(TCO!$C$94-(F$18*100000-Inputs!$F$44)+TCO!$C$95*TCO!$D$6+TCO!$C$92*TCO!$D$6*$A21)/100000 -> 1.7169143 | G21: =(TCO!$C$94-(G$18*100000-Inputs!$F$44)+TCO!$C$95*TCO!$D$6+TCO!$C$92*TCO!$D$6*$A21)/100000 -> 0.71691432
A22: 250 | B22: =(TCO!$C$94-(B$18*100000-Inputs!$F$44)+TCO!$C$95*TCO!$D$6+TCO!$C$92*TCO!$D$6*$A22)/100000 -> 6.7184014 | C22: =(TCO!$C$94-(C$18*100000-Inputs!$F$44)+TCO!$C$95*TCO!$D$6+TCO!$C$92*TCO!$D$6*$A22)/100000 -> 5.7184014 | D22: =(TCO!$C$94-(D$18*100000-Inputs!$F$44)+TCO!$C$95*TCO!$D$6+TCO!$C$92*TCO!$D$6*$A22)/100000 -> 4.7184014 | E22: =(TCO!$C$94-(E$18*100000-Inputs!$F$44)+TCO!$C$95*TCO!$D$6+TCO!$C$92*TCO!$D$6*$A22)/100000 -> 3.7184014 | F22: =(TCO!$C$94-(F$18*100000-Inputs!$F$44)+TCO!$C$95*TCO!$D$6+TCO!$C$92*TCO!$D$6*$A22)/100000 -> 2.7184014 | G22: =(TCO!$C$94-(G$18*100000-Inputs!$F$44)+TCO!$C$95*TCO!$D$6+TCO!$C$92*TCO!$D$6*$A22)/100000 -> 1.7184014
A23: 300 | B23: =(TCO!$C$94-(B$18*100000-Inputs!$F$44)+TCO!$C$95*TCO!$D$6+TCO!$C$92*TCO!$D$6*$A23)/100000 -> 7.7198885 | C23: =(TCO!$C$94-(C$18*100000-Inputs!$F$44)+TCO!$C$95*TCO!$D$6+TCO!$C$92*TCO!$D$6*$A23)/100000 -> 6.7198885 | D23: =(TCO!$C$94-(D$18*100000-Inputs!$F$44)+TCO!$C$95*TCO!$D$6+TCO!$C$92*TCO!$D$6*$A23)/100000 -> 5.7198885 | E23: =(TCO!$C$94-(E$18*100000-Inputs!$F$44)+TCO!$C$95*TCO!$D$6+TCO!$C$92*TCO!$D$6*$A23)/100000 -> 4.7198885 | F23: =(TCO!$C$94-(F$18*100000-Inputs!$F$44)+TCO!$C$95*TCO!$D$6+TCO!$C$92*TCO!$D$6*$A23)/100000 -> 3.7198885 | G23: =(TCO!$C$94-(G$18*100000-Inputs!$F$44)+TCO!$C$95*TCO!$D$6+TCO!$C$92*TCO!$D$6*$A23)/100000 -> 2.7198885
A24: 400 | B24: =(TCO!$C$94-(B$18*100000-Inputs!$F$44)+TCO!$C$95*TCO!$D$6+TCO!$C$92*TCO!$D$6*$A24)/100000 -> 9.7228627 | C24: =(TCO!$C$94-(C$18*100000-Inputs!$F$44)+TCO!$C$95*TCO!$D$6+TCO!$C$92*TCO!$D$6*$A24)/100000 -> 8.7228627 | D24: =(TCO!$C$94-(D$18*100000-Inputs!$F$44)+TCO!$C$95*TCO!$D$6+TCO!$C$92*TCO!$D$6*$A24)/100000 -> 7.7228627 | E24: =(TCO!$C$94-(E$18*100000-Inputs!$F$44)+TCO!$C$95*TCO!$D$6+TCO!$C$92*TCO!$D$6*$A24)/100000 -> 6.7228627 | F24: =(TCO!$C$94-(F$18*100000-Inputs!$F$44)+TCO!$C$95*TCO!$D$6+TCO!$C$92*TCO!$D$6*$A24)/100000 -> 5.7228627 | G24: =(TCO!$C$94-(G$18*100000-Inputs!$F$44)+TCO!$C$95*TCO!$D$6+TCO!$C$92*TCO!$D$6*$A24)/100000 -> 4.7228627
A25: 500 | B25: =(TCO!$C$94-(B$18*100000-Inputs!$F$44)+TCO!$C$95*TCO!$D$6+TCO!$C$92*TCO!$D$6*$A25)/100000 -> 11.725837 | C25: =(TCO!$C$94-(C$18*100000-Inputs!$F$44)+TCO!$C$95*TCO!$D$6+TCO!$C$92*TCO!$D$6*$A25)/100000 -> 10.725837 | D25: =(TCO!$C$94-(D$18*100000-Inputs!$F$44)+TCO!$C$95*TCO!$D$6+TCO!$C$92*TCO!$D$6*$A25)/100000 -> 9.7258368 | E25: =(TCO!$C$94-(E$18*100000-Inputs!$F$44)+TCO!$C$95*TCO!$D$6+TCO!$C$92*TCO!$D$6*$A25)/100000 -> 8.7258368 | F25: =(TCO!$C$94-(F$18*100000-Inputs!$F$44)+TCO!$C$95*TCO!$D$6+TCO!$C$92*TCO!$D$6*$A25)/100000 -> 7.7258368 | G25: =(TCO!$C$94-(G$18*100000-Inputs!$F$44)+TCO!$C$95*TCO!$D$6+TCO!$C$92*TCO!$D$6*$A25)/100000 -> 6.7258368
A26: 600 | B26: =(TCO!$C$94-(B$18*100000-Inputs!$F$44)+TCO!$C$95*TCO!$D$6+TCO!$C$92*TCO!$D$6*$A26)/100000 -> 13.728811 | C26: =(TCO!$C$94-(C$18*100000-Inputs!$F$44)+TCO!$C$95*TCO!$D$6+TCO!$C$92*TCO!$D$6*$A26)/100000 -> 12.728811 | D26: =(TCO!$C$94-(D$18*100000-Inputs!$F$44)+TCO!$C$95*TCO!$D$6+TCO!$C$92*TCO!$D$6*$A26)/100000 -> 11.728811 | E26: =(TCO!$C$94-(E$18*100000-Inputs!$F$44)+TCO!$C$95*TCO!$D$6+TCO!$C$92*TCO!$D$6*$A26)/100000 -> 10.728811 | F26: =(TCO!$C$94-(F$18*100000-Inputs!$F$44)+TCO!$C$95*TCO!$D$6+TCO!$C$92*TCO!$D$6*$A26)/100000 -> 9.728811 | G26: =(TCO!$C$94-(G$18*100000-Inputs!$F$44)+TCO!$C$95*TCO!$D$6+TCO!$C$92*TCO!$D$6*$A26)/100000 -> 8.728811
A27: 800 | B27: =(TCO!$C$94-(B$18*100000-Inputs!$F$44)+TCO!$C$95*TCO!$D$6+TCO!$C$92*TCO!$D$6*$A27)/100000 -> 17.734759 | C27: =(TCO!$C$94-(C$18*100000-Inputs!$F$44)+TCO!$C$95*TCO!$D$6+TCO!$C$92*TCO!$D$6*$A27)/100000 -> 16.734759 | D27: =(TCO!$C$94-(D$18*100000-Inputs!$F$44)+TCO!$C$95*TCO!$D$6+TCO!$C$92*TCO!$D$6*$A27)/100000 -> 15.734759 | E27: =(TCO!$C$94-(E$18*100000-Inputs!$F$44)+TCO!$C$95*TCO!$D$6+TCO!$C$92*TCO!$D$6*$A27)/100000 -> 14.734759 | F27: =(TCO!$C$94-(F$18*100000-Inputs!$F$44)+TCO!$C$95*TCO!$D$6+TCO!$C$92*TCO!$D$6*$A27)/100000 -> 13.734759 | G27: =(TCO!$C$94-(G$18*100000-Inputs!$F$44)+TCO!$C$95*TCO!$D$6+TCO!$C$92*TCO!$D$6*$A27)/100000 -> 12.734759
A30: Grid 3: retrofit minus continue-on-CNG (Rs lakh) by year-1 hydrogen price (rows) and installed kit cost in Rs lakh (columns)
A31: Rs/kg \ kit cost | B31: 1.5 | C31: 2 | D31: 2.5 | E31: 3 | F31: 4 | G31: 6
A32: 100 | B32: =(TCO!$C$90+(B$31*100000-Inputs!$F$28)+TCO!$C$91*TCO!$D$6+TCO!$C$92*TCO!$D$6*$A32)/100000 -> 1.100485 | C32: =(TCO!$C$90+(C$31*100000-Inputs!$F$28)+TCO!$C$91*TCO!$D$6+TCO!$C$92*TCO!$D$6*$A32)/100000 -> 1.600485 | D32: =(TCO!$C$90+(D$31*100000-Inputs!$F$28)+TCO!$C$91*TCO!$D$6+TCO!$C$92*TCO!$D$6*$A32)/100000 -> 2.100485 | E32: =(TCO!$C$90+(E$31*100000-Inputs!$F$28)+TCO!$C$91*TCO!$D$6+TCO!$C$92*TCO!$D$6*$A32)/100000 -> 2.600485 | F32: =(TCO!$C$90+(F$31*100000-Inputs!$F$28)+TCO!$C$91*TCO!$D$6+TCO!$C$92*TCO!$D$6*$A32)/100000 -> 3.600485 | G32: =(TCO!$C$90+(G$31*100000-Inputs!$F$28)+TCO!$C$91*TCO!$D$6+TCO!$C$92*TCO!$D$6*$A32)/100000 -> 5.600485
A33: 150 | B33: =(TCO!$C$90+(B$31*100000-Inputs!$F$28)+TCO!$C$91*TCO!$D$6+TCO!$C$92*TCO!$D$6*$A33)/100000 -> 2.1019721 | C33: =(TCO!$C$90+(C$31*100000-Inputs!$F$28)+TCO!$C$91*TCO!$D$6+TCO!$C$92*TCO!$D$6*$A33)/100000 -> 2.6019721 | D33: =(TCO!$C$90+(D$31*100000-Inputs!$F$28)+TCO!$C$91*TCO!$D$6+TCO!$C$92*TCO!$D$6*$A33)/100000 -> 3.1019721 | E33: =(TCO!$C$90+(E$31*100000-Inputs!$F$28)+TCO!$C$91*TCO!$D$6+TCO!$C$92*TCO!$D$6*$A33)/100000 -> 3.6019721 | F33: =(TCO!$C$90+(F$31*100000-Inputs!$F$28)+TCO!$C$91*TCO!$D$6+TCO!$C$92*TCO!$D$6*$A33)/100000 -> 4.6019721 | G33: =(TCO!$C$90+(G$31*100000-Inputs!$F$28)+TCO!$C$91*TCO!$D$6+TCO!$C$92*TCO!$D$6*$A33)/100000 -> 6.6019721
A34: 200 | B34: =(TCO!$C$90+(B$31*100000-Inputs!$F$28)+TCO!$C$91*TCO!$D$6+TCO!$C$92*TCO!$D$6*$A34)/100000 -> 3.1034592 | C34: =(TCO!$C$90+(C$31*100000-Inputs!$F$28)+TCO!$C$91*TCO!$D$6+TCO!$C$92*TCO!$D$6*$A34)/100000 -> 3.6034592 | D34: =(TCO!$C$90+(D$31*100000-Inputs!$F$28)+TCO!$C$91*TCO!$D$6+TCO!$C$92*TCO!$D$6*$A34)/100000 -> 4.1034592 | E34: =(TCO!$C$90+(E$31*100000-Inputs!$F$28)+TCO!$C$91*TCO!$D$6+TCO!$C$92*TCO!$D$6*$A34)/100000 -> 4.6034592 | F34: =(TCO!$C$90+(F$31*100000-Inputs!$F$28)+TCO!$C$91*TCO!$D$6+TCO!$C$92*TCO!$D$6*$A34)/100000 -> 5.6034592 | G34: =(TCO!$C$90+(G$31*100000-Inputs!$F$28)+TCO!$C$91*TCO!$D$6+TCO!$C$92*TCO!$D$6*$A34)/100000 -> 7.6034592
A35: 250 | B35: =(TCO!$C$90+(B$31*100000-Inputs!$F$28)+TCO!$C$91*TCO!$D$6+TCO!$C$92*TCO!$D$6*$A35)/100000 -> 4.1049462 | C35: =(TCO!$C$90+(C$31*100000-Inputs!$F$28)+TCO!$C$91*TCO!$D$6+TCO!$C$92*TCO!$D$6*$A35)/100000 -> 4.6049462 | D35: =(TCO!$C$90+(D$31*100000-Inputs!$F$28)+TCO!$C$91*TCO!$D$6+TCO!$C$92*TCO!$D$6*$A35)/100000 -> 5.1049462 | E35: =(TCO!$C$90+(E$31*100000-Inputs!$F$28)+TCO!$C$91*TCO!$D$6+TCO!$C$92*TCO!$D$6*$A35)/100000 -> 5.6049462 | F35: =(TCO!$C$90+(F$31*100000-Inputs!$F$28)+TCO!$C$91*TCO!$D$6+TCO!$C$92*TCO!$D$6*$A35)/100000 -> 6.6049462 | G35: =(TCO!$C$90+(G$31*100000-Inputs!$F$28)+TCO!$C$91*TCO!$D$6+TCO!$C$92*TCO!$D$6*$A35)/100000 -> 8.6049462
A36: 300 | B36: =(TCO!$C$90+(B$31*100000-Inputs!$F$28)+TCO!$C$91*TCO!$D$6+TCO!$C$92*TCO!$D$6*$A36)/100000 -> 5.1064333 | C36: =(TCO!$C$90+(C$31*100000-Inputs!$F$28)+TCO!$C$91*TCO!$D$6+TCO!$C$92*TCO!$D$6*$A36)/100000 -> 5.6064333 | D36: =(TCO!$C$90+(D$31*100000-Inputs!$F$28)+TCO!$C$91*TCO!$D$6+TCO!$C$92*TCO!$D$6*$A36)/100000 -> 6.1064333 | E36: =(TCO!$C$90+(E$31*100000-Inputs!$F$28)+TCO!$C$91*TCO!$D$6+TCO!$C$92*TCO!$D$6*$A36)/100000 -> 6.6064333 | F36: =(TCO!$C$90+(F$31*100000-Inputs!$F$28)+TCO!$C$91*TCO!$D$6+TCO!$C$92*TCO!$D$6*$A36)/100000 -> 7.6064333 | G36: =(TCO!$C$90+(G$31*100000-Inputs!$F$28)+TCO!$C$91*TCO!$D$6+TCO!$C$92*TCO!$D$6*$A36)/100000 -> 9.6064333
A37: 400 | B37: =(TCO!$C$90+(B$31*100000-Inputs!$F$28)+TCO!$C$91*TCO!$D$6+TCO!$C$92*TCO!$D$6*$A37)/100000 -> 7.1094075 | C37: =(TCO!$C$90+(C$31*100000-Inputs!$F$28)+TCO!$C$91*TCO!$D$6+TCO!$C$92*TCO!$D$6*$A37)/100000 -> 7.6094075 | D37: =(TCO!$C$90+(D$31*100000-Inputs!$F$28)+TCO!$C$91*TCO!$D$6+TCO!$C$92*TCO!$D$6*$A37)/100000 -> 8.1094075 | E37: =(TCO!$C$90+(E$31*100000-Inputs!$F$28)+TCO!$C$91*TCO!$D$6+TCO!$C$92*TCO!$D$6*$A37)/100000 -> 8.6094075 | F37: =(TCO!$C$90+(F$31*100000-Inputs!$F$28)+TCO!$C$91*TCO!$D$6+TCO!$C$92*TCO!$D$6*$A37)/100000 -> 9.6094075 | G37: =(TCO!$C$90+(G$31*100000-Inputs!$F$28)+TCO!$C$91*TCO!$D$6+TCO!$C$92*TCO!$D$6*$A37)/100000 -> 11.609408
A38: 500 | B38: =(TCO!$C$90+(B$31*100000-Inputs!$F$28)+TCO!$C$91*TCO!$D$6+TCO!$C$92*TCO!$D$6*$A38)/100000 -> 9.1123817 | C38: =(TCO!$C$90+(C$31*100000-Inputs!$F$28)+TCO!$C$91*TCO!$D$6+TCO!$C$92*TCO!$D$6*$A38)/100000 -> 9.6123817 | D38: =(TCO!$C$90+(D$31*100000-Inputs!$F$28)+TCO!$C$91*TCO!$D$6+TCO!$C$92*TCO!$D$6*$A38)/100000 -> 10.112382 | E38: =(TCO!$C$90+(E$31*100000-Inputs!$F$28)+TCO!$C$91*TCO!$D$6+TCO!$C$92*TCO!$D$6*$A38)/100000 -> 10.612382 | F38: =(TCO!$C$90+(F$31*100000-Inputs!$F$28)+TCO!$C$91*TCO!$D$6+TCO!$C$92*TCO!$D$6*$A38)/100000 -> 11.612382 | G38: =(TCO!$C$90+(G$31*100000-Inputs!$F$28)+TCO!$C$91*TCO!$D$6+TCO!$C$92*TCO!$D$6*$A38)/100000 -> 13.612382
A39: 600 | B39: =(TCO!$C$90+(B$31*100000-Inputs!$F$28)+TCO!$C$91*TCO!$D$6+TCO!$C$92*TCO!$D$6*$A39)/100000 -> 11.115356 | C39: =(TCO!$C$90+(C$31*100000-Inputs!$F$28)+TCO!$C$91*TCO!$D$6+TCO!$C$92*TCO!$D$6*$A39)/100000 -> 11.615356 | D39: =(TCO!$C$90+(D$31*100000-Inputs!$F$28)+TCO!$C$91*TCO!$D$6+TCO!$C$92*TCO!$D$6*$A39)/100000 -> 12.115356 | E39: =(TCO!$C$90+(E$31*100000-Inputs!$F$28)+TCO!$C$91*TCO!$D$6+TCO!$C$92*TCO!$D$6*$A39)/100000 -> 12.615356 | F39: =(TCO!$C$90+(F$31*100000-Inputs!$F$28)+TCO!$C$91*TCO!$D$6+TCO!$C$92*TCO!$D$6*$A39)/100000 -> 13.615356 | G39: =(TCO!$C$90+(G$31*100000-Inputs!$F$28)+TCO!$C$91*TCO!$D$6+TCO!$C$92*TCO!$D$6*$A39)/100000 -> 15.615356
A40: 800 | B40: =(TCO!$C$90+(B$31*100000-Inputs!$F$28)+TCO!$C$91*TCO!$D$6+TCO!$C$92*TCO!$D$6*$A40)/100000 -> 15.121304 | C40: =(TCO!$C$90+(C$31*100000-Inputs!$F$28)+TCO!$C$91*TCO!$D$6+TCO!$C$92*TCO!$D$6*$A40)/100000 -> 15.621304 | D40: =(TCO!$C$90+(D$31*100000-Inputs!$F$28)+TCO!$C$91*TCO!$D$6+TCO!$C$92*TCO!$D$6*$A40)/100000 -> 16.121304 | E40: =(TCO!$C$90+(E$31*100000-Inputs!$F$28)+TCO!$C$91*TCO!$D$6+TCO!$C$92*TCO!$D$6*$A40)/100000 -> 16.621304 | F40: =(TCO!$C$90+(F$31*100000-Inputs!$F$28)+TCO!$C$91*TCO!$D$6+TCO!$C$92*TCO!$D$6*$A40)/100000 -> 17.621304 | G40: =(TCO!$C$90+(G$31*100000-Inputs!$F$28)+TCO!$C$91*TCO!$D$6+TCO!$C$92*TCO!$D$6*$A40)/100000 -> 19.621304
A43: One-at-a-time sensitivities: extra cost of retrofit versus continuing on CNG (Rs lakh), other inputs at active values
A44: Driver | B44: Low value | C44: High value | D44: Extra cost at low | E44: Extra cost at high | F44: Note
A45: Year-1 delivered hydrogen price (Rs/kg) | B45: =Inputs!$E$35 -> 550 | C45: =Inputs!$D$35 -> 1000 | D45: =(TCO!$C$90+TCO!$C$91*TCO!$D$6+TCO!$C$92*TCO!$D$6*B45)/100000 -> 11.835104 | E45: =(TCO!$C$90+TCO!$C$91*TCO!$D$6+TCO!$C$92*TCO!$D$6*C45)/100000 -> 20.848487 | F45: Upside and downside inputs
A46: Installed kit cost (Rs) | B46: =Inputs!$E$28 -> 273804.96 | C46: =Inputs!$D$28 -> 402654.35 | D46: =(TCO!$C$65+(B46-Inputs!$F$28))/100000 -> 16.359354 | E46: =(TCO!$C$65+(C46-Inputs!$F$28))/100000 -> 17.647848
A47: Annual km | B47: =30000 -> 30000 | C47: =70000 -> 70000 | D47: =(TCO!$C$90+TCO!$C$91*B47+TCO!$C$92*B47*Inputs!$F$35)/100000 -> 10.659722 | E47: =(TCO!$C$90+TCO!$C$91*C47+TCO!$C$92*C47*Inputs!$F$35)/100000 -> 20.508893 | F47: More km increases the fuel-cost penalty at current hydrogen prices
A48: Hydrogen consumption (kg/100 km) | B48: =Inputs!$E$33 -> 1.6 | C48: =Inputs!$D$33 -> 2.3 | D48: =(TCO!$C$65+TCO!$C$92*(B48/Inputs!$F$33-1)*TCO!$D$6*Inputs!$F$35)/100000 -> 14.677162 | E48: =(TCO!$C$65+TCO!$C$92*(C48/Inputs!$F$33-1)*TCO!$D$6*Inputs!$F$35)/100000 -> 20.740218 | F48: Scales the hydrogen term
A49: CNG price (Rs/kg) | B49: =Inputs!$E$18 -> 95 | C49: =Inputs!$D$18 -> 78 | D49: =(TCO!$C$65-(B49/Inputs!$F$18-1)*SUMPRODUCT(TCO!$D$8:$H$8,TCO!$D$5:$H$5)*TCO!$D$6*(1-Inputs!$F$22)/Inputs!$F$19)/100000 -> 16.205542 | E49: =(TCO!$C$65-(C49/Inputs!$F$18-1)*SUMPRODUCT(TCO!$D$8:$H$8,TCO!$D$5:$H$5)*TCO!$D$6*(1-Inputs!$F$22)/Inputs!$F$19)/100000 -> 17.559161 | F49: Dearer CNG helps the retrofit
A50: Share of km on hydrogen | B50: =Inputs!$E$34 -> 0.85 | C50: =Inputs!$D$34 -> 0.5 | D50: =(TCO!$C$65+(B50-Inputs!$F$34)*TCO!$D$6*(Inputs!$F$33/100*SUMPRODUCT(TCO!$D$9:$H$9,TCO!$D$5:$H$5)-SUMPRODUCT(TCO!$D$7:$H$7,TCO!$D$5:$H$5)/Inputs!$F$21))/100000 -> 18.923214 | E50: =(TCO!$C$65+(C50-Inputs!$F$34)*TCO!$D$6*(Inputs!$F$33/100*SUMPRODUCT(TCO!$D$9:$H$9,TCO!$D$5:$H$5)-SUMPRODUCT(TCO!$D$7:$H$7,TCO!$D$5:$H$5)/Inputs!$F$21))/100000 -> 15.282033 | F50: At current prices, more hydrogen km cost more than petrol km

Sheet Donor_Tech
A1: Donor platform and technology-route comparison
A2: Donor figures are manufacturer-declared unless marked third-party; hydrogen figures are model outputs.
A4: Criterion | B4: Dzire Tour S CNG (primary) | C4: WagonR S-CNG / Tour H3 | D4: Ertiga S-CNG / Tour M | E4: Eeco CNG | F4: Source / note
A5: Engine | B5: 1197 cc, 4-cyl K12N | C5: 998 cc, 3-cyl K10C | D5: 1462 cc, 4-cyl K15C | E5: 1197 cc, 4-cyl K12N | F5: S-DONOR
A6: Power petrol / CNG (PS) | B6: 81.6 / ~70 (CNG third-party) | C6: ~66 / ~57 (CNG third-party) | D6: 103 / 87.8 | E6: 82 / n.a. | F6: S-DONOR; official CNG ratings for 1.0 and 1.2 L cars not captured
A7: Kerb mass CNG (kg) | B7: ~1045 (third-party) | C7: ~850-930 | D7: 1250-1255 | E7: 1085 | F7: S-DONOR
A8: Gross vehicle weight (kg) | B8: 1375 (Dzire S-CNG) | C8: 1340 | D8: 1820 | E8: n.a. | F8: S-DONOR
A9: CNG cylinder water volume (L) and location | B9: 55, boot, transverse | C9: 60, boot | D9: 60, boot | E9: 65, under rear floor area | F9: S-DONOR
A10: Boot volume without cylinder (L) | B10: 382 | C10: 335 | D10: 209 (3rd row up) | E10: van | F10: S-DONOR
A11: Declared CNG economy (km/kg) | B11: 32.1 | C11: 34.4 | D11: 26.5 | E11: 27.0 | F11: S-DONOR (MIDC declared); fleet real-world 24-30
A12: Ground clearance (mm) | B12: 163 | C12: 165 | D12: 185 | E12: 160 | F12: Under-floor hydrogen cylinders not credible; boot bay only
A13: Fleet presence (taxi / aggregator) | B13: Very high (app cabs, airport) | C13: High (Delhi taxis, private) | D13: Medium (outstation, 7 seats) | E13: Medium (tier-2 taxi, school van) | F13: Qualitative
A14: Hydrogen cylinder that fits the bay (350 bar) | B14: 60 L composite, OD 400 x 767 mm | C14: 60 L composite | D14: 60-74 L composite | E14: 60-74 L composite | F14: Luxfer G-Stor Pro V060H35 example: 36 kg, 1.45 kg H2 (S-CYL)
A15: Power margin after 45 percent hydrogen derate | B15: adequate for urban duty | C15: marginal (3-cyl, 41 PS) | D15: best (48 PS) | E15: adequate | F15: Model estimate
A16: Verdict as first donor | B16: PRIMARY: fleet workhorse, 4-cyl, sedan boot | C16: Alternative: private/taxi hatch, weakest power | D16: Alternative for larger storage (2 cylinders, 5-seat mode) | E16: Alternative for tier-2 fleets
A19: Technology route comparison for the same donor and duty (matched criteria)
A20: Criterion | B20: H2-ICE retrofit (selected) | C20: Fuel-cell conversion | D20: New BEV (sell donor) | E20: Continue on CNG | F20: Basis
A21: What changes | B21: Fuel storage and delivery, injectors, ECU, sensors; engine retained | C21: Entire powertrain: stack, battery, motor, inverter, cooling, tank, controls | D21: New vehicle | E21: Nothing | F21: Engineering scope
A22: Conversion or purchase cost (Rs lakh, model) | B22: =BOM!$F$42 -> 3.2212348 | C22: 15 to 25 (pilot), 8 to 12 (volume) | D22: =Inputs!$F$44/100000 -> 10.5 | E22: 0 | F22: BOM; fuel-cell figures are estimates from stack and battery cost literature (S-FCCOST)
A23: Energy cost per km, year 1 (Rs/km) | B23: =TCO!$C$72 -> 12 | C23: about half of H2-ICE per km on hydrogen | D23: =TCO!$C$71 -> 1.53 | E23: =TCO!$C$73 -> 3.646 | F23: TCO sheet
A24: Range per fill or charge (km) | B24: =Energy_Range!$B$17 -> 60.648649 | C24: about 2x H2-ICE for same tank | D24: 187 to 260 (Tiago EV, Punch EV tests) | E24: about 250 on CNG at 25 km/kg | F24: Energy_Range; Autocar India real-world tests (W3-S30)
A25: Refuel or recharge time | B25: 3 to 5 min (350 bar, non-cooled fill) | C25: 3 to 5 min | D25: about 58 min 10-80 percent DC (Tiago EV 24 kWh); 6-8 h AC | E25: 3 to 5 min | F25: SAE J2601; Tata specifications (W3-S27)
A26: Peak power versus petrol | B26: =Inputs!$F$70 -> 0.52 | C26: restored (electric drive) | D26: typically higher | E26: about 0.85 | F26: Model / spec
A27: Tailpipe CO2 on hydrogen km | B27: zero (NOx present) | C27: zero (water only) | D27: zero | E27: about 105 g/km | F27: Emissions sheet
A28: Approval route today | B28: None for retrofit; new-vehicle standard AIS-195 exists | C28: None for retrofit; AIS-157 covers new FCEVs | D28: Established | E28: Established | F28: WS2 findings
A29: Supplier readiness | B29: Injectors, valves, regulators production-intent; small cylinders scarce | C29: Stacks imported; no Indian light-duty supply chain | D29: Mature | E29: Mature | F29: WS1/WS3
A30: Verdict | B30: Selected: only route that is a retrofit at an affordable scope; economics hinge on hydrogen price | C30: Not a retrofit in cost terms; equals a new vehicle | D30: Benchmark to beat; lowest running cost | E30: Baseline

Sheet Sources
A1: Source register
A2: Access date 14 September 2026 unless noted. Status: observed / modelled / target / announced / spec / regulation. 'excerpt' or 'summary' in Limitations means the original could not be opened in the build environment.
A4: ID | B4: Claim / input supported | C4: Publisher | D4: Document title | E4: URL | F4: Publication / data date | G4: Page / table / section | H4: Geography | I4: Unit | J4: Status | K4: Limitations
A5: W1-S1 | B5: Hexagon Type IV cylinder dimensions/mass/H2 capacity (350 & 700 bar) | C5: Hexagon Purus | D5: Hydrogen Type 4 cylinder information | E5: https://s3.eu-central-1.amazonaws.com/hexagonpurus-website/HPU_0222_12_HydrogenType4_Tabelle_2pages.pdf | F5: REV. 08/22 | G5: p.2 table | H5: Global (Canada/Germany/USA plants) | I5: bar, mm, kg, L | J5: spec | K5: "frequently built units; minimum quantities may apply"
A6: W1-S2 | B6: Luxfer Type III 350 bar 60/74/205 L cylinders | C6: Luxfer Gas Cylinders | D6: G-Stor Pro H2 Type 3 (EU) spec table | E6: https://www.luxfercylinders.com/product/g-stor-h2-hydrogen-cylinders/ | F6: 2023–25 (page) | G6: EU table | H6: EU | I6: bar, mm, kg, L | J6: spec | K6: Firecrawl excerpt; Type III not Type IV
A7: W1-S3a | B7: Tour S petrol power/torque, FE, tanks, GC | C7: Maruti Suzuki | D7: Dzire Tour S page / Maruti Suzuki Commercial page | E7: https://www.marutisuzuki.com/tour/dzire ; https://www.marutisuzukicommercial.com/dzire-tour-s | F7: 2025–26 | G7: spec block | H7: India | I7: kW, Nm, km/l, L | J7: spec | K7: excerpt; CNG power not in excerpt
A8: W1-S3b | B8: Tour S S-CNG 32.12 km/kg | C8: Maruti Suzuki | D8: Media release: Maruti Suzuki launches the All-new Tour S | E8: https://www.marutisuzuki.com/content/dam/arena-eds/corporate/press-release/assets/documents/2023/february/Media_Release_Maruti_Suzuki_launches_the_All-new_Tour_S.pdf | F8: Feb 2023 | G8: body | H8: India | I8: km/kg | J8: spec (declared) | K8: excerpt
A9: W1-S3c | B9: Dzire 4th gen kerb/GVW/FE/boot/tanks | C9: Maruti Suzuki | D9: Arena Dzire brochure; Dzire price page | E9: https://www.marutisuzuki.com/content/dam/msil/arena/in/en/assets/cars/dzire/documents/Arena-Dzire-Brochure.pdf ; https://www.marutisuzuki.com/arena/dzire/price | F9: 2024–26 | G9: spec table | H9: India | I9: kg, L, km/l, km/kg | J9: spec | K9: excerpt
A10: W1-S3d | B10: WagonR kerb 850, GVW 1340, tank 32, boot 335; engines K10C/K12N | C10: Maruti Suzuki | D10: WagonR price page; WagonR page | E10: https://www.marutisuzuki.com/arena/wagon-r/price ; https://www.marutisuzuki.com/arena/wagon-r | F10: 2025–26 | G10: spec table | H10: India | I10: kg, L | J10: spec | K10: excerpt; variant for kerb/GVW not stated
A11: W1-S3d2 | B11: WagonR Tour H3 25.22 km/l, 34.41 km/kg | C11: Maruti Suzuki | D11: WagonR Tour H3 page | E11: https://www.marutisuzuki.com/tour/wagonr | F11: 2025–26 | G11: FAQ | H11: India | I11: km/l, km/kg | J11: spec | K11: excerpt
A12: W1-S3e | B12: Swift 1197 cc 60 kW @5700 | C12: Maruti Suzuki | D12: Swift page | E12: https://www.marutisuzuki.com/arena/swift | F12: 2025–26 | G12: spec | H12: India | I12: kW | J12: spec | K12: excerpt
A13: W1-S3f | B13: Ertiga 1462 cc, 75.8 kW @6000, 139 Nm @4300 | C13: Maruti Suzuki | D13: Ertiga page | E13: https://www.marutisuzuki.com/arena/ertiga | F13: 2025–26 | G13: spec | H13: India | I13: kW, Nm | J13: spec | K13: excerpt
A14: W1-S3g | B14: 1.5 L K-series S-CNG 64.6 kW @5500, 121.5 Nm | C14: Maruti Suzuki | D14: Press release: All New Brezza S-CNG | E14: https://www.marutisuzuki.com/corporate/media/press-releases/2023/march/maruti-suzuki-introduces-all-new-brezza-s-cng | F14: Mar 2023 | G14: body | H14: India | I14: kW, Nm | J14: spec | K14: same engine as Ertiga S-CNG; excerpt
A15: W1-S3h | B15: Ertiga CNG 121.5 Nm @4200 | C15: Maruti Suzuki | D15: Arena Ertiga brochure | E15: https://www.marutisuzuki.com/content/dam/msil/arena/in/en/assets/cars/ertiga/document/Arena-Ertiga-Brochure.pdf | F15: 2024 | G15: spec | H15: India | I15: Nm | J15: spec | K15: excerpt
... A87: W1-S14e | B87: AIS-024 / AIS-028 Ver.4 CNG code of practice | C87: ARAI (HMR) / MoRTH | D87: AIS-024 (Version 4) AIS-028 (Version 4) | E87: https://hmr.araiindia.com/Control/AIS/825201593205AM4_AIS-024_and_AIS-028_CNG-Ver4_F.pdf | F87: 2015 | G87: — | H87: India | I87: — | J87: standard | K87: blocked
A88: W2-S1 | B88: H-CNG added to CMVR Rule 115; IS 17314:2019 | C88: MoRTH (Gazette); PIB | D88: G.S.R. 585(E) "hydrogen CNG"; PIB "Notification allowing use of H-CNG issued" | E88: https://morth.nic.in/sites/default/files/notifications_document/GSR%20585(E)%2025%20September%202020%20hydrogen%20CNG.pdf ; https://www.pib.gov.in/PressReleasePage.aspx?PRID=1659706 | F88: 25-09-2020 | G88: Rule 115 insertion | H88: India | J88: In force | K88: Blocked; wording from search summary
A89: W2-S2 | B89: IS 17314:2019 H-CNG spec, 18 % H2 | C89: BIS (via PIB/press) | D89: IS 17314:2019 Hydrogen enriched CNG for automotive purposes | E89: (BIS catalogue; not accessed) | F89: 2019 | G89: — | H89: India | J89: In force | K89: 18 % figure from press, not standard text
A90: W2-S3 | B90: Rule 115 CNG kit provisions; s.52 14-day endorsement | C90: Indian Kanoon (CMVR text) | D90: Section 115 / 115B, CMVR 1989 | E90: https://indiankanoon.org/doc/10585089/ ; https://indiankanoon.org/doc/67316961/ | F90: — | G90: Rule 115 (sub-rules not numbered here) | H90: India | J90: In force | K90: Summary only
A91: W2-S4 | B91: ARAI retrofitment certification (Rule 115, Rule 126 agencies) | C91: ARAI | D91: Vehicle Retrofitment Certification in India | E91: https://www.araiindia.com/certification/certification/retrofitment | F91: — | G91: — | H91: India | J91: Current | K91: Blocked
A92: W2-S5 | B92: Retrofit framework (CNG/LPG/EV; AIS-123) | C92: EVreporter (ARAI compiled) | D92: Regulatory Framework for Retrofitting in India | E92: https://evreporter.com/regulatory-framework-for-retrofitting-in-india/ | F92: — | G92: — | H92: India | J92: — | K92: Secondary
A93: W2-S6 | B93: BS-VI CNG/LPG retrofit permitted | C93: MoRTH; PIB; Business Standard | D93: G.S.R. 625(E) "retrofitment in BS VI" | E93: https://morth.gov.in/sites/default/files/notifications_document/7GSR%20625(E)%2011th%20August%202022%20retrofitment%20in%20BS%20VI.pdf ; https://pib.gov.in/PressReleasePage.aspx?PRID=1853835 | F93: 11-08-2022 | G93: — | H93: India | J93: In force | K93: Blocked
A94: W2-S7 | B94: AIS-024/028 Version 4 exist | C94: ARAI (HMR) | D94: AIS-024 (Version 4) / AIS-028 (Version 4) | E94: https://hmr.araiindia.com/Control/AIS/825201593205AM4_AIS-024_and_AIS-028_CNG-Ver4_F.pdf | F94: — | G94: — | H94: India | J94: Published | K94: Blocked; title only
A95: W2-S8 | B95: TA cost Rs 40–50 lakh, 3-yr validity | C95: Autocar Professional | D95: Delays in MoRTH guidelines for BS VI CNG kits hurting retrofit business | E95: https://www.autocarpro.in/news-national/delays-in-morth-guidelines-for-bs-vi-cng-kits-hurting-retrofit-business-92660 | F95: 2022 (approx.) | G95: — | H95: India | J95: — | K95: Industry claim
A96: W2-S9 | B96: Rule 126 provisos (retrofit self-certification; imported CBUs for testing/research) | C96: Commercial Law Publishers (CMVR e-book) | D96: The Central Motor Vehicles Rules, 1989 — page 335 (Rule 126) | E96: https://ebook.commerciallawpublishers.com/fa/cmvr/files/basic-html/page335.html | F96: ed. incl. GSR 221(E) 30-03-2021 | G96: Rule 126 provisos | H96: India | J96: In force (pre-2026 text) | K96: Verbatim via Firecrawl; may pre-date 2026 amendment
A97: W2-S10 | B97: 2026 amendment substituting Rule 126 provisos; self-certification | C97: The Bar Bulletin; TeamLease RegTech | D97: Centre Notifies Changes to Motor Vehicle Type Approval Norms…; Draft CMV (…Amendment) Rules 2025 | E97: https://thebarbulletin.com/centre-revises-motor-vehicle-type-approval-norms-self-certification-retrofitted-vehicles/ ; https://teamleaseregtech.com/updates/article/52441/draft-central-motor-vehicles-amendment-rules-2025/ | F97: 2026 | G97: Rule 126 | H97: India | J97: In force (per source) | K97: GSR no./date NOT FOUND
A98: W2-S11 | B98: AIS 157:2020 notified for M/N FCEVs; ISO 14687 | C98: MoRTH via India Code; GKToday; Mercom | D98: 9th GSR 579(E) dated 23 September 2020 hydrogen fuel cell | E98: https://www.indiacode.nic.in/ViewFileUploaded?path=AC_CEN_30_42_00009_198859_1517807326286/notificationindividualfile/&file=9th_gsr_579%28e%29_dated_23_september_2020_hydrogen_fuel_cell.pdf ; https://indiacode.ecourtsindia.com/rules/7ec3e5bb/ ; https://gktoday.in/current-affairs/standards-for-safety-evaluation-of-vehicles-propelled-by-hydrogen-fuel-cells ; https://www.mercomindia.com/inclusion-hydrogen-fuel-central-motor-vehicles-act | F98: 23-09-2020 | G98: new rule (see S12) | H98: India | J98: In force | K98: Blocked; snippet
A99: W2-S12 | B99: FCEV rule numbered 125MA; fuel IS 16061:2021; H2-ICE Rule 125M | C99: Applus IDIADA | D99: IRIS Highlights – July 2026 | E99: https://www.digitalsolutions.applusidiada.com/blogs/news/iris-highlighs-july-2026 | F99: 07-2026 | G99: — | H99: India | J99: — | K99: Secondary digest
... A154: W2-S67 | B154: PESO hydrogen presentations at PNGRB | C154: PESO via PNGRB | D154: Statutory rules/regulations for CNG stations (PESO); Stakeholders interaction on hydrogen | E154: https://www.pngrb.gov.in/pdf/press-note/PESO_15032024.pdf ; https://pngrb.gov.in/pdf/press-note/20250306_PESO.pdf | F154: 03-2024 / 03-2025 | G154: — | H154: India | J154: — | K154: Blocked
A155: W3-S1 | B155: 72.10 lakh CNG vehicles registered | C155: AIR News (newsonair.gov.in) reporting Lok Sabha written reply, MoS PNG Suresh Gopi | D155: Total sales of CNG vehicles have increased over the past few years: Suresh Gopi | E155: https://www.newsonair.gov.in/total-sales-of-cng-vehicles-have-increased-over-the-past-few-years-suresh-gopi | H155: India | I155: vehicles | J155: observed (Vahan) | K155: page blocked; figure from search passage
A156: W3-S2 | B156: 58.61 lakh (Mar 2023) → 81.95 lakh (Mar 2025) CNG vehicles; +25% FY25; PNGRB VAT plea | C156: ET Energyworld / UNI / The Hindu BusinessLine / Energywatch quoting PNGRB | D156: PNGRB expands CGD network to 784 districts, sets 2034 target of 12.6 crore PNG connections; City Gas Distribution network now covers nearly 100 pc…; PNGRB in talks with states to rationalise VAT | E156: https://energy.economictimes.indiatimes.com/news/oil-and-gas/pngrb-expands-cgd-network-to-784-districts-sets-2034-target-of-12-6-crore-png-connections/123553997 ; https://www.thehindubusinessline.com/markets/commodities/pngrb-in-talks-with-states-to-rationalise-vat-on-natural-gas-cng/article69991018.ece | H156: India | I156: vehicles | J156: observed (PNGRB citing Vahan) | K156: secondary reporting of PNGRB statement
A157: W3-S3 | B157: 18,336 CNG stations & 12.63 crore PNG by 2034; ~1,206 stations added FY25 | C157: Business Standard; IBEF | D157: PNGRB targets 12.6 crore PNG connections, 18,336 CNG stations by 2034 | E157: https://www.business-standard.com/economy/news/pngrb-targets-12-6-crore-png-connections-18336-cng-stations-by-2034-125082700329_1.html ; https://www.ibef.org/news/india-eyes-126-million-png-connections-18-000-cng-stations-by-2034 | H157: India | I157: stations | J157: target / observed | K157: secondary
A158: W3-S4 | B158: 738 (2014) → 8,150+ CNG stations; 18,000 by 2030 | C158: Hardeep Singh Puri (MoPNG) on X; The Hindu BusinessLine | D158: One Nation, One Gas Grid (X post); India to double CNG stations to 18,000 by 2030 amid One Nation One Gas Grid plan: Puri | E158: https://x.com/HardeepSPuri/status/1961324393344491893 ; https://www.thehindubusinessline.com/economy/logistics/india-to-double-cng-stations-to-18000-by-2030-amid-one-nation-one-gas-grid-plan-puri/article69988711.ece | H158: India | I158: stations | J158: observed (ministerial) / target | K158: ministerial statement, not a PNGRB table
A159: W3-S5 | B159: outdated "2,830 stations" figure | C159: PRS Legislative Research | D159: National Gas Grid Including PNG and CNG (Standing Committee report summary) | E159: https://prsindia.org/policy/report-summaries/national-gas-grid-including-png-and-cng | H159: India | I159: stations | J159: outdated | K159: used only to flag staleness
A160: W3-S6 | B160: 17,700 stations by 2030 (MWP, rounds to 11A); "17,500 by 2030"; "7,400 in 2025" | C160: Autocar Professional; Construction World | D160: India's CNG infra development in high gear; India Plans 17,500 CNG-PNG Stations… by 2030 | E160: https://www.autocarpro.in/feature/indias-auto-industry-set-for-a-cng-boom-as-gas-infra-inches-to-100-penetration-117791 ; https://www.constructionworld.in/policy-updates-and-economic-news/india-plans-17500-cng-png-stations-aims-for-120-million-connections-by-2030/52110 | H160: India | I160: stations | J160: commitment/target | K160: industry press citing MoPNG/PNGRB
A161: W3-S7 | B161: CNG ₹86.98/kg Delhi (IGL, +₹3.89); ₹88/kg Mumbai (MGL, +₹2); reasons | C161: Goodreturns; Equentis; ETV Bharat; Infralog | D161: CNG Price in New Delhi Today; CNG, PNG Price Hike: New Rates in Mumbai and Delhi-NCR; CNG Price Hiked By Rs 2 Per Kg In Mumbai; MGL hikes CNG… amid rising spot RLNG costs | E161: https://www.goodreturns.in/cng-price-in-new-delhi.html ; https://www.equentis.com/blog/cng-png-price-hike-new-rates-in-mumbai-and-delhi-ncr/ ; https://www.etvbharat.com/en/business/cng-price-hiked-by-rs-2-per-kg-in-mumbai-enn26090104129 | H161: Delhi; Mumbai | I161: ₹/kg | J161: observed (retail) | K161: aggregator pages; IGL/MGL notices not opened
A162: W3-S8 | B162: Pune CNG ₹97.75/kg from 1 Sep 2026 | C162: MNGL (official rate card); Times of India | D162: CNG Rate Card — Revision in Prices w.e.f. midnight of 1st Sep 2026: Pune GA Rs 97.75/kg; MNGL hikes CNG price by Rs2 per kg in Pune | E162: https://mngl.in/cng/rate-card ; https://timesofindia.indiatimes.com/city/pune/mngl-hikes-cng-price-by-rs2-per-kg-in-pune/articleshow/133662320.cms | H162: Pune GA | I162: ₹/kg | J162: observed | K162: primary text visible in passage
A163: W3-S9 | B163: Ahmedabad CNG ₹94.02/kg | C163: CarDekho / Goodreturns city price pages | D163: CNG price in India Today | E163: https://www.cardekho.com/cng-price ; https://www.goodreturns.in/cng-price.html | H163: Ahmedabad | I163: ₹/kg | J163: observed (aggregator) | K163: supplier notice not verified
A164: W3-S10 | B164: Maruti FY25 CNG 6.12–6.2 lakh, 33%; 71.6% CNG-segment share (2024) | C164: Autocar India; Autocar Professional | D164: One in every three Maruti sold in FY2025 was a CNG; One-in-Three Maruti Vehicles Sold in FY25 Ran on CNG | E164: https://www.autocarindia.com/industry/one-in-every-three-maruti-sold-in-fy2025-was-a-cng-434994 ; https://www.autocarpro.in/news/one-in-three-maruti-vehicles-sold-in-fy25-ran-on-cng-125695 | H164: India | I164: units; % | J164: observed (company/industry data) | K164: secondary
A165: W3-S11 | B165: Maruti FY26 sales 24.22 lakh, exports 4.47 lakh; biogas plants ₹561 crore | C165: Maruti Suzuki (press releases, not accessible); Automotive World; scanx | D165: Maruti Suzuki announces Financial Results for FY2025-26; Annual Integrated Report 2025-26 | E165: https://www.marutisuzuki.com/corporate/media/press-releases/2026/april/maruti-suzuki-announces-financial-results-for-fy2025-26 ; https://www.marutisuzuki.com/corporate/media/press-releases/2026/august/maruti-suzuki-annual-integrated-report-2025-26 ; https://www.automotiveworld.com/news/annual-integrated-report-maps-maruti-suzukis-growth-push/ | H165: India | I165: units | J165: observed | K165: primary blocked; via secondary
A166: W3-S12 | B166: Maruti FY26 CNG >7 lakh; 42% share "last month"; FY27 target 9 lakh | C166: ET Auto; Business Standard; Moneycontrol | D166: Maruti Suzuki targets nearly 30% jump in CNG sales to 9 lakh units in FY27; Maruti Suzuki targets 900,000 units of CNG vehicle sales this fiscal | E166: https://auto.economictimes.indiatimes.com/news/passenger-vehicle/maruti-suzuki-aims-for-30-increase-in-cng-vehicle-sales/132637759 ; https://www.business-standard.com/companies/news/maruti-suzuki-targets-900-000-units-of-cng-vehicle-sales-this-fiscal-126072600153_1.html | H166: India | I166: units; % | J166: observed / target | K166: 42% is a monthly figure
... A230: W3-S77 | B230: PNGRB 2030/2040 projections (CGD 87 mmscmd 2030 base case) and critique | C230: PNGRB press note; PSU Watch | D230: Natural Gas Projections 2030–40 (press note 7 Apr 2025); PNGRB projects a natural gas boom, but experts urge a sobering reality check | E230: https://pngrb.gov.in/pdf/press-note/20250407_NG_Projections2030_40.pdf ; https://psuwatch.com/newsupdates/pngrb-projects-a-natural-gas-boom-but-experts-urge-a-sobering-reality-check | H230: India | I230: mmscmd | J230: modelled | K230: PDF blocked
A231: W4-S1 | B231: 700-bar Type IV system $12.1–13.3/kWh (median 12.7, 2020$) at 100k/yr; carbon fibre dominant | C231: US DOE Hydrogen Program | D231: Record #24006 "Onboard Type IV Compressed Hydrogen Storage System—Cost and Performance Status" | E231: https://www.hydrogen.energy.gov/docs/hydrogenprogramlibraries/pdfs/24006-onboard-storage-cost-performance-status.pdf | F231: 28 Apr 2025 / 2024 analysis | G231: Record summary (page not verified) | H231: USA (ANL/SA analysis) | I231: $/kWh (2020$) | J231: modelled | K231: Host blocked; values from search summary; 10k & 500k rows unread
A232: W4-S2 | B232: $14.2 / 15.7 / 21.3 per kWh at 500k / 100k / 10k systems/yr (2016$) | C232: US DOE | D232: Record #19008 onboard storage cost & performance status | E232: https://www.hydrogen.energy.gov/pdfs/19008_onboard_storage_cost_performance_status.pdf | F232: 25 Nov 2019 | G232: Record p.1 summary | H232: USA | I232: $/kWh | J232: modelled | K232: search summary
A233: W4-S3 | B233: 2013: 350-bar $15/kWh, 700-bar $19/kWh single tank (500k/yr); Record 13010 $16–20/kWh | C233: US DOE / Strategic Analysis | D233: Record #13010; "Hydrogen Storage Cost Analysis Final Public Report" (OSTI 1082754) | E233: https://www.hydrogen.energy.gov/docs/hydrogenprogramlibraries/pdfs/13010_onboard_storage_performance_cost.pdf ; https://digital.library.unt.edu/ark:/67531/metadc827980/m2/1/high_res_d/1082754.pdf | F233: 11 Jun 2013 / 2013 | G233: abstract/summary | H233: USA | I233: $/kWh | J233: modelled | K233: old dollar-year
A234: W4-S4 | B234: DOE targets $10/9/8 per kWh = $333/300/266 per kg | C234: US DOE | D234: Technical Targets for Onboard Hydrogen Storage for LDVs | E234: https://www.energy.gov/cmei/fuels/doe-technical-targets-onboard-hydrogen-storage-light-duty-vehicles | F234: current page | G234: Storage system cost row | H234: USA | I234: $/kWh, $/kg | J234: target | K234: targets not costs
A235: W4-S5 | B235: 12% cost reduction 2013→2015; volumes 10k–500k/yr | C235: US DOE FCTO | D235: Webinar: Onboard Type IV compressed H2 storage system cost | E235: https://www.energy.gov/sites/prod/files/2016/03/f30/fcto_webinarslides_compressed_h2_storage_system_cost_022516.pdf | F235: 25 Feb 2016 | G235: slide 8 | H235: USA | I235: % | J235: modelled | K235: snippet
A236: W4-S6 | B236: Compressed-gas storage USD 400–700 per kg H2 (Cerri et al.) | C236: MDPI Energies 16(13):5233 | D236: A Review on the Cost Analysis of Hydrogen Gas Storage Tanks for Fuel Cell Vehicles | E236: https://www.mdpi.com/1996-1073/16/13/5233 | F236: 2023 | G236: Table citing Cerri et al. [33] | H236: global | I236: USD/kg H2 | J236: literature | K236: secondary citation
A237: W4-S7 | B237: Type IV 700-bar tanks ~$700–1,200 per kg capacity | C237: Dataintelo (market report) | D237: Cryo-Compressed Hydrogen Storage Market | E237: https://dataintelo.com/report/cryo-compressed-hydrogen-storage-market | F237: 2025 | G237: Opportunities & threats | H237: global | I237: $/kg | J237: estimate | K237: low-grade commercial source
A238: W4-S8 | B238: Time Technoplast PESO approvals (Mar/Jun 2024), 250 L, BV cert, ₹2.30 crore trial order, ₹555 crore 9MFY26 | C238: Business Standard; Autocar Professional; Time Technoplast press release; Scanx | D238: multiple | E238: https://www.business-standard.com/markets/capital-market-news/time-technoplast-gets-final-approval-from-peso-for-manufacturing-composite-cylinders-124062100121_1.html ; https://www.autocarpro.in/news/time-technoplast-secures-international-certification-for-hydrogen-composite-cylinder-126444 ; https://www.timetechnoplast.com/pdf/investors-calendar/press-release/approval-for-manufacturing-of-type-iv-composite-cylinders-for-hydrogen.pdf | F238: 2024–2026 | G238: news | H238: India | I238: — | J238: observed | K238: no unit prices
A239: W4-S10 | B239: Bosch H2 PFI "suitable for retrofitting existing fleets" | C239: Bosch Mobility | D239: Port fuel injection for hydrogen engines | E239: https://www.bosch-mobility.com/en/solutions/powertrain/gas/port-fuel-injection-for-hydrogen-engines/ | F239: current | G239: product page | H239: global | I239: — | J239: observed | K239: no price
A240: W4-S11 | B240: CNG kit prices ₹45–65k (BS6 OBD-II incl. install), Lovato ₹31,999–58,000, Landi Renzo ₹32,000, install ₹3–7k, RTO ₹2–3k | C240: mycarhelpline; Cars24; IndiaMART; Autonexa; IOAGPL | D240: Best CNG kit brands 2026; CNG kit price in India; listings | E240: https://www.mycarhelpline.com/index.php?option=com_easyblog&view=entry&id=557&Itemid=91 ; https://www.cars24.com/article/cng-kit-price-in-india/ ; https://www.indiamart.com/proddetail/landirenzo-cng-kit-23070488673.html ; https://autonexa.com/cng-fitting-cost-in-india-complete-guide-price-break-down-kits-and-savings ; https://ioagpl.com/cng-kit-price/ | F240: 2025–2026 | G240: retail/trade listings | H240: India | I240: ₹ | J240: observed (retail) | K240: listings vary by city
A241: W4-S12 | B241: ARAI retrofit approval under Rule 115; "full approval in 45* days"; fee schedule not public; Scribd cost-breakdown doc exists; ₹15–25 lakh homologation anecdote | C241: ARAI; Scribd; Quora | D241: Retrofitment certification; Vehicle type approval; "Retrofitment Kit Approval" | E241: https://www.araiindia.com/certification/certification/retrofitment ; https://www.araiindia.com/certification/certification/vehicle ; https://www.scribd.com/document/975757543/Retrofitment-Kit-Approval-1 | F241: current | G241: pages | H241: India | I241: ₹ | J241: observed / anecdote | K241: fees NOT FOUND
A242: W4-S13 | B242: PFI gasoline conversion needs injectors + plugs; DI needs ignition/injection; custom pistons | C242: Ultimate Cell UK; OSTI 1008335 (NETL small H2 engine) | D242: trade guides | E242: https://ultimatecelldistributors.co.uk/insights/hydrogen-retrofit-for-diesel-petrol-engines/ ; https://www.osti.gov/servlets/purl/1008335 | F242: 2020s / 2011 | G242: — | H242: UK/US | I242: — | J242: qualitative | K242: low grade
... A313: W4-S86 | B313: IIT Madras–Hyundai HTWO centre operational by 2026 | C313: Careers360 | D313: IIT Madras unveils Hyundai HTWO Centre | E313: https://news.careers360.com/iit-madras-unveils-hyundai-htwo-centre-on-campus-operational-by-2026-iitm-hydrogen-india-research/amp | F313: 2025 | G313: news | H313: India | I313: — | J313: announced | K313: —
