Workbook

Sheet Assumptions
A1: NAADI pilot — assumptions register (units: INR lakh unless stated)
A2: Blue+yellow cells are inputs for the team to edit and ratify. Every value is labelled Fact / Sourced range / Estimate. Nothing here is primary research.
A3: PLANT ARCHETYPE (representative use case — TEAM ESTIMATES)
A4: Plant annual revenue (INR lakh) | B4: 50000 | C4: Estimate | D4: Estimate: mid-size speciality chemicals plant, ~INR 500 Cr/yr revenue. Team to ratify.
A5: Contribution margin (% of revenue) | B5: 0.3 | C5: Estimate | D5: Estimate: typical speciality-chem contribution margin used for lost-production valuation. Team to ratify.
A6: Operating hours per year | B6: 8000 | C6: Estimate | D6: Estimate: continuous plant, ~91% utilisation.
A7: Total pumps in plant (count) | B7: 200 | C7: Estimate | D7: Estimate: typical mid-size plant pump population; context only.
A8: Critical 'bad-actor' pumps in pilot (count) | B8: 25 | C8: Estimate | D8: Pilot scope: selected by criticality ranking per ISO 14224 taxonomy.
A9: Measurement points (2 bearing housings per pump) | B9: =B8*2 -> 50 | C9: Formula | D9: Drive-end + non-drive-end bearing housing per pump. (Formula)
A10: BASELINE LOSSES ON THE 25 PUMPS (TEAM ESTIMATES)
A11: Unplanned downtime caused by these pumps (h/yr) | B11: 60 | C11: Estimate | D11: Estimate: 3-4 pump-caused trips/yr with multi-hour restarts in a continuous process. Replace with the pilot plant's real 24-month history in Phase 0.
A12: Value of lost production (INR lakh per hour) | B12: =B4*B5/B6 -> 1.875 | C12: Formula | D12: Revenue x contribution margin / operating hours. (Formula)
A13: Pump repair events per year (count) | B13: 12 | C13: Estimate | D13: Estimate: MTBR ~25 months across 25 bad actors.
A14: Average direct repair cost per event | B14: 2.5 | C14: Estimate | D14: Estimate: mechanical seal/bearing cartridge replacement incl. labour.
A15: Catastrophic secondary-damage events avoided per year | B15: 2 | C15: Estimate | D15: Estimate: bearing run-to-seizure destroying shaft/impeller, downgraded to planned repair.
A16: Extra cost of a catastrophic vs planned repair | B16: 2.5 | C16: Estimate | D16: Estimate: secondary damage + emergency logistics premium.
A17: EFFECTIVENESS (SOURCED RANGES, APPLIED AT LOW END)
A18: Downtime reduction from PdM (fraction) | B18: 0.35 | C18: Sourced range | D18: SOURCED range: US DOE FEMP O&M Best Practices Guide R3.0 (2010) reports 35-45% downtime reduction for functioning PdM programmes; low end used. https://www.energy.gov/sites/prod/files/2020/04/f74/omguide_complete_w-eo-disclaimer.pdf
A19: Repair-spend reduction vs preventive-only (fraction) | B19: 0.1 | C19: Sourced range | D19: SOURCED range: DOE FEMP reports 8-12% savings of PdM over preventive maintenance alone; mid value used.
A20: PILOT COSTS (TEAM ESTIMATES — VENDOR QUOTES NEEDED)
A21: Wireless tri-axial vibration+temp sensor, Ex-rated, installed (per point) | B21: 0.35 | C21: Estimate | D21: Estimate: market range for industrial wireless sensors incl. mounting and commissioning. No vendor quote yet — TEAM INPUT REQUIRED before final.
A22: Edge gateways (count) | B22: 5 | C22: Estimate | D22: Estimate: 1 gateway per ~10 pumps/plant area.
A23: Cost per edge gateway | B23: 1.5 | C23: Estimate | D23: Estimate.
A24: Historian/CMMS integration + software + commissioning | B24: 10 | C24: Estimate | D24: Estimate: OPC-UA connector, dashboard, alert-to-work-order workflow.
A25: Operator & reliability-engineer training | B25: 2 | C25: Estimate | D25: Estimate.
A26: Annual OpEx (connectivity, compute, batteries, model upkeep) | B26: 6 | C26: Estimate | D26: Estimate: ~10%/yr sensor battery/replacement + compute + model retraining effort.
A27: FINANCE
A28: Discount rate for NPV | B28: 0.12 | C28: Estimate | D28: Estimate: typical Indian industrial hurdle rate.
A29: Evaluation horizon (years) | B29: 5 | C29: Estimate | D29: Per competition economic-feasibility convention.

Sheet Model
A1: NAADI pilot — unit economics (all formulas; INR lakh)
A3: ANNUAL BENEFIT
A4: Avoided downtime (h/yr) | B4: =Assumptions!B11*Assumptions!B18 -> 21
A5: Value of avoided downtime | B5: =B4*Assumptions!B12 -> 39.375
A6: Repair-spend saving | B6: =Assumptions!B13*Assumptions!B14*Assumptions!B19 -> 3
A7: Avoided catastrophic secondary damage | B7: =Assumptions!B15*Assumptions!B16 -> 5
A8: Total annual benefit | B8: =SUM(B5:B7) -> 47.375
A10: CAPEX
A11: Sensors installed | B11: =Assumptions!B9*Assumptions!B21 -> 17.5
A12: Edge gateways | B12: =Assumptions!B22*Assumptions!B23 -> 7.5
A13: Integration, software, commissioning | B13: =Assumptions!B24 -> 10
A14: Training | B14: =Assumptions!B25 -> 2
A15: Total CapEx | B15: =SUM(B11:B14) -> 37
A17: RETURNS
A18: Annual OpEx | B18: =Assumptions!B26 -> 6
A19: Net annual benefit | B19: =B8-B18 -> 41.375
A20: Simple payback (months) | B20: =B15/B19*12 -> 10.731118
A21: 5-year NPV @ discount rate | B21: =-B15+NPV(Assumptions!B28,B24:F24) -> 112.14762
A22: Cost per avoided downtime-hour (CapEx amortised over horizon) | B22: =(B15/Assumptions!B29+B18)/B4 -> 0.63809524
A23: Year | B23: 1 | C23: 2 | D23: 3 | E23: 4 | F23: 5
A24: Net cash flow per year (uniform, no ramp; a conservative ramp pushes payback ~2-3 months later) | B24: =$B$19 -> 41.375 | C24: =$B$19 -> 41.375 | D24: =$B$19 -> 41.375 | E24: =$B$19 -> 41.375 | F24: =$B$19 -> 41.375

Sheet Sensitivity
A1: Sensitivity — simple payback (months) under single-variable swings
A2: Each row recomputes the full model with one input changed; all else at base.
A4: Scenario | B4: Payback (mo)
A5: Base case (35% downtime cut, base margin, base CapEx) | B5: =Model!B15*1/((Assumptions!B11*Assumptions!B18*Assumptions!B12*1+Assumptions!B13*Assumptions!B14*Assumptions!B19+Assumptions!B15*Assumptions!B16)-Assumptions!B26)*12 -> 10.731118
A6: Downtime reduction only 20% (programme underperforms DOE band) | B6: =Model!B15*1/((Assumptions!B11*0.2*Assumptions!B12*1+Assumptions!B13*Assumptions!B14*Assumptions!B19+Assumptions!B15*Assumptions!B16)-Assumptions!B26)*12 -> 18.122449
A7: Downtime reduction 45% (top of DOE band) | B7: =Model!B15*1/((Assumptions!B11*0.45*Assumptions!B12*1+Assumptions!B13*Assumptions!B14*Assumptions!B19+Assumptions!B15*Assumptions!B16)-Assumptions!B26)*12 -> 8.4370546
A8: Lost-production value 1/3 lower | B8: =Model!B15*1/((Assumptions!B11*Assumptions!B18*Assumptions!B12*0.666666666666667+Assumptions!B13*Assumptions!B14*Assumptions!B19+Assumptions!B15*Assumptions!B16)-Assumptions!B26)*12 -> 15.716814
A9: CapEx overrun +30% | B9: =Model!B15*1.3/((Assumptions!B11*Assumptions!B18*Assumptions!B12*1+Assumptions!B13*Assumptions!B14*Assumptions!B19+Assumptions!B15*Assumptions!B16)-Assumptions!B26)*12 -> 13.950453
A10: Downside stack: 20% cut AND CapEx +30% | B10: =Model!B15*1.3/((Assumptions!B11*0.2*Assumptions!B12*1+Assumptions!B13*Assumptions!B14*Assumptions!B19+Assumptions!B15*Assumptions!B16)-Assumptions!B26)*12 -> 23.559184
A12: Reading: payback stays under ~20 months even if the programme delivers only 20% downtime reduction (below the DOE-reported band) or CapEx overruns 30%. The model breaks only if BOTH the plant's downtime history and the DOE effectiveness band are far off — which Phase 0 baselining will test.
A14: LEGEND: yellow+blue = team-editable inputs; black = formulas; currency in INR lakh. Sources for DOE ranges on the Assumptions sheet.
