Workbook

Sheet README
A1: PROJECT SATOSHI GATE — Paytm × Liminal Custody Solutions: transaction & accretion/dilution model
B2: Prepared for the Board / Investment Committee discussion. All ₹ figures in Cr unless stated. Model date: 23 Sep 2026.
B4: Purpose | C4: One workbook that traces every decision-relevant number from a labelled input to an output: valuation → FCF → leverage → EPS → transaction economics → decision thresholds.
B5: Source of truth | C5: The case document 'Project Satoshi Gate' (5 pp.) and 'Addendum 1: Modeling Inputs and Clarifications' (1 p.). Case inputs are never replaced by outside figures. External facts are used only for context, comparables and regulatory sequencing, and are labelled as such.
B6: Colour code | C6: Blue text on light-blue fill = CASE FACT (from the case document, cell comment gives the section). Blue text on yellow fill = TEAM / ANALYST ASSUMPTION (changeable). Blue text on orange fill = EXTERNAL FACT (sourced, dated). Black = formula. Green = link to another sheet. Green fill = key output.
B7: How to use | C7: Change the levers on 'Dashboard' (growth case, churn, capital drag level and interpretation, financing mix, minority stake terms, WACC). Every downstream sheet recalculates. Do not type over black formula cells.
B8: Sheet map | C8: Dashboard (levers + headline outputs) · Inputs (case facts, calculations on case facts, team assumptions) · Liminal_Ops (10-yr operating forecast, standalone and post-churn) · DCF (standalone value, what-you-need-to-believe, WACC×growth and churn×growth grids) · Financing (cash/debt/equity mixes, leverage, liquidity, cost of funds) · Sources_Uses · Accretion (EPS Y0–Y3 from the ₹7.50 baseline; accounting vs economic view) · Capital_Drag (three readings of the ₹750 Cr drag, ₹500–1,250 Cr grid, break-even drag, MDR offset) · Churn (0–60% grid, effective multiple, breakevens, maximum acceptable churn) · Structures (full / minority / JV / walk-away / hybrid side by side) · Earnout (retention-linked consideration, call-option strike, escrow) · Scenarios (base, upside, moderate, severe, break; dominant-variable test) · Thresholds (decision triggers, computed) · Synergies (tree with incrementality tests) · Comps · Precedents · Regulatory (external, sourced) · Audit_Trail.
B9: Conventions | C9: Y0 = trailing twelve months at signing (mid-Sep 2026). Y1 = first 12 months after close. Liminal revenue is modelled as ARR run-rate. Percentages stored as fractions. Negative = outflow. Breakeven year = first year in which the incremental line is ≥ 0 (PAT: accounting; FCF: cash, after capital drag and cost of funds).
B10: Evidence classes | C10: CASE FACT · CALCULATION (arithmetic on case facts) · ANALYST ASSUMPTION · EXTERNAL FACT (sourced) · INFERENCE · UNKNOWN. Every important number on the Audit_Trail sheet carries one of these tags.
B11: Not modelled | C11: Purchase-price-allocation amortisation is shown as a switchable line (default on for reported EPS, off for cash EPS). Liminal's tax-loss carry-forwards are ignored (conservative). Paytm standalone earnings are held flat at ₹480 Cr unless the growth lever is changed, so that the deal effect is isolated. Currency: ₹ only; the ~$470M is the case's own conversion.

Sheet Dashboard
A1: DASHBOARD — key levers (yellow) and headline outputs (green). Change a lever; every sheet recalculates.
A2: Levers are TEAM ASSUMPTIONS / scenario choices. Case facts live on 'Inputs' and are not levers.
A4: 1. SCENARIO LEVERS
A5: Liminal growth case (1 = bear, 2 = base, 3 = bull) | B5: 2 | G5: Selects a_g_bear / a_g_base / a_g_bull.
A6: ARR churn within 12 months of a FULL acquisition (case range 30–45%) | B6: 0.375 | G6: Case §3.1 range 30–45%; base = midpoint 37.5%. Set 0% to see the no-churn case.
A7: Recurring capital drag at full ownership (₹ Cr/yr) — case value 750; grid 500 / 750 / 1,000 / 1,250 | B7: 750 | G7: Case §3.2. Flex to test.
A8: Capital drag reading (1 = fixed cash drag as the case states; 2 = scales with retained/growing custodied assets; 3 = P&L operating cost) | B8: 1 | G8: See Capital_Drag for the three readings. Reading 1 is the case's literal wording.
A9: Discount rate for Liminal cash flows | B9: =a_wacc_base -> 0.13 | G9: Defaults to the Inputs base; overwrite to flex.
A10: Credit the ₹115 Cr MDR to the DEAL's breakeven? (0 = no: standalone Paytm item; 1 = yes: case-style offset) | B10: 0 | G10: The MDR accrues to Paytm with or without Liminal. Both views are always shown; this lever picks which one the verdict lines use.
A11: → Selected Liminal growth rate | B11: =CHOOSE(lv_gcase,a_g_bear,a_g_base,a_g_bull) -> 0.2
A13: 2. FINANCING LEVERS — full acquisition (₹4,000 Cr headline; case: ₹2,100 Cr cash portion from cash, new debt or mix; ₹1,900 Cr in Paytm shares)
A14: Cash consideration funded from balance-sheet cash (₹ Cr) | B14: 2100 | G14: Case headline: ₹2,100 Cr from existing cash.
A15: Cash consideration funded from new debt (₹ Cr) | B15: 0 | G15: Case headline: none.
A16: Consideration paid in new Paytm shares (₹ Cr) | B16: 1900 | G16: Case headline: ₹1,900 Cr.
A17: → Total consideration from the mix (must equal the price paid) | B17: =lv_mix_cash+lv_mix_debt+lv_mix_eq -> 4000
A18: Price paid for 100% (₹ Cr) — case headline 4,000; lower to test a renegotiated price | B18: =cf_deal -> 4000
A19: → Check: mix = price (should read 0) | B19: =lv_mix_total-lv_price -> 0
A21: 3. MINORITY / HYBRID LEVERS
A22: Minority stake | B22: =a_stake -> 0.26 | G22: Defaults to Inputs (26%).
A23: Implied 100% valuation for the minority entry (₹ Cr) — ceiling 4,000 (headline), floor = base DCF | B23: =a_min_val100 -> 2500 | G23: Defaults to Inputs (₹2,500 Cr = 11.4x ARR).
A24: Churn triggered at minority | B24: =a_min_churn -> 0 | G24: Defaults to Inputs (0%; a gate).
A25: Drag applied at minority (0 none / 1 pro-rata / 2 full) | B25: =a_min_drag_mode -> 0 | G25: Defaults to Inputs (0).
A26: → Minority price (₹ Cr) = stake × implied 100% valuation | B26: =lv_stake*lv_min_val100 -> 650
A27: → Implied entry multiple (× ARR) / discount to the headline pro-rata | B27: =lv_min_val100/cf_arr -> 11.363636 | C27: =1-lv_min_val100/lv_price -> 0.375
A29: 4. HEADLINE OUTPUTS — valuation → FCF → leverage → EPS → transaction economics → decision thresholds (green = key outputs)
A30: Output | B30: Full acquisition (levers) | C30: Minority stake | D30: Hybrid (minority + option) | E30: JV | F30: Walk away | G30: Read-across
A31: VALUATION — standalone DCF of 100% (₹ Cr) | B31: =dcf_ev -> 1218.8043 | C31: =dcf_ev -> 1218.8043 | D31: =dcf_ev -> 1218.8043 | E31: n/a | F31: n/a | G31: Financial value before churn and drag; compare with ₹4,000 Cr.
A32: Headline multiple / effective multiple on retained ARR | B32: =e_eff_mult -> 24.242424 | C32: =lv_min_val100/cf_arr -> 11.363636 | D32: =(lv_min_price+eo_total)/(cf_arr*(1+lv_g)^a_opt_year*(1-a_ctrl_churn)) -> 12.327652 | E32: n/a | F32: n/a | G32: Full: price ÷ year-1 retained ARR. Minority: entry valuation ÷ ARR. Hybrid: total consideration ÷ retained ARR at exercise.
A33: Breakeven 10-yr growth for DCF = price | B33: =dcf_be_growth -> 0.36843109 | G33: What you need to believe.
A34: FCF — year-1 incremental FCF after drag and cost of funds (₹ Cr) | B34: =e_fcf_y1 -> -1045.475 | C34: =Structures!D54 -> -29.925 | D34: =Structures!D105 -> -29.925 | E34: =Structures!D131 -> -13.41 | F34: =Structures!D139 -> -83.333333 | G34: Cash consumed in year 1.
A35: FCF breakeven year (99 = never within 10 yrs) | B35: =e_fcf_be -> 99 | C35: n/a | D35: =Structures!C113 -> 7 | E35: n/a | F35: n/a | G35: Case §5.3.
A36: PAT breakeven year (99 = never within 10 yrs) | B36: =e_pat_be -> 99 | C36: =Structures!C63 -> 7 | D36: =Structures!C112 -> 7 | E36: n/a | F36: n/a | G36: Addendum 1: accounting breakeven.
A37: LEVERAGE — gross debt ÷ EBITDA after close | B37: =e_lev_after -> 0.546875 | C37: =c_lev0 -> 0.546875 | D37: =Structures!C120 -> 1.328125 | E37: =c_lev0 -> 0.546875 | F37: =c_lev0 -> 0.546875 | G37: Guardrail ≤ a_max_lev.
A38: Cash after close (₹ Cr) | B38: =e_cash_after -> 6640 | C38: =Structures!C64 -> 8235 | D38: =Structures!C119 -> 7560.52 | E38: =cf_cash-a_jv_capital -> 8600 | F38: =cf_cash -> 8900 | G38: Guardrail ≥ a_min_cash.
A39: EPS — year-1 pro-forma ex-MDR (₹) | B39: =e_eps_y1 -> 5.2561362 | C39: =Structures!C61 -> 7.0485094 | D39: =Structures!C116 -> 7.0485094 | E39: =Structures!C134 -> 7.2960937 | F39: =Structures!C142 -> 6.5234375 | G39: From the ₹7.50 baseline.
A40: EPS — year-1 accretion / (dilution) vs ₹7.50 | B40: =e_eps_y1/cf_eps-1 -> -0.29918184 | C40: =Structures!C61/cf_eps-1 -> -0.06019875 | D40: =Structures!C116/cf_eps-1 -> -0.06019875 | E40: =Structures!C134/cf_eps-1 -> -0.0271875 | F40: =Structures!C142/cf_eps-1 -> -0.13020833 | G40: Case §3.3 lens.
A41: EPS — year-3 pro-forma ex-MDR (₹) | B41: =e_eps_y3 -> 5.2193652 | C41: =Structures!C62 -> 7.1714179 | D41: =Structures!C117 -> 6.5312617 | E41: =Structures!C135 -> 7.3523438 | F41: =cf_eps -> 7.5
A42: TRANSACTION ECONOMICS — NPV to Paytm (₹ Cr) | B42: =e_npv -> -7486.7574 | C42: =Structures!C60 -> -348.11089 | D42: =Structures!C115 -> -1187.3396 | E42: =Structures!C133 -> -283.57336 | F42: =Structures!C141 -> -196.76272 | G42: Economic verdict.
A43: Maximum total commitment (₹ Cr) | B43: =lv_price+lv_price*a_fees_pct+a_integ_full -> 4160 | C43: =lv_min_price+a_integ_min -> 665 | D43: =hy_max_total -> 2603.6 | E43: =a_jv_capital -> 300 | F43: =a_build_cost -> 250
A44: Maximum unconditional commitment (₹ Cr) | B44: =lv_price+lv_price*a_fees_pct+a_integ_full -> 4160 | C44: =lv_min_price+a_integ_min -> 665 | D44: =lv_min_price+a_integ_min -> 665 | E44: =a_jv_capital -> 300 | F44: =0 -> 0 | G44: Cash at risk before any gate.
A45: DECISION THRESHOLDS — max churn at headline price (NPV ≥ 0) | B45: =ch_max_churn -> none: NPV<0 even at 0% churn | G45: Above this: renegotiate or walk.
A46: Break-even capital drag (₹ Cr/yr) | B46: =cd_max_drag -> -629.73119 | G46: Negative: no capacity for any reserve.
A47: Reservation value for 100% at these levers (₹ Cr) | B47: =th_max_price_full -> -3486.7574 | G47: Walk-away line vs the consortium.
A48: Strategic premium embedded in the headline (₹ Cr) | B48: =th_strat_prem -> 7486.7574 | G48: Must be justified by option value.
A49: Hybrid passes the breakeven gate after exercise? (1 = yes) | D49: =th_hy_gate -> 0 | G49: 0 → hold the minority.
A51: 5. VERDICT LINES (formulas)
A52: Full acquisition at these levers | B52: =IF(e_npv>=0,"Value-creating","Value-destroying: NPV "&TEXT(e_npv,"#,##0")&" Cr; FCF breakeven "&IF(e_fcf_be=99,"never in 10 yrs","year "&e_fcf_be)) -> Value-destroying: NPV -7,487 Cr; FCF breakeven never in 10 yrs
A53: Minority stake at these levers | B53: =IF(th_min_npv>=0,"Financially self-supporting","Costs "&TEXT(-th_min_npv,"#,##0")&" Cr of NPV = the price of access + blocking rights; justify as an option, not as an investment") -> Costs 348 Cr of NPV = the price of access + blocking rights; justify as an option, not as an investment
A54: Hybrid: exercise the option at these gate settings? | B54: =IF(AND(th_hy_gate=1,th_hy_npv>=0),"Eligible to exercise (subject to consents, RBI treatment, compliance)","HOLD the minority: "&IF(th_hy_gate=0,"breakeven gate fails; ","")&IF(th_hy_npv<0,"NPV negative at these terms","")) -> HOLD the minority: breakeven gate fails; NPV negative at these terms

Sheet Inputs
A1: INPUTS — case facts, calculations on case facts, and team assumptions
A2: Blue on light-blue = CASE FACT (comment = case section). Blue on yellow = TEAM ASSUMPTION (per Addendum 1, disclosed and flexed). Black = calculation.
A4: A. CASE FACTS — Paytm baseline (case §1, 'Baseline financials (assume for modeling)')
A5: Market capitalisation (₹ Cr) | B5: 118750 | D5: Case §1 and §2 table: ₹1,18,750 Cr (~$14B), mid-Sep 2026. Case note: real, verified fact.
A6: Diluted shares outstanding (Cr) | B6: 64 | D6: Case §1: 64 Cr diluted shares.
A7: Cash (₹ Cr) | B7: 8900 | D7: Case §1: ₹8,900 Cr cash.
A8: Gross debt (₹ Cr) | B8: 350 | D8: Case §1: ₹350 Cr gross debt.
A9: Trailing revenue (₹ Cr) | B9: 8450 | D9: Case §1: trailing revenue ₹8,450 Cr.
A10: EBITDA (₹ Cr) | B10: 640 | D10: Case §1: EBITDA ₹640 Cr.
A11: PAT (₹ Cr) | B11: 480 | D11: Case §1: PAT ₹480 Cr. Starting point for all dilution calculations (case §5.3).
A12: Diluted EPS (₹) | B12: 7.5 | D12: Case §1: diluted EPS ₹7.50. Baseline for §5.3.
A13: Credit rating | B13: CRISIL AA- (Stable)
A15: B. CASE FACTS — Liminal and the proposed transaction (case §2, §3)
A16: Headline deal value (₹ Cr) | B16: 4000 | D16: Case §2: ₹4,000 Cr (~$470M).
A17: of which cash consideration (₹ Cr) | B17: 2100 | D17: Case §2: ₹2,100 Cr cash; may be funded from balance-sheet cash, new debt, or a mix.
A18: of which equity consideration (₹ Cr) | B18: 1900 | D18: Case §2: ₹1,900 Cr equity (Paytm shares issued to Liminal shareholders).
A19: Liminal ARR (₹ Cr) | B19: 220 | D19: Case §2 table: Target ARR ₹220 Cr (~$26M).
A20: Liminal net income today (₹ Cr) | B20: 0 | D20: Case §2: 'approximately breakeven at the net income level today'.
A21: Top-4 clients' share of ARR (HDFC Bank, Axis Bank, CoinDCX, ZebPay) | B21: 0.6 | D21: Case §2: together 60% of Liminal's ARR.
A22: ARR lost within 12 months of a FULL acquisition — low end | B22: 0.3 | D22: Case §3.1: assume 30% to 45% of ARR lost within 12 months of a full acquisition.
A23: ARR lost within 12 months of a FULL acquisition — high end | B23: 0.45 | D23: Case §3.1.
A24: Recurring annual FCF drag from bank-like capital reserves if Paytm owns the custody infrastructure (₹ Cr/yr) | B24: 750 | D24: Case §3.2: RBI requires bank-like capital reserves against custodied assets because Paytm holds a PA licence, not a banking licence → recurring annual FCF drag ₹750 Cr (~$88M).
A25: Incremental net revenue to Paytm from the new UPI MDR (₹ Cr/yr) | B25: 115 | D25: Case §3.4: 0.4% MDR on P2M UPI > ₹2,000, capped ₹300/txn, effective 15 Oct 2026; assume ₹115 Cr/yr incremental net revenue for Paytm. Case note: the MDR framework is a real fact; the ₹115 Cr is the case's modelling input.
A26: Competing bidder | B26: PhonePe–Mastercard exploratory consortium
A27: Case's stated implied multiple | B27: 18x Deal Value / ARR
A29: C. CALCULATIONS on case facts (no assumptions involved)
A30: Implied Paytm share price (₹) = market cap ÷ diluted shares | B30: =cf_mcap/cf_shares -> 1855.4688
A31: Paytm trailing P/E = market cap ÷ PAT | B31: =cf_mcap/cf_pat -> 247.39583
A32: Paytm earnings yield = PAT ÷ market cap | B32: =cf_pat/cf_mcap -> 0.0040421053
A33: Headline multiple = deal value ÷ ARR | B33: =cf_deal/cf_arr -> 18.181818
A34: New Paytm shares for the ₹1,900 Cr equity leg (Cr) = equity ÷ share price | B34: =cf_deal_eq/c_price -> 1.024
A35: …as % of existing share count | B35: =c_new_shares_case/cf_shares -> 0.016
A36: Top-4 clients' ARR (₹ Cr) | B36: =cf_arr*cf_top4 -> 132
A37: ARR at risk — low (₹ Cr) | B37: =cf_arr*cf_churn_lo -> 66
A38: ARR at risk — high (₹ Cr) | B38: =cf_arr*cf_churn_hi -> 99
A39: Case churn as % of top-4 book — low | B39: =cf_churn_lo/cf_top4 -> 0.5
A40: Case churn as % of top-4 book — high | B40: =cf_churn_hi/cf_top4 -> 0.75
A41: Capital drag ÷ Paytm EBITDA | B41: =cf_drag/cf_ebitda -> 1.171875
A42: Capital drag ÷ Paytm PAT | B42: =cf_drag/cf_pat -> 1.5625
A43: Capital drag ÷ Liminal ARR | B43: =cf_drag/cf_arr -> 3.4090909
A44: MDR net revenue ÷ capital drag (gross, revenue line) | B44: =cf_mdr/cf_drag -> 0.15333333
A45: Deal value ÷ Paytm market cap | B45: =cf_deal/cf_mcap -> 0.033684211
A46: Cash consideration ÷ Paytm cash | B46: =cf_deal_cash/cf_cash -> 0.23595506
A47: Paytm net cash today (₹ Cr) | B47: =cf_cash-cf_debt -> 8550
A48: Gross debt ÷ EBITDA today | B48: =cf_debt/cf_ebitda -> 0.546875
A50: D. TEAM ASSUMPTIONS — Liminal operating model (Addendum 1: unstated parameters are team assumptions)
A51: Liminal ARR growth — bear case (p.a.) | B51: 0.1 | D51: Bear: growth slows to a mature-SaaS rate. Range tested 0–40% on DCF sheet.
A52: Liminal ARR growth — base case (p.a.) | B52: 0.2 | D52: Base: an infrastructure SaaS provider at ₹220 Cr ARR growing 20%. Deliberately below the growth that justifies 18x (see DCF 'what you need to believe').
A53: Liminal ARR growth — bull case (p.a.) | B53: 0.3 | D53: Bull: sustained 30% for a decade; consistent with institutional digital-asset adoption scaling in India/UAE/Singapore.
A54: EBITDA margin today | B54: 0 | D54: Case: ~breakeven at net income. We set EBITDA ≈ 0 today (D&A ≈ capex, no tax).
A55: EBITDA margin improvement per year (pp) | B55: 0.05 | D55: Operating leverage of an infrastructure SaaS: +5pp per year.
A56: EBITDA margin cap (mature) | B56: 0.25 | D56: Mature margin of a regulated custody/infra business with compliance and security cost load; below pure software (30–40%).
A57: Tax rate | B57: 0.25 | D57: Indian corporate rate ~25.2% (s.115BAA). Losses not group-relieved (no group relief in India); Liminal's own carry-forwards ignored (conservative).
A58: D&A as % of revenue | B58: 0.03 | D58: Asset-light: mostly software, HSMs, security infrastructure.
A59: Capex as % of revenue | B59: 0.03 | D59: ≈ D&A in steady state.
A60: Working capital as % of incremental revenue | B60: 0.05 | D60: Custody fees billed monthly/quarterly; modest receivables.
A61: Share of lost revenue's cost base that stays for one year after churn | B61: 0.5 | D61: Costs do not fall as fast as revenue: half of the cost base tied to lost clients persists for 12 months (a 37.5% revenue loss on a breakeven cost base is a loss, not zero).
A62: Year in which full-acquisition churn hits (case: within 12 months) | B62: 1 | D62: Case §3.1: within 12 months of a full acquisition → year 1.
A63: Explicit forecast horizon (years) | B63: 10 | D63: 10 years; terminal value thereafter.
A65: E. TEAM ASSUMPTIONS — financing, cost of capital, accounting
A66: Pre-tax yield on Paytm surplus cash (opportunity cost of cash used) | B66: 0.06 | D66: Treasury yield on liquid Indian debt funds/deposits; tested 5–7%.
A67: Pre-tax cost of new debt for a CRISIL AA- issuer | B67: 0.085 | D67: AA- corporate bond/term-loan pricing; tested 8–10%. Interest is tax-deductible.
A68: Discount to market on Paytm shares issued as consideration | B68: 0 | D68: 0% base: SEBI ICDR preferential-issue floor pricing (90-day / 10-day VWAP) usually allows issuance near market; flex for a compressed stock.
A69: Transaction costs as % of consideration | B69: 0.015 | D69: Advisory, legal, diligence, stamp duty: ~1.5% of consideration (one-time, expensed, not in run-rate EPS).
A70: One-time integration/separation cost at full acquisition (₹ Cr) | B70: 100 | D70: Ring-fence build-out, information barriers, independent compliance, retention pool (cash, year 1).
A71: One-time costs for a minority investment (₹ Cr) | B71: 15 | D71: Diligence, documentation, shareholder agreement.
A72: Liquidity guardrail — minimum cash to hold (₹ Cr) | B72: 5000 | D72: Team guardrail to protect the AA- rating and PA-licence net-worth/escrow needs: keep ≥ ₹5,000 Cr (~7 months of revenue).
A73: Leverage guardrail — maximum gross debt ÷ EBITDA | B73: 1.5 | D73: Team guardrail for an AA- issuer with volatile earnings: ≤ 1.5x gross debt/EBITDA.
A74: Charge purchase-price-allocation amortisation in the headline EPS? (1 = yes, 0 = no) | B74: 0 | D74: 0 = case basis (case §2: EPS impact from new shares and financing costs). 1 = Ind AS reported basis (amortisation of acquired intangibles). The reported-basis EPS is always shown as a separate line.
A75: Share of purchase price allocated to amortisable intangibles (technology, customer contracts) | B75: 0.25 | D75: Typical for software/infra targets: 20–35% to identifiable intangibles; the rest is goodwill (not amortised, tested for impairment).
A76: Amortisation life of acquired intangibles (years) | B76: 8 | D76: Technology 5–7 yrs, customer relationships 8–10 yrs → blended 8.
A77: EBITDA flow-through of the ₹115 Cr MDR net revenue | B77: 0.8 | D77: Net revenue is after interchange/processing; some incremental collection, dispute and compliance cost → 80% reaches EBITDA. Tested 60–100%.
... A82: Breakeven gate: PAT and FCF must break even within N years of taking control | B82: 5 | D82: Board gate used in the decision framework.
A84: F. TEAM ASSUMPTIONS — alternative structures (minority, call option, JV, walk-away)
A85: Minority stake (case range 20–30%) | B85: 0.26 | D85: 26% = one share above the 25% special-resolution blocking threshold under the Companies Act 2013 (s.114): negative control without operational control.
A86: Implied valuation of 100% at which the minority stake is bought (₹ Cr) | B86: 2500 | D86: Entry valuation for the minority: ₹2,500 Cr = 11.4x ARR, i.e. Paytm's own EV/sales, the middle of the listed custody/infra comps range (5–11x) and the bull-case DCF pro-rata. Ceiling = ₹4,000 Cr headline (pro-rata ₹1,040 Cr); floor = base DCF (₹1,219 Cr).
A87: Share of the minority cheque that is primary (new shares into Liminal) vs secondary | B87: 0.5 | D87: Primary capital funds Liminal's growth and stays in the group; secondary gives sellers liquidity. 50/50 base.
A88: ARR churn triggered by a ring-fenced minority stake (year 1) | B88: 0 | D88: Base 0% because no change of control occurs and contracts are unaffected; this is a GATE to be validated by client consents, not a belief. Flex 0–20%.
A89: Capital drag applied to Paytm at minority (0 = none, 1 = pro-rata to stake, 2 = full ₹ drag) | B89: 0 | D89: Case ties the reserve to Paytm 'owning' the custody infrastructure. At a non-consolidated 26% we assume none, tested pro-rata and full. Written RBI comfort is a signing condition.
A90: Year at end of which the call option is exercised (if gates pass) | B90: 1 | D90: Validation period 12 months; option window months 12–24.
A91: ARR churn on exercising control (post-consent) | B91: 0.2 | D91: Control is only exercised if clients representing ≥ 80% of ARR have consented in writing; residual 20% churn assumed.
A92: Call-option strike multiple (× ARR at exercise) applied to the remaining stake, before the retention earn-out | B92: 10 | D92: 10x = the listed custody leader's subscription multiple (BitGo 9–11x) and a premium to FI-infrastructure software (4–6x); below the 18.2x headline. Strike = remaining stake × multiple × ARR at exercise, capped at the headline-equivalent; paid as 55% upfront (worst-case retained ARR) + retention earn-out. Tested 8–14x.
A93: Control tranche: amount funded from new debt (₹ Cr); the rest of the upfront comes from cash | B93: 500 | D93: ≤ 1.5x gross debt/EBITDA.
A94: Retained-ARR level at which the earn-out is zero | B94: 0.55 | D94: The case's worst case (45% churn) → sellers receive nothing extra below 55% retention.
A95: Retained-ARR level at which the earn-out is fully paid | B95: 1 | D95: 100% retention → full headline.
A96: Collar on Paytm shares used to settle the earn-out (± band) | B96: 0.15 | D96: Protects both sides against stock moves between exercise and settlement.
... A103: Walk-away: time to build/partner (years) | B103: 3 | D103: 24–36 months.
A105: G. TEAM ASSUMPTIONS — synergies (base case = zero; upside quantified on 'Synergies')
A106: Include synergies in the base case? (1 = yes, 0 = no) | B106: 0 | D106: Base excludes synergies: none is proven, most are not ownership-dependent, and the MDR is a standalone Paytm item.
A107: Partnership revenue to Liminal from Paytm use cases by year 3 (₹ Cr) | B107: 30 | D107: Custody/MPC fees on Paytm's tokenised-treasury, e₹ and cross-border pilots. Achievable under a commercial agreement WITHOUT ownership (not ownership-dependent).
A108: Cross-sell revenue to Liminal from Paytm's merchant/institutional base by year 3 (₹ Cr) | B108: 20 | D108: Ownership-dependent share only partly; requires the ring-fence not to be breached.
A109: Cost synergies (₹ Cr/yr) from year 2 | B109: 0 | D109: Deliberately zero: any shared-services integration breaches the information barrier that protects the franchise.
A110: Synergy ramp — share achieved in year 1 | B110: 0.25
A111: Synergy ramp — share achieved in year 2 | B111: 0.6

Sheet Liminal_Ops
A1: LIMINAL OPERATING FORECAST — 10 years, from case ARR ₹220 Cr and team assumptions (Inputs §D)
A2: Block 1: standalone, no churn, at the Dashboard growth case. Block 2: after a full acquisition, with the Dashboard churn applied in the churn year. Revenue = ARR run-rate.
A4: BLOCK 1 — Standalone Liminal (no churn) at the selected growth case
A5: Year | C5: 0 | D5: 1 | E5: 2 | F5: 3 | G5: 4 | H5: 5 | I5: 6 | J5: 7 | K5: 8 | L5: 9 | M5: 10
A6: Revenue (ARR run-rate) before churn | C6: =cf_arr -> 220 | D6: =C6*(1+lv_g) -> 264 | E6: =D6*(1+lv_g) -> 316.8 | F6: =E6*(1+lv_g) -> 380.16 | G6: =F6*(1+lv_g) -> 456.192 | H6: =G6*(1+lv_g) -> 547.4304 | I6: =H6*(1+lv_g) -> 656.91648 | J6: =I6*(1+lv_g) -> 788.29978 | K6: =J6*(1+lv_g) -> 945.95973 | ... M6: =L6*(1+lv_g) -> 1362.182
A7: Retention factor (1 − churn from churn year) | C7: =1 -> 1 | D7: =IF(D5>=a_churn_year,1-0,1) -> 1 | E7: =IF(E5>=a_churn_year,1-0,1) -> 1 | F7: =IF(F5>=a_churn_year,1-0,1) -> 1 | G7: =IF(G5>=a_churn_year,1-0,1) -> 1 | H7: =IF(H5>=a_churn_year,1-0,1) -> 1 | I7: =IF(I5>=a_churn_year,1-0,1) -> 1 | J7: =IF(J5>=a_churn_year,1-0,1) -> 1 | K7: =IF(K5>=a_churn_year,1-0,1) -> 1 | ... M7: =IF(M5>=a_churn_year,1-0,1) -> 1
A8: Revenue after churn | C8: =C6*C7 -> 220 | D8: =D6*D7 -> 264 | E8: =E6*E7 -> 316.8 | F8: =F6*F7 -> 380.16 | G8: =G6*G7 -> 456.192 | H8: =H6*H7 -> 547.4304 | I8: =I6*I7 -> 656.91648 | J8: =J6*J7 -> 788.29978 | ... M8: =M6*M7 -> 1362.182
A9: EBITDA margin (ramp) | C9: =MIN(a_m0+a_mstep*C5,a_mcap) -> 0 | D9: =MIN(a_m0+a_mstep*D5,a_mcap) -> 0.05 | E9: =MIN(a_m0+a_mstep*E5,a_mcap) -> 0.1 | F9: =MIN(a_m0+a_mstep*F5,a_mcap) -> 0.15 | G9: =MIN(a_m0+a_mstep*G5,a_mcap) -> 0.2 | H9: =MIN(a_m0+a_mstep*H5,a_mcap) -> 0.25 | I9: =MIN(a_m0+a_mstep*I5,a_mcap) -> 0.25 | J9: =MIN(a_m0+a_mstep*J5,a_mcap) -> 0.25 | ... M9: =MIN(a_m0+a_mstep*M5,a_mcap) -> 0.25
A10: Sticky cost of lost revenue (churn year only) | C10: =IF(C5=a_churn_year,a_sticky*(C6-C8)*(1-C9),0) -> 0 | D10: =IF(D5=a_churn_year,a_sticky*(D6-D8)*(1-D9),0) -> 0 | E10: =IF(E5=a_churn_year,a_sticky*(E6-E8)*(1-E9),0) -> 0 | F10: =IF(F5=a_churn_year,a_sticky*(F6-F8)*(1-F9),0) -> 0 | G10: =IF(G5=a_churn_year,a_sticky*(G6-G8)*(1-G9),0) -> 0 | H10: =IF(H5=a_churn_year,a_sticky*(H6-H8)*(1-H9),0) -> 0 | I10: =IF(I5=a_churn_year,a_sticky*(I6-I8)*(1-I9),0) -> 0 | J10: =IF(J5=a_churn_year,a_sticky*(J6-J8)*(1-J9),0) -> 0 | ... M10: =IF(M5=a_churn_year,a_sticky*(M6-M8)*(1-M9),0) -> 0
A11: EBITDA | C11: =C8*C9-C10 -> 0 | D11: =D8*D9-D10 -> 13.2 | E11: =E8*E9-E10 -> 31.68 | F11: =F8*F9-F10 -> 57.024 | G11: =G8*G9-G10 -> 91.2384 | H11: =H8*H9-H10 -> 136.8576 | I11: =I8*I9-I10 -> 164.22912 | J11: =J8*J9-J10 -> 197.07494 | ... M11: =M8*M9-M10 -> 340.5455
A12: Depreciation & amortisation | C12: =C8*a_da -> 6.6 | D12: =D8*a_da -> 7.92 | E12: =E8*a_da -> 9.504 | F12: =F8*a_da -> 11.4048 | G12: =G8*a_da -> 13.68576 | H12: =H8*a_da -> 16.422912 | I12: =I8*a_da -> 19.707494 | J12: =J8*a_da -> 23.648993 | ... M12: =M8*a_da -> 40.86546
A13: EBIT | C13: =C11-C12 -> -6.6 | D13: =D11-D12 -> 5.28 | E13: =E11-E12 -> 22.176 | F13: =F11-F12 -> 45.6192 | G13: =G11-G12 -> 77.55264 | H13: =H11-H12 -> 120.43469 | I13: =I11-I12 -> 144.52163 | J13: =J11-J12 -> 173.42595 | ... M13: =M11-M12 -> 299.68004
A14: Tax (only on positive EBIT; no group relief) | C14: =MAX(0,C13)*a_tax -> 0 | D14: =MAX(0,D13)*a_tax -> 1.32 | E14: =MAX(0,E13)*a_tax -> 5.544 | F14: =MAX(0,F13)*a_tax -> 11.4048 | G14: =MAX(0,G13)*a_tax -> 19.38816 | H14: =MAX(0,H13)*a_tax -> 30.108672 | I14: =MAX(0,I13)*a_tax -> 36.130406 | J14: =MAX(0,J13)*a_tax -> 43.356488 | ... M14: =MAX(0,M13)*a_tax -> 74.920011
A15: PAT (net income) | C15: =cf_lim_pat -> 0 | D15: =D13-D14 -> 3.96 | E15: =E13-E14 -> 16.632 | F15: =F13-F14 -> 34.2144 | G15: =G13-G14 -> 58.16448 | H15: =H13-H14 -> 90.326016 | I15: =I13-I14 -> 108.39122 | J15: =J13-J14 -> 130.06946 | K15: =K13-K14 -> 156.08336 | ... M15: =M13-M14 -> 224.76003
A16: Capex | C16: =C8*a_capex -> 6.6 | D16: =D8*a_capex -> 7.92 | E16: =E8*a_capex -> 9.504 | F16: =F8*a_capex -> 11.4048 | G16: =G8*a_capex -> 13.68576 | H16: =H8*a_capex -> 16.422912 | I16: =I8*a_capex -> 19.707494 | J16: =J8*a_capex -> 23.648993 | ... M16: =M8*a_capex -> 40.86546
A17: Increase in working capital | C17: =0 -> 0 | D17: =a_wc*(D8-C8) -> 2.2 | E17: =a_wc*(E8-D8) -> 2.64 | F17: =a_wc*(F8-E8) -> 3.168 | G17: =a_wc*(G8-F8) -> 3.8016 | H17: =a_wc*(H8-G8) -> 4.56192 | I17: =a_wc*(I8-H8) -> 5.474304 | J17: =a_wc*(J8-I8) -> 6.5691648 | K17: =a_wc*(K8-J8) -> 7.8829978 | ... M17: =a_wc*(M8-L8) -> 11.351517
A18: Unlevered free cash flow = PAT + D&A − capex − ΔWC | C18: =0 -> 0 | D18: =D15+D12-D16-D17 -> 1.76 | E18: =E15+E12-E16-E17 -> 13.992 | F18: =F15+F12-F16-F17 -> 31.0464 | G18: =G15+G12-G16-G17 -> 54.36288 | H18: =H15+H12-H16-H17 -> 85.764096 | I18: =I15+I12-I16-I17 -> 102.91692 | J18: =J15+J12-J16-J17 -> 123.5003 | K18: =K15+K12-K16-K17 -> 148.20036 | ... M18: =M15+M12-M16-M17 -> 213.40852
A20: BLOCK 2 — Liminal after a FULL acquisition (case churn applied in year 1)
A21: Year | C21: 0 | D21: 1 | E21: 2 | F21: 3 | G21: 4 | H21: 5 | I21: 6 | J21: 7 | K21: 8 | L21: 9 | M21: 10
A22: Revenue (ARR run-rate) before churn | C22: =cf_arr -> 220 | D22: =C22*(1+lv_g) -> 264 | E22: =D22*(1+lv_g) -> 316.8 | F22: =E22*(1+lv_g) -> 380.16 | G22: =F22*(1+lv_g) -> 456.192 | H22: =G22*(1+lv_g) -> 547.4304 | I22: =H22*(1+lv_g) -> 656.91648 | J22: =I22*(1+lv_g) -> 788.29978 | K22: =J22*(1+lv_g) -> 945.95973 | ... M22: =L22*(1+lv_g) -> 1362.182
A23: Retention factor (1 − churn from churn year) | C23: =1 -> 1 | D23: =IF(D21>=a_churn_year,1-lv_churn,1) -> 0.625 | E23: =IF(E21>=a_churn_year,1-lv_churn,1) -> 0.625 | F23: =IF(F21>=a_churn_year,1-lv_churn,1) -> 0.625 | G23: =IF(G21>=a_churn_year,1-lv_churn,1) -> 0.625 | H23: =IF(H21>=a_churn_year,1-lv_churn,1) -> 0.625 | I23: =IF(I21>=a_churn_year,1-lv_churn,1) -> 0.625 | J23: =IF(J21>=a_churn_year,1-lv_churn,1) -> 0.625 | K23: =IF(K21>=a_churn_year,1-lv_churn,1) -> 0.625 | ... M23: =IF(M21>=a_churn_year,1-lv_churn,1) -> 0.625
A24: Revenue after churn | C24: =C22*C23 -> 220 | D24: =D22*D23 -> 165 | E24: =E22*E23 -> 198 | F24: =F22*F23 -> 237.6 | G24: =G22*G23 -> 285.12 | H24: =H22*H23 -> 342.144 | I24: =I22*I23 -> 410.5728 | J24: =J22*J23 -> 492.68736 | ... M24: =M22*M23 -> 851.36376
A25: EBITDA margin (ramp) | C25: =MIN(a_m0+a_mstep*C21,a_mcap) -> 0 | D25: =MIN(a_m0+a_mstep*D21,a_mcap) -> 0.05 | E25: =MIN(a_m0+a_mstep*E21,a_mcap) -> 0.1 | F25: =MIN(a_m0+a_mstep*F21,a_mcap) -> 0.15 | G25: =MIN(a_m0+a_mstep*G21,a_mcap) -> 0.2 | H25: =MIN(a_m0+a_mstep*H21,a_mcap) -> 0.25 | I25: =MIN(a_m0+a_mstep*I21,a_mcap) -> 0.25 | J25: =MIN(a_m0+a_mstep*J21,a_mcap) -> 0.25 | ... M25: =MIN(a_m0+a_mstep*M21,a_mcap) -> 0.25
A26: Sticky cost of lost revenue (churn year only) | C26: =IF(C21=a_churn_year,a_sticky*(C22-C24)*(1-C25),0) -> 0 | D26: =IF(D21=a_churn_year,a_sticky*(D22-D24)*(1-D25),0) -> 47.025 | E26: =IF(E21=a_churn_year,a_sticky*(E22-E24)*(1-E25),0) -> 0 | F26: =IF(F21=a_churn_year,a_sticky*(F22-F24)*(1-F25),0) -> 0 | G26: =IF(G21=a_churn_year,a_sticky*(G22-G24)*(1-G25),0) -> 0 | H26: =IF(H21=a_churn_year,a_sticky*(H22-H24)*(1-H25),0) -> 0 | I26: =IF(I21=a_churn_year,a_sticky*(I22-I24)*(1-I25),0) -> 0 | J26: =IF(J21=a_churn_year,a_sticky*(J22-J24)*(1-J25),0) -> 0 | ... M26: =IF(M21=a_churn_year,a_sticky*(M22-M24)*(1-M25),0) -> 0
A27: EBITDA | C27: =C24*C25-C26 -> 0 | D27: =D24*D25-D26 -> -38.775 | E27: =E24*E25-E26 -> 19.8 | F27: =F24*F25-F26 -> 35.64 | G27: =G24*G25-G26 -> 57.024 | H27: =H24*H25-H26 -> 85.536 | I27: =I24*I25-I26 -> 102.6432 | J27: =J24*J25-J26 -> 123.17184 | ... M27: =M24*M25-M26 -> 212.84094
A28: Depreciation & amortisation | C28: =C24*a_da -> 6.6 | D28: =D24*a_da -> 4.95 | E28: =E24*a_da -> 5.94 | F28: =F24*a_da -> 7.128 | G28: =G24*a_da -> 8.5536 | H28: =H24*a_da -> 10.26432 | I28: =I24*a_da -> 12.317184 | J28: =J24*a_da -> 14.780621 | ... M28: =M24*a_da -> 25.540913
A29: EBIT | C29: =C27-C28 -> -6.6 | D29: =D27-D28 -> -43.725 | E29: =E27-E28 -> 13.86 | F29: =F27-F28 -> 28.512 | G29: =G27-G28 -> 48.4704 | H29: =H27-H28 -> 75.27168 | I29: =I27-I28 -> 90.326016 | J29: =J27-J28 -> 108.39122 | ... M29: =M27-M28 -> 187.30003
A30: Tax (only on positive EBIT; no group relief) | C30: =MAX(0,C29)*a_tax -> 0 | D30: =MAX(0,D29)*a_tax -> 0 | E30: =MAX(0,E29)*a_tax -> 3.465 | F30: =MAX(0,F29)*a_tax -> 7.128 | G30: =MAX(0,G29)*a_tax -> 12.1176 | H30: =MAX(0,H29)*a_tax -> 18.81792 | I30: =MAX(0,I29)*a_tax -> 22.581504 | J30: =MAX(0,J29)*a_tax -> 27.097805 | ... M30: =MAX(0,M29)*a_tax -> 46.825007
A31: PAT (net income) | C31: =cf_lim_pat -> 0 | D31: =D29-D30 -> -43.725 | E31: =E29-E30 -> 10.395 | F31: =F29-F30 -> 21.384 | G31: =G29-G30 -> 36.3528 | H31: =H29-H30 -> 56.45376 | I31: =I29-I30 -> 67.744512 | J31: =J29-J30 -> 81.293414 | K31: =K29-K30 -> 97.552097 | ... M31: =M29-M30 -> 140.47502
A32: Capex | C32: =C24*a_capex -> 6.6 | D32: =D24*a_capex -> 4.95 | E32: =E24*a_capex -> 5.94 | F32: =F24*a_capex -> 7.128 | G32: =G24*a_capex -> 8.5536 | H32: =H24*a_capex -> 10.26432 | I32: =I24*a_capex -> 12.317184 | J32: =J24*a_capex -> 14.780621 | ... M32: =M24*a_capex -> 25.540913
A33: Increase in working capital | C33: =0 -> 0 | D33: =a_wc*(D24-C24) -> -2.75 | E33: =a_wc*(E24-D24) -> 1.65 | F33: =a_wc*(F24-E24) -> 1.98 | G33: =a_wc*(G24-F24) -> 2.376 | H33: =a_wc*(H24-G24) -> 2.8512 | I33: =a_wc*(I24-H24) -> 3.42144 | J33: =a_wc*(J24-I24) -> 4.105728 | K33: =a_wc*(K24-J24) -> 4.9268736 | ... M33: =a_wc*(M24-L24) -> 7.094698
A34: Unlevered free cash flow = PAT + D&A − capex − ΔWC | C34: =0 -> 0 | D34: =D31+D28-D32-D33 -> -40.975 | E34: =E31+E28-E32-E33 -> 8.745 | F34: =F31+F28-F32-F33 -> 19.404 | G34: =G31+G28-G32-G33 -> 33.9768 | H34: =H31+H28-H32-H33 -> 53.60256 | I34: =I31+I28-I32-I33 -> 64.323072 | J34: =J31+J28-J32-J33 -> 77.187686 | K34: =K31+K28-K32-K33 -> 92.625224 | ... M34: =M31+M28-M32-M33 -> 133.38032
A36: BLOCK 3 — Standalone revenue and PAT by growth case (no churn), for reference
A37: Year | C37: 0 | D37: 1 | E37: 2 | F37: 3 | G37: 4 | H37: 5 | I37: 6 | J37: 7 | K37: 8 | L37: 9 | M37: 10
A38: Bear — revenue | C38: =cf_arr -> 220 | D38: =C38*(1+a_g_bear) -> 242 | E38: =D38*(1+a_g_bear) -> 266.2 | F38: =E38*(1+a_g_bear) -> 292.82 | G38: =F38*(1+a_g_bear) -> 322.102 | H38: =G38*(1+a_g_bear) -> 354.3122 | I38: =H38*(1+a_g_bear) -> 389.74342 | J38: =I38*(1+a_g_bear) -> 428.71776 | K38: =J38*(1+a_g_bear) -> 471.58954 | ... M38: =L38*(1+a_g_bear) -> 570.62334
A39: Bear — PAT (margin ramp, tax on positive EBIT) | C39: =cf_lim_pat -> 0 | D39: =(D38*(MIN(a_m0+a_mstep*D37,a_mcap)-a_da))*(1-a_tax*(D38*(MIN(a_m0+a_mstep*D37,a_mcap)-a_da)>0)) -> 3.63 | E39: =(E38*(MIN(a_m0+a_mstep*E37,a_mcap)-a_da))*(1-a_tax*(E38*(MIN(a_m0+a_mstep*E37,a_mcap)-a_da)>0)) -> 13.9755 | F39: =(F38*(MIN(a_m0+a_mstep*F37,a_mcap)-a_da))*(1-a_tax*(F38*(MIN(a_m0+a_mstep*F37,a_mcap)-a_da)>0)) -> 26.3538 | G39: =(G38*(MIN(a_m0+a_mstep*G37,a_mcap)-a_da))*(1-a_tax*(G38*(MIN(a_m0+a_mstep*G37,a_mcap)-a_da)>0)) -> 41.068005 | H39: =(H38*(MIN(a_m0+a_mstep*H37,a_mcap)-a_da))*(1-a_tax*(H38*(MIN(a_m0+a_mstep*H37,a_mcap)-a_da)>0)) -> 58.461513 | I39: =(I38*(MIN(a_m0+a_mstep*I37,a_mcap)-a_da))*(1-a_tax*(I38*(MIN(a_m0+a_mstep*I37,a_mcap)-a_da)>0)) -> 64.307664 | J39: =(J38*(MIN(a_m0+a_mstep*J37,a_mcap)-a_da))*(1-a_tax*(J38*(MIN(a_m0+a_mstep*J37,a_mcap)-a_da)>0)) -> 70.738431 | K39: =(K38*(MIN(a_m0+a_mstep*K37,a_mcap)-a_da))*(1-a_tax*(K38*(MIN(a_m0+a_mstep*K37,a_mcap)-a_da)>0)) -> 77.812274 | ... M39: =(M38*(MIN(a_m0+a_mstep*M37,a_mcap)-a_da))*(1-a_tax*(M38*(MIN(a_m0+a_mstep*M37,a_mcap)-a_da)>0)) -> 94.152851
A40: Base — revenue | C40: =cf_arr -> 220 | D40: =C40*(1+a_g_base) -> 264 | E40: =D40*(1+a_g_base) -> 316.8 | F40: =E40*(1+a_g_base) -> 380.16 | G40: =F40*(1+a_g_base) -> 456.192 | H40: =G40*(1+a_g_base) -> 547.4304 | I40: =H40*(1+a_g_base) -> 656.91648 | J40: =I40*(1+a_g_base) -> 788.29978 | K40: =J40*(1+a_g_base) -> 945.95973 | ... M40: =L40*(1+a_g_base) -> 1362.182
A41: Base — PAT (margin ramp, tax on positive EBIT) | C41: =cf_lim_pat -> 0 | D41: =(D40*(MIN(a_m0+a_mstep*D37,a_mcap)-a_da))*(1-a_tax*(D40*(MIN(a_m0+a_mstep*D37,a_mcap)-a_da)>0)) -> 3.96 | E41: =(E40*(MIN(a_m0+a_mstep*E37,a_mcap)-a_da))*(1-a_tax*(E40*(MIN(a_m0+a_mstep*E37,a_mcap)-a_da)>0)) -> 16.632 | F41: =(F40*(MIN(a_m0+a_mstep*F37,a_mcap)-a_da))*(1-a_tax*(F40*(MIN(a_m0+a_mstep*F37,a_mcap)-a_da)>0)) -> 34.2144 | G41: =(G40*(MIN(a_m0+a_mstep*G37,a_mcap)-a_da))*(1-a_tax*(G40*(MIN(a_m0+a_mstep*G37,a_mcap)-a_da)>0)) -> 58.16448 | H41: =(H40*(MIN(a_m0+a_mstep*H37,a_mcap)-a_da))*(1-a_tax*(H40*(MIN(a_m0+a_mstep*H37,a_mcap)-a_da)>0)) -> 90.326016 | I41: =(I40*(MIN(a_m0+a_mstep*I37,a_mcap)-a_da))*(1-a_tax*(I40*(MIN(a_m0+a_mstep*I37,a_mcap)-a_da)>0)) -> 108.39122 | J41: =(J40*(MIN(a_m0+a_mstep*J37,a_mcap)-a_da))*(1-a_tax*(J40*(MIN(a_m0+a_mstep*J37,a_mcap)-a_da)>0)) -> 130.06946 | K41: =(K40*(MIN(a_m0+a_mstep*K37,a_mcap)-a_da))*(1-a_tax*(K40*(MIN(a_m0+a_mstep*K37,a_mcap)-a_da)>0)) -> 156.08336 | ... M41: =(M40*(MIN(a_m0+a_mstep*M37,a_mcap)-a_da))*(1-a_tax*(M40*(MIN(a_m0+a_mstep*M37,a_mcap)-a_da)>0)) -> 224.76003
A42: Bull — revenue | C42: =cf_arr -> 220 | D42: =C42*(1+a_g_bull) -> 286 | E42: =D42*(1+a_g_bull) -> 371.8 | F42: =E42*(1+a_g_bull) -> 483.34 | G42: =F42*(1+a_g_bull) -> 628.342 | H42: =G42*(1+a_g_bull) -> 816.8446 | I42: =H42*(1+a_g_bull) -> 1061.898 | J42: =I42*(1+a_g_bull) -> 1380.4674 | K42: =J42*(1+a_g_bull) -> 1794.6076 | ... M42: =L42*(1+a_g_bull) -> 3032.8868
A43: Bull — PAT (margin ramp, tax on positive EBIT) | C43: =cf_lim_pat -> 0 | D43: =(D42*(MIN(a_m0+a_mstep*D37,a_mcap)-a_da))*(1-a_tax*(D42*(MIN(a_m0+a_mstep*D37,a_mcap)-a_da)>0)) -> 4.29 | E43: =(E42*(MIN(a_m0+a_mstep*E37,a_mcap)-a_da))*(1-a_tax*(E42*(MIN(a_m0+a_mstep*E37,a_mcap)-a_da)>0)) -> 19.5195 | F43: =(F42*(MIN(a_m0+a_mstep*F37,a_mcap)-a_da))*(1-a_tax*(F42*(MIN(a_m0+a_mstep*F37,a_mcap)-a_da)>0)) -> 43.5006 | G43: =(G42*(MIN(a_m0+a_mstep*G37,a_mcap)-a_da))*(1-a_tax*(G42*(MIN(a_m0+a_mstep*G37,a_mcap)-a_da)>0)) -> 80.113605 | H43: =(H42*(MIN(a_m0+a_mstep*H37,a_mcap)-a_da))*(1-a_tax*(H42*(MIN(a_m0+a_mstep*H37,a_mcap)-a_da)>0)) -> 134.77936 | I43: =(I42*(MIN(a_m0+a_mstep*I37,a_mcap)-a_da))*(1-a_tax*(I42*(MIN(a_m0+a_mstep*I37,a_mcap)-a_da)>0)) -> 175.21317 | J43: =(J42*(MIN(a_m0+a_mstep*J37,a_mcap)-a_da))*(1-a_tax*(J42*(MIN(a_m0+a_mstep*J37,a_mcap)-a_da)>0)) -> 227.77712 | K43: =(K42*(MIN(a_m0+a_mstep*K37,a_mcap)-a_da))*(1-a_tax*(K42*(MIN(a_m0+a_mstep*K37,a_mcap)-a_da)>0)) -> 296.11025 | ... M43: =(M42*(MIN(a_m0+a_mstep*M37,a_mcap)-a_da))*(1-a_tax*(M42*(MIN(a_m0+a_mstep*M37,a_mcap)-a_da)>0)) -> 500.42633

Sheet DCF
A1: DCF — standalone value of Liminal, what you need to believe for ₹4,000 Cr, and sensitivity grids
A2: Unlevered FCF from Liminal_Ops Block 1 (standalone, no churn). End-year discounting. Terminal value = Gordon growth. This is the STANDALONE FINANCIAL value; strategic/option value is assessed separately (Structures, Synergies).
A4: 1. Standalone DCF at Dashboard settings (growth case, WACC)
A5: Year | C5: 0 | D5: 1 | E5: 2 | F5: 3 | G5: 4 | H5: 5 | I5: 6 | J5: 7 | K5: 8 | L5: 9 | M5: 10
A6: Unlevered FCF (from Liminal_Ops Block 1) | C6: =Liminal_Ops!C18 -> 0 | D6: =Liminal_Ops!D18 -> 1.76 | E6: =Liminal_Ops!E18 -> 13.992 | F6: =Liminal_Ops!F18 -> 31.0464 | G6: =Liminal_Ops!G18 -> 54.36288 | H6: =Liminal_Ops!H18 -> 85.764096 | I6: =Liminal_Ops!I18 -> 102.91692 | J6: =Liminal_Ops!J18 -> 123.5003 | ... M6: =Liminal_Ops!M18 -> 213.40852
A7: Discount factor | C7: =1 -> 1 | D7: =1/(1+lv_wacc)^D5 -> 0.88495575 | E7: =1/(1+lv_wacc)^E5 -> 0.78314668 | F7: =1/(1+lv_wacc)^F5 -> 0.69305016 | G7: =1/(1+lv_wacc)^G5 -> 0.61331873 | H7: =1/(1+lv_wacc)^H5 -> 0.54275994 | I7: =1/(1+lv_wacc)^I5 -> 0.48031853 | J7: =1/(1+lv_wacc)^J5 -> 0.42506064 | K7: =1/(1+lv_wacc)^K5 -> 0.37615986 | ... M7: =1/(1+lv_wacc)^M5 -> 0.29458835
A8: PV of FCF | C8: =C6*C7 -> 0 | D8: =D6*D7 -> 1.5575221 | E8: =E6*E7 -> 10.957788 | F8: =F6*F7 -> 21.516713 | G8: =G6*G7 -> 33.341772 | H8: =H6*H7 -> 46.549315 | I8: =I6*I7 -> 49.432901 | J8: =J6*J7 -> 52.495116 | ... M8: =M6*M7 -> 62.867662
A9: Sum of PV of FCF, years 1–10 (₹ Cr) | B9: =SUM(D8:M8) -> 393.6662
A10: Terminal value at Y10 (₹ Cr) = FCF10 × (1 + g) ÷ (WACC − g) | B10: =M6*(1+a_tg)/(lv_wacc-a_tg) -> 2800.9868
A11: PV of terminal value (₹ Cr) | B11: =B10*M7 -> 825.13806
A12: Standalone DCF value of 100% of Liminal (₹ Cr) | B12: =B9+B11 -> 1218.8043
A13: Share of value from terminal value | B13: =B11/B12 -> 0.67700622
A14: Implied EV ÷ current ARR | B14: =B12/cf_arr -> 5.5400194
A15: DCF value − headline price (₹ Cr): negative = price exceeds standalone value | B15: =B12-lv_price -> -2781.1957
A16: Price ÷ DCF value − 1 = premium over standalone value | B16: =lv_price/B12-1 -> 2.2819052
A17: DCF value of the minority stake (pro-rata, before minority discount) (₹ Cr) | B17: =lv_stake*B12 -> 316.88911
A18: Minority price ÷ pro-rata DCF value − 1 | B18: =lv_min_price/B17-1 -> 1.0511907
A20: 2. WHAT YOU NEED TO BELIEVE — standalone DCF by 10-year growth rate (no churn, no drag), at the Dashboard WACC
A21: Helper rows compute unlevered FCF for each growth rate with the same formulas as Liminal_Ops (closed form). The grid then discounts each row at several WACCs.
A22: Year | C22: 0 | D22: 1 | E22: 2 | F22: 3 | G22: 4 | H22: 5 | I22: 6 | J22: 7 | K22: 8 | L22: 9 | M22: 10
A23: Growth 10% p.a. — unlevered FCF | B23: 0.1 | C23: =0 -> 0 | D23: =(((cf_arr*(1+$B23)^D22)*IF(D22>=a_churn_year,1-0,1))*(MIN(a_m0+a_mstep*D22,a_mcap)-a_da)-IF(D22=a_churn_year,a_sticky*((cf_arr*(1+$B23)^D22)-((cf_arr*(1+$B23)^D22)*IF(D22>=a_churn_year,1-0,1)))*(1-MIN(a_m0+a_mstep*D22,a_mcap)),0))-MAX(0,(((cf_arr*(1+$B23)^D22)*IF(D22>=a_churn_year,1-0,1))*(MIN(a_m0+a_mstep*D22,a_mcap)-a_da)-IF(D22=a_churn_year,a_sticky*((cf_arr*(1+$B23)^D22)-((cf_arr*(1+$B23)^D22)*IF(D22>=a_churn_year,1-0,1)))*(1-MIN(a_m0+a_mstep*D22,a_mcap)),0)))*a_tax+((cf_arr*(1+$B23)^D22)*IF(D22>=a_churn_year,1-0,1))*a_da-((cf_arr*(1+$B23)^D22)*IF(D22>=a_churn_year,1-0,1))*a_capex-a_wc*(((cf_arr*(1+$B23)^D22)*IF(D22>=a_churn_year,1-0,1))-(cf_arr*(1+$B23)^C22*IF(C22>=a_churn_year,1-0,1))) -> 2.53 | E23: =(((cf_arr*(1+$B23)^E22)*IF(E22>=a_churn_year,1-0,1))*(MIN(a_m0+a_mstep*E22,a_mcap)-a_da)-IF(E22=a_churn_year,a_sticky*((cf_arr*(1+$B23)^E22)-((cf_arr*(1+$B23)^E22)*IF(E22>=a_churn_year,1-0,1)))*(1-MIN(a_m0+a_mstep*E22,a_mcap)),0))-MAX(0,(((cf_arr*(1+$B23)^E22)*IF(E22>=a_churn_year,1-0,1))*(MIN(a_m0+a_mstep*E22,a_mcap)-a_da)-IF(E22=a_churn_year,a_sticky*((cf_arr*(1+$B23)^E22)-((cf_arr*(1+$B23)^E22)*IF(E22>=a_churn_year,1-0,1)))*(1-MIN(a_m0+a_mstep*E22,a_mcap)),0)))*a_tax+((cf_arr*(1+$B23)^E22)*IF(E22>=a_churn_year,1-0,1))*a_da-((cf_arr*(1+$B23)^E22)*IF(E22>=a_churn_year,1-0,1))*a_capex-a_wc*(((cf_arr*(1+$B23)^E22)*IF(E22>=a_churn_year,1-0,1))-(cf_arr*(1+$B23)^D22*IF(D22>=a_churn_year,1-0,1))) -> 12.7655 | F23: =(((cf_arr*(1+$B23)^F22)*IF(F22>=a_churn_year,1-0,1))*(MIN(a_m0+a_mstep*F22,a_mcap)-a_da)-IF(F22=a_churn_year,a_sticky*((cf_arr*(1+$B23)^F22)-((cf_arr*(1+$B23)^F22)*IF(F22>=a_churn_year,1-0,1)))*(1-MIN(a_m0+a_mstep*F22,a_mcap)),0))-MAX(0,(((cf_arr*(1+$B23)^F22)*IF(F22>=a_churn_year,1-0,1))*(MIN(a_m0+a_mstep*F22,a_mcap)-a_da)-IF(F22=a_churn_year,a_sticky*((cf_arr*(1+$B23)^F22)-((cf_arr*(1+$B23)^F22)*IF(F22>=a_churn_year,1-0,1)))*(1-MIN(a_m0+a_mstep*F22,a_mcap)),0)))*a_tax+((cf_arr*(1+$B23)^F22)*IF(F22>=a_churn_year,1-0,1))*a_da-((cf_arr*(1+$B23)^F22)*IF(F22>=a_churn_year,1-0,1))*a_capex-a_wc*(((cf_arr*(1+$B23)^F22)*IF(F22>=a_churn_year,1-0,1))-(cf_arr*(1+$B23)^E22*IF(E22>=a_churn_year,1-0,1))) -> 25.0228 | G23: =(((cf_arr*(1+$B23)^G22)*IF(G22>=a_churn_year,1-0,1))*(MIN(a_m0+a_mstep*G22,a_mcap)-a_da)-IF(G22=a_churn_year,a_sticky*((cf_arr*(1+$B23)^G22)-((cf_arr*(1+$B23)^G22)*IF(G22>=a_churn_year,1-0,1)))*(1-MIN(a_m0+a_mstep*G22,a_mcap)),0))-MAX(0,(((cf_arr*(1+$B23)^G22)*IF(G22>=a_churn_year,1-0,1))*(MIN(a_m0+a_mstep*G22,a_mcap)-a_da)-IF(G22=a_churn_year,a_sticky*((cf_arr*(1+$B23)^G22)-((cf_arr*(1+$B23)^G22)*IF(G22>=a_churn_year,1-0,1)))*(1-MIN(a_m0+a_mstep*G22,a_mcap)),0)))*a_tax+((cf_arr*(1+$B23)^G22)*IF(G22>=a_churn_year,1-0,1))*a_da-((cf_arr*(1+$B23)^G22)*IF(G22>=a_churn_year,1-0,1))*a_capex-a_wc*(((cf_arr*(1+$B23)^G22)*IF(G22>=a_churn_year,1-0,1))-(cf_arr*(1+$B23)^F22*IF(F22>=a_churn_year,1-0,1))) -> 39.603905 | H23: =(((cf_arr*(1+$B23)^H22)*IF(H22>=a_churn_year,1-0,1))*(MIN(a_m0+a_mstep*H22,a_mcap)-a_da)-IF(H22=a_churn_year,a_sticky*((cf_arr*(1+$B23)^H22)-((cf_arr*(1+$B23)^H22)*IF(H22>=a_churn_year,1-0,1)))*(1-MIN(a_m0+a_mstep*H22,a_mcap)),0))-MAX(0,(((cf_arr*(1+$B23)^H22)*IF(H22>=a_churn_year,1-0,1))*(MIN(a_m0+a_mstep*H22,a_mcap)-a_da)-IF(H22=a_churn_year,a_sticky*((cf_arr*(1+$B23)^H22)-((cf_arr*(1+$B23)^H22)*IF(H22>=a_churn_year,1-0,1)))*(1-MIN(a_m0+a_mstep*H22,a_mcap)),0)))*a_tax+((cf_arr*(1+$B23)^H22)*IF(H22>=a_churn_year,1-0,1))*a_da-((cf_arr*(1+$B23)^H22)*IF(H22>=a_churn_year,1-0,1))*a_capex-a_wc*(((cf_arr*(1+$B23)^H22)*IF(H22>=a_churn_year,1-0,1))-(cf_arr*(1+$B23)^G22*IF(G22>=a_churn_year,1-0,1))) -> 56.851003 | I23: =(((cf_arr*(1+$B23)^I22)*IF(I22>=a_churn_year,1-0,1))*(MIN(a_m0+a_mstep*I22,a_mcap)-a_da)-IF(I22=a_churn_year,a_sticky*((cf_arr*(1+$B23)^I22)-((cf_arr*(1+$B23)^I22)*IF(I22>=a_churn_year,1-0,1)))*(1-MIN(a_m0+a_mstep*I22,a_mcap)),0))-MAX(0,(((cf_arr*(1+$B23)^I22)*IF(I22>=a_churn_year,1-0,1))*(MIN(a_m0+a_mstep*I22,a_mcap)-a_da)-IF(I22=a_churn_year,a_sticky*((cf_arr*(1+$B23)^I22)-((cf_arr*(1+$B23)^I22)*IF(I22>=a_churn_year,1-0,1)))*(1-MIN(a_m0+a_mstep*I22,a_mcap)),0)))*a_tax+((cf_arr*(1+$B23)^I22)*IF(I22>=a_churn_year,1-0,1))*a_da-((cf_arr*(1+$B23)^I22)*IF(I22>=a_churn_year,1-0,1))*a_capex-a_wc*(((cf_arr*(1+$B23)^I22)*IF(I22>=a_churn_year,1-0,1))-(cf_arr*(1+$B23)^H22*IF(H22>=a_churn_year,1-0,1))) -> 62.536103 | J23: =(((cf_arr*(1+$B23)^J22)*IF(J22>=a_churn_year,1-0,1))*(MIN(a_m0+a_mstep*J22,a_mcap)-a_da)-IF(J22=a_churn_year,a_sticky*((cf_arr*(1+$B23)^J22)-((cf_arr*(1+$B23)^J22)*IF(J22>=a_churn_year,1-0,1)))*(1-MIN(a_m0+a_mstep*J22,a_mcap)),0))-MAX(0,(((cf_arr*(1+$B23)^J22)*IF(J22>=a_churn_year,1-0,1))*(MIN(a_m0+a_mstep*J22,a_mcap)-a_da)-IF(J22=a_churn_year,a_sticky*((cf_arr*(1+$B23)^J22)-((cf_arr*(1+$B23)^J22)*IF(J22>=a_churn_year,1-0,1)))*(1-MIN(a_m0+a_mstep*J22,a_mcap)),0)))*a_tax+((cf_arr*(1+$B23)^J22)*IF(J22>=a_churn_year,1-0,1))*a_da-((cf_arr*(1+$B23)^J22)*IF(J22>=a_churn_year,1-0,1))*a_capex-a_wc*(((cf_arr*(1+$B23)^J22)*IF(J22>=a_churn_year,1-0,1))-(cf_arr*(1+$B23)^I22*IF(I22>=a_churn_year,1-0,1))) -> 68.789714 | K23: =(((cf_arr*(1+$B23)^K22)*IF(K22>=a_churn_year,1-0,1))*(MIN(a_m0+a_mstep*K22,a_mcap)-a_da)-IF(K22=a_churn_year,a_sticky*((cf_arr*(1+$B23)^K22)-((cf_arr*(1+$B23)^K22)*IF(K22>=a_churn_year,1-0,1)))*(1-MIN(a_m0+a_mstep*K22,a_mcap)),0))-MAX(0,(((cf_arr*(1+$B23)^K22)*IF(K22>=a_churn_year,1-0,1))*(MIN(a_m0+a_mstep*K22,a_mcap)-a_da)-IF(K22=a_churn_year,a_sticky*((cf_arr*(1+$B23)^K22)-((cf_arr*(1+$B23)^K22)*IF(K22>=a_churn_year,1-0,1)))*(1-MIN(a_m0+a_mstep*K22,a_mcap)),0)))*a_tax+((cf_arr*(1+$B23)^K22)*IF(K22>=a_churn_year,1-0,1))*a_da-((cf_arr*(1+$B23)^K22)*IF(K22>=a_churn_year,1-0,1))*a_capex-a_wc*(((cf_arr*(1+$B23)^K22)*IF(K22>=a_churn_year,1-0,1))-(cf_arr*(1+$B23)^J22*IF(J22>=a_churn_year,1-0,1))) -> 75.668685 | ... M23: =(((cf_arr*(1+$B23)^M22)*IF(M22>=a_churn_year,1-0,1))*(MIN(a_m0+a_mstep*M22,a_mcap)-a_da)-IF(M22=a_churn_year,a_sticky*((cf_arr*(1+$B23)^M22)-((cf_arr*(1+$B23)^M22)*IF(M22>=a_churn_year,1-0,1)))*(1-MIN(a_m0+a_mstep*M22,a_mcap)),0))-MAX(0,(((cf_arr*(1+$B23)^M22)*IF(M22>=a_churn_year,1-0,1))*(MIN(a_m0+a_mstep*M22,a_mcap)-a_da)-IF(M22=a_churn_year,a_sticky*((cf_arr*(1+$B23)^M22)-((cf_arr*(1+$B23)^M22)*IF(M22>=a_churn_year,1-0,1)))*(1-MIN(a_m0+a_mstep*M22,a_mcap)),0)))*a_tax+((cf_arr*(1+$B23)^M22)*IF(M22>=a_churn_year,1-0,1))*a_da-((cf_arr*(1+$B23)^M22)*IF(M22>=a_churn_year,1-0,1))*a_capex-a_wc*(((cf_arr*(1+$B23)^M22)*IF(M22>=a_churn_year,1-0,1))-(cf_arr*(1+$B23)^L22*IF(L22>=a_churn_year,1-0,1))) -> 91.559109
A24: Growth 15% p.a. — unlevered FCF | B24: 0.15 | C24: =0 -> 0 | D24: =(((cf_arr*(1+$B24)^D22)*IF(D22>=a_churn_year,1-0,1))*(MIN(a_m0+a_mstep*D22,a_mcap)-a_da)-IF(D22=a_churn_year,a_sticky*((cf_arr*(1+$B24)^D22)-((cf_arr*(1+$B24)^D22)*IF(D22>=a_churn_year,1-0,1)))*(1-MIN(a_m0+a_mstep*D22,a_mcap)),0))-MAX(0,(((cf_arr*(1+$B24)^D22)*IF(D22>=a_churn_year,1-0,1))*(MIN(a_m0+a_mstep*D22,a_mcap)-a_da)-IF(D22=a_churn_year,a_sticky*((cf_arr*(1+$B24)^D22)-((cf_arr*(1+$B24)^D22)*IF(D22>=a_churn_year,1-0,1)))*(1-MIN(a_m0+a_mstep*D22,a_mcap)),0)))*a_tax+((cf_arr*(1+$B24)^D22)*IF(D22>=a_churn_year,1-0,1))*a_da-((cf_arr*(1+$B24)^D22)*IF(D22>=a_churn_year,1-0,1))*a_capex-a_wc*(((cf_arr*(1+$B24)^D22)*IF(D22>=a_churn_year,1-0,1))-(cf_arr*(1+$B24)^C22*IF(C22>=a_churn_year,1-0,1))) -> 2.145 | E24: =(((cf_arr*(1+$B24)^E22)*IF(E22>=a_churn_year,1-0,1))*(MIN(a_m0+a_mstep*E22,a_mcap)-a_da)-IF(E22=a_churn_year,a_sticky*((cf_arr*(1+$B24)^E22)-((cf_arr*(1+$B24)^E22)*IF(E22>=a_churn_year,1-0,1)))*(1-MIN(a_m0+a_mstep*E22,a_mcap)),0))-MAX(0,(((cf_arr*(1+$B24)^E22)*IF(E22>=a_churn_year,1-0,1))*(MIN(a_m0+a_mstep*E22,a_mcap)-a_da)-IF(E22=a_churn_year,a_sticky*((cf_arr*(1+$B24)^E22)-((cf_arr*(1+$B24)^E22)*IF(E22>=a_churn_year,1-0,1)))*(1-MIN(a_m0+a_mstep*E22,a_mcap)),0)))*a_tax+((cf_arr*(1+$B24)^E22)*IF(E22>=a_churn_year,1-0,1))*a_da-((cf_arr*(1+$B24)^E22)*IF(E22>=a_churn_year,1-0,1))*a_capex-a_wc*(((cf_arr*(1+$B24)^E22)*IF(E22>=a_churn_year,1-0,1))-(cf_arr*(1+$B24)^D22*IF(D22>=a_churn_year,1-0,1))) -> 13.377375 | F24: =(((cf_arr*(1+$B24)^F22)*IF(F22>=a_churn_year,1-0,1))*(MIN(a_m0+a_mstep*F22,a_mcap)-a_da)-IF(F22=a_churn_year,a_sticky*((cf_arr*(1+$B24)^F22)-((cf_arr*(1+$B24)^F22)*IF(F22>=a_churn_year,1-0,1)))*(1-MIN(a_m0+a_mstep*F22,a_mcap)),0))-MAX(0,(((cf_arr*(1+$B24)^F22)*IF(F22>=a_churn_year,1-0,1))*(MIN(a_m0+a_mstep*F22,a_mcap)-a_da)-IF(F22=a_churn_year,a_sticky*((cf_arr*(1+$B24)^F22)-((cf_arr*(1+$B24)^F22)*IF(F22>=a_churn_year,1-0,1)))*(1-MIN(a_m0+a_mstep*F22,a_mcap)),0)))*a_tax+((cf_arr*(1+$B24)^F22)*IF(F22>=a_churn_year,1-0,1))*a_da-((cf_arr*(1+$B24)^F22)*IF(F22>=a_churn_year,1-0,1))*a_capex-a_wc*(((cf_arr*(1+$B24)^F22)*IF(F22>=a_churn_year,1-0,1))-(cf_arr*(1+$B24)^E22*IF(E22>=a_churn_year,1-0,1))) -> 27.9312 | G24: =(((cf_arr*(1+$B24)^G22)*IF(G22>=a_churn_year,1-0,1))*(MIN(a_m0+a_mstep*G22,a_mcap)-a_da)-IF(G22=a_churn_year,a_sticky*((cf_arr*(1+$B24)^G22)-((cf_arr*(1+$B24)^G22)*IF(G22>=a_churn_year,1-0,1)))*(1-MIN(a_m0+a_mstep*G22,a_mcap)),0))-MAX(0,(((cf_arr*(1+$B24)^G22)*IF(G22>=a_churn_year,1-0,1))*(MIN(a_m0+a_mstep*G22,a_mcap)-a_da)-IF(G22=a_churn_year,a_sticky*((cf_arr*(1+$B24)^G22)-((cf_arr*(1+$B24)^G22)*IF(G22>=a_churn_year,1-0,1)))*(1-MIN(a_m0+a_mstep*G22,a_mcap)),0)))*a_tax+((cf_arr*(1+$B24)^G22)*IF(G22>=a_churn_year,1-0,1))*a_da-((cf_arr*(1+$B24)^G22)*IF(G22>=a_churn_year,1-0,1))*a_capex-a_wc*(((cf_arr*(1+$B24)^G22)*IF(G22>=a_churn_year,1-0,1))-(cf_arr*(1+$B24)^F22*IF(F22>=a_churn_year,1-0,1))) -> 46.550182 | H24: =(((cf_arr*(1+$B24)^H22)*IF(H22>=a_churn_year,1-0,1))*(MIN(a_m0+a_mstep*H22,a_mcap)-a_da)-IF(H22=a_churn_year,a_sticky*((cf_arr*(1+$B24)^H22)-((cf_arr*(1+$B24)^H22)*IF(H22>=a_churn_year,1-0,1)))*(1-MIN(a_m0+a_mstep*H22,a_mcap)),0))-MAX(0,(((cf_arr*(1+$B24)^H22)*IF(H22>=a_churn_year,1-0,1))*(MIN(a_m0+a_mstep*H22,a_mcap)-a_da)-IF(H22=a_churn_year,a_sticky*((cf_arr*(1+$B24)^H22)-((cf_arr*(1+$B24)^H22)*IF(H22>=a_churn_year,1-0,1)))*(1-MIN(a_m0+a_mstep*H22,a_mcap)),0)))*a_tax+((cf_arr*(1+$B24)^H22)*IF(H22>=a_churn_year,1-0,1))*a_da-((cf_arr*(1+$B24)^H22)*IF(H22>=a_churn_year,1-0,1))*a_capex-a_wc*(((cf_arr*(1+$B24)^H22)*IF(H22>=a_churn_year,1-0,1))-(cf_arr*(1+$B24)^G22*IF(G22>=a_churn_year,1-0,1))) -> 70.126406 | I24: =(((cf_arr*(1+$B24)^I22)*IF(I22>=a_churn_year,1-0,1))*(MIN(a_m0+a_mstep*I22,a_mcap)-a_da)-IF(I22=a_churn_year,a_sticky*((cf_arr*(1+$B24)^I22)-((cf_arr*(1+$B24)^I22)*IF(I22>=a_churn_year,1-0,1)))*(1-MIN(a_m0+a_mstep*I22,a_mcap)),0))-MAX(0,(((cf_arr*(1+$B24)^I22)*IF(I22>=a_churn_year,1-0,1))*(MIN(a_m0+a_mstep*I22,a_mcap)-a_da)-IF(I22=a_churn_year,a_sticky*((cf_arr*(1+$B24)^I22)-((cf_arr*(1+$B24)^I22)*IF(I22>=a_churn_year,1-0,1)))*(1-MIN(a_m0+a_mstep*I22,a_mcap)),0)))*a_tax+((cf_arr*(1+$B24)^I22)*IF(I22>=a_churn_year,1-0,1))*a_da-((cf_arr*(1+$B24)^I22)*IF(I22>=a_churn_year,1-0,1))*a_capex-a_wc*(((cf_arr*(1+$B24)^I22)*IF(I22>=a_churn_year,1-0,1))-(cf_arr*(1+$B24)^H22*IF(H22>=a_churn_year,1-0,1))) -> 80.645366 | J24: =(((cf_arr*(1+$B24)^J22)*IF(J22>=a_churn_year,1-0,1))*(MIN(a_m0+a_mstep*J22,a_mcap)-a_da)-IF(J22=a_churn_year,a_sticky*((cf_arr*(1+$B24)^J22)-((cf_arr*(1+$B24)^J22)*IF(J22>=a_churn_year,1-0,1)))*(1-MIN(a_m0+a_mstep*J22,a_mcap)),0))-MAX(0,(((cf_arr*(1+$B24)^J22)*IF(J22>=a_churn_year,1-0,1))*(MIN(a_m0+a_mstep*J22,a_mcap)-a_da)-IF(J22=a_churn_year,a_sticky*((cf_arr*(1+$B24)^J22)-((cf_arr*(1+$B24)^J22)*IF(J22>=a_churn_year,1-0,1)))*(1-MIN(a_m0+a_mstep*J22,a_mcap)),0)))*a_tax+((cf_arr*(1+$B24)^J22)*IF(J22>=a_churn_year,1-0,1))*a_da-((cf_arr*(1+$B24)^J22)*IF(J22>=a_churn_year,1-0,1))*a_capex-a_wc*(((cf_arr*(1+$B24)^J22)*IF(J22>=a_churn_year,1-0,1))-(cf_arr*(1+$B24)^I22*IF(I22>=a_churn_year,1-0,1))) -> 92.742171 | K24: =(((cf_arr*(1+$B24)^K22)*IF(K22>=a_churn_year,1-0,1))*(MIN(a_m0+a_mstep*K22,a_mcap)-a_da)-IF(K22=a_churn_year,a_sticky*((cf_arr*(1+$B24)^K22)-((cf_arr*(1+$B24)^K22)*IF(K22>=a_churn_year,1-0,1)))*(1-MIN(a_m0+a_mstep*K22,a_mcap)),0))-MAX(0,(((cf_arr*(1+$B24)^K22)*IF(K22>=a_churn_year,1-0,1))*(MIN(a_m0+a_mstep*K22,a_mcap)-a_da)-IF(K22=a_churn_year,a_sticky*((cf_arr*(1+$B24)^K22)-((cf_arr*(1+$B24)^K22)*IF(K22>=a_churn_year,1-0,1)))*(1-MIN(a_m0+a_mstep*K22,a_mcap)),0)))*a_tax+((cf_arr*(1+$B24)^K22)*IF(K22>=a_churn_year,1-0,1))*a_da-((cf_arr*(1+$B24)^K22)*IF(K22>=a_churn_year,1-0,1))*a_capex-a_wc*(((cf_arr*(1+$B24)^K22)*IF(K22>=a_churn_year,1-0,1))-(cf_arr*(1+$B24)^J22*IF(J22>=a_churn_year,1-0,1))) -> 106.6535 | ... M24: =(((cf_arr*(1+$B24)^M22)*IF(M22>=a_churn_year,1-0,1))*(MIN(a_m0+a_mstep*M22,a_mcap)-a_da)-IF(M22=a_churn_year,a_sticky*((cf_arr*(1+$B24)^M22)-((cf_arr*(1+$B24)^M22)*IF(M22>=a_churn_year,1-0,1)))*(1-MIN(a_m0+a_mstep*M22,a_mcap)),0))-MAX(0,(((cf_arr*(1+$B24)^M22)*IF(M22>=a_churn_year,1-0,1))*(MIN(a_m0+a_mstep*M22,a_mcap)-a_da)-IF(M22=a_churn_year,a_sticky*((cf_arr*(1+$B24)^M22)-((cf_arr*(1+$B24)^M22)*IF(M22>=a_churn_year,1-0,1)))*(1-MIN(a_m0+a_mstep*M22,a_mcap)),0)))*a_tax+((cf_arr*(1+$B24)^M22)*IF(M22>=a_churn_year,1-0,1))*a_da-((cf_arr*(1+$B24)^M22)*IF(M22>=a_churn_year,1-0,1))*a_capex-a_wc*(((cf_arr*(1+$B24)^M22)*IF(M22>=a_churn_year,1-0,1))-(cf_arr*(1+$B24)^L22*IF(L22>=a_churn_year,1-0,1))) -> 141.04925
A25: Growth 20% p.a. — unlevered FCF | B25: 0.2 | C25: =0 -> 0 | D25: =(((cf_arr*(1+$B25)^D22)*IF(D22>=a_churn_year,1-0,1))*(MIN(a_m0+a_mstep*D22,a_mcap)-a_da)-IF(D22=a_churn_year,a_sticky*((cf_arr*(1+$B25)^D22)-((cf_arr*(1+$B25)^D22)*IF(D22>=a_churn_year,1-0,1)))*(1-MIN(a_m0+a_mstep*D22,a_mcap)),0))-MAX(0,(((cf_arr*(1+$B25)^D22)*IF(D22>=a_churn_year,1-0,1))*(MIN(a_m0+a_mstep*D22,a_mcap)-a_da)-IF(D22=a_churn_year,a_sticky*((cf_arr*(1+$B25)^D22)-((cf_arr*(1+$B25)^D22)*IF(D22>=a_churn_year,1-0,1)))*(1-MIN(a_m0+a_mstep*D22,a_mcap)),0)))*a_tax+((cf_arr*(1+$B25)^D22)*IF(D22>=a_churn_year,1-0,1))*a_da-((cf_arr*(1+$B25)^D22)*IF(D22>=a_churn_year,1-0,1))*a_capex-a_wc*(((cf_arr*(1+$B25)^D22)*IF(D22>=a_churn_year,1-0,1))-(cf_arr*(1+$B25)^C22*IF(C22>=a_churn_year,1-0,1))) -> 1.76 | E25: =(((cf_arr*(1+$B25)^E22)*IF(E22>=a_churn_year,1-0,1))*(MIN(a_m0+a_mstep*E22,a_mcap)-a_da)-IF(E22=a_churn_year,a_sticky*((cf_arr*(1+$B25)^E22)-((cf_arr*(1+$B25)^E22)*IF(E22>=a_churn_year,1-0,1)))*(1-MIN(a_m0+a_mstep*E22,a_mcap)),0))-MAX(0,(((cf_arr*(1+$B25)^E22)*IF(E22>=a_churn_year,1-0,1))*(MIN(a_m0+a_mstep*E22,a_mcap)-a_da)-IF(E22=a_churn_year,a_sticky*((cf_arr*(1+$B25)^E22)-((cf_arr*(1+$B25)^E22)*IF(E22>=a_churn_year,1-0,1)))*(1-MIN(a_m0+a_mstep*E22,a_mcap)),0)))*a_tax+((cf_arr*(1+$B25)^E22)*IF(E22>=a_churn_year,1-0,1))*a_da-((cf_arr*(1+$B25)^E22)*IF(E22>=a_churn_year,1-0,1))*a_capex-a_wc*(((cf_arr*(1+$B25)^E22)*IF(E22>=a_churn_year,1-0,1))-(cf_arr*(1+$B25)^D22*IF(D22>=a_churn_year,1-0,1))) -> 13.992 | F25: =(((cf_arr*(1+$B25)^F22)*IF(F22>=a_churn_year,1-0,1))*(MIN(a_m0+a_mstep*F22,a_mcap)-a_da)-IF(F22=a_churn_year,a_sticky*((cf_arr*(1+$B25)^F22)-((cf_arr*(1+$B25)^F22)*IF(F22>=a_churn_year,1-0,1)))*(1-MIN(a_m0+a_mstep*F22,a_mcap)),0))-MAX(0,(((cf_arr*(1+$B25)^F22)*IF(F22>=a_churn_year,1-0,1))*(MIN(a_m0+a_mstep*F22,a_mcap)-a_da)-IF(F22=a_churn_year,a_sticky*((cf_arr*(1+$B25)^F22)-((cf_arr*(1+$B25)^F22)*IF(F22>=a_churn_year,1-0,1)))*(1-MIN(a_m0+a_mstep*F22,a_mcap)),0)))*a_tax+((cf_arr*(1+$B25)^F22)*IF(F22>=a_churn_year,1-0,1))*a_da-((cf_arr*(1+$B25)^F22)*IF(F22>=a_churn_year,1-0,1))*a_capex-a_wc*(((cf_arr*(1+$B25)^F22)*IF(F22>=a_churn_year,1-0,1))-(cf_arr*(1+$B25)^E22*IF(E22>=a_churn_year,1-0,1))) -> 31.0464 | G25: =(((cf_arr*(1+$B25)^G22)*IF(G22>=a_churn_year,1-0,1))*(MIN(a_m0+a_mstep*G22,a_mcap)-a_da)-IF(G22=a_churn_year,a_sticky*((cf_arr*(1+$B25)^G22)-((cf_arr*(1+$B25)^G22)*IF(G22>=a_churn_year,1-0,1)))*(1-MIN(a_m0+a_mstep*G22,a_mcap)),0))-MAX(0,(((cf_arr*(1+$B25)^G22)*IF(G22>=a_churn_year,1-0,1))*(MIN(a_m0+a_mstep*G22,a_mcap)-a_da)-IF(G22=a_churn_year,a_sticky*((cf_arr*(1+$B25)^G22)-((cf_arr*(1+$B25)^G22)*IF(G22>=a_churn_year,1-0,1)))*(1-MIN(a_m0+a_mstep*G22,a_mcap)),0)))*a_tax+((cf_arr*(1+$B25)^G22)*IF(G22>=a_churn_year,1-0,1))*a_da-((cf_arr*(1+$B25)^G22)*IF(G22>=a_churn_year,1-0,1))*a_capex-a_wc*(((cf_arr*(1+$B25)^G22)*IF(G22>=a_churn_year,1-0,1))-(cf_arr*(1+$B25)^F22*IF(F22>=a_churn_year,1-0,1))) -> 54.36288 | H25: =(((cf_arr*(1+$B25)^H22)*IF(H22>=a_churn_year,1-0,1))*(MIN(a_m0+a_mstep*H22,a_mcap)-a_da)-IF(H22=a_churn_year,a_sticky*((cf_arr*(1+$B25)^H22)-((cf_arr*(1+$B25)^H22)*IF(H22>=a_churn_year,1-0,1)))*(1-MIN(a_m0+a_mstep*H22,a_mcap)),0))-MAX(0,(((cf_arr*(1+$B25)^H22)*IF(H22>=a_churn_year,1-0,1))*(MIN(a_m0+a_mstep*H22,a_mcap)-a_da)-IF(H22=a_churn_year,a_sticky*((cf_arr*(1+$B25)^H22)-((cf_arr*(1+$B25)^H22)*IF(H22>=a_churn_year,1-0,1)))*(1-MIN(a_m0+a_mstep*H22,a_mcap)),0)))*a_tax+((cf_arr*(1+$B25)^H22)*IF(H22>=a_churn_year,1-0,1))*a_da-((cf_arr*(1+$B25)^H22)*IF(H22>=a_churn_year,1-0,1))*a_capex-a_wc*(((cf_arr*(1+$B25)^H22)*IF(H22>=a_churn_year,1-0,1))-(cf_arr*(1+$B25)^G22*IF(G22>=a_churn_year,1-0,1))) -> 85.764096 | I25: =(((cf_arr*(1+$B25)^I22)*IF(I22>=a_churn_year,1-0,1))*(MIN(a_m0+a_mstep*I22,a_mcap)-a_da)-IF(I22=a_churn_year,a_sticky*((cf_arr*(1+$B25)^I22)-((cf_arr*(1+$B25)^I22)*IF(I22>=a_churn_year,1-0,1)))*(1-MIN(a_m0+a_mstep*I22,a_mcap)),0))-MAX(0,(((cf_arr*(1+$B25)^I22)*IF(I22>=a_churn_year,1-0,1))*(MIN(a_m0+a_mstep*I22,a_mcap)-a_da)-IF(I22=a_churn_year,a_sticky*((cf_arr*(1+$B25)^I22)-((cf_arr*(1+$B25)^I22)*IF(I22>=a_churn_year,1-0,1)))*(1-MIN(a_m0+a_mstep*I22,a_mcap)),0)))*a_tax+((cf_arr*(1+$B25)^I22)*IF(I22>=a_churn_year,1-0,1))*a_da-((cf_arr*(1+$B25)^I22)*IF(I22>=a_churn_year,1-0,1))*a_capex-a_wc*(((cf_arr*(1+$B25)^I22)*IF(I22>=a_churn_year,1-0,1))-(cf_arr*(1+$B25)^H22*IF(H22>=a_churn_year,1-0,1))) -> 102.91692 | J25: =(((cf_arr*(1+$B25)^J22)*IF(J22>=a_churn_year,1-0,1))*(MIN(a_m0+a_mstep*J22,a_mcap)-a_da)-IF(J22=a_churn_year,a_sticky*((cf_arr*(1+$B25)^J22)-((cf_arr*(1+$B25)^J22)*IF(J22>=a_churn_year,1-0,1)))*(1-MIN(a_m0+a_mstep*J22,a_mcap)),0))-MAX(0,(((cf_arr*(1+$B25)^J22)*IF(J22>=a_churn_year,1-0,1))*(MIN(a_m0+a_mstep*J22,a_mcap)-a_da)-IF(J22=a_churn_year,a_sticky*((cf_arr*(1+$B25)^J22)-((cf_arr*(1+$B25)^J22)*IF(J22>=a_churn_year,1-0,1)))*(1-MIN(a_m0+a_mstep*J22,a_mcap)),0)))*a_tax+((cf_arr*(1+$B25)^J22)*IF(J22>=a_churn_year,1-0,1))*a_da-((cf_arr*(1+$B25)^J22)*IF(J22>=a_churn_year,1-0,1))*a_capex-a_wc*(((cf_arr*(1+$B25)^J22)*IF(J22>=a_churn_year,1-0,1))-(cf_arr*(1+$B25)^I22*IF(I22>=a_churn_year,1-0,1))) -> 123.5003 | K25: =(((cf_arr*(1+$B25)^K22)*IF(K22>=a_churn_year,1-0,1))*(MIN(a_m0+a_mstep*K22,a_mcap)-a_da)-IF(K22=a_churn_year,a_sticky*((cf_arr*(1+$B25)^K22)-((cf_arr*(1+$B25)^K22)*IF(K22>=a_churn_year,1-0,1)))*(1-MIN(a_m0+a_mstep*K22,a_mcap)),0))-MAX(0,(((cf_arr*(1+$B25)^K22)*IF(K22>=a_churn_year,1-0,1))*(MIN(a_m0+a_mstep*K22,a_mcap)-a_da)-IF(K22=a_churn_year,a_sticky*((cf_arr*(1+$B25)^K22)-((cf_arr*(1+$B25)^K22)*IF(K22>=a_churn_year,1-0,1)))*(1-MIN(a_m0+a_mstep*K22,a_mcap)),0)))*a_tax+((cf_arr*(1+$B25)^K22)*IF(K22>=a_churn_year,1-0,1))*a_da-((cf_arr*(1+$B25)^K22)*IF(K22>=a_churn_year,1-0,1))*a_capex-a_wc*(((cf_arr*(1+$B25)^K22)*IF(K22>=a_churn_year,1-0,1))-(cf_arr*(1+$B25)^J22*IF(J22>=a_churn_year,1-0,1))) -> 148.20036 | ... M25: =(((cf_arr*(1+$B25)^M22)*IF(M22>=a_churn_year,1-0,1))*(MIN(a_m0+a_mstep*M22,a_mcap)-a_da)-IF(M22=a_churn_year,a_sticky*((cf_arr*(1+$B25)^M22)-((cf_arr*(1+$B25)^M22)*IF(M22>=a_churn_year,1-0,1)))*(1-MIN(a_m0+a_mstep*M22,a_mcap)),0))-MAX(0,(((cf_arr*(1+$B25)^M22)*IF(M22>=a_churn_year,1-0,1))*(MIN(a_m0+a_mstep*M22,a_mcap)-a_da)-IF(M22=a_churn_year,a_sticky*((cf_arr*(1+$B25)^M22)-((cf_arr*(1+$B25)^M22)*IF(M22>=a_churn_year,1-0,1)))*(1-MIN(a_m0+a_mstep*M22,a_mcap)),0)))*a_tax+((cf_arr*(1+$B25)^M22)*IF(M22>=a_churn_year,1-0,1))*a_da-((cf_arr*(1+$B25)^M22)*IF(M22>=a_churn_year,1-0,1))*a_capex-a_wc*(((cf_arr*(1+$B25)^M22)*IF(M22>=a_churn_year,1-0,1))-(cf_arr*(1+$B25)^L22*IF(L22>=a_churn_year,1-0,1))) -> 213.40852
A26: Growth 25% p.a. — unlevered FCF | B26: 0.25 | C26: =0 -> 0 | D26: =(((cf_arr*(1+$B26)^D22)*IF(D22>=a_churn_year,1-0,1))*(MIN(a_m0+a_mstep*D22,a_mcap)-a_da)-IF(D22=a_churn_year,a_sticky*((cf_arr*(1+$B26)^D22)-((cf_arr*(1+$B26)^D22)*IF(D22>=a_churn_year,1-0,1)))*(1-MIN(a_m0+a_mstep*D22,a_mcap)),0))-MAX(0,(((cf_arr*(1+$B26)^D22)*IF(D22>=a_churn_year,1-0,1))*(MIN(a_m0+a_mstep*D22,a_mcap)-a_da)-IF(D22=a_churn_year,a_sticky*((cf_arr*(1+$B26)^D22)-((cf_arr*(1+$B26)^D22)*IF(D22>=a_churn_year,1-0,1)))*(1-MIN(a_m0+a_mstep*D22,a_mcap)),0)))*a_tax+((cf_arr*(1+$B26)^D22)*IF(D22>=a_churn_year,1-0,1))*a_da-((cf_arr*(1+$B26)^D22)*IF(D22>=a_churn_year,1-0,1))*a_capex-a_wc*(((cf_arr*(1+$B26)^D22)*IF(D22>=a_churn_year,1-0,1))-(cf_arr*(1+$B26)^C22*IF(C22>=a_churn_year,1-0,1))) -> 1.375 | E26: =(((cf_arr*(1+$B26)^E22)*IF(E22>=a_churn_year,1-0,1))*(MIN(a_m0+a_mstep*E22,a_mcap)-a_da)-IF(E22=a_churn_year,a_sticky*((cf_arr*(1+$B26)^E22)-((cf_arr*(1+$B26)^E22)*IF(E22>=a_churn_year,1-0,1)))*(1-MIN(a_m0+a_mstep*E22,a_mcap)),0))-MAX(0,(((cf_arr*(1+$B26)^E22)*IF(E22>=a_churn_year,1-0,1))*(MIN(a_m0+a_mstep*E22,a_mcap)-a_da)-IF(E22=a_churn_year,a_sticky*((cf_arr*(1+$B26)^E22)-((cf_arr*(1+$B26)^E22)*IF(E22>=a_churn_year,1-0,1)))*(1-MIN(a_m0+a_mstep*E22,a_mcap)),0)))*a_tax+((cf_arr*(1+$B26)^E22)*IF(E22>=a_churn_year,1-0,1))*a_da-((cf_arr*(1+$B26)^E22)*IF(E22>=a_churn_year,1-0,1))*a_capex-a_wc*(((cf_arr*(1+$B26)^E22)*IF(E22>=a_churn_year,1-0,1))-(cf_arr*(1+$B26)^D22*IF(D22>=a_churn_year,1-0,1))) -> 14.609375 | F26: =(((cf_arr*(1+$B26)^F22)*IF(F22>=a_churn_year,1-0,1))*(MIN(a_m0+a_mstep*F22,a_mcap)-a_da)-IF(F22=a_churn_year,a_sticky*((cf_arr*(1+$B26)^F22)-((cf_arr*(1+$B26)^F22)*IF(F22>=a_churn_year,1-0,1)))*(1-MIN(a_m0+a_mstep*F22,a_mcap)),0))-MAX(0,(((cf_arr*(1+$B26)^F22)*IF(F22>=a_churn_year,1-0,1))*(MIN(a_m0+a_mstep*F22,a_mcap)-a_da)-IF(F22=a_churn_year,a_sticky*((cf_arr*(1+$B26)^F22)-((cf_arr*(1+$B26)^F22)*IF(F22>=a_churn_year,1-0,1)))*(1-MIN(a_m0+a_mstep*F22,a_mcap)),0)))*a_tax+((cf_arr*(1+$B26)^F22)*IF(F22>=a_churn_year,1-0,1))*a_da-((cf_arr*(1+$B26)^F22)*IF(F22>=a_churn_year,1-0,1))*a_capex-a_wc*(((cf_arr*(1+$B26)^F22)*IF(F22>=a_churn_year,1-0,1))-(cf_arr*(1+$B26)^E22*IF(E22>=a_churn_year,1-0,1))) -> 34.375 | G26: =(((cf_arr*(1+$B26)^G22)*IF(G22>=a_churn_year,1-0,1))*(MIN(a_m0+a_mstep*G22,a_mcap)-a_da)-IF(G22=a_churn_year,a_sticky*((cf_arr*(1+$B26)^G22)-((cf_arr*(1+$B26)^G22)*IF(G22>=a_churn_year,1-0,1)))*(1-MIN(a_m0+a_mstep*G22,a_mcap)),0))-MAX(0,(((cf_arr*(1+$B26)^G22)*IF(G22>=a_churn_year,1-0,1))*(MIN(a_m0+a_mstep*G22,a_mcap)-a_da)-IF(G22=a_churn_year,a_sticky*((cf_arr*(1+$B26)^G22)-((cf_arr*(1+$B26)^G22)*IF(G22>=a_churn_year,1-0,1)))*(1-MIN(a_m0+a_mstep*G22,a_mcap)),0)))*a_tax+((cf_arr*(1+$B26)^G22)*IF(G22>=a_churn_year,1-0,1))*a_da-((cf_arr*(1+$B26)^G22)*IF(G22>=a_churn_year,1-0,1))*a_capex-a_wc*(((cf_arr*(1+$B26)^G22)*IF(G22>=a_churn_year,1-0,1))-(cf_arr*(1+$B26)^F22*IF(F22>=a_churn_year,1-0,1))) -> 63.110352 | H26: =(((cf_arr*(1+$B26)^H22)*IF(H22>=a_churn_year,1-0,1))*(MIN(a_m0+a_mstep*H22,a_mcap)-a_da)-IF(H22=a_churn_year,a_sticky*((cf_arr*(1+$B26)^H22)-((cf_arr*(1+$B26)^H22)*IF(H22>=a_churn_year,1-0,1)))*(1-MIN(a_m0+a_mstep*H22,a_mcap)),0))-MAX(0,(((cf_arr*(1+$B26)^H22)*IF(H22>=a_churn_year,1-0,1))*(MIN(a_m0+a_mstep*H22,a_mcap)-a_da)-IF(H22=a_churn_year,a_sticky*((cf_arr*(1+$B26)^H22)-((cf_arr*(1+$B26)^H22)*IF(H22>=a_churn_year,1-0,1)))*(1-MIN(a_m0+a_mstep*H22,a_mcap)),0)))*a_tax+((cf_arr*(1+$B26)^H22)*IF(H22>=a_churn_year,1-0,1))*a_da-((cf_arr*(1+$B26)^H22)*IF(H22>=a_churn_year,1-0,1))*a_capex-a_wc*(((cf_arr*(1+$B26)^H22)*IF(H22>=a_churn_year,1-0,1))-(cf_arr*(1+$B26)^G22*IF(G22>=a_churn_year,1-0,1))) -> 104.06494 | I26: =(((cf_arr*(1+$B26)^I22)*IF(I22>=a_churn_year,1-0,1))*(MIN(a_m0+a_mstep*I22,a_mcap)-a_da)-IF(I22=a_churn_year,a_sticky*((cf_arr*(1+$B26)^I22)-((cf_arr*(1+$B26)^I22)*IF(I22>=a_churn_year,1-0,1)))*(1-MIN(a_m0+a_mstep*I22,a_mcap)),0))-MAX(0,(((cf_arr*(1+$B26)^I22)*IF(I22>=a_churn_year,1-0,1))*(MIN(a_m0+a_mstep*I22,a_mcap)-a_da)-IF(I22=a_churn_year,a_sticky*((cf_arr*(1+$B26)^I22)-((cf_arr*(1+$B26)^I22)*IF(I22>=a_churn_year,1-0,1)))*(1-MIN(a_m0+a_mstep*I22,a_mcap)),0)))*a_tax+((cf_arr*(1+$B26)^I22)*IF(I22>=a_churn_year,1-0,1))*a_da-((cf_arr*(1+$B26)^I22)*IF(I22>=a_churn_year,1-0,1))*a_capex-a_wc*(((cf_arr*(1+$B26)^I22)*IF(I22>=a_churn_year,1-0,1))-(cf_arr*(1+$B26)^H22*IF(H22>=a_churn_year,1-0,1))) -> 130.08118 | J26: =(((cf_arr*(1+$B26)^J22)*IF(J22>=a_churn_year,1-0,1))*(MIN(a_m0+a_mstep*J22,a_mcap)-a_da)-IF(J22=a_churn_year,a_sticky*((cf_arr*(1+$B26)^J22)-((cf_arr*(1+$B26)^J22)*IF(J22>=a_churn_year,1-0,1)))*(1-MIN(a_m0+a_mstep*J22,a_mcap)),0))-MAX(0,(((cf_arr*(1+$B26)^J22)*IF(J22>=a_churn_year,1-0,1))*(MIN(a_m0+a_mstep*J22,a_mcap)-a_da)-IF(J22=a_churn_year,a_sticky*((cf_arr*(1+$B26)^J22)-((cf_arr*(1+$B26)^J22)*IF(J22>=a_churn_year,1-0,1)))*(1-MIN(a_m0+a_mstep*J22,a_mcap)),0)))*a_tax+((cf_arr*(1+$B26)^J22)*IF(J22>=a_churn_year,1-0,1))*a_da-((cf_arr*(1+$B26)^J22)*IF(J22>=a_churn_year,1-0,1))*a_capex-a_wc*(((cf_arr*(1+$B26)^J22)*IF(J22>=a_churn_year,1-0,1))-(cf_arr*(1+$B26)^I22*IF(I22>=a_churn_year,1-0,1))) -> 162.60147 | K26: =(((cf_arr*(1+$B26)^K22)*IF(K22>=a_churn_year,1-0,1))*(MIN(a_m0+a_mstep*K22,a_mcap)-a_da)-IF(K22=a_churn_year,a_sticky*((cf_arr*(1+$B26)^K22)-((cf_arr*(1+$B26)^K22)*IF(K22>=a_churn_year,1-0,1)))*(1-MIN(a_m0+a_mstep*K22,a_mcap)),0))-MAX(0,(((cf_arr*(1+$B26)^K22)*IF(K22>=a_churn_year,1-0,1))*(MIN(a_m0+a_mstep*K22,a_mcap)-a_da)-IF(K22=a_churn_year,a_sticky*((cf_arr*(1+$B26)^K22)-((cf_arr*(1+$B26)^K22)*IF(K22>=a_churn_year,1-0,1)))*(1-MIN(a_m0+a_mstep*K22,a_mcap)),0)))*a_tax+((cf_arr*(1+$B26)^K22)*IF(K22>=a_churn_year,1-0,1))*a_da-((cf_arr*(1+$B26)^K22)*IF(K22>=a_churn_year,1-0,1))*a_capex-a_wc*(((cf_arr*(1+$B26)^K22)*IF(K22>=a_churn_year,1-0,1))-(cf_arr*(1+$B26)^J22*IF(J22>=a_churn_year,1-0,1))) -> 203.25184 | ... M26: =(((cf_arr*(1+$B26)^M22)*IF(M22>=a_churn_year,1-0,1))*(MIN(a_m0+a_mstep*M22,a_mcap)-a_da)-IF(M22=a_churn_year,a_sticky*((cf_arr*(1+$B26)^M22)-((cf_arr*(1+$B26)^M22)*IF(M22>=a_churn_year,1-0,1)))*(1-MIN(a_m0+a_mstep*M22,a_mcap)),0))-MAX(0,(((cf_arr*(1+$B26)^M22)*IF(M22>=a_churn_year,1-0,1))*(MIN(a_m0+a_mstep*M22,a_mcap)-a_da)-IF(M22=a_churn_year,a_sticky*((cf_arr*(1+$B26)^M22)-((cf_arr*(1+$B26)^M22)*IF(M22>=a_churn_year,1-0,1)))*(1-MIN(a_m0+a_mstep*M22,a_mcap)),0)))*a_tax+((cf_arr*(1+$B26)^M22)*IF(M22>=a_churn_year,1-0,1))*a_da-((cf_arr*(1+$B26)^M22)*IF(M22>=a_churn_year,1-0,1))*a_capex-a_wc*(((cf_arr*(1+$B26)^M22)*IF(M22>=a_churn_year,1-0,1))-(cf_arr*(1+$B26)^L22*IF(L22>=a_churn_year,1-0,1))) -> 317.581
A27: Growth 30% p.a. — unlevered FCF | B27: 0.3 | C27: =0 -> 0 | D27: =(((cf_arr*(1+$B27)^D22)*IF(D22>=a_churn_year,1-0,1))*(MIN(a_m0+a_mstep*D22,a_mcap)-a_da)-IF(D22=a_churn_year,a_sticky*((cf_arr*(1+$B27)^D22)-((cf_arr*(1+$B27)^D22)*IF(D22>=a_churn_year,1-0,1)))*(1-MIN(a_m0+a_mstep*D22,a_mcap)),0))-MAX(0,(((cf_arr*(1+$B27)^D22)*IF(D22>=a_churn_year,1-0,1))*(MIN(a_m0+a_mstep*D22,a_mcap)-a_da)-IF(D22=a_churn_year,a_sticky*((cf_arr*(1+$B27)^D22)-((cf_arr*(1+$B27)^D22)*IF(D22>=a_churn_year,1-0,1)))*(1-MIN(a_m0+a_mstep*D22,a_mcap)),0)))*a_tax+((cf_arr*(1+$B27)^D22)*IF(D22>=a_churn_year,1-0,1))*a_da-((cf_arr*(1+$B27)^D22)*IF(D22>=a_churn_year,1-0,1))*a_capex-a_wc*(((cf_arr*(1+$B27)^D22)*IF(D22>=a_churn_year,1-0,1))-(cf_arr*(1+$B27)^C22*IF(C22>=a_churn_year,1-0,1))) -> 0.99 | E27: =(((cf_arr*(1+$B27)^E22)*IF(E22>=a_churn_year,1-0,1))*(MIN(a_m0+a_mstep*E22,a_mcap)-a_da)-IF(E22=a_churn_year,a_sticky*((cf_arr*(1+$B27)^E22)-((cf_arr*(1+$B27)^E22)*IF(E22>=a_churn_year,1-0,1)))*(1-MIN(a_m0+a_mstep*E22,a_mcap)),0))-MAX(0,(((cf_arr*(1+$B27)^E22)*IF(E22>=a_churn_year,1-0,1))*(MIN(a_m0+a_mstep*E22,a_mcap)-a_da)-IF(E22=a_churn_year,a_sticky*((cf_arr*(1+$B27)^E22)-((cf_arr*(1+$B27)^E22)*IF(E22>=a_churn_year,1-0,1)))*(1-MIN(a_m0+a_mstep*E22,a_mcap)),0)))*a_tax+((cf_arr*(1+$B27)^E22)*IF(E22>=a_churn_year,1-0,1))*a_da-((cf_arr*(1+$B27)^E22)*IF(E22>=a_churn_year,1-0,1))*a_capex-a_wc*(((cf_arr*(1+$B27)^E22)*IF(E22>=a_churn_year,1-0,1))-(cf_arr*(1+$B27)^D22*IF(D22>=a_churn_year,1-0,1))) -> 15.2295 | F27: =(((cf_arr*(1+$B27)^F22)*IF(F22>=a_churn_year,1-0,1))*(MIN(a_m0+a_mstep*F22,a_mcap)-a_da)-IF(F22=a_churn_year,a_sticky*((cf_arr*(1+$B27)^F22)-((cf_arr*(1+$B27)^F22)*IF(F22>=a_churn_year,1-0,1)))*(1-MIN(a_m0+a_mstep*F22,a_mcap)),0))-MAX(0,(((cf_arr*(1+$B27)^F22)*IF(F22>=a_churn_year,1-0,1))*(MIN(a_m0+a_mstep*F22,a_mcap)-a_da)-IF(F22=a_churn_year,a_sticky*((cf_arr*(1+$B27)^F22)-((cf_arr*(1+$B27)^F22)*IF(F22>=a_churn_year,1-0,1)))*(1-MIN(a_m0+a_mstep*F22,a_mcap)),0)))*a_tax+((cf_arr*(1+$B27)^F22)*IF(F22>=a_churn_year,1-0,1))*a_da-((cf_arr*(1+$B27)^F22)*IF(F22>=a_churn_year,1-0,1))*a_capex-a_wc*(((cf_arr*(1+$B27)^F22)*IF(F22>=a_churn_year,1-0,1))-(cf_arr*(1+$B27)^E22*IF(E22>=a_churn_year,1-0,1))) -> 37.9236 | G27: =(((cf_arr*(1+$B27)^G22)*IF(G22>=a_churn_year,1-0,1))*(MIN(a_m0+a_mstep*G22,a_mcap)-a_da)-IF(G22=a_churn_year,a_sticky*((cf_arr*(1+$B27)^G22)-((cf_arr*(1+$B27)^G22)*IF(G22>=a_churn_year,1-0,1)))*(1-MIN(a_m0+a_mstep*G22,a_mcap)),0))-MAX(0,(((cf_arr*(1+$B27)^G22)*IF(G22>=a_churn_year,1-0,1))*(MIN(a_m0+a_mstep*G22,a_mcap)-a_da)-IF(G22=a_churn_year,a_sticky*((cf_arr*(1+$B27)^G22)-((cf_arr*(1+$B27)^G22)*IF(G22>=a_churn_year,1-0,1)))*(1-MIN(a_m0+a_mstep*G22,a_mcap)),0)))*a_tax+((cf_arr*(1+$B27)^G22)*IF(G22>=a_churn_year,1-0,1))*a_da-((cf_arr*(1+$B27)^G22)*IF(G22>=a_churn_year,1-0,1))*a_capex-a_wc*(((cf_arr*(1+$B27)^G22)*IF(G22>=a_churn_year,1-0,1))-(cf_arr*(1+$B27)^F22*IF(F22>=a_churn_year,1-0,1))) -> 72.863505 | H27: =(((cf_arr*(1+$B27)^H22)*IF(H22>=a_churn_year,1-0,1))*(MIN(a_m0+a_mstep*H22,a_mcap)-a_da)-IF(H22=a_churn_year,a_sticky*((cf_arr*(1+$B27)^H22)-((cf_arr*(1+$B27)^H22)*IF(H22>=a_churn_year,1-0,1)))*(1-MIN(a_m0+a_mstep*H22,a_mcap)),0))-MAX(0,(((cf_arr*(1+$B27)^H22)*IF(H22>=a_churn_year,1-0,1))*(MIN(a_m0+a_mstep*H22,a_mcap)-a_da)-IF(H22=a_churn_year,a_sticky*((cf_arr*(1+$B27)^H22)-((cf_arr*(1+$B27)^H22)*IF(H22>=a_churn_year,1-0,1)))*(1-MIN(a_m0+a_mstep*H22,a_mcap)),0)))*a_tax+((cf_arr*(1+$B27)^H22)*IF(H22>=a_churn_year,1-0,1))*a_da-((cf_arr*(1+$B27)^H22)*IF(H22>=a_churn_year,1-0,1))*a_capex-a_wc*(((cf_arr*(1+$B27)^H22)*IF(H22>=a_churn_year,1-0,1))-(cf_arr*(1+$B27)^G22*IF(G22>=a_churn_year,1-0,1))) -> 125.35423 | I27: =(((cf_arr*(1+$B27)^I22)*IF(I22>=a_churn_year,1-0,1))*(MIN(a_m0+a_mstep*I22,a_mcap)-a_da)-IF(I22=a_churn_year,a_sticky*((cf_arr*(1+$B27)^I22)-((cf_arr*(1+$B27)^I22)*IF(I22>=a_churn_year,1-0,1)))*(1-MIN(a_m0+a_mstep*I22,a_mcap)),0))-MAX(0,(((cf_arr*(1+$B27)^I22)*IF(I22>=a_churn_year,1-0,1))*(MIN(a_m0+a_mstep*I22,a_mcap)-a_da)-IF(I22=a_churn_year,a_sticky*((cf_arr*(1+$B27)^I22)-((cf_arr*(1+$B27)^I22)*IF(I22>=a_churn_year,1-0,1)))*(1-MIN(a_m0+a_mstep*I22,a_mcap)),0)))*a_tax+((cf_arr*(1+$B27)^I22)*IF(I22>=a_churn_year,1-0,1))*a_da-((cf_arr*(1+$B27)^I22)*IF(I22>=a_churn_year,1-0,1))*a_capex-a_wc*(((cf_arr*(1+$B27)^I22)*IF(I22>=a_churn_year,1-0,1))-(cf_arr*(1+$B27)^H22*IF(H22>=a_churn_year,1-0,1))) -> 162.9605 | J27: =(((cf_arr*(1+$B27)^J22)*IF(J22>=a_churn_year,1-0,1))*(MIN(a_m0+a_mstep*J22,a_mcap)-a_da)-IF(J22=a_churn_year,a_sticky*((cf_arr*(1+$B27)^J22)-((cf_arr*(1+$B27)^J22)*IF(J22>=a_churn_year,1-0,1)))*(1-MIN(a_m0+a_mstep*J22,a_mcap)),0))-MAX(0,(((cf_arr*(1+$B27)^J22)*IF(J22>=a_churn_year,1-0,1))*(MIN(a_m0+a_mstep*J22,a_mcap)-a_da)-IF(J22=a_churn_year,a_sticky*((cf_arr*(1+$B27)^J22)-((cf_arr*(1+$B27)^J22)*IF(J22>=a_churn_year,1-0,1)))*(1-MIN(a_m0+a_mstep*J22,a_mcap)),0)))*a_tax+((cf_arr*(1+$B27)^J22)*IF(J22>=a_churn_year,1-0,1))*a_da-((cf_arr*(1+$B27)^J22)*IF(J22>=a_churn_year,1-0,1))*a_capex-a_wc*(((cf_arr*(1+$B27)^J22)*IF(J22>=a_churn_year,1-0,1))-(cf_arr*(1+$B27)^I22*IF(I22>=a_churn_year,1-0,1))) -> 211.84865 | K27: =(((cf_arr*(1+$B27)^K22)*IF(K22>=a_churn_year,1-0,1))*(MIN(a_m0+a_mstep*K22,a_mcap)-a_da)-IF(K22=a_churn_year,a_sticky*((cf_arr*(1+$B27)^K22)-((cf_arr*(1+$B27)^K22)*IF(K22>=a_churn_year,1-0,1)))*(1-MIN(a_m0+a_mstep*K22,a_mcap)),0))-MAX(0,(((cf_arr*(1+$B27)^K22)*IF(K22>=a_churn_year,1-0,1))*(MIN(a_m0+a_mstep*K22,a_mcap)-a_da)-IF(K22=a_churn_year,a_sticky*((cf_arr*(1+$B27)^K22)-((cf_arr*(1+$B27)^K22)*IF(K22>=a_churn_year,1-0,1)))*(1-MIN(a_m0+a_mstep*K22,a_mcap)),0)))*a_tax+((cf_arr*(1+$B27)^K22)*IF(K22>=a_churn_year,1-0,1))*a_da-((cf_arr*(1+$B27)^K22)*IF(K22>=a_churn_year,1-0,1))*a_capex-a_wc*(((cf_arr*(1+$B27)^K22)*IF(K22>=a_churn_year,1-0,1))-(cf_arr*(1+$B27)^J22*IF(J22>=a_churn_year,1-0,1))) -> 275.40324 | ... M27: =(((cf_arr*(1+$B27)^M22)*IF(M22>=a_churn_year,1-0,1))*(MIN(a_m0+a_mstep*M22,a_mcap)-a_da)-IF(M22=a_churn_year,a_sticky*((cf_arr*(1+$B27)^M22)-((cf_arr*(1+$B27)^M22)*IF(M22>=a_churn_year,1-0,1)))*(1-MIN(a_m0+a_mstep*M22,a_mcap)),0))-MAX(0,(((cf_arr*(1+$B27)^M22)*IF(M22>=a_churn_year,1-0,1))*(MIN(a_m0+a_mstep*M22,a_mcap)-a_da)-IF(M22=a_churn_year,a_sticky*((cf_arr*(1+$B27)^M22)-((cf_arr*(1+$B27)^M22)*IF(M22>=a_churn_year,1-0,1)))*(1-MIN(a_m0+a_mstep*M22,a_mcap)),0)))*a_tax+((cf_arr*(1+$B27)^M22)*IF(M22>=a_churn_year,1-0,1))*a_da-((cf_arr*(1+$B27)^M22)*IF(M22>=a_churn_year,1-0,1))*a_capex-a_wc*(((cf_arr*(1+$B27)^M22)*IF(M22>=a_churn_year,1-0,1))-(cf_arr*(1+$B27)^L22*IF(L22>=a_churn_year,1-0,1))) -> 465.43148
A28: Growth 35% p.a. — unlevered FCF | B28: 0.35 | C28: =0 -> 0 | D28: =(((cf_arr*(1+$B28)^D22)*IF(D22>=a_churn_year,1-0,1))*(MIN(a_m0+a_mstep*D22,a_mcap)-a_da)-IF(D22=a_churn_year,a_sticky*((cf_arr*(1+$B28)^D22)-((cf_arr*(1+$B28)^D22)*IF(D22>=a_churn_year,1-0,1)))*(1-MIN(a_m0+a_mstep*D22,a_mcap)),0))-MAX(0,(((cf_arr*(1+$B28)^D22)*IF(D22>=a_churn_year,1-0,1))*(MIN(a_m0+a_mstep*D22,a_mcap)-a_da)-IF(D22=a_churn_year,a_sticky*((cf_arr*(1+$B28)^D22)-((cf_arr*(1+$B28)^D22)*IF(D22>=a_churn_year,1-0,1)))*(1-MIN(a_m0+a_mstep*D22,a_mcap)),0)))*a_tax+((cf_arr*(1+$B28)^D22)*IF(D22>=a_churn_year,1-0,1))*a_da-((cf_arr*(1+$B28)^D22)*IF(D22>=a_churn_year,1-0,1))*a_capex-a_wc*(((cf_arr*(1+$B28)^D22)*IF(D22>=a_churn_year,1-0,1))-(cf_arr*(1+$B28)^C22*IF(C22>=a_churn_year,1-0,1))) -> 0.605 | E28: =(((cf_arr*(1+$B28)^E22)*IF(E22>=a_churn_year,1-0,1))*(MIN(a_m0+a_mstep*E22,a_mcap)-a_da)-IF(E22=a_churn_year,a_sticky*((cf_arr*(1+$B28)^E22)-((cf_arr*(1+$B28)^E22)*IF(E22>=a_churn_year,1-0,1)))*(1-MIN(a_m0+a_mstep*E22,a_mcap)),0))-MAX(0,(((cf_arr*(1+$B28)^E22)*IF(E22>=a_churn_year,1-0,1))*(MIN(a_m0+a_mstep*E22,a_mcap)-a_da)-IF(E22=a_churn_year,a_sticky*((cf_arr*(1+$B28)^E22)-((cf_arr*(1+$B28)^E22)*IF(E22>=a_churn_year,1-0,1)))*(1-MIN(a_m0+a_mstep*E22,a_mcap)),0)))*a_tax+((cf_arr*(1+$B28)^E22)*IF(E22>=a_churn_year,1-0,1))*a_da-((cf_arr*(1+$B28)^E22)*IF(E22>=a_churn_year,1-0,1))*a_capex-a_wc*(((cf_arr*(1+$B28)^E22)*IF(E22>=a_churn_year,1-0,1))-(cf_arr*(1+$B28)^D22*IF(D22>=a_churn_year,1-0,1))) -> 15.852375 | F28: =(((cf_arr*(1+$B28)^F22)*IF(F22>=a_churn_year,1-0,1))*(MIN(a_m0+a_mstep*F22,a_mcap)-a_da)-IF(F22=a_churn_year,a_sticky*((cf_arr*(1+$B28)^F22)-((cf_arr*(1+$B28)^F22)*IF(F22>=a_churn_year,1-0,1)))*(1-MIN(a_m0+a_mstep*F22,a_mcap)),0))-MAX(0,(((cf_arr*(1+$B28)^F22)*IF(F22>=a_churn_year,1-0,1))*(MIN(a_m0+a_mstep*F22,a_mcap)-a_da)-IF(F22=a_churn_year,a_sticky*((cf_arr*(1+$B28)^F22)-((cf_arr*(1+$B28)^F22)*IF(F22>=a_churn_year,1-0,1)))*(1-MIN(a_m0+a_mstep*F22,a_mcap)),0)))*a_tax+((cf_arr*(1+$B28)^F22)*IF(F22>=a_churn_year,1-0,1))*a_da-((cf_arr*(1+$B28)^F22)*IF(F22>=a_churn_year,1-0,1))*a_capex-a_wc*(((cf_arr*(1+$B28)^F22)*IF(F22>=a_churn_year,1-0,1))-(cf_arr*(1+$B28)^E22*IF(E22>=a_churn_year,1-0,1))) -> 41.6988 | G28: =(((cf_arr*(1+$B28)^G22)*IF(G22>=a_churn_year,1-0,1))*(MIN(a_m0+a_mstep*G22,a_mcap)-a_da)-IF(G22=a_churn_year,a_sticky*((cf_arr*(1+$B28)^G22)-((cf_arr*(1+$B28)^G22)*IF(G22>=a_churn_year,1-0,1)))*(1-MIN(a_m0+a_mstep*G22,a_mcap)),0))-MAX(0,(((cf_arr*(1+$B28)^G22)*IF(G22>=a_churn_year,1-0,1))*(MIN(a_m0+a_mstep*G22,a_mcap)-a_da)-IF(G22=a_churn_year,a_sticky*((cf_arr*(1+$B28)^G22)-((cf_arr*(1+$B28)^G22)*IF(G22>=a_churn_year,1-0,1)))*(1-MIN(a_m0+a_mstep*G22,a_mcap)),0)))*a_tax+((cf_arr*(1+$B28)^G22)*IF(G22>=a_churn_year,1-0,1))*a_da-((cf_arr*(1+$B28)^G22)*IF(G22>=a_churn_year,1-0,1))*a_capex-a_wc*(((cf_arr*(1+$B28)^G22)*IF(G22>=a_churn_year,1-0,1))-(cf_arr*(1+$B28)^F22*IF(F22>=a_churn_year,1-0,1))) -> 83.695807 | H28: =(((cf_arr*(1+$B28)^H22)*IF(H22>=a_churn_year,1-0,1))*(MIN(a_m0+a_mstep*H22,a_mcap)-a_da)-IF(H22=a_churn_year,a_sticky*((cf_arr*(1+$B28)^H22)-((cf_arr*(1+$B28)^H22)*IF(H22>=a_churn_year,1-0,1)))*(1-MIN(a_m0+a_mstep*H22,a_mcap)),0))-MAX(0,(((cf_arr*(1+$B28)^H22)*IF(H22>=a_churn_year,1-0,1))*(MIN(a_m0+a_mstep*H22,a_mcap)-a_da)-IF(H22=a_churn_year,a_sticky*((cf_arr*(1+$B28)^H22)-((cf_arr*(1+$B28)^H22)*IF(H22>=a_churn_year,1-0,1)))*(1-MIN(a_m0+a_mstep*H22,a_mcap)),0)))*a_tax+((cf_arr*(1+$B28)^H22)*IF(H22>=a_churn_year,1-0,1))*a_da-((cf_arr*(1+$B28)^H22)*IF(H22>=a_churn_year,1-0,1))*a_capex-a_wc*(((cf_arr*(1+$B28)^H22)*IF(H22>=a_churn_year,1-0,1))-(cf_arr*(1+$B28)^G22*IF(G22>=a_churn_year,1-0,1))) -> 149.98261 | I28: =(((cf_arr*(1+$B28)^I22)*IF(I22>=a_churn_year,1-0,1))*(MIN(a_m0+a_mstep*I22,a_mcap)-a_da)-IF(I22=a_churn_year,a_sticky*((cf_arr*(1+$B28)^I22)-((cf_arr*(1+$B28)^I22)*IF(I22>=a_churn_year,1-0,1)))*(1-MIN(a_m0+a_mstep*I22,a_mcap)),0))-MAX(0,(((cf_arr*(1+$B28)^I22)*IF(I22>=a_churn_year,1-0,1))*(MIN(a_m0+a_mstep*I22,a_mcap)-a_da)-IF(I22=a_churn_year,a_sticky*((cf_arr*(1+$B28)^I22)-((cf_arr*(1+$B28)^I22)*IF(I22>=a_churn_year,1-0,1)))*(1-MIN(a_m0+a_mstep*I22,a_mcap)),0)))*a_tax+((cf_arr*(1+$B28)^I22)*IF(I22>=a_churn_year,1-0,1))*a_da-((cf_arr*(1+$B28)^I22)*IF(I22>=a_churn_year,1-0,1))*a_capex-a_wc*(((cf_arr*(1+$B28)^I22)*IF(I22>=a_churn_year,1-0,1))-(cf_arr*(1+$B28)^H22*IF(H22>=a_churn_year,1-0,1))) -> 202.47653 | J28: =(((cf_arr*(1+$B28)^J22)*IF(J22>=a_churn_year,1-0,1))*(MIN(a_m0+a_mstep*J22,a_mcap)-a_da)-IF(J22=a_churn_year,a_sticky*((cf_arr*(1+$B28)^J22)-((cf_arr*(1+$B28)^J22)*IF(J22>=a_churn_year,1-0,1)))*(1-MIN(a_m0+a_mstep*J22,a_mcap)),0))-MAX(0,(((cf_arr*(1+$B28)^J22)*IF(J22>=a_churn_year,1-0,1))*(MIN(a_m0+a_mstep*J22,a_mcap)-a_da)-IF(J22=a_churn_year,a_sticky*((cf_arr*(1+$B28)^J22)-((cf_arr*(1+$B28)^J22)*IF(J22>=a_churn_year,1-0,1)))*(1-MIN(a_m0+a_mstep*J22,a_mcap)),0)))*a_tax+((cf_arr*(1+$B28)^J22)*IF(J22>=a_churn_year,1-0,1))*a_da-((cf_arr*(1+$B28)^J22)*IF(J22>=a_churn_year,1-0,1))*a_capex-a_wc*(((cf_arr*(1+$B28)^J22)*IF(J22>=a_churn_year,1-0,1))-(cf_arr*(1+$B28)^I22*IF(I22>=a_churn_year,1-0,1))) -> 273.34332 | K28: =(((cf_arr*(1+$B28)^K22)*IF(K22>=a_churn_year,1-0,1))*(MIN(a_m0+a_mstep*K22,a_mcap)-a_da)-IF(K22=a_churn_year,a_sticky*((cf_arr*(1+$B28)^K22)-((cf_arr*(1+$B28)^K22)*IF(K22>=a_churn_year,1-0,1)))*(1-MIN(a_m0+a_mstep*K22,a_mcap)),0))-MAX(0,(((cf_arr*(1+$B28)^K22)*IF(K22>=a_churn_year,1-0,1))*(MIN(a_m0+a_mstep*K22,a_mcap)-a_da)-IF(K22=a_churn_year,a_sticky*((cf_arr*(1+$B28)^K22)-((cf_arr*(1+$B28)^K22)*IF(K22>=a_churn_year,1-0,1)))*(1-MIN(a_m0+a_mstep*K22,a_mcap)),0)))*a_tax+((cf_arr*(1+$B28)^K22)*IF(K22>=a_churn_year,1-0,1))*a_da-((cf_arr*(1+$B28)^K22)*IF(K22>=a_churn_year,1-0,1))*a_capex-a_wc*(((cf_arr*(1+$B28)^K22)*IF(K22>=a_churn_year,1-0,1))-(cf_arr*(1+$B28)^J22*IF(J22>=a_churn_year,1-0,1))) -> 369.01348 | ... M28: =(((cf_arr*(1+$B28)^M22)*IF(M22>=a_churn_year,1-0,1))*(MIN(a_m0+a_mstep*M22,a_mcap)-a_da)-IF(M22=a_churn_year,a_sticky*((cf_arr*(1+$B28)^M22)-((cf_arr*(1+$B28)^M22)*IF(M22>=a_churn_year,1-0,1)))*(1-MIN(a_m0+a_mstep*M22,a_mcap)),0))-MAX(0,(((cf_arr*(1+$B28)^M22)*IF(M22>=a_churn_year,1-0,1))*(MIN(a_m0+a_mstep*M22,a_mcap)-a_da)-IF(M22=a_churn_year,a_sticky*((cf_arr*(1+$B28)^M22)-((cf_arr*(1+$B28)^M22)*IF(M22>=a_churn_year,1-0,1)))*(1-MIN(a_m0+a_mstep*M22,a_mcap)),0)))*a_tax+((cf_arr*(1+$B28)^M22)*IF(M22>=a_churn_year,1-0,1))*a_da-((cf_arr*(1+$B28)^M22)*IF(M22>=a_churn_year,1-0,1))*a_capex-a_wc*(((cf_arr*(1+$B28)^M22)*IF(M22>=a_churn_year,1-0,1))-(cf_arr*(1+$B28)^L22*IF(L22>=a_churn_year,1-0,1))) -> 672.52706
A29: Growth 40% p.a. — unlevered FCF | B29: 0.4 | C29: =0 -> 0 | D29: =(((cf_arr*(1+$B29)^D22)*IF(D22>=a_churn_year,1-0,1))*(MIN(a_m0+a_mstep*D22,a_mcap)-a_da)-IF(D22=a_churn_year,a_sticky*((cf_arr*(1+$B29)^D22)-((cf_arr*(1+$B29)^D22)*IF(D22>=a_churn_year,1-0,1)))*(1-MIN(a_m0+a_mstep*D22,a_mcap)),0))-MAX(0,(((cf_arr*(1+$B29)^D22)*IF(D22>=a_churn_year,1-0,1))*(MIN(a_m0+a_mstep*D22,a_mcap)-a_da)-IF(D22=a_churn_year,a_sticky*((cf_arr*(1+$B29)^D22)-((cf_arr*(1+$B29)^D22)*IF(D22>=a_churn_year,1-0,1)))*(1-MIN(a_m0+a_mstep*D22,a_mcap)),0)))*a_tax+((cf_arr*(1+$B29)^D22)*IF(D22>=a_churn_year,1-0,1))*a_da-((cf_arr*(1+$B29)^D22)*IF(D22>=a_churn_year,1-0,1))*a_capex-a_wc*(((cf_arr*(1+$B29)^D22)*IF(D22>=a_churn_year,1-0,1))-(cf_arr*(1+$B29)^C22*IF(C22>=a_churn_year,1-0,1))) -> 0.22 | E29: =(((cf_arr*(1+$B29)^E22)*IF(E22>=a_churn_year,1-0,1))*(MIN(a_m0+a_mstep*E22,a_mcap)-a_da)-IF(E22=a_churn_year,a_sticky*((cf_arr*(1+$B29)^E22)-((cf_arr*(1+$B29)^E22)*IF(E22>=a_churn_year,1-0,1)))*(1-MIN(a_m0+a_mstep*E22,a_mcap)),0))-MAX(0,(((cf_arr*(1+$B29)^E22)*IF(E22>=a_churn_year,1-0,1))*(MIN(a_m0+a_mstep*E22,a_mcap)-a_da)-IF(E22=a_churn_year,a_sticky*((cf_arr*(1+$B29)^E22)-((cf_arr*(1+$B29)^E22)*IF(E22>=a_churn_year,1-0,1)))*(1-MIN(a_m0+a_mstep*E22,a_mcap)),0)))*a_tax+((cf_arr*(1+$B29)^E22)*IF(E22>=a_churn_year,1-0,1))*a_da-((cf_arr*(1+$B29)^E22)*IF(E22>=a_churn_year,1-0,1))*a_capex-a_wc*(((cf_arr*(1+$B29)^E22)*IF(E22>=a_churn_year,1-0,1))-(cf_arr*(1+$B29)^D22*IF(D22>=a_churn_year,1-0,1))) -> 16.478 | F29: =(((cf_arr*(1+$B29)^F22)*IF(F22>=a_churn_year,1-0,1))*(MIN(a_m0+a_mstep*F22,a_mcap)-a_da)-IF(F22=a_churn_year,a_sticky*((cf_arr*(1+$B29)^F22)-((cf_arr*(1+$B29)^F22)*IF(F22>=a_churn_year,1-0,1)))*(1-MIN(a_m0+a_mstep*F22,a_mcap)),0))-MAX(0,(((cf_arr*(1+$B29)^F22)*IF(F22>=a_churn_year,1-0,1))*(MIN(a_m0+a_mstep*F22,a_mcap)-a_da)-IF(F22=a_churn_year,a_sticky*((cf_arr*(1+$B29)^F22)-((cf_arr*(1+$B29)^F22)*IF(F22>=a_churn_year,1-0,1)))*(1-MIN(a_m0+a_mstep*F22,a_mcap)),0)))*a_tax+((cf_arr*(1+$B29)^F22)*IF(F22>=a_churn_year,1-0,1))*a_da-((cf_arr*(1+$B29)^F22)*IF(F22>=a_churn_year,1-0,1))*a_capex-a_wc*(((cf_arr*(1+$B29)^F22)*IF(F22>=a_churn_year,1-0,1))-(cf_arr*(1+$B29)^E22*IF(E22>=a_churn_year,1-0,1))) -> 45.7072 | G29: =(((cf_arr*(1+$B29)^G22)*IF(G22>=a_churn_year,1-0,1))*(MIN(a_m0+a_mstep*G22,a_mcap)-a_da)-IF(G22=a_churn_year,a_sticky*((cf_arr*(1+$B29)^G22)-((cf_arr*(1+$B29)^G22)*IF(G22>=a_churn_year,1-0,1)))*(1-MIN(a_m0+a_mstep*G22,a_mcap)),0))-MAX(0,(((cf_arr*(1+$B29)^G22)*IF(G22>=a_churn_year,1-0,1))*(MIN(a_m0+a_mstep*G22,a_mcap)-a_da)-IF(G22=a_churn_year,a_sticky*((cf_arr*(1+$B29)^G22)-((cf_arr*(1+$B29)^G22)*IF(G22>=a_churn_year,1-0,1)))*(1-MIN(a_m0+a_mstep*G22,a_mcap)),0)))*a_tax+((cf_arr*(1+$B29)^G22)*IF(G22>=a_churn_year,1-0,1))*a_da-((cf_arr*(1+$B29)^G22)*IF(G22>=a_churn_year,1-0,1))*a_capex-a_wc*(((cf_arr*(1+$B29)^G22)*IF(G22>=a_churn_year,1-0,1))-(cf_arr*(1+$B29)^F22*IF(F22>=a_churn_year,1-0,1))) -> 95.68328 | H29: =(((cf_arr*(1+$B29)^H22)*IF(H22>=a_churn_year,1-0,1))*(MIN(a_m0+a_mstep*H22,a_mcap)-a_da)-IF(H22=a_churn_year,a_sticky*((cf_arr*(1+$B29)^H22)-((cf_arr*(1+$B29)^H22)*IF(H22>=a_churn_year,1-0,1)))*(1-MIN(a_m0+a_mstep*H22,a_mcap)),0))-MAX(0,(((cf_arr*(1+$B29)^H22)*IF(H22>=a_churn_year,1-0,1))*(MIN(a_m0+a_mstep*H22,a_mcap)-a_da)-IF(H22=a_churn_year,a_sticky*((cf_arr*(1+$B29)^H22)-((cf_arr*(1+$B29)^H22)*IF(H22>=a_churn_year,1-0,1)))*(1-MIN(a_m0+a_mstep*H22,a_mcap)),0)))*a_tax+((cf_arr*(1+$B29)^H22)*IF(H22>=a_churn_year,1-0,1))*a_da-((cf_arr*(1+$B29)^H22)*IF(H22>=a_churn_year,1-0,1))*a_capex-a_wc*(((cf_arr*(1+$B29)^H22)*IF(H22>=a_churn_year,1-0,1))-(cf_arr*(1+$B29)^G22*IF(G22>=a_churn_year,1-0,1))) -> 178.32707 | I29: =(((cf_arr*(1+$B29)^I22)*IF(I22>=a_churn_year,1-0,1))*(MIN(a_m0+a_mstep*I22,a_mcap)-a_da)-IF(I22=a_churn_year,a_sticky*((cf_arr*(1+$B29)^I22)-((cf_arr*(1+$B29)^I22)*IF(I22>=a_churn_year,1-0,1)))*(1-MIN(a_m0+a_mstep*I22,a_mcap)),0))-MAX(0,(((cf_arr*(1+$B29)^I22)*IF(I22>=a_churn_year,1-0,1))*(MIN(a_m0+a_mstep*I22,a_mcap)-a_da)-IF(I22=a_churn_year,a_sticky*((cf_arr*(1+$B29)^I22)-((cf_arr*(1+$B29)^I22)*IF(I22>=a_churn_year,1-0,1)))*(1-MIN(a_m0+a_mstep*I22,a_mcap)),0)))*a_tax+((cf_arr*(1+$B29)^I22)*IF(I22>=a_churn_year,1-0,1))*a_da-((cf_arr*(1+$B29)^I22)*IF(I22>=a_churn_year,1-0,1))*a_capex-a_wc*(((cf_arr*(1+$B29)^I22)*IF(I22>=a_churn_year,1-0,1))-(cf_arr*(1+$B29)^H22*IF(H22>=a_churn_year,1-0,1))) -> 249.6579 | J29: =(((cf_arr*(1+$B29)^J22)*IF(J22>=a_churn_year,1-0,1))*(MIN(a_m0+a_mstep*J22,a_mcap)-a_da)-IF(J22=a_churn_year,a_sticky*((cf_arr*(1+$B29)^J22)-((cf_arr*(1+$B29)^J22)*IF(J22>=a_churn_year,1-0,1)))*(1-MIN(a_m0+a_mstep*J22,a_mcap)),0))-MAX(0,(((cf_arr*(1+$B29)^J22)*IF(J22>=a_churn_year,1-0,1))*(MIN(a_m0+a_mstep*J22,a_mcap)-a_da)-IF(J22=a_churn_year,a_sticky*((cf_arr*(1+$B29)^J22)-((cf_arr*(1+$B29)^J22)*IF(J22>=a_churn_year,1-0,1)))*(1-MIN(a_m0+a_mstep*J22,a_mcap)),0)))*a_tax+((cf_arr*(1+$B29)^J22)*IF(J22>=a_churn_year,1-0,1))*a_da-((cf_arr*(1+$B29)^J22)*IF(J22>=a_churn_year,1-0,1))*a_capex-a_wc*(((cf_arr*(1+$B29)^J22)*IF(J22>=a_churn_year,1-0,1))-(cf_arr*(1+$B29)^I22*IF(I22>=a_churn_year,1-0,1))) -> 349.52106 | K29: =(((cf_arr*(1+$B29)^K22)*IF(K22>=a_churn_year,1-0,1))*(MIN(a_m0+a_mstep*K22,a_mcap)-a_da)-IF(K22=a_churn_year,a_sticky*((cf_arr*(1+$B29)^K22)-((cf_arr*(1+$B29)^K22)*IF(K22>=a_churn_year,1-0,1)))*(1-MIN(a_m0+a_mstep*K22,a_mcap)),0))-MAX(0,(((cf_arr*(1+$B29)^K22)*IF(K22>=a_churn_year,1-0,1))*(MIN(a_m0+a_mstep*K22,a_mcap)-a_da)-IF(K22=a_churn_year,a_sticky*((cf_arr*(1+$B29)^K22)-((cf_arr*(1+$B29)^K22)*IF(K22>=a_churn_year,1-0,1)))*(1-MIN(a_m0+a_mstep*K22,a_mcap)),0)))*a_tax+((cf_arr*(1+$B29)^K22)*IF(K22>=a_churn_year,1-0,1))*a_da-((cf_arr*(1+$B29)^K22)*IF(K22>=a_churn_year,1-0,1))*a_capex-a_wc*(((cf_arr*(1+$B29)^K22)*IF(K22>=a_churn_year,1-0,1))-(cf_arr*(1+$B29)^J22*IF(J22>=a_churn_year,1-0,1))) -> 489.32949 | ... M29: =(((cf_arr*(1+$B29)^M22)*IF(M22>=a_churn_year,1-0,1))*(MIN(a_m0+a_mstep*M22,a_mcap)-a_da)-IF(M22=a_churn_year,a_sticky*((cf_arr*(1+$B29)^M22)-((cf_arr*(1+$B29)^M22)*IF(M22>=a_churn_year,1-0,1)))*(1-MIN(a_m0+a_mstep*M22,a_mcap)),0))-MAX(0,(((cf_arr*(1+$B29)^M22)*IF(M22>=a_churn_year,1-0,1))*(MIN(a_m0+a_mstep*M22,a_mcap)-a_da)-IF(M22=a_churn_year,a_sticky*((cf_arr*(1+$B29)^M22)-((cf_arr*(1+$B29)^M22)*IF(M22>=a_churn_year,1-0,1)))*(1-MIN(a_m0+a_mstep*M22,a_mcap)),0)))*a_tax+((cf_arr*(1+$B29)^M22)*IF(M22>=a_churn_year,1-0,1))*a_da-((cf_arr*(1+$B29)^M22)*IF(M22>=a_churn_year,1-0,1))*a_capex-a_wc*(((cf_arr*(1+$B29)^M22)*IF(M22>=a_churn_year,1-0,1))-(cf_arr*(1+$B29)^L22*IF(L22>=a_churn_year,1-0,1))) -> 959.08579
A30: Growth 45% p.a. — unlevered FCF | B30: 0.45 | C30: =0 -> 0 | D30: =(((cf_arr*(1+$B30)^D22)*IF(D22>=a_churn_year,1-0,1))*(MIN(a_m0+a_mstep*D22,a_mcap)-a_da)-IF(D22=a_churn_year,a_sticky*((cf_arr*(1+$B30)^D22)-((cf_arr*(1+$B30)^D22)*IF(D22>=a_churn_year,1-0,1)))*(1-MIN(a_m0+a_mstep*D22,a_mcap)),0))-MAX(0,(((cf_arr*(1+$B30)^D22)*IF(D22>=a_churn_year,1-0,1))*(MIN(a_m0+a_mstep*D22,a_mcap)-a_da)-IF(D22=a_churn_year,a_sticky*((cf_arr*(1+$B30)^D22)-((cf_arr*(1+$B30)^D22)*IF(D22>=a_churn_year,1-0,1)))*(1-MIN(a_m0+a_mstep*D22,a_mcap)),0)))*a_tax+((cf_arr*(1+$B30)^D22)*IF(D22>=a_churn_year,1-0,1))*a_da-((cf_arr*(1+$B30)^D22)*IF(D22>=a_churn_year,1-0,1))*a_capex-a_wc*(((cf_arr*(1+$B30)^D22)*IF(D22>=a_churn_year,1-0,1))-(cf_arr*(1+$B30)^C22*IF(C22>=a_churn_year,1-0,1))) -> -0.165 | E30: =(((cf_arr*(1+$B30)^E22)*IF(E22>=a_churn_year,1-0,1))*(MIN(a_m0+a_mstep*E22,a_mcap)-a_da)-IF(E22=a_churn_year,a_sticky*((cf_arr*(1+$B30)^E22)-((cf_arr*(1+$B30)^E22)*IF(E22>=a_churn_year,1-0,1)))*(1-MIN(a_m0+a_mstep*E22,a_mcap)),0))-MAX(0,(((cf_arr*(1+$B30)^E22)*IF(E22>=a_churn_year,1-0,1))*(MIN(a_m0+a_mstep*E22,a_mcap)-a_da)-IF(E22=a_churn_year,a_sticky*((cf_arr*(1+$B30)^E22)-((cf_arr*(1+$B30)^E22)*IF(E22>=a_churn_year,1-0,1)))*(1-MIN(a_m0+a_mstep*E22,a_mcap)),0)))*a_tax+((cf_arr*(1+$B30)^E22)*IF(E22>=a_churn_year,1-0,1))*a_da-((cf_arr*(1+$B30)^E22)*IF(E22>=a_churn_year,1-0,1))*a_capex-a_wc*(((cf_arr*(1+$B30)^E22)*IF(E22>=a_churn_year,1-0,1))-(cf_arr*(1+$B30)^D22*IF(D22>=a_churn_year,1-0,1))) -> 17.106375 | F30: =(((cf_arr*(1+$B30)^F22)*IF(F22>=a_churn_year,1-0,1))*(MIN(a_m0+a_mstep*F22,a_mcap)-a_da)-IF(F22=a_churn_year,a_sticky*((cf_arr*(1+$B30)^F22)-((cf_arr*(1+$B30)^F22)*IF(F22>=a_churn_year,1-0,1)))*(1-MIN(a_m0+a_mstep*F22,a_mcap)),0))-MAX(0,(((cf_arr*(1+$B30)^F22)*IF(F22>=a_churn_year,1-0,1))*(MIN(a_m0+a_mstep*F22,a_mcap)-a_da)-IF(F22=a_churn_year,a_sticky*((cf_arr*(1+$B30)^F22)-((cf_arr*(1+$B30)^F22)*IF(F22>=a_churn_year,1-0,1)))*(1-MIN(a_m0+a_mstep*F22,a_mcap)),0)))*a_tax+((cf_arr*(1+$B30)^F22)*IF(F22>=a_churn_year,1-0,1))*a_da-((cf_arr*(1+$B30)^F22)*IF(F22>=a_churn_year,1-0,1))*a_capex-a_wc*(((cf_arr*(1+$B30)^F22)*IF(F22>=a_churn_year,1-0,1))-(cf_arr*(1+$B30)^E22*IF(E22>=a_churn_year,1-0,1))) -> 49.9554 | G30: =(((cf_arr*(1+$B30)^G22)*IF(G22>=a_churn_year,1-0,1))*(MIN(a_m0+a_mstep*G22,a_mcap)-a_da)-IF(G22=a_churn_year,a_sticky*((cf_arr*(1+$B30)^G22)-((cf_arr*(1+$B30)^G22)*IF(G22>=a_churn_year,1-0,1)))*(1-MIN(a_m0+a_mstep*G22,a_mcap)),0))-MAX(0,(((cf_arr*(1+$B30)^G22)*IF(G22>=a_churn_year,1-0,1))*(MIN(a_m0+a_mstep*G22,a_mcap)-a_da)-IF(G22=a_churn_year,a_sticky*((cf_arr*(1+$B30)^G22)-((cf_arr*(1+$B30)^G22)*IF(G22>=a_churn_year,1-0,1)))*(1-MIN(a_m0+a_mstep*G22,a_mcap)),0)))*a_tax+((cf_arr*(1+$B30)^G22)*IF(G22>=a_churn_year,1-0,1))*a_da-((cf_arr*(1+$B30)^G22)*IF(G22>=a_churn_year,1-0,1))*a_capex-a_wc*(((cf_arr*(1+$B30)^G22)*IF(G22>=a_churn_year,1-0,1))-(cf_arr*(1+$B30)^F22*IF(F22>=a_churn_year,1-0,1))) -> 108.90451 | H30: =(((cf_arr*(1+$B30)^H22)*IF(H22>=a_churn_year,1-0,1))*(MIN(a_m0+a_mstep*H22,a_mcap)-a_da)-IF(H22=a_churn_year,a_sticky*((cf_arr*(1+$B30)^H22)-((cf_arr*(1+$B30)^H22)*IF(H22>=a_churn_year,1-0,1)))*(1-MIN(a_m0+a_mstep*H22,a_mcap)),0))-MAX(0,(((cf_arr*(1+$B30)^H22)*IF(H22>=a_churn_year,1-0,1))*(MIN(a_m0+a_mstep*H22,a_mcap)-a_da)-IF(H22=a_churn_year,a_sticky*((cf_arr*(1+$B30)^H22)-((cf_arr*(1+$B30)^H22)*IF(H22>=a_churn_year,1-0,1)))*(1-MIN(a_m0+a_mstep*H22,a_mcap)),0)))*a_tax+((cf_arr*(1+$B30)^H22)*IF(H22>=a_churn_year,1-0,1))*a_da-((cf_arr*(1+$B30)^H22)*IF(H22>=a_churn_year,1-0,1))*a_capex-a_wc*(((cf_arr*(1+$B30)^H22)*IF(H22>=a_churn_year,1-0,1))-(cf_arr*(1+$B30)^G22*IF(G22>=a_churn_year,1-0,1))) -> 210.79184 | I30: =(((cf_arr*(1+$B30)^I22)*IF(I22>=a_churn_year,1-0,1))*(MIN(a_m0+a_mstep*I22,a_mcap)-a_da)-IF(I22=a_churn_year,a_sticky*((cf_arr*(1+$B30)^I22)-((cf_arr*(1+$B30)^I22)*IF(I22>=a_churn_year,1-0,1)))*(1-MIN(a_m0+a_mstep*I22,a_mcap)),0))-MAX(0,(((cf_arr*(1+$B30)^I22)*IF(I22>=a_churn_year,1-0,1))*(MIN(a_m0+a_mstep*I22,a_mcap)-a_da)-IF(I22=a_churn_year,a_sticky*((cf_arr*(1+$B30)^I22)-((cf_arr*(1+$B30)^I22)*IF(I22>=a_churn_year,1-0,1)))*(1-MIN(a_m0+a_mstep*I22,a_mcap)),0)))*a_tax+((cf_arr*(1+$B30)^I22)*IF(I22>=a_churn_year,1-0,1))*a_da-((cf_arr*(1+$B30)^I22)*IF(I22>=a_churn_year,1-0,1))*a_capex-a_wc*(((cf_arr*(1+$B30)^I22)*IF(I22>=a_churn_year,1-0,1))-(cf_arr*(1+$B30)^H22*IF(H22>=a_churn_year,1-0,1))) -> 305.64817 | J30: =(((cf_arr*(1+$B30)^J22)*IF(J22>=a_churn_year,1-0,1))*(MIN(a_m0+a_mstep*J22,a_mcap)-a_da)-IF(J22=a_churn_year,a_sticky*((cf_arr*(1+$B30)^J22)-((cf_arr*(1+$B30)^J22)*IF(J22>=a_churn_year,1-0,1)))*(1-MIN(a_m0+a_mstep*J22,a_mcap)),0))-MAX(0,(((cf_arr*(1+$B30)^J22)*IF(J22>=a_churn_year,1-0,1))*(MIN(a_m0+a_mstep*J22,a_mcap)-a_da)-IF(J22=a_churn_year,a_sticky*((cf_arr*(1+$B30)^J22)-((cf_arr*(1+$B30)^J22)*IF(J22>=a_churn_year,1-0,1)))*(1-MIN(a_m0+a_mstep*J22,a_mcap)),0)))*a_tax+((cf_arr*(1+$B30)^J22)*IF(J22>=a_churn_year,1-0,1))*a_da-((cf_arr*(1+$B30)^J22)*IF(J22>=a_churn_year,1-0,1))*a_capex-a_wc*(((cf_arr*(1+$B30)^J22)*IF(J22>=a_churn_year,1-0,1))-(cf_arr*(1+$B30)^I22*IF(I22>=a_churn_year,1-0,1))) -> 443.18984 | K30: =(((cf_arr*(1+$B30)^K22)*IF(K22>=a_churn_year,1-0,1))*(MIN(a_m0+a_mstep*K22,a_mcap)-a_da)-IF(K22=a_churn_year,a_sticky*((cf_arr*(1+$B30)^K22)-((cf_arr*(1+$B30)^K22)*IF(K22>=a_churn_year,1-0,1)))*(1-MIN(a_m0+a_mstep*K22,a_mcap)),0))-MAX(0,(((cf_arr*(1+$B30)^K22)*IF(K22>=a_churn_year,1-0,1))*(MIN(a_m0+a_mstep*K22,a_mcap)-a_da)-IF(K22=a_churn_year,a_sticky*((cf_arr*(1+$B30)^K22)-((cf_arr*(1+$B30)^K22)*IF(K22>=a_churn_year,1-0,1)))*(1-MIN(a_m0+a_mstep*K22,a_mcap)),0)))*a_tax+((cf_arr*(1+$B30)^K22)*IF(K22>=a_churn_year,1-0,1))*a_da-((cf_arr*(1+$B30)^K22)*IF(K22>=a_churn_year,1-0,1))*a_capex-a_wc*(((cf_arr*(1+$B30)^K22)*IF(K22>=a_churn_year,1-0,1))-(cf_arr*(1+$B30)^J22*IF(J22>=a_churn_year,1-0,1))) -> 642.62527 | ... M30: =(((cf_arr*(1+$B30)^M22)*IF(M22>=a_churn_year,1-0,1))*(MIN(a_m0+a_mstep*M22,a_mcap)-a_da)-IF(M22=a_churn_year,a_sticky*((cf_arr*(1+$B30)^M22)-((cf_arr*(1+$B30)^M22)*IF(M22>=a_churn_year,1-0,1)))*(1-MIN(a_m0+a_mstep*M22,a_mcap)),0))-MAX(0,(((cf_arr*(1+$B30)^M22)*IF(M22>=a_churn_year,1-0,1))*(MIN(a_m0+a_mstep*M22,a_mcap)-a_da)-IF(M22=a_churn_year,a_sticky*((cf_arr*(1+$B30)^M22)-((cf_arr*(1+$B30)^M22)*IF(M22>=a_churn_year,1-0,1)))*(1-MIN(a_m0+a_mstep*M22,a_mcap)),0)))*a_tax+((cf_arr*(1+$B30)^M22)*IF(M22>=a_churn_year,1-0,1))*a_da-((cf_arr*(1+$B30)^M22)*IF(M22>=a_churn_year,1-0,1))*a_capex-a_wc*(((cf_arr*(1+$B30)^M22)*IF(M22>=a_churn_year,1-0,1))-(cf_arr*(1+$B30)^L22*IF(L22>=a_churn_year,1-0,1))) -> 1351.1196
A31: Growth 50% p.a. — unlevered FCF | B31: 0.5 | C31: =0 -> 0 | D31: =(((cf_arr*(1+$B31)^D22)*IF(D22>=a_churn_year,1-0,1))*(MIN(a_m0+a_mstep*D22,a_mcap)-a_da)-IF(D22=a_churn_year,a_sticky*((cf_arr*(1+$B31)^D22)-((cf_arr*(1+$B31)^D22)*IF(D22>=a_churn_year,1-0,1)))*(1-MIN(a_m0+a_mstep*D22,a_mcap)),0))-MAX(0,(((cf_arr*(1+$B31)^D22)*IF(D22>=a_churn_year,1-0,1))*(MIN(a_m0+a_mstep*D22,a_mcap)-a_da)-IF(D22=a_churn_year,a_sticky*((cf_arr*(1+$B31)^D22)-((cf_arr*(1+$B31)^D22)*IF(D22>=a_churn_year,1-0,1)))*(1-MIN(a_m0+a_mstep*D22,a_mcap)),0)))*a_tax+((cf_arr*(1+$B31)^D22)*IF(D22>=a_churn_year,1-0,1))*a_da-((cf_arr*(1+$B31)^D22)*IF(D22>=a_churn_year,1-0,1))*a_capex-a_wc*(((cf_arr*(1+$B31)^D22)*IF(D22>=a_churn_year,1-0,1))-(cf_arr*(1+$B31)^C22*IF(C22>=a_churn_year,1-0,1))) -> -0.55 | E31: =(((cf_arr*(1+$B31)^E22)*IF(E22>=a_churn_year,1-0,1))*(MIN(a_m0+a_mstep*E22,a_mcap)-a_da)-IF(E22=a_churn_year,a_sticky*((cf_arr*(1+$B31)^E22)-((cf_arr*(1+$B31)^E22)*IF(E22>=a_churn_year,1-0,1)))*(1-MIN(a_m0+a_mstep*E22,a_mcap)),0))-MAX(0,(((cf_arr*(1+$B31)^E22)*IF(E22>=a_churn_year,1-0,1))*(MIN(a_m0+a_mstep*E22,a_mcap)-a_da)-IF(E22=a_churn_year,a_sticky*((cf_arr*(1+$B31)^E22)-((cf_arr*(1+$B31)^E22)*IF(E22>=a_churn_year,1-0,1)))*(1-MIN(a_m0+a_mstep*E22,a_mcap)),0)))*a_tax+((cf_arr*(1+$B31)^E22)*IF(E22>=a_churn_year,1-0,1))*a_da-((cf_arr*(1+$B31)^E22)*IF(E22>=a_churn_year,1-0,1))*a_capex-a_wc*(((cf_arr*(1+$B31)^E22)*IF(E22>=a_churn_year,1-0,1))-(cf_arr*(1+$B31)^D22*IF(D22>=a_churn_year,1-0,1))) -> 17.7375 | F31: =(((cf_arr*(1+$B31)^F22)*IF(F22>=a_churn_year,1-0,1))*(MIN(a_m0+a_mstep*F22,a_mcap)-a_da)-IF(F22=a_churn_year,a_sticky*((cf_arr*(1+$B31)^F22)-((cf_arr*(1+$B31)^F22)*IF(F22>=a_churn_year,1-0,1)))*(1-MIN(a_m0+a_mstep*F22,a_mcap)),0))-MAX(0,(((cf_arr*(1+$B31)^F22)*IF(F22>=a_churn_year,1-0,1))*(MIN(a_m0+a_mstep*F22,a_mcap)-a_da)-IF(F22=a_churn_year,a_sticky*((cf_arr*(1+$B31)^F22)-((cf_arr*(1+$B31)^F22)*IF(F22>=a_churn_year,1-0,1)))*(1-MIN(a_m0+a_mstep*F22,a_mcap)),0)))*a_tax+((cf_arr*(1+$B31)^F22)*IF(F22>=a_churn_year,1-0,1))*a_da-((cf_arr*(1+$B31)^F22)*IF(F22>=a_churn_year,1-0,1))*a_capex-a_wc*(((cf_arr*(1+$B31)^F22)*IF(F22>=a_churn_year,1-0,1))-(cf_arr*(1+$B31)^E22*IF(E22>=a_churn_year,1-0,1))) -> 54.45 | G31: =(((cf_arr*(1+$B31)^G22)*IF(G22>=a_churn_year,1-0,1))*(MIN(a_m0+a_mstep*G22,a_mcap)-a_da)-IF(G22=a_churn_year,a_sticky*((cf_arr*(1+$B31)^G22)-((cf_arr*(1+$B31)^G22)*IF(G22>=a_churn_year,1-0,1)))*(1-MIN(a_m0+a_mstep*G22,a_mcap)),0))-MAX(0,(((cf_arr*(1+$B31)^G22)*IF(G22>=a_churn_year,1-0,1))*(MIN(a_m0+a_mstep*G22,a_mcap)-a_da)-IF(G22=a_churn_year,a_sticky*((cf_arr*(1+$B31)^G22)-((cf_arr*(1+$B31)^G22)*IF(G22>=a_churn_year,1-0,1)))*(1-MIN(a_m0+a_mstep*G22,a_mcap)),0)))*a_tax+((cf_arr*(1+$B31)^G22)*IF(G22>=a_churn_year,1-0,1))*a_da-((cf_arr*(1+$B31)^G22)*IF(G22>=a_churn_year,1-0,1))*a_capex-a_wc*(((cf_arr*(1+$B31)^G22)*IF(G22>=a_churn_year,1-0,1))-(cf_arr*(1+$B31)^F22*IF(F22>=a_churn_year,1-0,1))) -> 123.44062 | H31: =(((cf_arr*(1+$B31)^H22)*IF(H22>=a_churn_year,1-0,1))*(MIN(a_m0+a_mstep*H22,a_mcap)-a_da)-IF(H22=a_churn_year,a_sticky*((cf_arr*(1+$B31)^H22)-((cf_arr*(1+$B31)^H22)*IF(H22>=a_churn_year,1-0,1)))*(1-MIN(a_m0+a_mstep*H22,a_mcap)),0))-MAX(0,(((cf_arr*(1+$B31)^H22)*IF(H22>=a_churn_year,1-0,1))*(MIN(a_m0+a_mstep*H22,a_mcap)-a_da)-IF(H22=a_churn_year,a_sticky*((cf_arr*(1+$B31)^H22)-((cf_arr*(1+$B31)^H22)*IF(H22>=a_churn_year,1-0,1)))*(1-MIN(a_m0+a_mstep*H22,a_mcap)),0)))*a_tax+((cf_arr*(1+$B31)^H22)*IF(H22>=a_churn_year,1-0,1))*a_da-((cf_arr*(1+$B31)^H22)*IF(H22>=a_churn_year,1-0,1))*a_capex-a_wc*(((cf_arr*(1+$B31)^H22)*IF(H22>=a_churn_year,1-0,1))-(cf_arr*(1+$B31)^G22*IF(G22>=a_churn_year,1-0,1))) -> 247.80937 | I31: =(((cf_arr*(1+$B31)^I22)*IF(I22>=a_churn_year,1-0,1))*(MIN(a_m0+a_mstep*I22,a_mcap)-a_da)-IF(I22=a_churn_year,a_sticky*((cf_arr*(1+$B31)^I22)-((cf_arr*(1+$B31)^I22)*IF(I22>=a_churn_year,1-0,1)))*(1-MIN(a_m0+a_mstep*I22,a_mcap)),0))-MAX(0,(((cf_arr*(1+$B31)^I22)*IF(I22>=a_churn_year,1-0,1))*(MIN(a_m0+a_mstep*I22,a_mcap)-a_da)-IF(I22=a_churn_year,a_sticky*((cf_arr*(1+$B31)^I22)-((cf_arr*(1+$B31)^I22)*IF(I22>=a_churn_year,1-0,1)))*(1-MIN(a_m0+a_mstep*I22,a_mcap)),0)))*a_tax+((cf_arr*(1+$B31)^I22)*IF(I22>=a_churn_year,1-0,1))*a_da-((cf_arr*(1+$B31)^I22)*IF(I22>=a_churn_year,1-0,1))*a_capex-a_wc*(((cf_arr*(1+$B31)^I22)*IF(I22>=a_churn_year,1-0,1))-(cf_arr*(1+$B31)^H22*IF(H22>=a_churn_year,1-0,1))) -> 371.71406 | J31: =(((cf_arr*(1+$B31)^J22)*IF(J22>=a_churn_year,1-0,1))*(MIN(a_m0+a_mstep*J22,a_mcap)-a_da)-IF(J22=a_churn_year,a_sticky*((cf_arr*(1+$B31)^J22)-((cf_arr*(1+$B31)^J22)*IF(J22>=a_churn_year,1-0,1)))*(1-MIN(a_m0+a_mstep*J22,a_mcap)),0))-MAX(0,(((cf_arr*(1+$B31)^J22)*IF(J22>=a_churn_year,1-0,1))*(MIN(a_m0+a_mstep*J22,a_mcap)-a_da)-IF(J22=a_churn_year,a_sticky*((cf_arr*(1+$B31)^J22)-((cf_arr*(1+$B31)^J22)*IF(J22>=a_churn_year,1-0,1)))*(1-MIN(a_m0+a_mstep*J22,a_mcap)),0)))*a_tax+((cf_arr*(1+$B31)^J22)*IF(J22>=a_churn_year,1-0,1))*a_da-((cf_arr*(1+$B31)^J22)*IF(J22>=a_churn_year,1-0,1))*a_capex-a_wc*(((cf_arr*(1+$B31)^J22)*IF(J22>=a_churn_year,1-0,1))-(cf_arr*(1+$B31)^I22*IF(I22>=a_churn_year,1-0,1))) -> 557.57109 | K31: =(((cf_arr*(1+$B31)^K22)*IF(K22>=a_churn_year,1-0,1))*(MIN(a_m0+a_mstep*K22,a_mcap)-a_da)-IF(K22=a_churn_year,a_sticky*((cf_arr*(1+$B31)^K22)-((cf_arr*(1+$B31)^K22)*IF(K22>=a_churn_year,1-0,1)))*(1-MIN(a_m0+a_mstep*K22,a_mcap)),0))-MAX(0,(((cf_arr*(1+$B31)^K22)*IF(K22>=a_churn_year,1-0,1))*(MIN(a_m0+a_mstep*K22,a_mcap)-a_da)-IF(K22=a_churn_year,a_sticky*((cf_arr*(1+$B31)^K22)-((cf_arr*(1+$B31)^K22)*IF(K22>=a_churn_year,1-0,1)))*(1-MIN(a_m0+a_mstep*K22,a_mcap)),0)))*a_tax+((cf_arr*(1+$B31)^K22)*IF(K22>=a_churn_year,1-0,1))*a_da-((cf_arr*(1+$B31)^K22)*IF(K22>=a_churn_year,1-0,1))*a_capex-a_wc*(((cf_arr*(1+$B31)^K22)*IF(K22>=a_churn_year,1-0,1))-(cf_arr*(1+$B31)^J22*IF(J22>=a_churn_year,1-0,1))) -> 836.35664 | ... M31: =(((cf_arr*(1+$B31)^M22)*IF(M22>=a_churn_year,1-0,1))*(MIN(a_m0+a_mstep*M22,a_mcap)-a_da)-IF(M22=a_churn_year,a_sticky*((cf_arr*(1+$B31)^M22)-((cf_arr*(1+$B31)^M22)*IF(M22>=a_churn_year,1-0,1)))*(1-MIN(a_m0+a_mstep*M22,a_mcap)),0))-MAX(0,(((cf_arr*(1+$B31)^M22)*IF(M22>=a_churn_year,1-0,1))*(MIN(a_m0+a_mstep*M22,a_mcap)-a_da)-IF(M22=a_churn_year,a_sticky*((cf_arr*(1+$B31)^M22)-((cf_arr*(1+$B31)^M22)*IF(M22>=a_churn_year,1-0,1)))*(1-MIN(a_m0+a_mstep*M22,a_mcap)),0)))*a_tax+((cf_arr*(1+$B31)^M22)*IF(M22>=a_churn_year,1-0,1))*a_da-((cf_arr*(1+$B31)^M22)*IF(M22>=a_churn_year,1-0,1))*a_capex-a_wc*(((cf_arr*(1+$B31)^M22)*IF(M22>=a_churn_year,1-0,1))-(cf_arr*(1+$B31)^L22*IF(L22>=a_churn_year,1-0,1))) -> 1881.8024
A33: WACC → | D33: 0.11 | E33: 0.12 | F33: 0.13 | G33: 0.14 | H33: 0.15
A34: Growth ↓ / DCF value of 100% (₹ Cr)
A35: Growth 10% | B35: =B23 -> 0.1 | D35: =SUMPRODUCT(D23:M23,1/(1+D$33)^D$22:M$22)+M23*(1+a_tg)/(D$33-a_tg)/(1+D$33)^M$22 -> 819.2495 | E35: =SUMPRODUCT(D23:M23,1/(1+E$33)^D$22:M$22)+M23*(1+a_tg)/(E$33-a_tg)/(1+E$33)^M$22 -> 682.72394 | F35: =SUMPRODUCT(D23:M23,1/(1+F$33)^D$22:M$22)+M23*(1+a_tg)/(F$33-a_tg)/(1+F$33)^M$22 -> 581.15592 | G35: =SUMPRODUCT(D23:M23,1/(1+G$33)^D$22:M$22)+M23*(1+a_tg)/(G$33-a_tg)/(1+G$33)^M$22 -> 502.84545 | H35: =SUMPRODUCT(D23:M23,1/(1+H$33)^D$22:M$22)+M23*(1+a_tg)/(H$33-a_tg)/(1+H$33)^M$22 -> 440.77589
A36: Growth 15% | B36: =B24 -> 0.15 | D36: =SUMPRODUCT(D24:M24,1/(1+D$33)^D$22:M$22)+M24*(1+a_tg)/(D$33-a_tg)/(1+D$33)^M$22 -> 1206.5013 | E36: =SUMPRODUCT(D24:M24,1/(1+E$33)^D$22:M$22)+M24*(1+a_tg)/(E$33-a_tg)/(1+E$33)^M$22 -> 998.57507 | F36: =SUMPRODUCT(D24:M24,1/(1+F$33)^D$22:M$22)+M24*(1+a_tg)/(F$33-a_tg)/(1+F$33)^M$22 -> 844.36286 | G36: =SUMPRODUCT(D24:M24,1/(1+G$33)^D$22:M$22)+M24*(1+a_tg)/(G$33-a_tg)/(1+G$33)^M$22 -> 725.85026 | H36: =SUMPRODUCT(D24:M24,1/(1+H$33)^D$22:M$22)+M24*(1+a_tg)/(H$33-a_tg)/(1+H$33)^M$22 -> 632.23696
A37: Growth 20% | B37: =B25 -> 0.2 | D37: =SUMPRODUCT(D25:M25,1/(1+D$33)^D$22:M$22)+M25*(1+a_tg)/(D$33-a_tg)/(1+D$33)^M$22 -> 1761.1334 | E37: =SUMPRODUCT(D25:M25,1/(1+E$33)^D$22:M$22)+M25*(1+a_tg)/(E$33-a_tg)/(1+E$33)^M$22 -> 1449.4196 | F37: =SUMPRODUCT(D25:M25,1/(1+F$33)^D$22:M$22)+M25*(1+a_tg)/(F$33-a_tg)/(1+F$33)^M$22 -> 1218.8043 | G37: =SUMPRODUCT(D25:M25,1/(1+G$33)^D$22:M$22)+M25*(1+a_tg)/(G$33-a_tg)/(1+G$33)^M$22 -> 1042.0439 | H37: =SUMPRODUCT(D25:M25,1/(1+H$33)^D$22:M$22)+M25*(1+a_tg)/(H$33-a_tg)/(1+H$33)^M$22 -> 902.80864
A38: Growth 25% | B38: =B26 -> 0.25 | D38: =SUMPRODUCT(D26:M26,1/(1+D$33)^D$22:M$22)+M26*(1+a_tg)/(D$33-a_tg)/(1+D$33)^M$22 -> 2546.1139 | E38: =SUMPRODUCT(D26:M26,1/(1+E$33)^D$22:M$22)+M26*(1+a_tg)/(E$33-a_tg)/(1+E$33)^M$22 -> 2085.7041 | F38: =SUMPRODUCT(D26:M26,1/(1+F$33)^D$22:M$22)+M26*(1+a_tg)/(F$33-a_tg)/(1+F$33)^M$22 -> 1745.7698 | G38: =SUMPRODUCT(D26:M26,1/(1+G$33)^D$22:M$22)+M26*(1+a_tg)/(G$33-a_tg)/(1+G$33)^M$22 -> 1485.7842 | H38: =SUMPRODUCT(D26:M26,1/(1+H$33)^D$22:M$22)+M26*(1+a_tg)/(H$33-a_tg)/(1+H$33)^M$22 -> 1281.4602
A39: Growth 30% | B39: =B27 -> 0.3 | D39: =SUMPRODUCT(D27:M27,1/(1+D$33)^D$22:M$22)+M27*(1+a_tg)/(D$33-a_tg)/(1+D$33)^M$22 -> 3644.4785 | E39: =SUMPRODUCT(D27:M27,1/(1+E$33)^D$22:M$22)+M27*(1+a_tg)/(E$33-a_tg)/(1+E$33)^M$22 -> 2973.8855 | F39: =SUMPRODUCT(D27:M27,1/(1+F$33)^D$22:M$22)+M27*(1+a_tg)/(F$33-a_tg)/(1+F$33)^M$22 -> 2479.5982 | G39: =SUMPRODUCT(D27:M27,1/(1+G$33)^D$22:M$22)+M27*(1+a_tg)/(G$33-a_tg)/(1+G$33)^M$22 -> 2102.2414 | H39: =SUMPRODUCT(D27:M27,1/(1+H$33)^D$22:M$22)+M27*(1+a_tg)/(H$33-a_tg)/(1+H$33)^M$22 -> 1806.2385
A40: Growth 35% | B40: =B28 -> 0.35 | D40: =SUMPRODUCT(D28:M28,1/(1+D$33)^D$22:M$22)+M28*(1+a_tg)/(D$33-a_tg)/(1+D$33)^M$22 -> 5164.6142 | E40: =SUMPRODUCT(D28:M28,1/(1+E$33)^D$22:M$22)+M28*(1+a_tg)/(E$33-a_tg)/(1+E$33)^M$22 -> 4200.6341 | F40: =SUMPRODUCT(D28:M28,1/(1+F$33)^D$22:M$22)+M28*(1+a_tg)/(F$33-a_tg)/(1+F$33)^M$22 -> 3491.0934 | G40: =SUMPRODUCT(D28:M28,1/(1+G$33)^D$22:M$22)+M28*(1+a_tg)/(G$33-a_tg)/(1+G$33)^M$22 -> 2950.2206 | H40: =SUMPRODUCT(D28:M28,1/(1+H$33)^D$22:M$22)+M28*(1+a_tg)/(H$33-a_tg)/(1+H$33)^M$22 -> 2526.631
A41: Growth 40% | B41: =B29 -> 0.4 | D41: =SUMPRODUCT(D29:M29,1/(1+D$33)^D$22:M$22)+M29*(1+a_tg)/(D$33-a_tg)/(1+D$33)^M$22 -> 7246.6582 | E41: =SUMPRODUCT(D29:M29,1/(1+E$33)^D$22:M$22)+M29*(1+a_tg)/(E$33-a_tg)/(1+E$33)^M$22 -> 5877.9234 | F41: =SUMPRODUCT(D29:M29,1/(1+F$33)^D$22:M$22)+M29*(1+a_tg)/(F$33-a_tg)/(1+F$33)^M$22 -> 4871.6594 | G41: =SUMPRODUCT(D29:M29,1/(1+G$33)^D$22:M$22)+M29*(1+a_tg)/(G$33-a_tg)/(1+G$33)^M$22 -> 4105.5772 | H41: =SUMPRODUCT(D29:M29,1/(1+H$33)^D$22:M$22)+M29*(1+a_tg)/(H$33-a_tg)/(1+H$33)^M$22 -> 3506.4237
A42: Growth 45% | B42: =B30 -> 0.45 | D42: =SUMPRODUCT(D30:M30,1/(1+D$33)^D$22:M$22)+M30*(1+a_tg)/(D$33-a_tg)/(1+D$33)^M$22 -> 10070.195 | E42: =SUMPRODUCT(D30:M30,1/(1+E$33)^D$22:M$22)+M30*(1+a_tg)/(E$33-a_tg)/(1+E$33)^M$22 -> 8149.1484 | F42: =SUMPRODUCT(D30:M30,1/(1+F$33)^D$22:M$22)+M30*(1+a_tg)/(F$33-a_tg)/(1+F$33)^M$22 -> 6738.2705 | G42: =SUMPRODUCT(D30:M30,1/(1+G$33)^D$22:M$22)+M30*(1+a_tg)/(G$33-a_tg)/(1+G$33)^M$22 -> 5665.3206 | H42: =SUMPRODUCT(D30:M30,1/(1+H$33)^D$22:M$22)+M30*(1+a_tg)/(H$33-a_tg)/(1+H$33)^M$22 -> 4827.135
A43: Growth 50% | B43: =B31 -> 0.5 | D43: =SUMPRODUCT(D31:M31,1/(1+D$33)^D$22:M$22)+M31*(1+a_tg)/(D$33-a_tg)/(1+D$33)^M$22 -> 13863.449 | E43: =SUMPRODUCT(D31:M31,1/(1+E$33)^D$22:M$22)+M31*(1+a_tg)/(E$33-a_tg)/(1+E$33)^M$22 -> 11196.435 | F43: =SUMPRODUCT(D31:M31,1/(1+F$33)^D$22:M$22)+M31*(1+a_tg)/(F$33-a_tg)/(1+F$33)^M$22 -> 9239.4062 | G43: =SUMPRODUCT(D31:M31,1/(1+G$33)^D$22:M$22)+M31*(1+a_tg)/(G$33-a_tg)/(1+G$33)^M$22 -> 7752.5131 | H43: =SUMPRODUCT(D31:M31,1/(1+H$33)^D$22:M$22)+M31*(1+a_tg)/(H$33-a_tg)/(1+H$33)^M$22 -> 6592.1127
A45: Same grid as EV ÷ current ARR
A46: Growth 10% | D46: =D35/cf_arr -> 3.7238614 | E46: =E35/cf_arr -> 3.1032907 | F46: =F35/cf_arr -> 2.6416178 | G46: =G35/cf_arr -> 2.2856611 | H46: =H35/cf_arr -> 2.0035268
A47: Growth 15% | D47: =D36/cf_arr -> 5.4840967 | E47: =E36/cf_arr -> 4.5389776 | F47: =F36/cf_arr -> 3.838013 | G47: =G36/cf_arr -> 3.2993194 | H47: =H36/cf_arr -> 2.8738043
A48: Growth 20% | D48: =D37/cf_arr -> 8.0051519 | E48: =E37/cf_arr -> 6.5882708 | F48: =F37/cf_arr -> 5.5400194 | G48: =G37/cf_arr -> 4.736563 | H48: =H37/cf_arr -> 4.1036756
A49: Growth 25% | D49: =D38/cf_arr -> 11.573245 | E49: =E38/cf_arr -> 9.4804731 | F49: =F38/cf_arr -> 7.9353175 | G49: =G38/cf_arr -> 6.7535645 | H49: =H38/cf_arr -> 5.8248193
A50: Growth 30% | D50: =D39/cf_arr -> 16.565812 | E50: =E39/cf_arr -> 13.517661 | F50: =F39/cf_arr -> 11.270901 | G50: =G39/cf_arr -> 9.5556427 | H50: =H39/cf_arr -> 8.2101752
A51: Growth 35% | D51: =D40/cf_arr -> 23.475519 | E51: =E40/cf_arr -> 19.093791 | F51: =F40/cf_arr -> 15.868606 | G51: =G40/cf_arr -> 13.410094 | H51: =H40/cf_arr -> 11.484686
A52: Growth 40% | D52: =D41/cf_arr -> 32.939356 | E52: =E41/cf_arr -> 26.717834 | F52: =F41/cf_arr -> 22.143906 | G52: =G41/cf_arr -> 18.661715 | H52: =H41/cf_arr -> 15.93829
A53: Growth 45% | D53: =D42/cf_arr -> 45.773611 | E53: =E42/cf_arr -> 37.041584 | F53: =F42/cf_arr -> 30.628502 | G53: =G42/cf_arr -> 25.751457 | H53: =H42/cf_arr -> 21.941523
A54: Growth 50% | D54: =D43/cf_arr -> 63.015678 | E54: =E43/cf_arr -> 50.892888 | F54: =F43/cf_arr -> 41.997301 | G54: =G43/cf_arr -> 35.238696 | H54: =H43/cf_arr -> 29.964149
A56: 3. BREAKEVEN GROWTH — growth rate at which the standalone DCF equals the price paid (at Dashboard WACC)
A57: DCF at the Dashboard WACC by growth (helper) | D57: =SUMPRODUCT(D23:M23,1/(1+lv_wacc)^D$22:M$22)+M23*(1+a_tg)/(lv_wacc-a_tg)/(1+lv_wacc)^M$22 -> 581.15592 | E57: =SUMPRODUCT(D24:M24,1/(1+lv_wacc)^D$22:M$22)+M24*(1+a_tg)/(lv_wacc-a_tg)/(1+lv_wacc)^M$22 -> 844.36286 | F57: =SUMPRODUCT(D25:M25,1/(1+lv_wacc)^D$22:M$22)+M25*(1+a_tg)/(lv_wacc-a_tg)/(1+lv_wacc)^M$22 -> 1218.8043 | G57: =SUMPRODUCT(D26:M26,1/(1+lv_wacc)^D$22:M$22)+M26*(1+a_tg)/(lv_wacc-a_tg)/(1+lv_wacc)^M$22 -> 1745.7698 | H57: =SUMPRODUCT(D27:M27,1/(1+lv_wacc)^D$22:M$22)+M27*(1+a_tg)/(lv_wacc-a_tg)/(1+lv_wacc)^M$22 -> 2479.5982 | I57: =SUMPRODUCT(D28:M28,1/(1+lv_wacc)^D$22:M$22)+M28*(1+a_tg)/(lv_wacc-a_tg)/(1+lv_wacc)^M$22 -> 3491.0934 | J57: =SUMPRODUCT(D29:M29,1/(1+lv_wacc)^D$22:M$22)+M29*(1+a_tg)/(lv_wacc-a_tg)/(1+lv_wacc)^M$22 -> 4871.6594 | K57: =SUMPRODUCT(D30:M30,1/(1+lv_wacc)^D$22:M$22)+M30*(1+a_tg)/(lv_wacc-a_tg)/(1+lv_wacc)^M$22 -> 6738.2705 | L57: =SUMPRODUCT(D31:M31,1/(1+lv_wacc)^D$22:M$22)+M31*(1+a_tg)/(lv_wacc-a_tg)/(1+lv_wacc)^M$22 -> 9239.4062
A58: Growth grid (helper) | D58: =B23 -> 0.1 | E58: =B24 -> 0.15 | F58: =B25 -> 0.2 | G58: =B26 -> 0.25 | H58: =B27 -> 0.3 | I58: =B28 -> 0.35 | J58: =B29 -> 0.4 | K58: =B30 -> 0.45 | L58: =B31 -> 0.5
A59: Number of grid points with DCF below the price (helper) | B59: =COUNTIF(D57:L57,"<"&lv_price) -> 6
A60: Breakeven 10-year growth rate for DCF = price (linear interpolation; 'n/a' if outside 10–50%) | B60: =IF(OR(B59=0,B59=9),"outside grid",INDEX(D58:L58,B59)+(INDEX(D58:L58,B59+1)-INDEX(D58:L58,B59))*(lv_price-INDEX(D57:L57,B59))/(INDEX(D57:L57,B59+1)-INDEX(D57:L57,B59))) -> 0.36843109
A61: Reading: the price is rational as a STANDALONE investment only if Liminal compounds ARR at ≥ this rate for ten years with zero churn and no capital drag, and still reaches a 25% EBITDA margin.
A63: 4. VALUE OF THE RETAINED BUSINESS — churn (year 1) × growth, at Dashboard WACC; value of 100% (₹ Cr)
A64: Exact closed-form rows: churn removes revenue permanently from year 1 and leaves half of its cost base for one year (Inputs a_sticky).
A65: Year | C65: 0 | D65: 1 | E65: 2 | F65: 3 | G65: 4 | H65: 5 | I65: 6 | J65: 7 | K65: 8 | L65: 9 | M65: 10
A66: Churn ↓ / growth → | D66: 0.1 | E66: 0.2 | F66: 0.3 | G66: 0.4
A67: Churn 0.0% | B67: 0 | D67: =SUMPRODUCT(D73:M73,1/(1+lv_wacc)^D$65:M$65)+M73*(1+a_tg)/(lv_wacc-a_tg)/(1+lv_wacc)^M$65 -> 581.15592 | E67: =SUMPRODUCT(D74:M74,1/(1+lv_wacc)^D$65:M$65)+M74*(1+a_tg)/(lv_wacc-a_tg)/(1+lv_wacc)^M$65 -> 1218.8043 | F67: =SUMPRODUCT(D75:M75,1/(1+lv_wacc)^D$65:M$65)+M75*(1+a_tg)/(lv_wacc-a_tg)/(1+lv_wacc)^M$65 -> 2479.5982 | G67: =SUMPRODUCT(D76:M76,1/(1+lv_wacc)^D$65:M$65)+M76*(1+a_tg)/(lv_wacc-a_tg)/(1+lv_wacc)^M$65 -> 4871.6594
A68: Churn 30.0% | B68: 0.3 | D68: =SUMPRODUCT(D77:M77,1/(1+lv_wacc)^D$65:M$65)+M77*(1+a_tg)/(lv_wacc-a_tg)/(1+lv_wacc)^M$65 -> 379.96136 | E68: =SUMPRODUCT(D78:M78,1/(1+lv_wacc)^D$65:M$65)+M78*(1+a_tg)/(lv_wacc-a_tg)/(1+lv_wacc)^M$65 -> 823.609 | F68: =SUMPRODUCT(D79:M79,1/(1+lv_wacc)^D$65:M$65)+M79*(1+a_tg)/(lv_wacc-a_tg)/(1+lv_wacc)^M$65 -> 1703.4586 | G68: =SUMPRODUCT(D80:M80,1/(1+lv_wacc)^D$65:M$65)+M80*(1+a_tg)/(lv_wacc-a_tg)/(1+lv_wacc)^M$65 -> 3375.1952
A69: Churn 37.5% | B69: 0.375 | D69: =SUMPRODUCT(D81:M81,1/(1+lv_wacc)^D$65:M$65)+M81*(1+a_tg)/(lv_wacc-a_tg)/(1+lv_wacc)^M$65 -> 329.39502 | E69: =SUMPRODUCT(D82:M82,1/(1+lv_wacc)^D$65:M$65)+M82*(1+a_tg)/(lv_wacc-a_tg)/(1+lv_wacc)^M$65 -> 724.51815 | F69: =SUMPRODUCT(D83:M83,1/(1+lv_wacc)^D$65:M$65)+M83*(1+a_tg)/(lv_wacc-a_tg)/(1+lv_wacc)^M$65 -> 1509.1073 | G69: =SUMPRODUCT(D84:M84,1/(1+lv_wacc)^D$65:M$65)+M84*(1+a_tg)/(lv_wacc-a_tg)/(1+lv_wacc)^M$65 -> 3000.7385
A70: Churn 45.0% | B70: 0.45 | D70: =SUMPRODUCT(D85:M85,1/(1+lv_wacc)^D$65:M$65)+M85*(1+a_tg)/(lv_wacc-a_tg)/(1+lv_wacc)^M$65 -> 278.82868 | E70: =SUMPRODUCT(D86:M86,1/(1+lv_wacc)^D$65:M$65)+M86*(1+a_tg)/(lv_wacc-a_tg)/(1+lv_wacc)^M$65 -> 625.4273 | F70: =SUMPRODUCT(D87:M87,1/(1+lv_wacc)^D$65:M$65)+M87*(1+a_tg)/(lv_wacc-a_tg)/(1+lv_wacc)^M$65 -> 1314.756 | G70: =SUMPRODUCT(D88:M88,1/(1+lv_wacc)^D$65:M$65)+M88*(1+a_tg)/(lv_wacc-a_tg)/(1+lv_wacc)^M$65 -> 2626.2817
A72: Helper FCF rows (churn, growth):
A73: FCF: churn 0.0%, growth 10% | C73: =0 -> 0 | D73: =(((cf_arr*(1+D$66)^D65)*IF(D65>=a_churn_year,1-$B$67,1))*(MIN(a_m0+a_mstep*D65,a_mcap)-a_da)-IF(D65=a_churn_year,a_sticky*((cf_arr*(1+D$66)^D65)-((cf_arr*(1+D$66)^D65)*IF(D65>=a_churn_year,1-$B$67,1)))*(1-MIN(a_m0+a_mstep*D65,a_mcap)),0))-MAX(0,(((cf_arr*(1+D$66)^D65)*IF(D65>=a_churn_year,1-$B$67,1))*(MIN(a_m0+a_mstep*D65,a_mcap)-a_da)-IF(D65=a_churn_year,a_sticky*((cf_arr*(1+D$66)^D65)-((cf_arr*(1+D$66)^D65)*IF(D65>=a_churn_year,1-$B$67,1)))*(1-MIN(a_m0+a_mstep*D65,a_mcap)),0)))*a_tax+((cf_arr*(1+D$66)^D65)*IF(D65>=a_churn_year,1-$B$67,1))*a_da-((cf_arr*(1+D$66)^D65)*IF(D65>=a_churn_year,1-$B$67,1))*a_capex-a_wc*(((cf_arr*(1+D$66)^D65)*IF(D65>=a_churn_year,1-$B$67,1))-(cf_arr*(1+D$66)^C65*IF(C65>=a_churn_year,1-$B$67,1))) -> 2.53 | E73: =(((cf_arr*(1+D$66)^E65)*IF(E65>=a_churn_year,1-$B$67,1))*(MIN(a_m0+a_mstep*E65,a_mcap)-a_da)-IF(E65=a_churn_year,a_sticky*((cf_arr*(1+D$66)^E65)-((cf_arr*(1+D$66)^E65)*IF(E65>=a_churn_year,1-$B$67,1)))*(1-MIN(a_m0+a_mstep*E65,a_mcap)),0))-MAX(0,(((cf_arr*(1+D$66)^E65)*IF(E65>=a_churn_year,1-$B$67,1))*(MIN(a_m0+a_mstep*E65,a_mcap)-a_da)-IF(E65=a_churn_year,a_sticky*((cf_arr*(1+D$66)^E65)-((cf_arr*(1+D$66)^E65)*IF(E65>=a_churn_year,1-$B$67,1)))*(1-MIN(a_m0+a_mstep*E65,a_mcap)),0)))*a_tax+((cf_arr*(1+D$66)^E65)*IF(E65>=a_churn_year,1-$B$67,1))*a_da-((cf_arr*(1+D$66)^E65)*IF(E65>=a_churn_year,1-$B$67,1))*a_capex-a_wc*(((cf_arr*(1+D$66)^E65)*IF(E65>=a_churn_year,1-$B$67,1))-(cf_arr*(1+D$66)^D65*IF(D65>=a_churn_year,1-$B$67,1))) -> 12.7655 | F73: =(((cf_arr*(1+D$66)^F65)*IF(F65>=a_churn_year,1-$B$67,1))*(MIN(a_m0+a_mstep*F65,a_mcap)-a_da)-IF(F65=a_churn_year,a_sticky*((cf_arr*(1+D$66)^F65)-((cf_arr*(1+D$66)^F65)*IF(F65>=a_churn_year,1-$B$67,1)))*(1-MIN(a_m0+a_mstep*F65,a_mcap)),0))-MAX(0,(((cf_arr*(1+D$66)^F65)*IF(F65>=a_churn_year,1-$B$67,1))*(MIN(a_m0+a_mstep*F65,a_mcap)-a_da)-IF(F65=a_churn_year,a_sticky*((cf_arr*(1+D$66)^F65)-((cf_arr*(1+D$66)^F65)*IF(F65>=a_churn_year,1-$B$67,1)))*(1-MIN(a_m0+a_mstep*F65,a_mcap)),0)))*a_tax+((cf_arr*(1+D$66)^F65)*IF(F65>=a_churn_year,1-$B$67,1))*a_da-((cf_arr*(1+D$66)^F65)*IF(F65>=a_churn_year,1-$B$67,1))*a_capex-a_wc*(((cf_arr*(1+D$66)^F65)*IF(F65>=a_churn_year,1-$B$67,1))-(cf_arr*(1+D$66)^E65*IF(E65>=a_churn_year,1-$B$67,1))) -> 25.0228 | G73: =(((cf_arr*(1+D$66)^G65)*IF(G65>=a_churn_year,1-$B$67,1))*(MIN(a_m0+a_mstep*G65,a_mcap)-a_da)-IF(G65=a_churn_year,a_sticky*((cf_arr*(1+D$66)^G65)-((cf_arr*(1+D$66)^G65)*IF(G65>=a_churn_year,1-$B$67,1)))*(1-MIN(a_m0+a_mstep*G65,a_mcap)),0))-MAX(0,(((cf_arr*(1+D$66)^G65)*IF(G65>=a_churn_year,1-$B$67,1))*(MIN(a_m0+a_mstep*G65,a_mcap)-a_da)-IF(G65=a_churn_year,a_sticky*((cf_arr*(1+D$66)^G65)-((cf_arr*(1+D$66)^G65)*IF(G65>=a_churn_year,1-$B$67,1)))*(1-MIN(a_m0+a_mstep*G65,a_mcap)),0)))*a_tax+((cf_arr*(1+D$66)^G65)*IF(G65>=a_churn_year,1-$B$67,1))*a_da-((cf_arr*(1+D$66)^G65)*IF(G65>=a_churn_year,1-$B$67,1))*a_capex-a_wc*(((cf_arr*(1+D$66)^G65)*IF(G65>=a_churn_year,1-$B$67,1))-(cf_arr*(1+D$66)^F65*IF(F65>=a_churn_year,1-$B$67,1))) -> 39.603905 | H73: =(((cf_arr*(1+D$66)^H65)*IF(H65>=a_churn_year,1-$B$67,1))*(MIN(a_m0+a_mstep*H65,a_mcap)-a_da)-IF(H65=a_churn_year,a_sticky*((cf_arr*(1+D$66)^H65)-((cf_arr*(1+D$66)^H65)*IF(H65>=a_churn_year,1-$B$67,1)))*(1-MIN(a_m0+a_mstep*H65,a_mcap)),0))-MAX(0,(((cf_arr*(1+D$66)^H65)*IF(H65>=a_churn_year,1-$B$67,1))*(MIN(a_m0+a_mstep*H65,a_mcap)-a_da)-IF(H65=a_churn_year,a_sticky*((cf_arr*(1+D$66)^H65)-((cf_arr*(1+D$66)^H65)*IF(H65>=a_churn_year,1-$B$67,1)))*(1-MIN(a_m0+a_mstep*H65,a_mcap)),0)))*a_tax+((cf_arr*(1+D$66)^H65)*IF(H65>=a_churn_year,1-$B$67,1))*a_da-((cf_arr*(1+D$66)^H65)*IF(H65>=a_churn_year,1-$B$67,1))*a_capex-a_wc*(((cf_arr*(1+D$66)^H65)*IF(H65>=a_churn_year,1-$B$67,1))-(cf_arr*(1+D$66)^G65*IF(G65>=a_churn_year,1-$B$67,1))) -> 56.851003 | I73: =(((cf_arr*(1+D$66)^I65)*IF(I65>=a_churn_year,1-$B$67,1))*(MIN(a_m0+a_mstep*I65,a_mcap)-a_da)-IF(I65=a_churn_year,a_sticky*((cf_arr*(1+D$66)^I65)-((cf_arr*(1+D$66)^I65)*IF(I65>=a_churn_year,1-$B$67,1)))*(1-MIN(a_m0+a_mstep*I65,a_mcap)),0))-MAX(0,(((cf_arr*(1+D$66)^I65)*IF(I65>=a_churn_year,1-$B$67,1))*(MIN(a_m0+a_mstep*I65,a_mcap)-a_da)-IF(I65=a_churn_year,a_sticky*((cf_arr*(1+D$66)^I65)-((cf_arr*(1+D$66)^I65)*IF(I65>=a_churn_year,1-$B$67,1)))*(1-MIN(a_m0+a_mstep*I65,a_mcap)),0)))*a_tax+((cf_arr*(1+D$66)^I65)*IF(I65>=a_churn_year,1-$B$67,1))*a_da-((cf_arr*(1+D$66)^I65)*IF(I65>=a_churn_year,1-$B$67,1))*a_capex-a_wc*(((cf_arr*(1+D$66)^I65)*IF(I65>=a_churn_year,1-$B$67,1))-(cf_arr*(1+D$66)^H65*IF(H65>=a_churn_year,1-$B$67,1))) -> 62.536103 | J73: =(((cf_arr*(1+D$66)^J65)*IF(J65>=a_churn_year,1-$B$67,1))*(MIN(a_m0+a_mstep*J65,a_mcap)-a_da)-IF(J65=a_churn_year,a_sticky*((cf_arr*(1+D$66)^J65)-((cf_arr*(1+D$66)^J65)*IF(J65>=a_churn_year,1-$B$67,1)))*(1-MIN(a_m0+a_mstep*J65,a_mcap)),0))-MAX(0,(((cf_arr*(1+D$66)^J65)*IF(J65>=a_churn_year,1-$B$67,1))*(MIN(a_m0+a_mstep*J65,a_mcap)-a_da)-IF(J65=a_churn_year,a_sticky*((cf_arr*(1+D$66)^J65)-((cf_arr*(1+D$66)^J65)*IF(J65>=a_churn_year,1-$B$67,1)))*(1-MIN(a_m0+a_mstep*J65,a_mcap)),0)))*a_tax+((cf_arr*(1+D$66)^J65)*IF(J65>=a_churn_year,1-$B$67,1))*a_da-((cf_arr*(1+D$66)^J65)*IF(J65>=a_churn_year,1-$B$67,1))*a_capex-a_wc*(((cf_arr*(1+D$66)^J65)*IF(J65>=a_churn_year,1-$B$67,1))-(cf_arr*(1+D$66)^I65*IF(I65>=a_churn_year,1-$B$67,1))) -> 68.789714 | K73: =(((cf_arr*(1+D$66)^K65)*IF(K65>=a_churn_year,1-$B$67,1))*(MIN(a_m0+a_mstep*K65,a_mcap)-a_da)-IF(K65=a_churn_year,a_sticky*((cf_arr*(1+D$66)^K65)-((cf_arr*(1+D$66)^K65)*IF(K65>=a_churn_year,1-$B$67,1)))*(1-MIN(a_m0+a_mstep*K65,a_mcap)),0))-MAX(0,(((cf_arr*(1+D$66)^K65)*IF(K65>=a_churn_year,1-$B$67,1))*(MIN(a_m0+a_mstep*K65,a_mcap)-a_da)-IF(K65=a_churn_year,a_sticky*((cf_arr*(1+D$66)^K65)-((cf_arr*(1+D$66)^K65)*IF(K65>=a_churn_year,1-$B$67,1)))*(1-MIN(a_m0+a_mstep*K65,a_mcap)),0)))*a_tax+((cf_arr*(1+D$66)^K65)*IF(K65>=a_churn_year,1-$B$67,1))*a_da-((cf_arr*(1+D$66)^K65)*IF(K65>=a_churn_year,1-$B$67,1))*a_capex-a_wc*(((cf_arr*(1+D$66)^K65)*IF(K65>=a_churn_year,1-$B$67,1))-(cf_arr*(1+D$66)^J65*IF(J65>=a_churn_year,1-$B$67,1))) -> 75.668685 | L73: =(((cf_arr*(1+D$66)^L65)*IF(L65>=a_churn_year,1-$B$67,1))*(MIN(a_m0+a_mstep*L65,a_mcap)-a_da)-IF(L65=a_churn_year,a_sticky*((cf_arr*(1+D$66)^L65)-((cf_arr*(1+D$66)^L65)*IF(L65>=a_churn_year,1-$B$67,1)))*(1-MIN(a_m0+a_mstep*L65,a_mcap)),0))-MAX(0,(((cf_arr*(1+D$66)^L65)*IF(L65>=a_churn_year,1-$B$67,1))*(MIN(a_m0+a_mstep*L65,a_mcap)-a_da)-IF(L65=a_churn_year,a_sticky*((cf_arr*(1+D$66)^L65)-((cf_arr*(1+D$66)^L65)*IF(L65>=a_churn_year,1-$B$67,1)))*(1-MIN(a_m0+a_mstep*L65,a_mcap)),0)))*a_tax+((cf_arr*(1+D$66)^L65)*IF(L65>=a_churn_year,1-$B$67,1))*a_da-((cf_arr*(1+D$66)^L65)*IF(L65>=a_churn_year,1-$B$67,1))*a_capex-a_wc*(((cf_arr*(1+D$66)^L65)*IF(L65>=a_churn_year,1-$B$67,1))-(cf_arr*(1+D$66)^K65*IF(K65>=a_churn_year,1-$B$67,1))) -> 83.235553 | M73: =(((cf_arr*(1+D$66)^M65)*IF(M65>=a_churn_year,1-$B$67,1))*(MIN(a_m0+a_mstep*M65,a_mcap)-a_da)-IF(M65=a_churn_year,a_sticky*((cf_arr*(1+D$66)^M65)-((cf_arr*(1+D$66)^M65)*IF(M65>=a_churn_year,1-$B$67,1)))*(1-MIN(a_m0+a_mstep*M65,a_mcap)),0))-MAX(0,(((cf_arr*(1+D$66)^M65)*IF(M65>=a_churn_year,1-$B$67,1))*(MIN(a_m0+a_mstep*M65,a_mcap)-a_da)-IF(M65=a_churn_year,a_sticky*((cf_arr*(1+D$66)^M65)-((cf_arr*(1+D$66)^M65)*IF(M65>=a_churn_year,1-$B$67,1)))*(1-MIN(a_m0+a_mstep*M65,a_mcap)),0)))*a_tax+((cf_arr*(1+D$66)^M65)*IF(M65>=a_churn_year,1-$B$67,1))*a_da-((cf_arr*(1+D$66)^M65)*IF(M65>=a_churn_year,1-$B$67,1))*a_capex-a_wc*(((cf_arr*(1+D$66)^M65)*IF(M65>=a_churn_year,1-$B$67,1))-(cf_arr*(1+D$66)^L65*IF(L65>=a_churn_year,1-$B$67,1))) -> 91.559109
A74: FCF: churn 0.0%, growth 20% | C74: =0 -> 0 | D74: =(((cf_arr*(1+E$66)^D65)*IF(D65>=a_churn_year,1-$B$67,1))*(MIN(a_m0+a_mstep*D65,a_mcap)-a_da)-IF(D65=a_churn_year,a_sticky*((cf_arr*(1+E$66)^D65)-((cf_arr*(1+E$66)^D65)*IF(D65>=a_churn_year,1-$B$67,1)))*(1-MIN(a_m0+a_mstep*D65,a_mcap)),0))-MAX(0,(((cf_arr*(1+E$66)^D65)*IF(D65>=a_churn_year,1-$B$67,1))*(MIN(a_m0+a_mstep*D65,a_mcap)-a_da)-IF(D65=a_churn_year,a_sticky*((cf_arr*(1+E$66)^D65)-((cf_arr*(1+E$66)^D65)*IF(D65>=a_churn_year,1-$B$67,1)))*(1-MIN(a_m0+a_mstep*D65,a_mcap)),0)))*a_tax+((cf_arr*(1+E$66)^D65)*IF(D65>=a_churn_year,1-$B$67,1))*a_da-((cf_arr*(1+E$66)^D65)*IF(D65>=a_churn_year,1-$B$67,1))*a_capex-a_wc*(((cf_arr*(1+E$66)^D65)*IF(D65>=a_churn_year,1-$B$67,1))-(cf_arr*(1+E$66)^C65*IF(C65>=a_churn_year,1-$B$67,1))) -> 1.76 | E74: =(((cf_arr*(1+E$66)^E65)*IF(E65>=a_churn_year,1-$B$67,1))*(MIN(a_m0+a_mstep*E65,a_mcap)-a_da)-IF(E65=a_churn_year,a_sticky*((cf_arr*(1+E$66)^E65)-((cf_arr*(1+E$66)^E65)*IF(E65>=a_churn_year,1-$B$67,1)))*(1-MIN(a_m0+a_mstep*E65,a_mcap)),0))-MAX(0,(((cf_arr*(1+E$66)^E65)*IF(E65>=a_churn_year,1-$B$67,1))*(MIN(a_m0+a_mstep*E65,a_mcap)-a_da)-IF(E65=a_churn_year,a_sticky*((cf_arr*(1+E$66)^E65)-((cf_arr*(1+E$66)^E65)*IF(E65>=a_churn_year,1-$B$67,1)))*(1-MIN(a_m0+a_mstep*E65,a_mcap)),0)))*a_tax+((cf_arr*(1+E$66)^E65)*IF(E65>=a_churn_year,1-$B$67,1))*a_da-((cf_arr*(1+E$66)^E65)*IF(E65>=a_churn_year,1-$B$67,1))*a_capex-a_wc*(((cf_arr*(1+E$66)^E65)*IF(E65>=a_churn_year,1-$B$67,1))-(cf_arr*(1+E$66)^D65*IF(D65>=a_churn_year,1-$B$67,1))) -> 13.992 | F74: =(((cf_arr*(1+E$66)^F65)*IF(F65>=a_churn_year,1-$B$67,1))*(MIN(a_m0+a_mstep*F65,a_mcap)-a_da)-IF(F65=a_churn_year,a_sticky*((cf_arr*(1+E$66)^F65)-((cf_arr*(1+E$66)^F65)*IF(F65>=a_churn_year,1-$B$67,1)))*(1-MIN(a_m0+a_mstep*F65,a_mcap)),0))-MAX(0,(((cf_arr*(1+E$66)^F65)*IF(F65>=a_churn_year,1-$B$67,1))*(MIN(a_m0+a_mstep*F65,a_mcap)-a_da)-IF(F65=a_churn_year,a_sticky*((cf_arr*(1+E$66)^F65)-((cf_arr*(1+E$66)^F65)*IF(F65>=a_churn_year,1-$B$67,1)))*(1-MIN(a_m0+a_mstep*F65,a_mcap)),0)))*a_tax+((cf_arr*(1+E$66)^F65)*IF(F65>=a_churn_year,1-$B$67,1))*a_da-((cf_arr*(1+E$66)^F65)*IF(F65>=a_churn_year,1-$B$67,1))*a_capex-a_wc*(((cf_arr*(1+E$66)^F65)*IF(F65>=a_churn_year,1-$B$67,1))-(cf_arr*(1+E$66)^E65*IF(E65>=a_churn_year,1-$B$67,1))) -> 31.0464 | G74: =(((cf_arr*(1+E$66)^G65)*IF(G65>=a_churn_year,1-$B$67,1))*(MIN(a_m0+a_mstep*G65,a_mcap)-a_da)-IF(G65=a_churn_year,a_sticky*((cf_arr*(1+E$66)^G65)-((cf_arr*(1+E$66)^G65)*IF(G65>=a_churn_year,1-$B$67,1)))*(1-MIN(a_m0+a_mstep*G65,a_mcap)),0))-MAX(0,(((cf_arr*(1+E$66)^G65)*IF(G65>=a_churn_year,1-$B$67,1))*(MIN(a_m0+a_mstep*G65,a_mcap)-a_da)-IF(G65=a_churn_year,a_sticky*((cf_arr*(1+E$66)^G65)-((cf_arr*(1+E$66)^G65)*IF(G65>=a_churn_year,1-$B$67,1)))*(1-MIN(a_m0+a_mstep*G65,a_mcap)),0)))*a_tax+((cf_arr*(1+E$66)^G65)*IF(G65>=a_churn_year,1-$B$67,1))*a_da-((cf_arr*(1+E$66)^G65)*IF(G65>=a_churn_year,1-$B$67,1))*a_capex-a_wc*(((cf_arr*(1+E$66)^G65)*IF(G65>=a_churn_year,1-$B$67,1))-(cf_arr*(1+E$66)^F65*IF(F65>=a_churn_year,1-$B$67,1))) -> 54.36288 | H74: =(((cf_arr*(1+E$66)^H65)*IF(H65>=a_churn_year,1-$B$67,1))*(MIN(a_m0+a_mstep*H65,a_mcap)-a_da)-IF(H65=a_churn_year,a_sticky*((cf_arr*(1+E$66)^H65)-((cf_arr*(1+E$66)^H65)*IF(H65>=a_churn_year,1-$B$67,1)))*(1-MIN(a_m0+a_mstep*H65,a_mcap)),0))-MAX(0,(((cf_arr*(1+E$66)^H65)*IF(H65>=a_churn_year,1-$B$67,1))*(MIN(a_m0+a_mstep*H65,a_mcap)-a_da)-IF(H65=a_churn_year,a_sticky*((cf_arr*(1+E$66)^H65)-((cf_arr*(1+E$66)^H65)*IF(H65>=a_churn_year,1-$B$67,1)))*(1-MIN(a_m0+a_mstep*H65,a_mcap)),0)))*a_tax+((cf_arr*(1+E$66)^H65)*IF(H65>=a_churn_year,1-$B$67,1))*a_da-((cf_arr*(1+E$66)^H65)*IF(H65>=a_churn_year,1-$B$67,1))*a_capex-a_wc*(((cf_arr*(1+E$66)^H65)*IF(H65>=a_churn_year,1-$B$67,1))-(cf_arr*(1+E$66)^G65*IF(G65>=a_churn_year,1-$B$67,1))) -> 85.764096 | I74: =(((cf_arr*(1+E$66)^I65)*IF(I65>=a_churn_year,1-$B$67,1))*(MIN(a_m0+a_mstep*I65,a_mcap)-a_da)-IF(I65=a_churn_year,a_sticky*((cf_arr*(1+E$66)^I65)-((cf_arr*(1+E$66)^I65)*IF(I65>=a_churn_year,1-$B$67,1)))*(1-MIN(a_m0+a_mstep*I65,a_mcap)),0))-MAX(0,(((cf_arr*(1+E$66)^I65)*IF(I65>=a_churn_year,1-$B$67,1))*(MIN(a_m0+a_mstep*I65,a_mcap)-a_da)-IF(I65=a_churn_year,a_sticky*((cf_arr*(1+E$66)^I65)-((cf_arr*(1+E$66)^I65)*IF(I65>=a_churn_year,1-$B$67,1)))*(1-MIN(a_m0+a_mstep*I65,a_mcap)),0)))*a_tax+((cf_arr*(1+E$66)^I65)*IF(I65>=a_churn_year,1-$B$67,1))*a_da-((cf_arr*(1+E$66)^I65)*IF(I65>=a_churn_year,1-$B$67,1))*a_capex-a_wc*(((cf_arr*(1+E$66)^I65)*IF(I65>=a_churn_year,1-$B$67,1))-(cf_arr*(1+E$66)^H65*IF(H65>=a_churn_year,1-$B$67,1))) -> 102.91692 | J74: =(((cf_arr*(1+E$66)^J65)*IF(J65>=a_churn_year,1-$B$67,1))*(MIN(a_m0+a_mstep*J65,a_mcap)-a_da)-IF(J65=a_churn_year,a_sticky*((cf_arr*(1+E$66)^J65)-((cf_arr*(1+E$66)^J65)*IF(J65>=a_churn_year,1-$B$67,1)))*(1-MIN(a_m0+a_mstep*J65,a_mcap)),0))-MAX(0,(((cf_arr*(1+E$66)^J65)*IF(J65>=a_churn_year,1-$B$67,1))*(MIN(a_m0+a_mstep*J65,a_mcap)-a_da)-IF(J65=a_churn_year,a_sticky*((cf_arr*(1+E$66)^J65)-((cf_arr*(1+E$66)^J65)*IF(J65>=a_churn_year,1-$B$67,1)))*(1-MIN(a_m0+a_mstep*J65,a_mcap)),0)))*a_tax+((cf_arr*(1+E$66)^J65)*IF(J65>=a_churn_year,1-$B$67,1))*a_da-((cf_arr*(1+E$66)^J65)*IF(J65>=a_churn_year,1-$B$67,1))*a_capex-a_wc*(((cf_arr*(1+E$66)^J65)*IF(J65>=a_churn_year,1-$B$67,1))-(cf_arr*(1+E$66)^I65*IF(I65>=a_churn_year,1-$B$67,1))) -> 123.5003 | K74: =(((cf_arr*(1+E$66)^K65)*IF(K65>=a_churn_year,1-$B$67,1))*(MIN(a_m0+a_mstep*K65,a_mcap)-a_da)-IF(K65=a_churn_year,a_sticky*((cf_arr*(1+E$66)^K65)-((cf_arr*(1+E$66)^K65)*IF(K65>=a_churn_year,1-$B$67,1)))*(1-MIN(a_m0+a_mstep*K65,a_mcap)),0))-MAX(0,(((cf_arr*(1+E$66)^K65)*IF(K65>=a_churn_year,1-$B$67,1))*(MIN(a_m0+a_mstep*K65,a_mcap)-a_da)-IF(K65=a_churn_year,a_sticky*((cf_arr*(1+E$66)^K65)-((cf_arr*(1+E$66)^K65)*IF(K65>=a_churn_year,1-$B$67,1)))*(1-MIN(a_m0+a_mstep*K65,a_mcap)),0)))*a_tax+((cf_arr*(1+E$66)^K65)*IF(K65>=a_churn_year,1-$B$67,1))*a_da-((cf_arr*(1+E$66)^K65)*IF(K65>=a_churn_year,1-$B$67,1))*a_capex-a_wc*(((cf_arr*(1+E$66)^K65)*IF(K65>=a_churn_year,1-$B$67,1))-(cf_arr*(1+E$66)^J65*IF(J65>=a_churn_year,1-$B$67,1))) -> 148.20036 | L74: =(((cf_arr*(1+E$66)^L65)*IF(L65>=a_churn_year,1-$B$67,1))*(MIN(a_m0+a_mstep*L65,a_mcap)-a_da)-IF(L65=a_churn_year,a_sticky*((cf_arr*(1+E$66)^L65)-((cf_arr*(1+E$66)^L65)*IF(L65>=a_churn_year,1-$B$67,1)))*(1-MIN(a_m0+a_mstep*L65,a_mcap)),0))-MAX(0,(((cf_arr*(1+E$66)^L65)*IF(L65>=a_churn_year,1-$B$67,1))*(MIN(a_m0+a_mstep*L65,a_mcap)-a_da)-IF(L65=a_churn_year,a_sticky*((cf_arr*(1+E$66)^L65)-((cf_arr*(1+E$66)^L65)*IF(L65>=a_churn_year,1-$B$67,1)))*(1-MIN(a_m0+a_mstep*L65,a_mcap)),0)))*a_tax+((cf_arr*(1+E$66)^L65)*IF(L65>=a_churn_year,1-$B$67,1))*a_da-((cf_arr*(1+E$66)^L65)*IF(L65>=a_churn_year,1-$B$67,1))*a_capex-a_wc*(((cf_arr*(1+E$66)^L65)*IF(L65>=a_churn_year,1-$B$67,1))-(cf_arr*(1+E$66)^K65*IF(K65>=a_churn_year,1-$B$67,1))) -> 177.84043 | M74: =(((cf_arr*(1+E$66)^M65)*IF(M65>=a_churn_year,1-$B$67,1))*(MIN(a_m0+a_mstep*M65,a_mcap)-a_da)-IF(M65=a_churn_year,a_sticky*((cf_arr*(1+E$66)^M65)-((cf_arr*(1+E$66)^M65)*IF(M65>=a_churn_year,1-$B$67,1)))*(1-MIN(a_m0+a_mstep*M65,a_mcap)),0))-MAX(0,(((cf_arr*(1+E$66)^M65)*IF(M65>=a_churn_year,1-$B$67,1))*(MIN(a_m0+a_mstep*M65,a_mcap)-a_da)-IF(M65=a_churn_year,a_sticky*((cf_arr*(1+E$66)^M65)-((cf_arr*(1+E$66)^M65)*IF(M65>=a_churn_year,1-$B$67,1)))*(1-MIN(a_m0+a_mstep*M65,a_mcap)),0)))*a_tax+((cf_arr*(1+E$66)^M65)*IF(M65>=a_churn_year,1-$B$67,1))*a_da-((cf_arr*(1+E$66)^M65)*IF(M65>=a_churn_year,1-$B$67,1))*a_capex-a_wc*(((cf_arr*(1+E$66)^M65)*IF(M65>=a_churn_year,1-$B$67,1))-(cf_arr*(1+E$66)^L65*IF(L65>=a_churn_year,1-$B$67,1))) -> 213.40852
A75: FCF: churn 0.0%, growth 30% | C75: =0 -> 0 | D75: =(((cf_arr*(1+F$66)^D65)*IF(D65>=a_churn_year,1-$B$67,1))*(MIN(a_m0+a_mstep*D65,a_mcap)-a_da)-IF(D65=a_churn_year,a_sticky*((cf_arr*(1+F$66)^D65)-((cf_arr*(1+F$66)^D65)*IF(D65>=a_churn_year,1-$B$67,1)))*(1-MIN(a_m0+a_mstep*D65,a_mcap)),0))-MAX(0,(((cf_arr*(1+F$66)^D65)*IF(D65>=a_churn_year,1-$B$67,1))*(MIN(a_m0+a_mstep*D65,a_mcap)-a_da)-IF(D65=a_churn_year,a_sticky*((cf_arr*(1+F$66)^D65)-((cf_arr*(1+F$66)^D65)*IF(D65>=a_churn_year,1-$B$67,1)))*(1-MIN(a_m0+a_mstep*D65,a_mcap)),0)))*a_tax+((cf_arr*(1+F$66)^D65)*IF(D65>=a_churn_year,1-$B$67,1))*a_da-((cf_arr*(1+F$66)^D65)*IF(D65>=a_churn_year,1-$B$67,1))*a_capex-a_wc*(((cf_arr*(1+F$66)^D65)*IF(D65>=a_churn_year,1-$B$67,1))-(cf_arr*(1+F$66)^C65*IF(C65>=a_churn_year,1-$B$67,1))) -> 0.99 | E75: =(((cf_arr*(1+F$66)^E65)*IF(E65>=a_churn_year,1-$B$67,1))*(MIN(a_m0+a_mstep*E65,a_mcap)-a_da)-IF(E65=a_churn_year,a_sticky*((cf_arr*(1+F$66)^E65)-((cf_arr*(1+F$66)^E65)*IF(E65>=a_churn_year,1-$B$67,1)))*(1-MIN(a_m0+a_mstep*E65,a_mcap)),0))-MAX(0,(((cf_arr*(1+F$66)^E65)*IF(E65>=a_churn_year,1-$B$67,1))*(MIN(a_m0+a_mstep*E65,a_mcap)-a_da)-IF(E65=a_churn_year,a_sticky*((cf_arr*(1+F$66)^E65)-((cf_arr*(1+F$66)^E65)*IF(E65>=a_churn_year,1-$B$67,1)))*(1-MIN(a_m0+a_mstep*E65,a_mcap)),0)))*a_tax+((cf_arr*(1+F$66)^E65)*IF(E65>=a_churn_year,1-$B$67,1))*a_da-((cf_arr*(1+F$66)^E65)*IF(E65>=a_churn_year,1-$B$67,1))*a_capex-a_wc*(((cf_arr*(1+F$66)^E65)*IF(E65>=a_churn_year,1-$B$67,1))-(cf_arr*(1+F$66)^D65*IF(D65>=a_churn_year,1-$B$67,1))) -> 15.2295 | F75: =(((cf_arr*(1+F$66)^F65)*IF(F65>=a_churn_year,1-$B$67,1))*(MIN(a_m0+a_mstep*F65,a_mcap)-a_da)-IF(F65=a_churn_year,a_sticky*((cf_arr*(1+F$66)^F65)-((cf_arr*(1+F$66)^F65)*IF(F65>=a_churn_year,1-$B$67,1)))*(1-MIN(a_m0+a_mstep*F65,a_mcap)),0))-MAX(0,(((cf_arr*(1+F$66)^F65)*IF(F65>=a_churn_year,1-$B$67,1))*(MIN(a_m0+a_mstep*F65,a_mcap)-a_da)-IF(F65=a_churn_year,a_sticky*((cf_arr*(1+F$66)^F65)-((cf_arr*(1+F$66)^F65)*IF(F65>=a_churn_year,1-$B$67,1)))*(1-MIN(a_m0+a_mstep*F65,a_mcap)),0)))*a_tax+((cf_arr*(1+F$66)^F65)*IF(F65>=a_churn_year,1-$B$67,1))*a_da-((cf_arr*(1+F$66)^F65)*IF(F65>=a_churn_year,1-$B$67,1))*a_capex-a_wc*(((cf_arr*(1+F$66)^F65)*IF(F65>=a_churn_year,1-$B$67,1))-(cf_arr*(1+F$66)^E65*IF(E65>=a_churn_year,1-$B$67,1))) -> 37.9236 | G75: =(((cf_arr*(1+F$66)^G65)*IF(G65>=a_churn_year,1-$B$67,1))*(MIN(a_m0+a_mstep*G65,a_mcap)-a_da)-IF(G65=a_churn_year,a_sticky*((cf_arr*(1+F$66)^G65)-((cf_arr*(1+F$66)^G65)*IF(G65>=a_churn_year,1-$B$67,1)))*(1-MIN(a_m0+a_mstep*G65,a_mcap)),0))-MAX(0,(((cf_arr*(1+F$66)^G65)*IF(G65>=a_churn_year,1-$B$67,1))*(MIN(a_m0+a_mstep*G65,a_mcap)-a_da)-IF(G65=a_churn_year,a_sticky*((cf_arr*(1+F$66)^G65)-((cf_arr*(1+F$66)^G65)*IF(G65>=a_churn_year,1-$B$67,1)))*(1-MIN(a_m0+a_mstep*G65,a_mcap)),0)))*a_tax+((cf_arr*(1+F$66)^G65)*IF(G65>=a_churn_year,1-$B$67,1))*a_da-((cf_arr*(1+F$66)^G65)*IF(G65>=a_churn_year,1-$B$67,1))*a_capex-a_wc*(((cf_arr*(1+F$66)^G65)*IF(G65>=a_churn_year,1-$B$67,1))-(cf_arr*(1+F$66)^F65*IF(F65>=a_churn_year,1-$B$67,1))) -> 72.863505 | H75: =(((cf_arr*(1+F$66)^H65)*IF(H65>=a_churn_year,1-$B$67,1))*(MIN(a_m0+a_mstep*H65,a_mcap)-a_da)-IF(H65=a_churn_year,a_sticky*((cf_arr*(1+F$66)^H65)-((cf_arr*(1+F$66)^H65)*IF(H65>=a_churn_year,1-$B$67,1)))*(1-MIN(a_m0+a_mstep*H65,a_mcap)),0))-MAX(0,(((cf_arr*(1+F$66)^H65)*IF(H65>=a_churn_year,1-$B$67,1))*(MIN(a_m0+a_mstep*H65,a_mcap)-a_da)-IF(H65=a_churn_year,a_sticky*((cf_arr*(1+F$66)^H65)-((cf_arr*(1+F$66)^H65)*IF(H65>=a_churn_year,1-$B$67,1)))*(1-MIN(a_m0+a_mstep*H65,a_mcap)),0)))*a_tax+((cf_arr*(1+F$66)^H65)*IF(H65>=a_churn_year,1-$B$67,1))*a_da-((cf_arr*(1+F$66)^H65)*IF(H65>=a_churn_year,1-$B$67,1))*a_capex-a_wc*(((cf_arr*(1+F$66)^H65)*IF(H65>=a_churn_year,1-$B$67,1))-(cf_arr*(1+F$66)^G65*IF(G65>=a_churn_year,1-$B$67,1))) -> 125.35423 | I75: =(((cf_arr*(1+F$66)^I65)*IF(I65>=a_churn_year,1-$B$67,1))*(MIN(a_m0+a_mstep*I65,a_mcap)-a_da)-IF(I65=a_churn_year,a_sticky*((cf_arr*(1+F$66)^I65)-((cf_arr*(1+F$66)^I65)*IF(I65>=a_churn_year,1-$B$67,1)))*(1-MIN(a_m0+a_mstep*I65,a_mcap)),0))-MAX(0,(((cf_arr*(1+F$66)^I65)*IF(I65>=a_churn_year,1-$B$67,1))*(MIN(a_m0+a_mstep*I65,a_mcap)-a_da)-IF(I65=a_churn_year,a_sticky*((cf_arr*(1+F$66)^I65)-((cf_arr*(1+F$66)^I65)*IF(I65>=a_churn_year,1-$B$67,1)))*(1-MIN(a_m0+a_mstep*I65,a_mcap)),0)))*a_tax+((cf_arr*(1+F$66)^I65)*IF(I65>=a_churn_year,1-$B$67,1))*a_da-((cf_arr*(1+F$66)^I65)*IF(I65>=a_churn_year,1-$B$67,1))*a_capex-a_wc*(((cf_arr*(1+F$66)^I65)*IF(I65>=a_churn_year,1-$B$67,1))-(cf_arr*(1+F$66)^H65*IF(H65>=a_churn_year,1-$B$67,1))) -> 162.9605 | J75: =(((cf_arr*(1+F$66)^J65)*IF(J65>=a_churn_year,1-$B$67,1))*(MIN(a_m0+a_mstep*J65,a_mcap)-a_da)-IF(J65=a_churn_year,a_sticky*((cf_arr*(1+F$66)^J65)-((cf_arr*(1+F$66)^J65)*IF(J65>=a_churn_year,1-$B$67,1)))*(1-MIN(a_m0+a_mstep*J65,a_mcap)),0))-MAX(0,(((cf_arr*(1+F$66)^J65)*IF(J65>=a_churn_year,1-$B$67,1))*(MIN(a_m0+a_mstep*J65,a_mcap)-a_da)-IF(J65=a_churn_year,a_sticky*((cf_arr*(1+F$66)^J65)-((cf_arr*(1+F$66)^J65)*IF(J65>=a_churn_year,1-$B$67,1)))*(1-MIN(a_m0+a_mstep*J65,a_mcap)),0)))*a_tax+((cf_arr*(1+F$66)^J65)*IF(J65>=a_churn_year,1-$B$67,1))*a_da-((cf_arr*(1+F$66)^J65)*IF(J65>=a_churn_year,1-$B$67,1))*a_capex-a_wc*(((cf_arr*(1+F$66)^J65)*IF(J65>=a_churn_year,1-$B$67,1))-(cf_arr*(1+F$66)^I65*IF(I65>=a_churn_year,1-$B$67,1))) -> 211.84865 | K75: =(((cf_arr*(1+F$66)^K65)*IF(K65>=a_churn_year,1-$B$67,1))*(MIN(a_m0+a_mstep*K65,a_mcap)-a_da)-IF(K65=a_churn_year,a_sticky*((cf_arr*(1+F$66)^K65)-((cf_arr*(1+F$66)^K65)*IF(K65>=a_churn_year,1-$B$67,1)))*(1-MIN(a_m0+a_mstep*K65,a_mcap)),0))-MAX(0,(((cf_arr*(1+F$66)^K65)*IF(K65>=a_churn_year,1-$B$67,1))*(MIN(a_m0+a_mstep*K65,a_mcap)-a_da)-IF(K65=a_churn_year,a_sticky*((cf_arr*(1+F$66)^K65)-((cf_arr*(1+F$66)^K65)*IF(K65>=a_churn_year,1-$B$67,1)))*(1-MIN(a_m0+a_mstep*K65,a_mcap)),0)))*a_tax+((cf_arr*(1+F$66)^K65)*IF(K65>=a_churn_year,1-$B$67,1))*a_da-((cf_arr*(1+F$66)^K65)*IF(K65>=a_churn_year,1-$B$67,1))*a_capex-a_wc*(((cf_arr*(1+F$66)^K65)*IF(K65>=a_churn_year,1-$B$67,1))-(cf_arr*(1+F$66)^J65*IF(J65>=a_churn_year,1-$B$67,1))) -> 275.40324 | L75: =(((cf_arr*(1+F$66)^L65)*IF(L65>=a_churn_year,1-$B$67,1))*(MIN(a_m0+a_mstep*L65,a_mcap)-a_da)-IF(L65=a_churn_year,a_sticky*((cf_arr*(1+F$66)^L65)-((cf_arr*(1+F$66)^L65)*IF(L65>=a_churn_year,1-$B$67,1)))*(1-MIN(a_m0+a_mstep*L65,a_mcap)),0))-MAX(0,(((cf_arr*(1+F$66)^L65)*IF(L65>=a_churn_year,1-$B$67,1))*(MIN(a_m0+a_mstep*L65,a_mcap)-a_da)-IF(L65=a_churn_year,a_sticky*((cf_arr*(1+F$66)^L65)-((cf_arr*(1+F$66)^L65)*IF(L65>=a_churn_year,1-$B$67,1)))*(1-MIN(a_m0+a_mstep*L65,a_mcap)),0)))*a_tax+((cf_arr*(1+F$66)^L65)*IF(L65>=a_churn_year,1-$B$67,1))*a_da-((cf_arr*(1+F$66)^L65)*IF(L65>=a_churn_year,1-$B$67,1))*a_capex-a_wc*(((cf_arr*(1+F$66)^L65)*IF(L65>=a_churn_year,1-$B$67,1))-(cf_arr*(1+F$66)^K65*IF(K65>=a_churn_year,1-$B$67,1))) -> 358.02421 | M75: =(((cf_arr*(1+F$66)^M65)*IF(M65>=a_churn_year,1-$B$67,1))*(MIN(a_m0+a_mstep*M65,a_mcap)-a_da)-IF(M65=a_churn_year,a_sticky*((cf_arr*(1+F$66)^M65)-((cf_arr*(1+F$66)^M65)*IF(M65>=a_churn_year,1-$B$67,1)))*(1-MIN(a_m0+a_mstep*M65,a_mcap)),0))-MAX(0,(((cf_arr*(1+F$66)^M65)*IF(M65>=a_churn_year,1-$B$67,1))*(MIN(a_m0+a_mstep*M65,a_mcap)-a_da)-IF(M65=a_churn_year,a_sticky*((cf_arr*(1+F$66)^M65)-((cf_arr*(1+F$66)^M65)*IF(M65>=a_churn_year,1-$B$67,1)))*(1-MIN(a_m0+a_mstep*M65,a_mcap)),0)))*a_tax+((cf_arr*(1+F$66)^M65)*IF(M65>=a_churn_year,1-$B$67,1))*a_da-((cf_arr*(1+F$66)^M65)*IF(M65>=a_churn_year,1-$B$67,1))*a_capex-a_wc*(((cf_arr*(1+F$66)^M65)*IF(M65>=a_churn_year,1-$B$67,1))-(cf_arr*(1+F$66)^L65*IF(L65>=a_churn_year,1-$B$67,1))) -> 465.43148
A76: FCF: churn 0.0%, growth 40% | C76: =0 -> 0 | D76: =(((cf_arr*(1+G$66)^D65)*IF(D65>=a_churn_year,1-$B$67,1))*(MIN(a_m0+a_mstep*D65,a_mcap)-a_da)-IF(D65=a_churn_year,a_sticky*((cf_arr*(1+G$66)^D65)-((cf_arr*(1+G$66)^D65)*IF(D65>=a_churn_year,1-$B$67,1)))*(1-MIN(a_m0+a_mstep*D65,a_mcap)),0))-MAX(0,(((cf_arr*(1+G$66)^D65)*IF(D65>=a_churn_year,1-$B$67,1))*(MIN(a_m0+a_mstep*D65,a_mcap)-a_da)-IF(D65=a_churn_year,a_sticky*((cf_arr*(1+G$66)^D65)-((cf_arr*(1+G$66)^D65)*IF(D65>=a_churn_year,1-$B$67,1)))*(1-MIN(a_m0+a_mstep*D65,a_mcap)),0)))*a_tax+((cf_arr*(1+G$66)^D65)*IF(D65>=a_churn_year,1-$B$67,1))*a_da-((cf_arr*(1+G$66)^D65)*IF(D65>=a_churn_year,1-$B$67,1))*a_capex-a_wc*(((cf_arr*(1+G$66)^D65)*IF(D65>=a_churn_year,1-$B$67,1))-(cf_arr*(1+G$66)^C65*IF(C65>=a_churn_year,1-$B$67,1))) -> 0.22 | E76: =(((cf_arr*(1+G$66)^E65)*IF(E65>=a_churn_year,1-$B$67,1))*(MIN(a_m0+a_mstep*E65,a_mcap)-a_da)-IF(E65=a_churn_year,a_sticky*((cf_arr*(1+G$66)^E65)-((cf_arr*(1+G$66)^E65)*IF(E65>=a_churn_year,1-$B$67,1)))*(1-MIN(a_m0+a_mstep*E65,a_mcap)),0))-MAX(0,(((cf_arr*(1+G$66)^E65)*IF(E65>=a_churn_year,1-$B$67,1))*(MIN(a_m0+a_mstep*E65,a_mcap)-a_da)-IF(E65=a_churn_year,a_sticky*((cf_arr*(1+G$66)^E65)-((cf_arr*(1+G$66)^E65)*IF(E65>=a_churn_year,1-$B$67,1)))*(1-MIN(a_m0+a_mstep*E65,a_mcap)),0)))*a_tax+((cf_arr*(1+G$66)^E65)*IF(E65>=a_churn_year,1-$B$67,1))*a_da-((cf_arr*(1+G$66)^E65)*IF(E65>=a_churn_year,1-$B$67,1))*a_capex-a_wc*(((cf_arr*(1+G$66)^E65)*IF(E65>=a_churn_year,1-$B$67,1))-(cf_arr*(1+G$66)^D65*IF(D65>=a_churn_year,1-$B$67,1))) -> 16.478 | F76: =(((cf_arr*(1+G$66)^F65)*IF(F65>=a_churn_year,1-$B$67,1))*(MIN(a_m0+a_mstep*F65,a_mcap)-a_da)-IF(F65=a_churn_year,a_sticky*((cf_arr*(1+G$66)^F65)-((cf_arr*(1+G$66)^F65)*IF(F65>=a_churn_year,1-$B$67,1)))*(1-MIN(a_m0+a_mstep*F65,a_mcap)),0))-MAX(0,(((cf_arr*(1+G$66)^F65)*IF(F65>=a_churn_year,1-$B$67,1))*(MIN(a_m0+a_mstep*F65,a_mcap)-a_da)-IF(F65=a_churn_year,a_sticky*((cf_arr*(1+G$66)^F65)-((cf_arr*(1+G$66)^F65)*IF(F65>=a_churn_year,1-$B$67,1)))*(1-MIN(a_m0+a_mstep*F65,a_mcap)),0)))*a_tax+((cf_arr*(1+G$66)^F65)*IF(F65>=a_churn_year,1-$B$67,1))*a_da-((cf_arr*(1+G$66)^F65)*IF(F65>=a_churn_year,1-$B$67,1))*a_capex-a_wc*(((cf_arr*(1+G$66)^F65)*IF(F65>=a_churn_year,1-$B$67,1))-(cf_arr*(1+G$66)^E65*IF(E65>=a_churn_year,1-$B$67,1))) -> 45.7072 | G76: =(((cf_arr*(1+G$66)^G65)*IF(G65>=a_churn_year,1-$B$67,1))*(MIN(a_m0+a_mstep*G65,a_mcap)-a_da)-IF(G65=a_churn_year,a_sticky*((cf_arr*(1+G$66)^G65)-((cf_arr*(1+G$66)^G65)*IF(G65>=a_churn_year,1-$B$67,1)))*(1-MIN(a_m0+a_mstep*G65,a_mcap)),0))-MAX(0,(((cf_arr*(1+G$66)^G65)*IF(G65>=a_churn_year,1-$B$67,1))*(MIN(a_m0+a_mstep*G65,a_mcap)-a_da)-IF(G65=a_churn_year,a_sticky*((cf_arr*(1+G$66)^G65)-((cf_arr*(1+G$66)^G65)*IF(G65>=a_churn_year,1-$B$67,1)))*(1-MIN(a_m0+a_mstep*G65,a_mcap)),0)))*a_tax+((cf_arr*(1+G$66)^G65)*IF(G65>=a_churn_year,1-$B$67,1))*a_da-((cf_arr*(1+G$66)^G65)*IF(G65>=a_churn_year,1-$B$67,1))*a_capex-a_wc*(((cf_arr*(1+G$66)^G65)*IF(G65>=a_churn_year,1-$B$67,1))-(cf_arr*(1+G$66)^F65*IF(F65>=a_churn_year,1-$B$67,1))) -> 95.68328 | H76: =(((cf_arr*(1+G$66)^H65)*IF(H65>=a_churn_year,1-$B$67,1))*(MIN(a_m0+a_mstep*H65,a_mcap)-a_da)-IF(H65=a_churn_year,a_sticky*((cf_arr*(1+G$66)^H65)-((cf_arr*(1+G$66)^H65)*IF(H65>=a_churn_year,1-$B$67,1)))*(1-MIN(a_m0+a_mstep*H65,a_mcap)),0))-MAX(0,(((cf_arr*(1+G$66)^H65)*IF(H65>=a_churn_year,1-$B$67,1))*(MIN(a_m0+a_mstep*H65,a_mcap)-a_da)-IF(H65=a_churn_year,a_sticky*((cf_arr*(1+G$66)^H65)-((cf_arr*(1+G$66)^H65)*IF(H65>=a_churn_year,1-$B$67,1)))*(1-MIN(a_m0+a_mstep*H65,a_mcap)),0)))*a_tax+((cf_arr*(1+G$66)^H65)*IF(H65>=a_churn_year,1-$B$67,1))*a_da-((cf_arr*(1+G$66)^H65)*IF(H65>=a_churn_year,1-$B$67,1))*a_capex-a_wc*(((cf_arr*(1+G$66)^H65)*IF(H65>=a_churn_year,1-$B$67,1))-(cf_arr*(1+G$66)^G65*IF(G65>=a_churn_year,1-$B$67,1))) -> 178.32707 | I76: =(((cf_arr*(1+G$66)^I65)*IF(I65>=a_churn_year,1-$B$67,1))*(MIN(a_m0+a_mstep*I65,a_mcap)-a_da)-IF(I65=a_churn_year,a_sticky*((cf_arr*(1+G$66)^I65)-((cf_arr*(1+G$66)^I65)*IF(I65>=a_churn_year,1-$B$67,1)))*(1-MIN(a_m0+a_mstep*I65,a_mcap)),0))-MAX(0,(((cf_arr*(1+G$66)^I65)*IF(I65>=a_churn_year,1-$B$67,1))*(MIN(a_m0+a_mstep*I65,a_mcap)-a_da)-IF(I65=a_churn_year,a_sticky*((cf_arr*(1+G$66)^I65)-((cf_arr*(1+G$66)^I65)*IF(I65>=a_churn_year,1-$B$67,1)))*(1-MIN(a_m0+a_mstep*I65,a_mcap)),0)))*a_tax+((cf_arr*(1+G$66)^I65)*IF(I65>=a_churn_year,1-$B$67,1))*a_da-((cf_arr*(1+G$66)^I65)*IF(I65>=a_churn_year,1-$B$67,1))*a_capex-a_wc*(((cf_arr*(1+G$66)^I65)*IF(I65>=a_churn_year,1-$B$67,1))-(cf_arr*(1+G$66)^H65*IF(H65>=a_churn_year,1-$B$67,1))) -> 249.6579 | J76: =(((cf_arr*(1+G$66)^J65)*IF(J65>=a_churn_year,1-$B$67,1))*(MIN(a_m0+a_mstep*J65,a_mcap)-a_da)-IF(J65=a_churn_year,a_sticky*((cf_arr*(1+G$66)^J65)-((cf_arr*(1+G$66)^J65)*IF(J65>=a_churn_year,1-$B$67,1)))*(1-MIN(a_m0+a_mstep*J65,a_mcap)),0))-MAX(0,(((cf_arr*(1+G$66)^J65)*IF(J65>=a_churn_year,1-$B$67,1))*(MIN(a_m0+a_mstep*J65,a_mcap)-a_da)-IF(J65=a_churn_year,a_sticky*((cf_arr*(1+G$66)^J65)-((cf_arr*(1+G$66)^J65)*IF(J65>=a_churn_year,1-$B$67,1)))*(1-MIN(a_m0+a_mstep*J65,a_mcap)),0)))*a_tax+((cf_arr*(1+G$66)^J65)*IF(J65>=a_churn_year,1-$B$67,1))*a_da-((cf_arr*(1+G$66)^J65)*IF(J65>=a_churn_year,1-$B$67,1))*a_capex-a_wc*(((cf_arr*(1+G$66)^J65)*IF(J65>=a_churn_year,1-$B$67,1))-(cf_arr*(1+G$66)^I65*IF(I65>=a_churn_year,1-$B$67,1))) -> 349.52106 | K76: =(((cf_arr*(1+G$66)^K65)*IF(K65>=a_churn_year,1-$B$67,1))*(MIN(a_m0+a_mstep*K65,a_mcap)-a_da)-IF(K65=a_churn_year,a_sticky*((cf_arr*(1+G$66)^K65)-((cf_arr*(1+G$66)^K65)*IF(K65>=a_churn_year,1-$B$67,1)))*(1-MIN(a_m0+a_mstep*K65,a_mcap)),0))-MAX(0,(((cf_arr*(1+G$66)^K65)*IF(K65>=a_churn_year,1-$B$67,1))*(MIN(a_m0+a_mstep*K65,a_mcap)-a_da)-IF(K65=a_churn_year,a_sticky*((cf_arr*(1+G$66)^K65)-((cf_arr*(1+G$66)^K65)*IF(K65>=a_churn_year,1-$B$67,1)))*(1-MIN(a_m0+a_mstep*K65,a_mcap)),0)))*a_tax+((cf_arr*(1+G$66)^K65)*IF(K65>=a_churn_year,1-$B$67,1))*a_da-((cf_arr*(1+G$66)^K65)*IF(K65>=a_churn_year,1-$B$67,1))*a_capex-a_wc*(((cf_arr*(1+G$66)^K65)*IF(K65>=a_churn_year,1-$B$67,1))-(cf_arr*(1+G$66)^J65*IF(J65>=a_churn_year,1-$B$67,1))) -> 489.32949 | L76: =(((cf_arr*(1+G$66)^L65)*IF(L65>=a_churn_year,1-$B$67,1))*(MIN(a_m0+a_mstep*L65,a_mcap)-a_da)-IF(L65=a_churn_year,a_sticky*((cf_arr*(1+G$66)^L65)-((cf_arr*(1+G$66)^L65)*IF(L65>=a_churn_year,1-$B$67,1)))*(1-MIN(a_m0+a_mstep*L65,a_mcap)),0))-MAX(0,(((cf_arr*(1+G$66)^L65)*IF(L65>=a_churn_year,1-$B$67,1))*(MIN(a_m0+a_mstep*L65,a_mcap)-a_da)-IF(L65=a_churn_year,a_sticky*((cf_arr*(1+G$66)^L65)-((cf_arr*(1+G$66)^L65)*IF(L65>=a_churn_year,1-$B$67,1)))*(1-MIN(a_m0+a_mstep*L65,a_mcap)),0)))*a_tax+((cf_arr*(1+G$66)^L65)*IF(L65>=a_churn_year,1-$B$67,1))*a_da-((cf_arr*(1+G$66)^L65)*IF(L65>=a_churn_year,1-$B$67,1))*a_capex-a_wc*(((cf_arr*(1+G$66)^L65)*IF(L65>=a_churn_year,1-$B$67,1))-(cf_arr*(1+G$66)^K65*IF(K65>=a_churn_year,1-$B$67,1))) -> 685.06128 | M76: =(((cf_arr*(1+G$66)^M65)*IF(M65>=a_churn_year,1-$B$67,1))*(MIN(a_m0+a_mstep*M65,a_mcap)-a_da)-IF(M65=a_churn_year,a_sticky*((cf_arr*(1+G$66)^M65)-((cf_arr*(1+G$66)^M65)*IF(M65>=a_churn_year,1-$B$67,1)))*(1-MIN(a_m0+a_mstep*M65,a_mcap)),0))-MAX(0,(((cf_arr*(1+G$66)^M65)*IF(M65>=a_churn_year,1-$B$67,1))*(MIN(a_m0+a_mstep*M65,a_mcap)-a_da)-IF(M65=a_churn_year,a_sticky*((cf_arr*(1+G$66)^M65)-((cf_arr*(1+G$66)^M65)*IF(M65>=a_churn_year,1-$B$67,1)))*(1-MIN(a_m0+a_mstep*M65,a_mcap)),0)))*a_tax+((cf_arr*(1+G$66)^M65)*IF(M65>=a_churn_year,1-$B$67,1))*a_da-((cf_arr*(1+G$66)^M65)*IF(M65>=a_churn_year,1-$B$67,1))*a_capex-a_wc*(((cf_arr*(1+G$66)^M65)*IF(M65>=a_churn_year,1-$B$67,1))-(cf_arr*(1+G$66)^L65*IF(L65>=a_churn_year,1-$B$67,1))) -> 959.08579
A77: FCF: churn 30.0%, growth 10% | C77: =0 -> 0 | D77: =(((cf_arr*(1+D$66)^D65)*IF(D65>=a_churn_year,1-$B$68,1))*(MIN(a_m0+a_mstep*D65,a_mcap)-a_da)-IF(D65=a_churn_year,a_sticky*((cf_arr*(1+D$66)^D65)-((cf_arr*(1+D$66)^D65)*IF(D65>=a_churn_year,1-$B$68,1)))*(1-MIN(a_m0+a_mstep*D65,a_mcap)),0))-MAX(0,(((cf_arr*(1+D$66)^D65)*IF(D65>=a_churn_year,1-$B$68,1))*(MIN(a_m0+a_mstep*D65,a_mcap)-a_da)-IF(D65=a_churn_year,a_sticky*((cf_arr*(1+D$66)^D65)-((cf_arr*(1+D$66)^D65)*IF(D65>=a_churn_year,1-$B$68,1)))*(1-MIN(a_m0+a_mstep*D65,a_mcap)),0)))*a_tax+((cf_arr*(1+D$66)^D65)*IF(D65>=a_churn_year,1-$B$68,1))*a_da-((cf_arr*(1+D$66)^D65)*IF(D65>=a_churn_year,1-$B$68,1))*a_capex-a_wc*(((cf_arr*(1+D$66)^D65)*IF(D65>=a_churn_year,1-$B$68,1))-(cf_arr*(1+D$66)^C65*IF(C65>=a_churn_year,1-$B$68,1))) -> -28.567 | E77: =(((cf_arr*(1+D$66)^E65)*IF(E65>=a_churn_year,1-$B$68,1))*(MIN(a_m0+a_mstep*E65,a_mcap)-a_da)-IF(E65=a_churn_year,a_sticky*((cf_arr*(1+D$66)^E65)-((cf_arr*(1+D$66)^E65)*IF(E65>=a_churn_year,1-$B$68,1)))*(1-MIN(a_m0+a_mstep*E65,a_mcap)),0))-MAX(0,(((cf_arr*(1+D$66)^E65)*IF(E65>=a_churn_year,1-$B$68,1))*(MIN(a_m0+a_mstep*E65,a_mcap)-a_da)-IF(E65=a_churn_year,a_sticky*((cf_arr*(1+D$66)^E65)-((cf_arr*(1+D$66)^E65)*IF(E65>=a_churn_year,1-$B$68,1)))*(1-MIN(a_m0+a_mstep*E65,a_mcap)),0)))*a_tax+((cf_arr*(1+D$66)^E65)*IF(E65>=a_churn_year,1-$B$68,1))*a_da-((cf_arr*(1+D$66)^E65)*IF(E65>=a_churn_year,1-$B$68,1))*a_capex-a_wc*(((cf_arr*(1+D$66)^E65)*IF(E65>=a_churn_year,1-$B$68,1))-(cf_arr*(1+D$66)^D65*IF(D65>=a_churn_year,1-$B$68,1))) -> 8.93585 | F77: =(((cf_arr*(1+D$66)^F65)*IF(F65>=a_churn_year,1-$B$68,1))*(MIN(a_m0+a_mstep*F65,a_mcap)-a_da)-IF(F65=a_churn_year,a_sticky*((cf_arr*(1+D$66)^F65)-((cf_arr*(1+D$66)^F65)*IF(F65>=a_churn_year,1-$B$68,1)))*(1-MIN(a_m0+a_mstep*F65,a_mcap)),0))-MAX(0,(((cf_arr*(1+D$66)^F65)*IF(F65>=a_churn_year,1-$B$68,1))*(MIN(a_m0+a_mstep*F65,a_mcap)-a_da)-IF(F65=a_churn_year,a_sticky*((cf_arr*(1+D$66)^F65)-((cf_arr*(1+D$66)^F65)*IF(F65>=a_churn_year,1-$B$68,1)))*(1-MIN(a_m0+a_mstep*F65,a_mcap)),0)))*a_tax+((cf_arr*(1+D$66)^F65)*IF(F65>=a_churn_year,1-$B$68,1))*a_da-((cf_arr*(1+D$66)^F65)*IF(F65>=a_churn_year,1-$B$68,1))*a_capex-a_wc*(((cf_arr*(1+D$66)^F65)*IF(F65>=a_churn_year,1-$B$68,1))-(cf_arr*(1+D$66)^E65*IF(E65>=a_churn_year,1-$B$68,1))) -> 17.51596 | G77: =(((cf_arr*(1+D$66)^G65)*IF(G65>=a_churn_year,1-$B$68,1))*(MIN(a_m0+a_mstep*G65,a_mcap)-a_da)-IF(G65=a_churn_year,a_sticky*((cf_arr*(1+D$66)^G65)-((cf_arr*(1+D$66)^G65)*IF(G65>=a_churn_year,1-$B$68,1)))*(1-MIN(a_m0+a_mstep*G65,a_mcap)),0))-MAX(0,(((cf_arr*(1+D$66)^G65)*IF(G65>=a_churn_year,1-$B$68,1))*(MIN(a_m0+a_mstep*G65,a_mcap)-a_da)-IF(G65=a_churn_year,a_sticky*((cf_arr*(1+D$66)^G65)-((cf_arr*(1+D$66)^G65)*IF(G65>=a_churn_year,1-$B$68,1)))*(1-MIN(a_m0+a_mstep*G65,a_mcap)),0)))*a_tax+((cf_arr*(1+D$66)^G65)*IF(G65>=a_churn_year,1-$B$68,1))*a_da-((cf_arr*(1+D$66)^G65)*IF(G65>=a_churn_year,1-$B$68,1))*a_capex-a_wc*(((cf_arr*(1+D$66)^G65)*IF(G65>=a_churn_year,1-$B$68,1))-(cf_arr*(1+D$66)^F65*IF(F65>=a_churn_year,1-$B$68,1))) -> 27.722734 | H77: =(((cf_arr*(1+D$66)^H65)*IF(H65>=a_churn_year,1-$B$68,1))*(MIN(a_m0+a_mstep*H65,a_mcap)-a_da)-IF(H65=a_churn_year,a_sticky*((cf_arr*(1+D$66)^H65)-((cf_arr*(1+D$66)^H65)*IF(H65>=a_churn_year,1-$B$68,1)))*(1-MIN(a_m0+a_mstep*H65,a_mcap)),0))-MAX(0,(((cf_arr*(1+D$66)^H65)*IF(H65>=a_churn_year,1-$B$68,1))*(MIN(a_m0+a_mstep*H65,a_mcap)-a_da)-IF(H65=a_churn_year,a_sticky*((cf_arr*(1+D$66)^H65)-((cf_arr*(1+D$66)^H65)*IF(H65>=a_churn_year,1-$B$68,1)))*(1-MIN(a_m0+a_mstep*H65,a_mcap)),0)))*a_tax+((cf_arr*(1+D$66)^H65)*IF(H65>=a_churn_year,1-$B$68,1))*a_da-((cf_arr*(1+D$66)^H65)*IF(H65>=a_churn_year,1-$B$68,1))*a_capex-a_wc*(((cf_arr*(1+D$66)^H65)*IF(H65>=a_churn_year,1-$B$68,1))-(cf_arr*(1+D$66)^G65*IF(G65>=a_churn_year,1-$B$68,1))) -> 39.795702 | I77: =(((cf_arr*(1+D$66)^I65)*IF(I65>=a_churn_year,1-$B$68,1))*(MIN(a_m0+a_mstep*I65,a_mcap)-a_da)-IF(I65=a_churn_year,a_sticky*((cf_arr*(1+D$66)^I65)-((cf_arr*(1+D$66)^I65)*IF(I65>=a_churn_year,1-$B$68,1)))*(1-MIN(a_m0+a_mstep*I65,a_mcap)),0))-MAX(0,(((cf_arr*(1+D$66)^I65)*IF(I65>=a_churn_year,1-$B$68,1))*(MIN(a_m0+a_mstep*I65,a_mcap)-a_da)-IF(I65=a_churn_year,a_sticky*((cf_arr*(1+D$66)^I65)-((cf_arr*(1+D$66)^I65)*IF(I65>=a_churn_year,1-$B$68,1)))*(1-MIN(a_m0+a_mstep*I65,a_mcap)),0)))*a_tax+((cf_arr*(1+D$66)^I65)*IF(I65>=a_churn_year,1-$B$68,1))*a_da-((cf_arr*(1+D$66)^I65)*IF(I65>=a_churn_year,1-$B$68,1))*a_capex-a_wc*(((cf_arr*(1+D$66)^I65)*IF(I65>=a_churn_year,1-$B$68,1))-(cf_arr*(1+D$66)^H65*IF(H65>=a_churn_year,1-$B$68,1))) -> 43.775272 | J77: =(((cf_arr*(1+D$66)^J65)*IF(J65>=a_churn_year,1-$B$68,1))*(MIN(a_m0+a_mstep*J65,a_mcap)-a_da)-IF(J65=a_churn_year,a_sticky*((cf_arr*(1+D$66)^J65)-((cf_arr*(1+D$66)^J65)*IF(J65>=a_churn_year,1-$B$68,1)))*(1-MIN(a_m0+a_mstep*J65,a_mcap)),0))-MAX(0,(((cf_arr*(1+D$66)^J65)*IF(J65>=a_churn_year,1-$B$68,1))*(MIN(a_m0+a_mstep*J65,a_mcap)-a_da)-IF(J65=a_churn_year,a_sticky*((cf_arr*(1+D$66)^J65)-((cf_arr*(1+D$66)^J65)*IF(J65>=a_churn_year,1-$B$68,1)))*(1-MIN(a_m0+a_mstep*J65,a_mcap)),0)))*a_tax+((cf_arr*(1+D$66)^J65)*IF(J65>=a_churn_year,1-$B$68,1))*a_da-((cf_arr*(1+D$66)^J65)*IF(J65>=a_churn_year,1-$B$68,1))*a_capex-a_wc*(((cf_arr*(1+D$66)^J65)*IF(J65>=a_churn_year,1-$B$68,1))-(cf_arr*(1+D$66)^I65*IF(I65>=a_churn_year,1-$B$68,1))) -> 48.1528 | K77: =(((cf_arr*(1+D$66)^K65)*IF(K65>=a_churn_year,1-$B$68,1))*(MIN(a_m0+a_mstep*K65,a_mcap)-a_da)-IF(K65=a_churn_year,a_sticky*((cf_arr*(1+D$66)^K65)-((cf_arr*(1+D$66)^K65)*IF(K65>=a_churn_year,1-$B$68,1)))*(1-MIN(a_m0+a_mstep*K65,a_mcap)),0))-MAX(0,(((cf_arr*(1+D$66)^K65)*IF(K65>=a_churn_year,1-$B$68,1))*(MIN(a_m0+a_mstep*K65,a_mcap)-a_da)-IF(K65=a_churn_year,a_sticky*((cf_arr*(1+D$66)^K65)-((cf_arr*(1+D$66)^K65)*IF(K65>=a_churn_year,1-$B$68,1)))*(1-MIN(a_m0+a_mstep*K65,a_mcap)),0)))*a_tax+((cf_arr*(1+D$66)^K65)*IF(K65>=a_churn_year,1-$B$68,1))*a_da-((cf_arr*(1+D$66)^K65)*IF(K65>=a_churn_year,1-$B$68,1))*a_capex-a_wc*(((cf_arr*(1+D$66)^K65)*IF(K65>=a_churn_year,1-$B$68,1))-(cf_arr*(1+D$66)^J65*IF(J65>=a_churn_year,1-$B$68,1))) -> 52.968079 | L77: =(((cf_arr*(1+D$66)^L65)*IF(L65>=a_churn_year,1-$B$68,1))*(MIN(a_m0+a_mstep*L65,a_mcap)-a_da)-IF(L65=a_churn_year,a_sticky*((cf_arr*(1+D$66)^L65)-((cf_arr*(1+D$66)^L65)*IF(L65>=a_churn_year,1-$B$68,1)))*(1-MIN(a_m0+a_mstep*L65,a_mcap)),0))-MAX(0,(((cf_arr*(1+D$66)^L65)*IF(L65>=a_churn_year,1-$B$68,1))*(MIN(a_m0+a_mstep*L65,a_mcap)-a_da)-IF(L65=a_churn_year,a_sticky*((cf_arr*(1+D$66)^L65)-((cf_arr*(1+D$66)^L65)*IF(L65>=a_churn_year,1-$B$68,1)))*(1-MIN(a_m0+a_mstep*L65,a_mcap)),0)))*a_tax+((cf_arr*(1+D$66)^L65)*IF(L65>=a_churn_year,1-$B$68,1))*a_da-((cf_arr*(1+D$66)^L65)*IF(L65>=a_churn_year,1-$B$68,1))*a_capex-a_wc*(((cf_arr*(1+D$66)^L65)*IF(L65>=a_churn_year,1-$B$68,1))-(cf_arr*(1+D$66)^K65*IF(K65>=a_churn_year,1-$B$68,1))) -> 58.264887 | M77: =(((cf_arr*(1+D$66)^M65)*IF(M65>=a_churn_year,1-$B$68,1))*(MIN(a_m0+a_mstep*M65,a_mcap)-a_da)-IF(M65=a_churn_year,a_sticky*((cf_arr*(1+D$66)^M65)-((cf_arr*(1+D$66)^M65)*IF(M65>=a_churn_year,1-$B$68,1)))*(1-MIN(a_m0+a_mstep*M65,a_mcap)),0))-MAX(0,(((cf_arr*(1+D$66)^M65)*IF(M65>=a_churn_year,1-$B$68,1))*(MIN(a_m0+a_mstep*M65,a_mcap)-a_da)-IF(M65=a_churn_year,a_sticky*((cf_arr*(1+D$66)^M65)-((cf_arr*(1+D$66)^M65)*IF(M65>=a_churn_year,1-$B$68,1)))*(1-MIN(a_m0+a_mstep*M65,a_mcap)),0)))*a_tax+((cf_arr*(1+D$66)^M65)*IF(M65>=a_churn_year,1-$B$68,1))*a_da-((cf_arr*(1+D$66)^M65)*IF(M65>=a_churn_year,1-$B$68,1))*a_capex-a_wc*(((cf_arr*(1+D$66)^M65)*IF(M65>=a_churn_year,1-$B$68,1))-(cf_arr*(1+D$66)^L65*IF(L65>=a_churn_year,1-$B$68,1))) -> 64.091376
A78: FCF: churn 30.0%, growth 20% | C78: =0 -> 0 | D78: =(((cf_arr*(1+E$66)^D65)*IF(D65>=a_churn_year,1-$B$68,1))*(MIN(a_m0+a_mstep*D65,a_mcap)-a_da)-IF(D65=a_churn_year,a_sticky*((cf_arr*(1+E$66)^D65)-((cf_arr*(1+E$66)^D65)*IF(D65>=a_churn_year,1-$B$68,1)))*(1-MIN(a_m0+a_mstep*D65,a_mcap)),0))-MAX(0,(((cf_arr*(1+E$66)^D65)*IF(D65>=a_churn_year,1-$B$68,1))*(MIN(a_m0+a_mstep*D65,a_mcap)-a_da)-IF(D65=a_churn_year,a_sticky*((cf_arr*(1+E$66)^D65)-((cf_arr*(1+E$66)^D65)*IF(D65>=a_churn_year,1-$B$68,1)))*(1-MIN(a_m0+a_mstep*D65,a_mcap)),0)))*a_tax+((cf_arr*(1+E$66)^D65)*IF(D65>=a_churn_year,1-$B$68,1))*a_da-((cf_arr*(1+E$66)^D65)*IF(D65>=a_churn_year,1-$B$68,1))*a_capex-a_wc*(((cf_arr*(1+E$66)^D65)*IF(D65>=a_churn_year,1-$B$68,1))-(cf_arr*(1+E$66)^C65*IF(C65>=a_churn_year,1-$B$68,1))) -> -32.164 | E78: =(((cf_arr*(1+E$66)^E65)*IF(E65>=a_churn_year,1-$B$68,1))*(MIN(a_m0+a_mstep*E65,a_mcap)-a_da)-IF(E65=a_churn_year,a_sticky*((cf_arr*(1+E$66)^E65)-((cf_arr*(1+E$66)^E65)*IF(E65>=a_churn_year,1-$B$68,1)))*(1-MIN(a_m0+a_mstep*E65,a_mcap)),0))-MAX(0,(((cf_arr*(1+E$66)^E65)*IF(E65>=a_churn_year,1-$B$68,1))*(MIN(a_m0+a_mstep*E65,a_mcap)-a_da)-IF(E65=a_churn_year,a_sticky*((cf_arr*(1+E$66)^E65)-((cf_arr*(1+E$66)^E65)*IF(E65>=a_churn_year,1-$B$68,1)))*(1-MIN(a_m0+a_mstep*E65,a_mcap)),0)))*a_tax+((cf_arr*(1+E$66)^E65)*IF(E65>=a_churn_year,1-$B$68,1))*a_da-((cf_arr*(1+E$66)^E65)*IF(E65>=a_churn_year,1-$B$68,1))*a_capex-a_wc*(((cf_arr*(1+E$66)^E65)*IF(E65>=a_churn_year,1-$B$68,1))-(cf_arr*(1+E$66)^D65*IF(D65>=a_churn_year,1-$B$68,1))) -> 9.7944 | F78: =(((cf_arr*(1+E$66)^F65)*IF(F65>=a_churn_year,1-$B$68,1))*(MIN(a_m0+a_mstep*F65,a_mcap)-a_da)-IF(F65=a_churn_year,a_sticky*((cf_arr*(1+E$66)^F65)-((cf_arr*(1+E$66)^F65)*IF(F65>=a_churn_year,1-$B$68,1)))*(1-MIN(a_m0+a_mstep*F65,a_mcap)),0))-MAX(0,(((cf_arr*(1+E$66)^F65)*IF(F65>=a_churn_year,1-$B$68,1))*(MIN(a_m0+a_mstep*F65,a_mcap)-a_da)-IF(F65=a_churn_year,a_sticky*((cf_arr*(1+E$66)^F65)-((cf_arr*(1+E$66)^F65)*IF(F65>=a_churn_year,1-$B$68,1)))*(1-MIN(a_m0+a_mstep*F65,a_mcap)),0)))*a_tax+((cf_arr*(1+E$66)^F65)*IF(F65>=a_churn_year,1-$B$68,1))*a_da-((cf_arr*(1+E$66)^F65)*IF(F65>=a_churn_year,1-$B$68,1))*a_capex-a_wc*(((cf_arr*(1+E$66)^F65)*IF(F65>=a_churn_year,1-$B$68,1))-(cf_arr*(1+E$66)^E65*IF(E65>=a_churn_year,1-$B$68,1))) -> 21.73248 | G78: =(((cf_arr*(1+E$66)^G65)*IF(G65>=a_churn_year,1-$B$68,1))*(MIN(a_m0+a_mstep*G65,a_mcap)-a_da)-IF(G65=a_churn_year,a_sticky*((cf_arr*(1+E$66)^G65)-((cf_arr*(1+E$66)^G65)*IF(G65>=a_churn_year,1-$B$68,1)))*(1-MIN(a_m0+a_mstep*G65,a_mcap)),0))-MAX(0,(((cf_arr*(1+E$66)^G65)*IF(G65>=a_churn_year,1-$B$68,1))*(MIN(a_m0+a_mstep*G65,a_mcap)-a_da)-IF(G65=a_churn_year,a_sticky*((cf_arr*(1+E$66)^G65)-((cf_arr*(1+E$66)^G65)*IF(G65>=a_churn_year,1-$B$68,1)))*(1-MIN(a_m0+a_mstep*G65,a_mcap)),0)))*a_tax+((cf_arr*(1+E$66)^G65)*IF(G65>=a_churn_year,1-$B$68,1))*a_da-((cf_arr*(1+E$66)^G65)*IF(G65>=a_churn_year,1-$B$68,1))*a_capex-a_wc*(((cf_arr*(1+E$66)^G65)*IF(G65>=a_churn_year,1-$B$68,1))-(cf_arr*(1+E$66)^F65*IF(F65>=a_churn_year,1-$B$68,1))) -> 38.054016 | H78: =(((cf_arr*(1+E$66)^H65)*IF(H65>=a_churn_year,1-$B$68,1))*(MIN(a_m0+a_mstep*H65,a_mcap)-a_da)-IF(H65=a_churn_year,a_sticky*((cf_arr*(1+E$66)^H65)-((cf_arr*(1+E$66)^H65)*IF(H65>=a_churn_year,1-$B$68,1)))*(1-MIN(a_m0+a_mstep*H65,a_mcap)),0))-MAX(0,(((cf_arr*(1+E$66)^H65)*IF(H65>=a_churn_year,1-$B$68,1))*(MIN(a_m0+a_mstep*H65,a_mcap)-a_da)-IF(H65=a_churn_year,a_sticky*((cf_arr*(1+E$66)^H65)-((cf_arr*(1+E$66)^H65)*IF(H65>=a_churn_year,1-$B$68,1)))*(1-MIN(a_m0+a_mstep*H65,a_mcap)),0)))*a_tax+((cf_arr*(1+E$66)^H65)*IF(H65>=a_churn_year,1-$B$68,1))*a_da-((cf_arr*(1+E$66)^H65)*IF(H65>=a_churn_year,1-$B$68,1))*a_capex-a_wc*(((cf_arr*(1+E$66)^H65)*IF(H65>=a_churn_year,1-$B$68,1))-(cf_arr*(1+E$66)^G65*IF(G65>=a_churn_year,1-$B$68,1))) -> 60.034867 | I78: =(((cf_arr*(1+E$66)^I65)*IF(I65>=a_churn_year,1-$B$68,1))*(MIN(a_m0+a_mstep*I65,a_mcap)-a_da)-IF(I65=a_churn_year,a_sticky*((cf_arr*(1+E$66)^I65)-((cf_arr*(1+E$66)^I65)*IF(I65>=a_churn_year,1-$B$68,1)))*(1-MIN(a_m0+a_mstep*I65,a_mcap)),0))-MAX(0,(((cf_arr*(1+E$66)^I65)*IF(I65>=a_churn_year,1-$B$68,1))*(MIN(a_m0+a_mstep*I65,a_mcap)-a_da)-IF(I65=a_churn_year,a_sticky*((cf_arr*(1+E$66)^I65)-((cf_arr*(1+E$66)^I65)*IF(I65>=a_churn_year,1-$B$68,1)))*(1-MIN(a_m0+a_mstep*I65,a_mcap)),0)))*a_tax+((cf_arr*(1+E$66)^I65)*IF(I65>=a_churn_year,1-$B$68,1))*a_da-((cf_arr*(1+E$66)^I65)*IF(I65>=a_churn_year,1-$B$68,1))*a_capex-a_wc*(((cf_arr*(1+E$66)^I65)*IF(I65>=a_churn_year,1-$B$68,1))-(cf_arr*(1+E$66)^H65*IF(H65>=a_churn_year,1-$B$68,1))) -> 72.041841 | J78: =(((cf_arr*(1+E$66)^J65)*IF(J65>=a_churn_year,1-$B$68,1))*(MIN(a_m0+a_mstep*J65,a_mcap)-a_da)-IF(J65=a_churn_year,a_sticky*((cf_arr*(1+E$66)^J65)-((cf_arr*(1+E$66)^J65)*IF(J65>=a_churn_year,1-$B$68,1)))*(1-MIN(a_m0+a_mstep*J65,a_mcap)),0))-MAX(0,(((cf_arr*(1+E$66)^J65)*IF(J65>=a_churn_year,1-$B$68,1))*(MIN(a_m0+a_mstep*J65,a_mcap)-a_da)-IF(J65=a_churn_year,a_sticky*((cf_arr*(1+E$66)^J65)-((cf_arr*(1+E$66)^J65)*IF(J65>=a_churn_year,1-$B$68,1)))*(1-MIN(a_m0+a_mstep*J65,a_mcap)),0)))*a_tax+((cf_arr*(1+E$66)^J65)*IF(J65>=a_churn_year,1-$B$68,1))*a_da-((cf_arr*(1+E$66)^J65)*IF(J65>=a_churn_year,1-$B$68,1))*a_capex-a_wc*(((cf_arr*(1+E$66)^J65)*IF(J65>=a_churn_year,1-$B$68,1))-(cf_arr*(1+E$66)^I65*IF(I65>=a_churn_year,1-$B$68,1))) -> 86.450209 | K78: =(((cf_arr*(1+E$66)^K65)*IF(K65>=a_churn_year,1-$B$68,1))*(MIN(a_m0+a_mstep*K65,a_mcap)-a_da)-IF(K65=a_churn_year,a_sticky*((cf_arr*(1+E$66)^K65)-((cf_arr*(1+E$66)^K65)*IF(K65>=a_churn_year,1-$B$68,1)))*(1-MIN(a_m0+a_mstep*K65,a_mcap)),0))-MAX(0,(((cf_arr*(1+E$66)^K65)*IF(K65>=a_churn_year,1-$B$68,1))*(MIN(a_m0+a_mstep*K65,a_mcap)-a_da)-IF(K65=a_churn_year,a_sticky*((cf_arr*(1+E$66)^K65)-((cf_arr*(1+E$66)^K65)*IF(K65>=a_churn_year,1-$B$68,1)))*(1-MIN(a_m0+a_mstep*K65,a_mcap)),0)))*a_tax+((cf_arr*(1+E$66)^K65)*IF(K65>=a_churn_year,1-$B$68,1))*a_da-((cf_arr*(1+E$66)^K65)*IF(K65>=a_churn_year,1-$B$68,1))*a_capex-a_wc*(((cf_arr*(1+E$66)^K65)*IF(K65>=a_churn_year,1-$B$68,1))-(cf_arr*(1+E$66)^J65*IF(J65>=a_churn_year,1-$B$68,1))) -> 103.74025 | L78: =(((cf_arr*(1+E$66)^L65)*IF(L65>=a_churn_year,1-$B$68,1))*(MIN(a_m0+a_mstep*L65,a_mcap)-a_da)-IF(L65=a_churn_year,a_sticky*((cf_arr*(1+E$66)^L65)-((cf_arr*(1+E$66)^L65)*IF(L65>=a_churn_year,1-$B$68,1)))*(1-MIN(a_m0+a_mstep*L65,a_mcap)),0))-MAX(0,(((cf_arr*(1+E$66)^L65)*IF(L65>=a_churn_year,1-$B$68,1))*(MIN(a_m0+a_mstep*L65,a_mcap)-a_da)-IF(L65=a_churn_year,a_sticky*((cf_arr*(1+E$66)^L65)-((cf_arr*(1+E$66)^L65)*IF(L65>=a_churn_year,1-$B$68,1)))*(1-MIN(a_m0+a_mstep*L65,a_mcap)),0)))*a_tax+((cf_arr*(1+E$66)^L65)*IF(L65>=a_churn_year,1-$B$68,1))*a_da-((cf_arr*(1+E$66)^L65)*IF(L65>=a_churn_year,1-$B$68,1))*a_capex-a_wc*(((cf_arr*(1+E$66)^L65)*IF(L65>=a_churn_year,1-$B$68,1))-(cf_arr*(1+E$66)^K65*IF(K65>=a_churn_year,1-$B$68,1))) -> 124.4883 | M78: =(((cf_arr*(1+E$66)^M65)*IF(M65>=a_churn_year,1-$B$68,1))*(MIN(a_m0+a_mstep*M65,a_mcap)-a_da)-IF(M65=a_churn_year,a_sticky*((cf_arr*(1+E$66)^M65)-((cf_arr*(1+E$66)^M65)*IF(M65>=a_churn_year,1-$B$68,1)))*(1-MIN(a_m0+a_mstep*M65,a_mcap)),0))-MAX(0,(((cf_arr*(1+E$66)^M65)*IF(M65>=a_churn_year,1-$B$68,1))*(MIN(a_m0+a_mstep*M65,a_mcap)-a_da)-IF(M65=a_churn_year,a_sticky*((cf_arr*(1+E$66)^M65)-((cf_arr*(1+E$66)^M65)*IF(M65>=a_churn_year,1-$B$68,1)))*(1-MIN(a_m0+a_mstep*M65,a_mcap)),0)))*a_tax+((cf_arr*(1+E$66)^M65)*IF(M65>=a_churn_year,1-$B$68,1))*a_da-((cf_arr*(1+E$66)^M65)*IF(M65>=a_churn_year,1-$B$68,1))*a_capex-a_wc*(((cf_arr*(1+E$66)^M65)*IF(M65>=a_churn_year,1-$B$68,1))-(cf_arr*(1+E$66)^L65*IF(L65>=a_churn_year,1-$B$68,1))) -> 149.38596
A79: FCF: churn 30.0%, growth 30% | C79: =0 -> 0 | D79: =(((cf_arr*(1+F$66)^D65)*IF(D65>=a_churn_year,1-$B$68,1))*(MIN(a_m0+a_mstep*D65,a_mcap)-a_da)-IF(D65=a_churn_year,a_sticky*((cf_arr*(1+F$66)^D65)-((cf_arr*(1+F$66)^D65)*IF(D65>=a_churn_year,1-$B$68,1)))*(1-MIN(a_m0+a_mstep*D65,a_mcap)),0))-MAX(0,(((cf_arr*(1+F$66)^D65)*IF(D65>=a_churn_year,1-$B$68,1))*(MIN(a_m0+a_mstep*D65,a_mcap)-a_da)-IF(D65=a_churn_year,a_sticky*((cf_arr*(1+F$66)^D65)-((cf_arr*(1+F$66)^D65)*IF(D65>=a_churn_year,1-$B$68,1)))*(1-MIN(a_m0+a_mstep*D65,a_mcap)),0)))*a_tax+((cf_arr*(1+F$66)^D65)*IF(D65>=a_churn_year,1-$B$68,1))*a_da-((cf_arr*(1+F$66)^D65)*IF(D65>=a_churn_year,1-$B$68,1))*a_capex-a_wc*(((cf_arr*(1+F$66)^D65)*IF(D65>=a_churn_year,1-$B$68,1))-(cf_arr*(1+F$66)^C65*IF(C65>=a_churn_year,1-$B$68,1))) -> -35.761 | E79: =(((cf_arr*(1+F$66)^E65)*IF(E65>=a_churn_year,1-$B$68,1))*(MIN(a_m0+a_mstep*E65,a_mcap)-a_da)-IF(E65=a_churn_year,a_sticky*((cf_arr*(1+F$66)^E65)-((cf_arr*(1+F$66)^E65)*IF(E65>=a_churn_year,1-$B$68,1)))*(1-MIN(a_m0+a_mstep*E65,a_mcap)),0))-MAX(0,(((cf_arr*(1+F$66)^E65)*IF(E65>=a_churn_year,1-$B$68,1))*(MIN(a_m0+a_mstep*E65,a_mcap)-a_da)-IF(E65=a_churn_year,a_sticky*((cf_arr*(1+F$66)^E65)-((cf_arr*(1+F$66)^E65)*IF(E65>=a_churn_year,1-$B$68,1)))*(1-MIN(a_m0+a_mstep*E65,a_mcap)),0)))*a_tax+((cf_arr*(1+F$66)^E65)*IF(E65>=a_churn_year,1-$B$68,1))*a_da-((cf_arr*(1+F$66)^E65)*IF(E65>=a_churn_year,1-$B$68,1))*a_capex-a_wc*(((cf_arr*(1+F$66)^E65)*IF(E65>=a_churn_year,1-$B$68,1))-(cf_arr*(1+F$66)^D65*IF(D65>=a_churn_year,1-$B$68,1))) -> 10.66065 | F79: =(((cf_arr*(1+F$66)^F65)*IF(F65>=a_churn_year,1-$B$68,1))*(MIN(a_m0+a_mstep*F65,a_mcap)-a_da)-IF(F65=a_churn_year,a_sticky*((cf_arr*(1+F$66)^F65)-((cf_arr*(1+F$66)^F65)*IF(F65>=a_churn_year,1-$B$68,1)))*(1-MIN(a_m0+a_mstep*F65,a_mcap)),0))-MAX(0,(((cf_arr*(1+F$66)^F65)*IF(F65>=a_churn_year,1-$B$68,1))*(MIN(a_m0+a_mstep*F65,a_mcap)-a_da)-IF(F65=a_churn_year,a_sticky*((cf_arr*(1+F$66)^F65)-((cf_arr*(1+F$66)^F65)*IF(F65>=a_churn_year,1-$B$68,1)))*(1-MIN(a_m0+a_mstep*F65,a_mcap)),0)))*a_tax+((cf_arr*(1+F$66)^F65)*IF(F65>=a_churn_year,1-$B$68,1))*a_da-((cf_arr*(1+F$66)^F65)*IF(F65>=a_churn_year,1-$B$68,1))*a_capex-a_wc*(((cf_arr*(1+F$66)^F65)*IF(F65>=a_churn_year,1-$B$68,1))-(cf_arr*(1+F$66)^E65*IF(E65>=a_churn_year,1-$B$68,1))) -> 26.54652 | G79: =(((cf_arr*(1+F$66)^G65)*IF(G65>=a_churn_year,1-$B$68,1))*(MIN(a_m0+a_mstep*G65,a_mcap)-a_da)-IF(G65=a_churn_year,a_sticky*((cf_arr*(1+F$66)^G65)-((cf_arr*(1+F$66)^G65)*IF(G65>=a_churn_year,1-$B$68,1)))*(1-MIN(a_m0+a_mstep*G65,a_mcap)),0))-MAX(0,(((cf_arr*(1+F$66)^G65)*IF(G65>=a_churn_year,1-$B$68,1))*(MIN(a_m0+a_mstep*G65,a_mcap)-a_da)-IF(G65=a_churn_year,a_sticky*((cf_arr*(1+F$66)^G65)-((cf_arr*(1+F$66)^G65)*IF(G65>=a_churn_year,1-$B$68,1)))*(1-MIN(a_m0+a_mstep*G65,a_mcap)),0)))*a_tax+((cf_arr*(1+F$66)^G65)*IF(G65>=a_churn_year,1-$B$68,1))*a_da-((cf_arr*(1+F$66)^G65)*IF(G65>=a_churn_year,1-$B$68,1))*a_capex-a_wc*(((cf_arr*(1+F$66)^G65)*IF(G65>=a_churn_year,1-$B$68,1))-(cf_arr*(1+F$66)^F65*IF(F65>=a_churn_year,1-$B$68,1))) -> 51.004453 | H79: =(((cf_arr*(1+F$66)^H65)*IF(H65>=a_churn_year,1-$B$68,1))*(MIN(a_m0+a_mstep*H65,a_mcap)-a_da)-IF(H65=a_churn_year,a_sticky*((cf_arr*(1+F$66)^H65)-((cf_arr*(1+F$66)^H65)*IF(H65>=a_churn_year,1-$B$68,1)))*(1-MIN(a_m0+a_mstep*H65,a_mcap)),0))-MAX(0,(((cf_arr*(1+F$66)^H65)*IF(H65>=a_churn_year,1-$B$68,1))*(MIN(a_m0+a_mstep*H65,a_mcap)-a_da)-IF(H65=a_churn_year,a_sticky*((cf_arr*(1+F$66)^H65)-((cf_arr*(1+F$66)^H65)*IF(H65>=a_churn_year,1-$B$68,1)))*(1-MIN(a_m0+a_mstep*H65,a_mcap)),0)))*a_tax+((cf_arr*(1+F$66)^H65)*IF(H65>=a_churn_year,1-$B$68,1))*a_da-((cf_arr*(1+F$66)^H65)*IF(H65>=a_churn_year,1-$B$68,1))*a_capex-a_wc*(((cf_arr*(1+F$66)^H65)*IF(H65>=a_churn_year,1-$B$68,1))-(cf_arr*(1+F$66)^G65*IF(G65>=a_churn_year,1-$B$68,1))) -> 87.74796 | I79: =(((cf_arr*(1+F$66)^I65)*IF(I65>=a_churn_year,1-$B$68,1))*(MIN(a_m0+a_mstep*I65,a_mcap)-a_da)-IF(I65=a_churn_year,a_sticky*((cf_arr*(1+F$66)^I65)-((cf_arr*(1+F$66)^I65)*IF(I65>=a_churn_year,1-$B$68,1)))*(1-MIN(a_m0+a_mstep*I65,a_mcap)),0))-MAX(0,(((cf_arr*(1+F$66)^I65)*IF(I65>=a_churn_year,1-$B$68,1))*(MIN(a_m0+a_mstep*I65,a_mcap)-a_da)-IF(I65=a_churn_year,a_sticky*((cf_arr*(1+F$66)^I65)-((cf_arr*(1+F$66)^I65)*IF(I65>=a_churn_year,1-$B$68,1)))*(1-MIN(a_m0+a_mstep*I65,a_mcap)),0)))*a_tax+((cf_arr*(1+F$66)^I65)*IF(I65>=a_churn_year,1-$B$68,1))*a_da-((cf_arr*(1+F$66)^I65)*IF(I65>=a_churn_year,1-$B$68,1))*a_capex-a_wc*(((cf_arr*(1+F$66)^I65)*IF(I65>=a_churn_year,1-$B$68,1))-(cf_arr*(1+F$66)^H65*IF(H65>=a_churn_year,1-$B$68,1))) -> 114.07235 | J79: =(((cf_arr*(1+F$66)^J65)*IF(J65>=a_churn_year,1-$B$68,1))*(MIN(a_m0+a_mstep*J65,a_mcap)-a_da)-IF(J65=a_churn_year,a_sticky*((cf_arr*(1+F$66)^J65)-((cf_arr*(1+F$66)^J65)*IF(J65>=a_churn_year,1-$B$68,1)))*(1-MIN(a_m0+a_mstep*J65,a_mcap)),0))-MAX(0,(((cf_arr*(1+F$66)^J65)*IF(J65>=a_churn_year,1-$B$68,1))*(MIN(a_m0+a_mstep*J65,a_mcap)-a_da)-IF(J65=a_churn_year,a_sticky*((cf_arr*(1+F$66)^J65)-((cf_arr*(1+F$66)^J65)*IF(J65>=a_churn_year,1-$B$68,1)))*(1-MIN(a_m0+a_mstep*J65,a_mcap)),0)))*a_tax+((cf_arr*(1+F$66)^J65)*IF(J65>=a_churn_year,1-$B$68,1))*a_da-((cf_arr*(1+F$66)^J65)*IF(J65>=a_churn_year,1-$B$68,1))*a_capex-a_wc*(((cf_arr*(1+F$66)^J65)*IF(J65>=a_churn_year,1-$B$68,1))-(cf_arr*(1+F$66)^I65*IF(I65>=a_churn_year,1-$B$68,1))) -> 148.29405 | K79: =(((cf_arr*(1+F$66)^K65)*IF(K65>=a_churn_year,1-$B$68,1))*(MIN(a_m0+a_mstep*K65,a_mcap)-a_da)-IF(K65=a_churn_year,a_sticky*((cf_arr*(1+F$66)^K65)-((cf_arr*(1+F$66)^K65)*IF(K65>=a_churn_year,1-$B$68,1)))*(1-MIN(a_m0+a_mstep*K65,a_mcap)),0))-MAX(0,(((cf_arr*(1+F$66)^K65)*IF(K65>=a_churn_year,1-$B$68,1))*(MIN(a_m0+a_mstep*K65,a_mcap)-a_da)-IF(K65=a_churn_year,a_sticky*((cf_arr*(1+F$66)^K65)-((cf_arr*(1+F$66)^K65)*IF(K65>=a_churn_year,1-$B$68,1)))*(1-MIN(a_m0+a_mstep*K65,a_mcap)),0)))*a_tax+((cf_arr*(1+F$66)^K65)*IF(K65>=a_churn_year,1-$B$68,1))*a_da-((cf_arr*(1+F$66)^K65)*IF(K65>=a_churn_year,1-$B$68,1))*a_capex-a_wc*(((cf_arr*(1+F$66)^K65)*IF(K65>=a_churn_year,1-$B$68,1))-(cf_arr*(1+F$66)^J65*IF(J65>=a_churn_year,1-$B$68,1))) -> 192.78227 | L79: =(((cf_arr*(1+F$66)^L65)*IF(L65>=a_churn_year,1-$B$68,1))*(MIN(a_m0+a_mstep*L65,a_mcap)-a_da)-IF(L65=a_churn_year,a_sticky*((cf_arr*(1+F$66)^L65)-((cf_arr*(1+F$66)^L65)*IF(L65>=a_churn_year,1-$B$68,1)))*(1-MIN(a_m0+a_mstep*L65,a_mcap)),0))-MAX(0,(((cf_arr*(1+F$66)^L65)*IF(L65>=a_churn_year,1-$B$68,1))*(MIN(a_m0+a_mstep*L65,a_mcap)-a_da)-IF(L65=a_churn_year,a_sticky*((cf_arr*(1+F$66)^L65)-((cf_arr*(1+F$66)^L65)*IF(L65>=a_churn_year,1-$B$68,1)))*(1-MIN(a_m0+a_mstep*L65,a_mcap)),0)))*a_tax+((cf_arr*(1+F$66)^L65)*IF(L65>=a_churn_year,1-$B$68,1))*a_da-((cf_arr*(1+F$66)^L65)*IF(L65>=a_churn_year,1-$B$68,1))*a_capex-a_wc*(((cf_arr*(1+F$66)^L65)*IF(L65>=a_churn_year,1-$B$68,1))-(cf_arr*(1+F$66)^K65*IF(K65>=a_churn_year,1-$B$68,1))) -> 250.61695 | M79: =(((cf_arr*(1+F$66)^M65)*IF(M65>=a_churn_year,1-$B$68,1))*(MIN(a_m0+a_mstep*M65,a_mcap)-a_da)-IF(M65=a_churn_year,a_sticky*((cf_arr*(1+F$66)^M65)-((cf_arr*(1+F$66)^M65)*IF(M65>=a_churn_year,1-$B$68,1)))*(1-MIN(a_m0+a_mstep*M65,a_mcap)),0))-MAX(0,(((cf_arr*(1+F$66)^M65)*IF(M65>=a_churn_year,1-$B$68,1))*(MIN(a_m0+a_mstep*M65,a_mcap)-a_da)-IF(M65=a_churn_year,a_sticky*((cf_arr*(1+F$66)^M65)-((cf_arr*(1+F$66)^M65)*IF(M65>=a_churn_year,1-$B$68,1)))*(1-MIN(a_m0+a_mstep*M65,a_mcap)),0)))*a_tax+((cf_arr*(1+F$66)^M65)*IF(M65>=a_churn_year,1-$B$68,1))*a_da-((cf_arr*(1+F$66)^M65)*IF(M65>=a_churn_year,1-$B$68,1))*a_capex-a_wc*(((cf_arr*(1+F$66)^M65)*IF(M65>=a_churn_year,1-$B$68,1))-(cf_arr*(1+F$66)^L65*IF(L65>=a_churn_year,1-$B$68,1))) -> 325.80203
A80: FCF: churn 30.0%, growth 40% | C80: =0 -> 0 | D80: =(((cf_arr*(1+G$66)^D65)*IF(D65>=a_churn_year,1-$B$68,1))*(MIN(a_m0+a_mstep*D65,a_mcap)-a_da)-IF(D65=a_churn_year,a_sticky*((cf_arr*(1+G$66)^D65)-((cf_arr*(1+G$66)^D65)*IF(D65>=a_churn_year,1-$B$68,1)))*(1-MIN(a_m0+a_mstep*D65,a_mcap)),0))-MAX(0,(((cf_arr*(1+G$66)^D65)*IF(D65>=a_churn_year,1-$B$68,1))*(MIN(a_m0+a_mstep*D65,a_mcap)-a_da)-IF(D65=a_churn_year,a_sticky*((cf_arr*(1+G$66)^D65)-((cf_arr*(1+G$66)^D65)*IF(D65>=a_churn_year,1-$B$68,1)))*(1-MIN(a_m0+a_mstep*D65,a_mcap)),0)))*a_tax+((cf_arr*(1+G$66)^D65)*IF(D65>=a_churn_year,1-$B$68,1))*a_da-((cf_arr*(1+G$66)^D65)*IF(D65>=a_churn_year,1-$B$68,1))*a_capex-a_wc*(((cf_arr*(1+G$66)^D65)*IF(D65>=a_churn_year,1-$B$68,1))-(cf_arr*(1+G$66)^C65*IF(C65>=a_churn_year,1-$B$68,1))) -> -39.358 | E80: =(((cf_arr*(1+G$66)^E65)*IF(E65>=a_churn_year,1-$B$68,1))*(MIN(a_m0+a_mstep*E65,a_mcap)-a_da)-IF(E65=a_churn_year,a_sticky*((cf_arr*(1+G$66)^E65)-((cf_arr*(1+G$66)^E65)*IF(E65>=a_churn_year,1-$B$68,1)))*(1-MIN(a_m0+a_mstep*E65,a_mcap)),0))-MAX(0,(((cf_arr*(1+G$66)^E65)*IF(E65>=a_churn_year,1-$B$68,1))*(MIN(a_m0+a_mstep*E65,a_mcap)-a_da)-IF(E65=a_churn_year,a_sticky*((cf_arr*(1+G$66)^E65)-((cf_arr*(1+G$66)^E65)*IF(E65>=a_churn_year,1-$B$68,1)))*(1-MIN(a_m0+a_mstep*E65,a_mcap)),0)))*a_tax+((cf_arr*(1+G$66)^E65)*IF(E65>=a_churn_year,1-$B$68,1))*a_da-((cf_arr*(1+G$66)^E65)*IF(E65>=a_churn_year,1-$B$68,1))*a_capex-a_wc*(((cf_arr*(1+G$66)^E65)*IF(E65>=a_churn_year,1-$B$68,1))-(cf_arr*(1+G$66)^D65*IF(D65>=a_churn_year,1-$B$68,1))) -> 11.5346 | F80: =(((cf_arr*(1+G$66)^F65)*IF(F65>=a_churn_year,1-$B$68,1))*(MIN(a_m0+a_mstep*F65,a_mcap)-a_da)-IF(F65=a_churn_year,a_sticky*((cf_arr*(1+G$66)^F65)-((cf_arr*(1+G$66)^F65)*IF(F65>=a_churn_year,1-$B$68,1)))*(1-MIN(a_m0+a_mstep*F65,a_mcap)),0))-MAX(0,(((cf_arr*(1+G$66)^F65)*IF(F65>=a_churn_year,1-$B$68,1))*(MIN(a_m0+a_mstep*F65,a_mcap)-a_da)-IF(F65=a_churn_year,a_sticky*((cf_arr*(1+G$66)^F65)-((cf_arr*(1+G$66)^F65)*IF(F65>=a_churn_year,1-$B$68,1)))*(1-MIN(a_m0+a_mstep*F65,a_mcap)),0)))*a_tax+((cf_arr*(1+G$66)^F65)*IF(F65>=a_churn_year,1-$B$68,1))*a_da-((cf_arr*(1+G$66)^F65)*IF(F65>=a_churn_year,1-$B$68,1))*a_capex-a_wc*(((cf_arr*(1+G$66)^F65)*IF(F65>=a_churn_year,1-$B$68,1))-(cf_arr*(1+G$66)^E65*IF(E65>=a_churn_year,1-$B$68,1))) -> 31.99504 | G80: =(((cf_arr*(1+G$66)^G65)*IF(G65>=a_churn_year,1-$B$68,1))*(MIN(a_m0+a_mstep*G65,a_mcap)-a_da)-IF(G65=a_churn_year,a_sticky*((cf_arr*(1+G$66)^G65)-((cf_arr*(1+G$66)^G65)*IF(G65>=a_churn_year,1-$B$68,1)))*(1-MIN(a_m0+a_mstep*G65,a_mcap)),0))-MAX(0,(((cf_arr*(1+G$66)^G65)*IF(G65>=a_churn_year,1-$B$68,1))*(MIN(a_m0+a_mstep*G65,a_mcap)-a_da)-IF(G65=a_churn_year,a_sticky*((cf_arr*(1+G$66)^G65)-((cf_arr*(1+G$66)^G65)*IF(G65>=a_churn_year,1-$B$68,1)))*(1-MIN(a_m0+a_mstep*G65,a_mcap)),0)))*a_tax+((cf_arr*(1+G$66)^G65)*IF(G65>=a_churn_year,1-$B$68,1))*a_da-((cf_arr*(1+G$66)^G65)*IF(G65>=a_churn_year,1-$B$68,1))*a_capex-a_wc*(((cf_arr*(1+G$66)^G65)*IF(G65>=a_churn_year,1-$B$68,1))-(cf_arr*(1+G$66)^F65*IF(F65>=a_churn_year,1-$B$68,1))) -> 66.978296 | H80: =(((cf_arr*(1+G$66)^H65)*IF(H65>=a_churn_year,1-$B$68,1))*(MIN(a_m0+a_mstep*H65,a_mcap)-a_da)-IF(H65=a_churn_year,a_sticky*((cf_arr*(1+G$66)^H65)-((cf_arr*(1+G$66)^H65)*IF(H65>=a_churn_year,1-$B$68,1)))*(1-MIN(a_m0+a_mstep*H65,a_mcap)),0))-MAX(0,(((cf_arr*(1+G$66)^H65)*IF(H65>=a_churn_year,1-$B$68,1))*(MIN(a_m0+a_mstep*H65,a_mcap)-a_da)-IF(H65=a_churn_year,a_sticky*((cf_arr*(1+G$66)^H65)-((cf_arr*(1+G$66)^H65)*IF(H65>=a_churn_year,1-$B$68,1)))*(1-MIN(a_m0+a_mstep*H65,a_mcap)),0)))*a_tax+((cf_arr*(1+G$66)^H65)*IF(H65>=a_churn_year,1-$B$68,1))*a_da-((cf_arr*(1+G$66)^H65)*IF(H65>=a_churn_year,1-$B$68,1))*a_capex-a_wc*(((cf_arr*(1+G$66)^H65)*IF(H65>=a_churn_year,1-$B$68,1))-(cf_arr*(1+G$66)^G65*IF(G65>=a_churn_year,1-$B$68,1))) -> 124.82895 | I80: =(((cf_arr*(1+G$66)^I65)*IF(I65>=a_churn_year,1-$B$68,1))*(MIN(a_m0+a_mstep*I65,a_mcap)-a_da)-IF(I65=a_churn_year,a_sticky*((cf_arr*(1+G$66)^I65)-((cf_arr*(1+G$66)^I65)*IF(I65>=a_churn_year,1-$B$68,1)))*(1-MIN(a_m0+a_mstep*I65,a_mcap)),0))-MAX(0,(((cf_arr*(1+G$66)^I65)*IF(I65>=a_churn_year,1-$B$68,1))*(MIN(a_m0+a_mstep*I65,a_mcap)-a_da)-IF(I65=a_churn_year,a_sticky*((cf_arr*(1+G$66)^I65)-((cf_arr*(1+G$66)^I65)*IF(I65>=a_churn_year,1-$B$68,1)))*(1-MIN(a_m0+a_mstep*I65,a_mcap)),0)))*a_tax+((cf_arr*(1+G$66)^I65)*IF(I65>=a_churn_year,1-$B$68,1))*a_da-((cf_arr*(1+G$66)^I65)*IF(I65>=a_churn_year,1-$B$68,1))*a_capex-a_wc*(((cf_arr*(1+G$66)^I65)*IF(I65>=a_churn_year,1-$B$68,1))-(cf_arr*(1+G$66)^H65*IF(H65>=a_churn_year,1-$B$68,1))) -> 174.76053 | J80: =(((cf_arr*(1+G$66)^J65)*IF(J65>=a_churn_year,1-$B$68,1))*(MIN(a_m0+a_mstep*J65,a_mcap)-a_da)-IF(J65=a_churn_year,a_sticky*((cf_arr*(1+G$66)^J65)-((cf_arr*(1+G$66)^J65)*IF(J65>=a_churn_year,1-$B$68,1)))*(1-MIN(a_m0+a_mstep*J65,a_mcap)),0))-MAX(0,(((cf_arr*(1+G$66)^J65)*IF(J65>=a_churn_year,1-$B$68,1))*(MIN(a_m0+a_mstep*J65,a_mcap)-a_da)-IF(J65=a_churn_year,a_sticky*((cf_arr*(1+G$66)^J65)-((cf_arr*(1+G$66)^J65)*IF(J65>=a_churn_year,1-$B$68,1)))*(1-MIN(a_m0+a_mstep*J65,a_mcap)),0)))*a_tax+((cf_arr*(1+G$66)^J65)*IF(J65>=a_churn_year,1-$B$68,1))*a_da-((cf_arr*(1+G$66)^J65)*IF(J65>=a_churn_year,1-$B$68,1))*a_capex-a_wc*(((cf_arr*(1+G$66)^J65)*IF(J65>=a_churn_year,1-$B$68,1))-(cf_arr*(1+G$66)^I65*IF(I65>=a_churn_year,1-$B$68,1))) -> 244.66474 | K80: =(((cf_arr*(1+G$66)^K65)*IF(K65>=a_churn_year,1-$B$68,1))*(MIN(a_m0+a_mstep*K65,a_mcap)-a_da)-IF(K65=a_churn_year,a_sticky*((cf_arr*(1+G$66)^K65)-((cf_arr*(1+G$66)^K65)*IF(K65>=a_churn_year,1-$B$68,1)))*(1-MIN(a_m0+a_mstep*K65,a_mcap)),0))-MAX(0,(((cf_arr*(1+G$66)^K65)*IF(K65>=a_churn_year,1-$B$68,1))*(MIN(a_m0+a_mstep*K65,a_mcap)-a_da)-IF(K65=a_churn_year,a_sticky*((cf_arr*(1+G$66)^K65)-((cf_arr*(1+G$66)^K65)*IF(K65>=a_churn_year,1-$B$68,1)))*(1-MIN(a_m0+a_mstep*K65,a_mcap)),0)))*a_tax+((cf_arr*(1+G$66)^K65)*IF(K65>=a_churn_year,1-$B$68,1))*a_da-((cf_arr*(1+G$66)^K65)*IF(K65>=a_churn_year,1-$B$68,1))*a_capex-a_wc*(((cf_arr*(1+G$66)^K65)*IF(K65>=a_churn_year,1-$B$68,1))-(cf_arr*(1+G$66)^J65*IF(J65>=a_churn_year,1-$B$68,1))) -> 342.53064 | L80: =(((cf_arr*(1+G$66)^L65)*IF(L65>=a_churn_year,1-$B$68,1))*(MIN(a_m0+a_mstep*L65,a_mcap)-a_da)-IF(L65=a_churn_year,a_sticky*((cf_arr*(1+G$66)^L65)-((cf_arr*(1+G$66)^L65)*IF(L65>=a_churn_year,1-$B$68,1)))*(1-MIN(a_m0+a_mstep*L65,a_mcap)),0))-MAX(0,(((cf_arr*(1+G$66)^L65)*IF(L65>=a_churn_year,1-$B$68,1))*(MIN(a_m0+a_mstep*L65,a_mcap)-a_da)-IF(L65=a_churn_year,a_sticky*((cf_arr*(1+G$66)^L65)-((cf_arr*(1+G$66)^L65)*IF(L65>=a_churn_year,1-$B$68,1)))*(1-MIN(a_m0+a_mstep*L65,a_mcap)),0)))*a_tax+((cf_arr*(1+G$66)^L65)*IF(L65>=a_churn_year,1-$B$68,1))*a_da-((cf_arr*(1+G$66)^L65)*IF(L65>=a_churn_year,1-$B$68,1))*a_capex-a_wc*(((cf_arr*(1+G$66)^L65)*IF(L65>=a_churn_year,1-$B$68,1))-(cf_arr*(1+G$66)^K65*IF(K65>=a_churn_year,1-$B$68,1))) -> 479.5429 | M80: =(((cf_arr*(1+G$66)^M65)*IF(M65>=a_churn_year,1-$B$68,1))*(MIN(a_m0+a_mstep*M65,a_mcap)-a_da)-IF(M65=a_churn_year,a_sticky*((cf_arr*(1+G$66)^M65)-((cf_arr*(1+G$66)^M65)*IF(M65>=a_churn_year,1-$B$68,1)))*(1-MIN(a_m0+a_mstep*M65,a_mcap)),0))-MAX(0,(((cf_arr*(1+G$66)^M65)*IF(M65>=a_churn_year,1-$B$68,1))*(MIN(a_m0+a_mstep*M65,a_mcap)-a_da)-IF(M65=a_churn_year,a_sticky*((cf_arr*(1+G$66)^M65)-((cf_arr*(1+G$66)^M65)*IF(M65>=a_churn_year,1-$B$68,1)))*(1-MIN(a_m0+a_mstep*M65,a_mcap)),0)))*a_tax+((cf_arr*(1+G$66)^M65)*IF(M65>=a_churn_year,1-$B$68,1))*a_da-((cf_arr*(1+G$66)^M65)*IF(M65>=a_churn_year,1-$B$68,1))*a_capex-a_wc*(((cf_arr*(1+G$66)^M65)*IF(M65>=a_churn_year,1-$B$68,1))-(cf_arr*(1+G$66)^L65*IF(L65>=a_churn_year,1-$B$68,1))) -> 671.36005
A81: FCF: churn 37.5%, growth 10% | C81: =0 -> 0 | D81: =(((cf_arr*(1+D$66)^D65)*IF(D65>=a_churn_year,1-$B$69,1))*(MIN(a_m0+a_mstep*D65,a_mcap)-a_da)-IF(D65=a_churn_year,a_sticky*((cf_arr*(1+D$66)^D65)-((cf_arr*(1+D$66)^D65)*IF(D65>=a_churn_year,1-$B$69,1)))*(1-MIN(a_m0+a_mstep*D65,a_mcap)),0))-MAX(0,(((cf_arr*(1+D$66)^D65)*IF(D65>=a_churn_year,1-$B$69,1))*(MIN(a_m0+a_mstep*D65,a_mcap)-a_da)-IF(D65=a_churn_year,a_sticky*((cf_arr*(1+D$66)^D65)-((cf_arr*(1+D$66)^D65)*IF(D65>=a_churn_year,1-$B$69,1)))*(1-MIN(a_m0+a_mstep*D65,a_mcap)),0)))*a_tax+((cf_arr*(1+D$66)^D65)*IF(D65>=a_churn_year,1-$B$69,1))*a_da-((cf_arr*(1+D$66)^D65)*IF(D65>=a_churn_year,1-$B$69,1))*a_capex-a_wc*(((cf_arr*(1+D$66)^D65)*IF(D65>=a_churn_year,1-$B$69,1))-(cf_arr*(1+D$66)^C65*IF(C65>=a_churn_year,1-$B$69,1))) -> -36.64375 | E81: =(((cf_arr*(1+D$66)^E65)*IF(E65>=a_churn_year,1-$B$69,1))*(MIN(a_m0+a_mstep*E65,a_mcap)-a_da)-IF(E65=a_churn_year,a_sticky*((cf_arr*(1+D$66)^E65)-((cf_arr*(1+D$66)^E65)*IF(E65>=a_churn_year,1-$B$69,1)))*(1-MIN(a_m0+a_mstep*E65,a_mcap)),0))-MAX(0,(((cf_arr*(1+D$66)^E65)*IF(E65>=a_churn_year,1-$B$69,1))*(MIN(a_m0+a_mstep*E65,a_mcap)-a_da)-IF(E65=a_churn_year,a_sticky*((cf_arr*(1+D$66)^E65)-((cf_arr*(1+D$66)^E65)*IF(E65>=a_churn_year,1-$B$69,1)))*(1-MIN(a_m0+a_mstep*E65,a_mcap)),0)))*a_tax+((cf_arr*(1+D$66)^E65)*IF(E65>=a_churn_year,1-$B$69,1))*a_da-((cf_arr*(1+D$66)^E65)*IF(E65>=a_churn_year,1-$B$69,1))*a_capex-a_wc*(((cf_arr*(1+D$66)^E65)*IF(E65>=a_churn_year,1-$B$69,1))-(cf_arr*(1+D$66)^D65*IF(D65>=a_churn_year,1-$B$69,1))) -> 7.9784375 | F81: =(((cf_arr*(1+D$66)^F65)*IF(F65>=a_churn_year,1-$B$69,1))*(MIN(a_m0+a_mstep*F65,a_mcap)-a_da)-IF(F65=a_churn_year,a_sticky*((cf_arr*(1+D$66)^F65)-((cf_arr*(1+D$66)^F65)*IF(F65>=a_churn_year,1-$B$69,1)))*(1-MIN(a_m0+a_mstep*F65,a_mcap)),0))-MAX(0,(((cf_arr*(1+D$66)^F65)*IF(F65>=a_churn_year,1-$B$69,1))*(MIN(a_m0+a_mstep*F65,a_mcap)-a_da)-IF(F65=a_churn_year,a_sticky*((cf_arr*(1+D$66)^F65)-((cf_arr*(1+D$66)^F65)*IF(F65>=a_churn_year,1-$B$69,1)))*(1-MIN(a_m0+a_mstep*F65,a_mcap)),0)))*a_tax+((cf_arr*(1+D$66)^F65)*IF(F65>=a_churn_year,1-$B$69,1))*a_da-((cf_arr*(1+D$66)^F65)*IF(F65>=a_churn_year,1-$B$69,1))*a_capex-a_wc*(((cf_arr*(1+D$66)^F65)*IF(F65>=a_churn_year,1-$B$69,1))-(cf_arr*(1+D$66)^E65*IF(E65>=a_churn_year,1-$B$69,1))) -> 15.63925 | G81: =(((cf_arr*(1+D$66)^G65)*IF(G65>=a_churn_year,1-$B$69,1))*(MIN(a_m0+a_mstep*G65,a_mcap)-a_da)-IF(G65=a_churn_year,a_sticky*((cf_arr*(1+D$66)^G65)-((cf_arr*(1+D$66)^G65)*IF(G65>=a_churn_year,1-$B$69,1)))*(1-MIN(a_m0+a_mstep*G65,a_mcap)),0))-MAX(0,(((cf_arr*(1+D$66)^G65)*IF(G65>=a_churn_year,1-$B$69,1))*(MIN(a_m0+a_mstep*G65,a_mcap)-a_da)-IF(G65=a_churn_year,a_sticky*((cf_arr*(1+D$66)^G65)-((cf_arr*(1+D$66)^G65)*IF(G65>=a_churn_year,1-$B$69,1)))*(1-MIN(a_m0+a_mstep*G65,a_mcap)),0)))*a_tax+((cf_arr*(1+D$66)^G65)*IF(G65>=a_churn_year,1-$B$69,1))*a_da-((cf_arr*(1+D$66)^G65)*IF(G65>=a_churn_year,1-$B$69,1))*a_capex-a_wc*(((cf_arr*(1+D$66)^G65)*IF(G65>=a_churn_year,1-$B$69,1))-(cf_arr*(1+D$66)^F65*IF(F65>=a_churn_year,1-$B$69,1))) -> 24.752441 | H81: =(((cf_arr*(1+D$66)^H65)*IF(H65>=a_churn_year,1-$B$69,1))*(MIN(a_m0+a_mstep*H65,a_mcap)-a_da)-IF(H65=a_churn_year,a_sticky*((cf_arr*(1+D$66)^H65)-((cf_arr*(1+D$66)^H65)*IF(H65>=a_churn_year,1-$B$69,1)))*(1-MIN(a_m0+a_mstep*H65,a_mcap)),0))-MAX(0,(((cf_arr*(1+D$66)^H65)*IF(H65>=a_churn_year,1-$B$69,1))*(MIN(a_m0+a_mstep*H65,a_mcap)-a_da)-IF(H65=a_churn_year,a_sticky*((cf_arr*(1+D$66)^H65)-((cf_arr*(1+D$66)^H65)*IF(H65>=a_churn_year,1-$B$69,1)))*(1-MIN(a_m0+a_mstep*H65,a_mcap)),0)))*a_tax+((cf_arr*(1+D$66)^H65)*IF(H65>=a_churn_year,1-$B$69,1))*a_da-((cf_arr*(1+D$66)^H65)*IF(H65>=a_churn_year,1-$B$69,1))*a_capex-a_wc*(((cf_arr*(1+D$66)^H65)*IF(H65>=a_churn_year,1-$B$69,1))-(cf_arr*(1+D$66)^G65*IF(G65>=a_churn_year,1-$B$69,1))) -> 35.531877 | I81: =(((cf_arr*(1+D$66)^I65)*IF(I65>=a_churn_year,1-$B$69,1))*(MIN(a_m0+a_mstep*I65,a_mcap)-a_da)-IF(I65=a_churn_year,a_sticky*((cf_arr*(1+D$66)^I65)-((cf_arr*(1+D$66)^I65)*IF(I65>=a_churn_year,1-$B$69,1)))*(1-MIN(a_m0+a_mstep*I65,a_mcap)),0))-MAX(0,(((cf_arr*(1+D$66)^I65)*IF(I65>=a_churn_year,1-$B$69,1))*(MIN(a_m0+a_mstep*I65,a_mcap)-a_da)-IF(I65=a_churn_year,a_sticky*((cf_arr*(1+D$66)^I65)-((cf_arr*(1+D$66)^I65)*IF(I65>=a_churn_year,1-$B$69,1)))*(1-MIN(a_m0+a_mstep*I65,a_mcap)),0)))*a_tax+((cf_arr*(1+D$66)^I65)*IF(I65>=a_churn_year,1-$B$69,1))*a_da-((cf_arr*(1+D$66)^I65)*IF(I65>=a_churn_year,1-$B$69,1))*a_capex-a_wc*(((cf_arr*(1+D$66)^I65)*IF(I65>=a_churn_year,1-$B$69,1))-(cf_arr*(1+D$66)^H65*IF(H65>=a_churn_year,1-$B$69,1))) -> 39.085065 | J81: =(((cf_arr*(1+D$66)^J65)*IF(J65>=a_churn_year,1-$B$69,1))*(MIN(a_m0+a_mstep*J65,a_mcap)-a_da)-IF(J65=a_churn_year,a_sticky*((cf_arr*(1+D$66)^J65)-((cf_arr*(1+D$66)^J65)*IF(J65>=a_churn_year,1-$B$69,1)))*(1-MIN(a_m0+a_mstep*J65,a_mcap)),0))-MAX(0,(((cf_arr*(1+D$66)^J65)*IF(J65>=a_churn_year,1-$B$69,1))*(MIN(a_m0+a_mstep*J65,a_mcap)-a_da)-IF(J65=a_churn_year,a_sticky*((cf_arr*(1+D$66)^J65)-((cf_arr*(1+D$66)^J65)*IF(J65>=a_churn_year,1-$B$69,1)))*(1-MIN(a_m0+a_mstep*J65,a_mcap)),0)))*a_tax+((cf_arr*(1+D$66)^J65)*IF(J65>=a_churn_year,1-$B$69,1))*a_da-((cf_arr*(1+D$66)^J65)*IF(J65>=a_churn_year,1-$B$69,1))*a_capex-a_wc*(((cf_arr*(1+D$66)^J65)*IF(J65>=a_churn_year,1-$B$69,1))-(cf_arr*(1+D$66)^I65*IF(I65>=a_churn_year,1-$B$69,1))) -> 42.993571 | K81: =(((cf_arr*(1+D$66)^K65)*IF(K65>=a_churn_year,1-$B$69,1))*(MIN(a_m0+a_mstep*K65,a_mcap)-a_da)-IF(K65=a_churn_year,a_sticky*((cf_arr*(1+D$66)^K65)-((cf_arr*(1+D$66)^K65)*IF(K65>=a_churn_year,1-$B$69,1)))*(1-MIN(a_m0+a_mstep*K65,a_mcap)),0))-MAX(0,(((cf_arr*(1+D$66)^K65)*IF(K65>=a_churn_year,1-$B$69,1))*(MIN(a_m0+a_mstep*K65,a_mcap)-a_da)-IF(K65=a_churn_year,a_sticky*((cf_arr*(1+D$66)^K65)-((cf_arr*(1+D$66)^K65)*IF(K65>=a_churn_year,1-$B$69,1)))*(1-MIN(a_m0+a_mstep*K65,a_mcap)),0)))*a_tax+((cf_arr*(1+D$66)^K65)*IF(K65>=a_churn_year,1-$B$69,1))*a_da-((cf_arr*(1+D$66)^K65)*IF(K65>=a_churn_year,1-$B$69,1))*a_capex-a_wc*(((cf_arr*(1+D$66)^K65)*IF(K65>=a_churn_year,1-$B$69,1))-(cf_arr*(1+D$66)^J65*IF(J65>=a_churn_year,1-$B$69,1))) -> 47.292928 | L81: =(((cf_arr*(1+D$66)^L65)*IF(L65>=a_churn_year,1-$B$69,1))*(MIN(a_m0+a_mstep*L65,a_mcap)-a_da)-IF(L65=a_churn_year,a_sticky*((cf_arr*(1+D$66)^L65)-((cf_arr*(1+D$66)^L65)*IF(L65>=a_churn_year,1-$B$69,1)))*(1-MIN(a_m0+a_mstep*L65,a_mcap)),0))-MAX(0,(((cf_arr*(1+D$66)^L65)*IF(L65>=a_churn_year,1-$B$69,1))*(MIN(a_m0+a_mstep*L65,a_mcap)-a_da)-IF(L65=a_churn_year,a_sticky*((cf_arr*(1+D$66)^L65)-((cf_arr*(1+D$66)^L65)*IF(L65>=a_churn_year,1-$B$69,1)))*(1-MIN(a_m0+a_mstep*L65,a_mcap)),0)))*a_tax+((cf_arr*(1+D$66)^L65)*IF(L65>=a_churn_year,1-$B$69,1))*a_da-((cf_arr*(1+D$66)^L65)*IF(L65>=a_churn_year,1-$B$69,1))*a_capex-a_wc*(((cf_arr*(1+D$66)^L65)*IF(L65>=a_churn_year,1-$B$69,1))-(cf_arr*(1+D$66)^K65*IF(K65>=a_churn_year,1-$B$69,1))) -> 52.022221 | M81: =(((cf_arr*(1+D$66)^M65)*IF(M65>=a_churn_year,1-$B$69,1))*(MIN(a_m0+a_mstep*M65,a_mcap)-a_da)-IF(M65=a_churn_year,a_sticky*((cf_arr*(1+D$66)^M65)-((cf_arr*(1+D$66)^M65)*IF(M65>=a_churn_year,1-$B$69,1)))*(1-MIN(a_m0+a_mstep*M65,a_mcap)),0))-MAX(0,(((cf_arr*(1+D$66)^M65)*IF(M65>=a_churn_year,1-$B$69,1))*(MIN(a_m0+a_mstep*M65,a_mcap)-a_da)-IF(M65=a_churn_year,a_sticky*((cf_arr*(1+D$66)^M65)-((cf_arr*(1+D$66)^M65)*IF(M65>=a_churn_year,1-$B$69,1)))*(1-MIN(a_m0+a_mstep*M65,a_mcap)),0)))*a_tax+((cf_arr*(1+D$66)^M65)*IF(M65>=a_churn_year,1-$B$69,1))*a_da-((cf_arr*(1+D$66)^M65)*IF(M65>=a_churn_year,1-$B$69,1))*a_capex-a_wc*(((cf_arr*(1+D$66)^M65)*IF(M65>=a_churn_year,1-$B$69,1))-(cf_arr*(1+D$66)^L65*IF(L65>=a_churn_year,1-$B$69,1))) -> 57.224443
A82: FCF: churn 37.5%, growth 20% | C82: =0 -> 0 | D82: =(((cf_arr*(1+E$66)^D65)*IF(D65>=a_churn_year,1-$B$69,1))*(MIN(a_m0+a_mstep*D65,a_mcap)-a_da)-IF(D65=a_churn_year,a_sticky*((cf_arr*(1+E$66)^D65)-((cf_arr*(1+E$66)^D65)*IF(D65>=a_churn_year,1-$B$69,1)))*(1-MIN(a_m0+a_mstep*D65,a_mcap)),0))-MAX(0,(((cf_arr*(1+E$66)^D65)*IF(D65>=a_churn_year,1-$B$69,1))*(MIN(a_m0+a_mstep*D65,a_mcap)-a_da)-IF(D65=a_churn_year,a_sticky*((cf_arr*(1+E$66)^D65)-((cf_arr*(1+E$66)^D65)*IF(D65>=a_churn_year,1-$B$69,1)))*(1-MIN(a_m0+a_mstep*D65,a_mcap)),0)))*a_tax+((cf_arr*(1+E$66)^D65)*IF(D65>=a_churn_year,1-$B$69,1))*a_da-((cf_arr*(1+E$66)^D65)*IF(D65>=a_churn_year,1-$B$69,1))*a_capex-a_wc*(((cf_arr*(1+E$66)^D65)*IF(D65>=a_churn_year,1-$B$69,1))-(cf_arr*(1+E$66)^C65*IF(C65>=a_churn_year,1-$B$69,1))) -> -40.975 | E82: =(((cf_arr*(1+E$66)^E65)*IF(E65>=a_churn_year,1-$B$69,1))*(MIN(a_m0+a_mstep*E65,a_mcap)-a_da)-IF(E65=a_churn_year,a_sticky*((cf_arr*(1+E$66)^E65)-((cf_arr*(1+E$66)^E65)*IF(E65>=a_churn_year,1-$B$69,1)))*(1-MIN(a_m0+a_mstep*E65,a_mcap)),0))-MAX(0,(((cf_arr*(1+E$66)^E65)*IF(E65>=a_churn_year,1-$B$69,1))*(MIN(a_m0+a_mstep*E65,a_mcap)-a_da)-IF(E65=a_churn_year,a_sticky*((cf_arr*(1+E$66)^E65)-((cf_arr*(1+E$66)^E65)*IF(E65>=a_churn_year,1-$B$69,1)))*(1-MIN(a_m0+a_mstep*E65,a_mcap)),0)))*a_tax+((cf_arr*(1+E$66)^E65)*IF(E65>=a_churn_year,1-$B$69,1))*a_da-((cf_arr*(1+E$66)^E65)*IF(E65>=a_churn_year,1-$B$69,1))*a_capex-a_wc*(((cf_arr*(1+E$66)^E65)*IF(E65>=a_churn_year,1-$B$69,1))-(cf_arr*(1+E$66)^D65*IF(D65>=a_churn_year,1-$B$69,1))) -> 8.745 | F82: =(((cf_arr*(1+E$66)^F65)*IF(F65>=a_churn_year,1-$B$69,1))*(MIN(a_m0+a_mstep*F65,a_mcap)-a_da)-IF(F65=a_churn_year,a_sticky*((cf_arr*(1+E$66)^F65)-((cf_arr*(1+E$66)^F65)*IF(F65>=a_churn_year,1-$B$69,1)))*(1-MIN(a_m0+a_mstep*F65,a_mcap)),0))-MAX(0,(((cf_arr*(1+E$66)^F65)*IF(F65>=a_churn_year,1-$B$69,1))*(MIN(a_m0+a_mstep*F65,a_mcap)-a_da)-IF(F65=a_churn_year,a_sticky*((cf_arr*(1+E$66)^F65)-((cf_arr*(1+E$66)^F65)*IF(F65>=a_churn_year,1-$B$69,1)))*(1-MIN(a_m0+a_mstep*F65,a_mcap)),0)))*a_tax+((cf_arr*(1+E$66)^F65)*IF(F65>=a_churn_year,1-$B$69,1))*a_da-((cf_arr*(1+E$66)^F65)*IF(F65>=a_churn_year,1-$B$69,1))*a_capex-a_wc*(((cf_arr*(1+E$66)^F65)*IF(F65>=a_churn_year,1-$B$69,1))-(cf_arr*(1+E$66)^E65*IF(E65>=a_churn_year,1-$B$69,1))) -> 19.404 | G82: =(((cf_arr*(1+E$66)^G65)*IF(G65>=a_churn_year,1-$B$69,1))*(MIN(a_m0+a_mstep*G65,a_mcap)-a_da)-IF(G65=a_churn_year,a_sticky*((cf_arr*(1+E$66)^G65)-((cf_arr*(1+E$66)^G65)*IF(G65>=a_churn_year,1-$B$69,1)))*(1-MIN(a_m0+a_mstep*G65,a_mcap)),0))-MAX(0,(((cf_arr*(1+E$66)^G65)*IF(G65>=a_churn_year,1-$B$69,1))*(MIN(a_m0+a_mstep*G65,a_mcap)-a_da)-IF(G65=a_churn_year,a_sticky*((cf_arr*(1+E$66)^G65)-((cf_arr*(1+E$66)^G65)*IF(G65>=a_churn_year,1-$B$69,1)))*(1-MIN(a_m0+a_mstep*G65,a_mcap)),0)))*a_tax+((cf_arr*(1+E$66)^G65)*IF(G65>=a_churn_year,1-$B$69,1))*a_da-((cf_arr*(1+E$66)^G65)*IF(G65>=a_churn_year,1-$B$69,1))*a_capex-a_wc*(((cf_arr*(1+E$66)^G65)*IF(G65>=a_churn_year,1-$B$69,1))-(cf_arr*(1+E$66)^F65*IF(F65>=a_churn_year,1-$B$69,1))) -> 33.9768 | H82: =(((cf_arr*(1+E$66)^H65)*IF(H65>=a_churn_year,1-$B$69,1))*(MIN(a_m0+a_mstep*H65,a_mcap)-a_da)-IF(H65=a_churn_year,a_sticky*((cf_arr*(1+E$66)^H65)-((cf_arr*(1+E$66)^H65)*IF(H65>=a_churn_year,1-$B$69,1)))*(1-MIN(a_m0+a_mstep*H65,a_mcap)),0))-MAX(0,(((cf_arr*(1+E$66)^H65)*IF(H65>=a_churn_year,1-$B$69,1))*(MIN(a_m0+a_mstep*H65,a_mcap)-a_da)-IF(H65=a_churn_year,a_sticky*((cf_arr*(1+E$66)^H65)-((cf_arr*(1+E$66)^H65)*IF(H65>=a_churn_year,1-$B$69,1)))*(1-MIN(a_m0+a_mstep*H65,a_mcap)),0)))*a_tax+((cf_arr*(1+E$66)^H65)*IF(H65>=a_churn_year,1-$B$69,1))*a_da-((cf_arr*(1+E$66)^H65)*IF(H65>=a_churn_year,1-$B$69,1))*a_capex-a_wc*(((cf_arr*(1+E$66)^H65)*IF(H65>=a_churn_year,1-$B$69,1))-(cf_arr*(1+E$66)^G65*IF(G65>=a_churn_year,1-$B$69,1))) -> 53.60256 | I82: =(((cf_arr*(1+E$66)^I65)*IF(I65>=a_churn_year,1-$B$69,1))*(MIN(a_m0+a_mstep*I65,a_mcap)-a_da)-IF(I65=a_churn_year,a_sticky*((cf_arr*(1+E$66)^I65)-((cf_arr*(1+E$66)^I65)*IF(I65>=a_churn_year,1-$B$69,1)))*(1-MIN(a_m0+a_mstep*I65,a_mcap)),0))-MAX(0,(((cf_arr*(1+E$66)^I65)*IF(I65>=a_churn_year,1-$B$69,1))*(MIN(a_m0+a_mstep*I65,a_mcap)-a_da)-IF(I65=a_churn_year,a_sticky*((cf_arr*(1+E$66)^I65)-((cf_arr*(1+E$66)^I65)*IF(I65>=a_churn_year,1-$B$69,1)))*(1-MIN(a_m0+a_mstep*I65,a_mcap)),0)))*a_tax+((cf_arr*(1+E$66)^I65)*IF(I65>=a_churn_year,1-$B$69,1))*a_da-((cf_arr*(1+E$66)^I65)*IF(I65>=a_churn_year,1-$B$69,1))*a_capex-a_wc*(((cf_arr*(1+E$66)^I65)*IF(I65>=a_churn_year,1-$B$69,1))-(cf_arr*(1+E$66)^H65*IF(H65>=a_churn_year,1-$B$69,1))) -> 64.323072 | J82: =(((cf_arr*(1+E$66)^J65)*IF(J65>=a_churn_year,1-$B$69,1))*(MIN(a_m0+a_mstep*J65,a_mcap)-a_da)-IF(J65=a_churn_year,a_sticky*((cf_arr*(1+E$66)^J65)-((cf_arr*(1+E$66)^J65)*IF(J65>=a_churn_year,1-$B$69,1)))*(1-MIN(a_m0+a_mstep*J65,a_mcap)),0))-MAX(0,(((cf_arr*(1+E$66)^J65)*IF(J65>=a_churn_year,1-$B$69,1))*(MIN(a_m0+a_mstep*J65,a_mcap)-a_da)-IF(J65=a_churn_year,a_sticky*((cf_arr*(1+E$66)^J65)-((cf_arr*(1+E$66)^J65)*IF(J65>=a_churn_year,1-$B$69,1)))*(1-MIN(a_m0+a_mstep*J65,a_mcap)),0)))*a_tax+((cf_arr*(1+E$66)^J65)*IF(J65>=a_churn_year,1-$B$69,1))*a_da-((cf_arr*(1+E$66)^J65)*IF(J65>=a_churn_year,1-$B$69,1))*a_capex-a_wc*(((cf_arr*(1+E$66)^J65)*IF(J65>=a_churn_year,1-$B$69,1))-(cf_arr*(1+E$66)^I65*IF(I65>=a_churn_year,1-$B$69,1))) -> 77.187686 | K82: =(((cf_arr*(1+E$66)^K65)*IF(K65>=a_churn_year,1-$B$69,1))*(MIN(a_m0+a_mstep*K65,a_mcap)-a_da)-IF(K65=a_churn_year,a_sticky*((cf_arr*(1+E$66)^K65)-((cf_arr*(1+E$66)^K65)*IF(K65>=a_churn_year,1-$B$69,1)))*(1-MIN(a_m0+a_mstep*K65,a_mcap)),0))-MAX(0,(((cf_arr*(1+E$66)^K65)*IF(K65>=a_churn_year,1-$B$69,1))*(MIN(a_m0+a_mstep*K65,a_mcap)-a_da)-IF(K65=a_churn_year,a_sticky*((cf_arr*(1+E$66)^K65)-((cf_arr*(1+E$66)^K65)*IF(K65>=a_churn_year,1-$B$69,1)))*(1-MIN(a_m0+a_mstep*K65,a_mcap)),0)))*a_tax+((cf_arr*(1+E$66)^K65)*IF(K65>=a_churn_year,1-$B$69,1))*a_da-((cf_arr*(1+E$66)^K65)*IF(K65>=a_churn_year,1-$B$69,1))*a_capex-a_wc*(((cf_arr*(1+E$66)^K65)*IF(K65>=a_churn_year,1-$B$69,1))-(cf_arr*(1+E$66)^J65*IF(J65>=a_churn_year,1-$B$69,1))) -> 92.625224 | L82: =(((cf_arr*(1+E$66)^L65)*IF(L65>=a_churn_year,1-$B$69,1))*(MIN(a_m0+a_mstep*L65,a_mcap)-a_da)-IF(L65=a_churn_year,a_sticky*((cf_arr*(1+E$66)^L65)-((cf_arr*(1+E$66)^L65)*IF(L65>=a_churn_year,1-$B$69,1)))*(1-MIN(a_m0+a_mstep*L65,a_mcap)),0))-MAX(0,(((cf_arr*(1+E$66)^L65)*IF(L65>=a_churn_year,1-$B$69,1))*(MIN(a_m0+a_mstep*L65,a_mcap)-a_da)-IF(L65=a_churn_year,a_sticky*((cf_arr*(1+E$66)^L65)-((cf_arr*(1+E$66)^L65)*IF(L65>=a_churn_year,1-$B$69,1)))*(1-MIN(a_m0+a_mstep*L65,a_mcap)),0)))*a_tax+((cf_arr*(1+E$66)^L65)*IF(L65>=a_churn_year,1-$B$69,1))*a_da-((cf_arr*(1+E$66)^L65)*IF(L65>=a_churn_year,1-$B$69,1))*a_capex-a_wc*(((cf_arr*(1+E$66)^L65)*IF(L65>=a_churn_year,1-$B$69,1))-(cf_arr*(1+E$66)^K65*IF(K65>=a_churn_year,1-$B$69,1))) -> 111.15027 | M82: =(((cf_arr*(1+E$66)^M65)*IF(M65>=a_churn_year,1-$B$69,1))*(MIN(a_m0+a_mstep*M65,a_mcap)-a_da)-IF(M65=a_churn_year,a_sticky*((cf_arr*(1+E$66)^M65)-((cf_arr*(1+E$66)^M65)*IF(M65>=a_churn_year,1-$B$69,1)))*(1-MIN(a_m0+a_mstep*M65,a_mcap)),0))-MAX(0,(((cf_arr*(1+E$66)^M65)*IF(M65>=a_churn_year,1-$B$69,1))*(MIN(a_m0+a_mstep*M65,a_mcap)-a_da)-IF(M65=a_churn_year,a_sticky*((cf_arr*(1+E$66)^M65)-((cf_arr*(1+E$66)^M65)*IF(M65>=a_churn_year,1-$B$69,1)))*(1-MIN(a_m0+a_mstep*M65,a_mcap)),0)))*a_tax+((cf_arr*(1+E$66)^M65)*IF(M65>=a_churn_year,1-$B$69,1))*a_da-((cf_arr*(1+E$66)^M65)*IF(M65>=a_churn_year,1-$B$69,1))*a_capex-a_wc*(((cf_arr*(1+E$66)^M65)*IF(M65>=a_churn_year,1-$B$69,1))-(cf_arr*(1+E$66)^L65*IF(L65>=a_churn_year,1-$B$69,1))) -> 133.38032
A83: FCF: churn 37.5%, growth 30% | C83: =0 -> 0 | D83: =(((cf_arr*(1+F$66)^D65)*IF(D65>=a_churn_year,1-$B$69,1))*(MIN(a_m0+a_mstep*D65,a_mcap)-a_da)-IF(D65=a_churn_year,a_sticky*((cf_arr*(1+F$66)^D65)-((cf_arr*(1+F$66)^D65)*IF(D65>=a_churn_year,1-$B$69,1)))*(1-MIN(a_m0+a_mstep*D65,a_mcap)),0))-MAX(0,(((cf_arr*(1+F$66)^D65)*IF(D65>=a_churn_year,1-$B$69,1))*(MIN(a_m0+a_mstep*D65,a_mcap)-a_da)-IF(D65=a_churn_year,a_sticky*((cf_arr*(1+F$66)^D65)-((cf_arr*(1+F$66)^D65)*IF(D65>=a_churn_year,1-$B$69,1)))*(1-MIN(a_m0+a_mstep*D65,a_mcap)),0)))*a_tax+((cf_arr*(1+F$66)^D65)*IF(D65>=a_churn_year,1-$B$69,1))*a_da-((cf_arr*(1+F$66)^D65)*IF(D65>=a_churn_year,1-$B$69,1))*a_capex-a_wc*(((cf_arr*(1+F$66)^D65)*IF(D65>=a_churn_year,1-$B$69,1))-(cf_arr*(1+F$66)^C65*IF(C65>=a_churn_year,1-$B$69,1))) -> -45.30625 | E83: =(((cf_arr*(1+F$66)^E65)*IF(E65>=a_churn_year,1-$B$69,1))*(MIN(a_m0+a_mstep*E65,a_mcap)-a_da)-IF(E65=a_churn_year,a_sticky*((cf_arr*(1+F$66)^E65)-((cf_arr*(1+F$66)^E65)*IF(E65>=a_churn_year,1-$B$69,1)))*(1-MIN(a_m0+a_mstep*E65,a_mcap)),0))-MAX(0,(((cf_arr*(1+F$66)^E65)*IF(E65>=a_churn_year,1-$B$69,1))*(MIN(a_m0+a_mstep*E65,a_mcap)-a_da)-IF(E65=a_churn_year,a_sticky*((cf_arr*(1+F$66)^E65)-((cf_arr*(1+F$66)^E65)*IF(E65>=a_churn_year,1-$B$69,1)))*(1-MIN(a_m0+a_mstep*E65,a_mcap)),0)))*a_tax+((cf_arr*(1+F$66)^E65)*IF(E65>=a_churn_year,1-$B$69,1))*a_da-((cf_arr*(1+F$66)^E65)*IF(E65>=a_churn_year,1-$B$69,1))*a_capex-a_wc*(((cf_arr*(1+F$66)^E65)*IF(E65>=a_churn_year,1-$B$69,1))-(cf_arr*(1+F$66)^D65*IF(D65>=a_churn_year,1-$B$69,1))) -> 9.5184375 | F83: =(((cf_arr*(1+F$66)^F65)*IF(F65>=a_churn_year,1-$B$69,1))*(MIN(a_m0+a_mstep*F65,a_mcap)-a_da)-IF(F65=a_churn_year,a_sticky*((cf_arr*(1+F$66)^F65)-((cf_arr*(1+F$66)^F65)*IF(F65>=a_churn_year,1-$B$69,1)))*(1-MIN(a_m0+a_mstep*F65,a_mcap)),0))-MAX(0,(((cf_arr*(1+F$66)^F65)*IF(F65>=a_churn_year,1-$B$69,1))*(MIN(a_m0+a_mstep*F65,a_mcap)-a_da)-IF(F65=a_churn_year,a_sticky*((cf_arr*(1+F$66)^F65)-((cf_arr*(1+F$66)^F65)*IF(F65>=a_churn_year,1-$B$69,1)))*(1-MIN(a_m0+a_mstep*F65,a_mcap)),0)))*a_tax+((cf_arr*(1+F$66)^F65)*IF(F65>=a_churn_year,1-$B$69,1))*a_da-((cf_arr*(1+F$66)^F65)*IF(F65>=a_churn_year,1-$B$69,1))*a_capex-a_wc*(((cf_arr*(1+F$66)^F65)*IF(F65>=a_churn_year,1-$B$69,1))-(cf_arr*(1+F$66)^E65*IF(E65>=a_churn_year,1-$B$69,1))) -> 23.70225 | G83: =(((cf_arr*(1+F$66)^G65)*IF(G65>=a_churn_year,1-$B$69,1))*(MIN(a_m0+a_mstep*G65,a_mcap)-a_da)-IF(G65=a_churn_year,a_sticky*((cf_arr*(1+F$66)^G65)-((cf_arr*(1+F$66)^G65)*IF(G65>=a_churn_year,1-$B$69,1)))*(1-MIN(a_m0+a_mstep*G65,a_mcap)),0))-MAX(0,(((cf_arr*(1+F$66)^G65)*IF(G65>=a_churn_year,1-$B$69,1))*(MIN(a_m0+a_mstep*G65,a_mcap)-a_da)-IF(G65=a_churn_year,a_sticky*((cf_arr*(1+F$66)^G65)-((cf_arr*(1+F$66)^G65)*IF(G65>=a_churn_year,1-$B$69,1)))*(1-MIN(a_m0+a_mstep*G65,a_mcap)),0)))*a_tax+((cf_arr*(1+F$66)^G65)*IF(G65>=a_churn_year,1-$B$69,1))*a_da-((cf_arr*(1+F$66)^G65)*IF(G65>=a_churn_year,1-$B$69,1))*a_capex-a_wc*(((cf_arr*(1+F$66)^G65)*IF(G65>=a_churn_year,1-$B$69,1))-(cf_arr*(1+F$66)^F65*IF(F65>=a_churn_year,1-$B$69,1))) -> 45.539691 | H83: =(((cf_arr*(1+F$66)^H65)*IF(H65>=a_churn_year,1-$B$69,1))*(MIN(a_m0+a_mstep*H65,a_mcap)-a_da)-IF(H65=a_churn_year,a_sticky*((cf_arr*(1+F$66)^H65)-((cf_arr*(1+F$66)^H65)*IF(H65>=a_churn_year,1-$B$69,1)))*(1-MIN(a_m0+a_mstep*H65,a_mcap)),0))-MAX(0,(((cf_arr*(1+F$66)^H65)*IF(H65>=a_churn_year,1-$B$69,1))*(MIN(a_m0+a_mstep*H65,a_mcap)-a_da)-IF(H65=a_churn_year,a_sticky*((cf_arr*(1+F$66)^H65)-((cf_arr*(1+F$66)^H65)*IF(H65>=a_churn_year,1-$B$69,1)))*(1-MIN(a_m0+a_mstep*H65,a_mcap)),0)))*a_tax+((cf_arr*(1+F$66)^H65)*IF(H65>=a_churn_year,1-$B$69,1))*a_da-((cf_arr*(1+F$66)^H65)*IF(H65>=a_churn_year,1-$B$69,1))*a_capex-a_wc*(((cf_arr*(1+F$66)^H65)*IF(H65>=a_churn_year,1-$B$69,1))-(cf_arr*(1+F$66)^G65*IF(G65>=a_churn_year,1-$B$69,1))) -> 78.346393 | I83: =(((cf_arr*(1+F$66)^I65)*IF(I65>=a_churn_year,1-$B$69,1))*(MIN(a_m0+a_mstep*I65,a_mcap)-a_da)-IF(I65=a_churn_year,a_sticky*((cf_arr*(1+F$66)^I65)-((cf_arr*(1+F$66)^I65)*IF(I65>=a_churn_year,1-$B$69,1)))*(1-MIN(a_m0+a_mstep*I65,a_mcap)),0))-MAX(0,(((cf_arr*(1+F$66)^I65)*IF(I65>=a_churn_year,1-$B$69,1))*(MIN(a_m0+a_mstep*I65,a_mcap)-a_da)-IF(I65=a_churn_year,a_sticky*((cf_arr*(1+F$66)^I65)-((cf_arr*(1+F$66)^I65)*IF(I65>=a_churn_year,1-$B$69,1)))*(1-MIN(a_m0+a_mstep*I65,a_mcap)),0)))*a_tax+((cf_arr*(1+F$66)^I65)*IF(I65>=a_churn_year,1-$B$69,1))*a_da-((cf_arr*(1+F$66)^I65)*IF(I65>=a_churn_year,1-$B$69,1))*a_capex-a_wc*(((cf_arr*(1+F$66)^I65)*IF(I65>=a_churn_year,1-$B$69,1))-(cf_arr*(1+F$66)^H65*IF(H65>=a_churn_year,1-$B$69,1))) -> 101.85031 | J83: =(((cf_arr*(1+F$66)^J65)*IF(J65>=a_churn_year,1-$B$69,1))*(MIN(a_m0+a_mstep*J65,a_mcap)-a_da)-IF(J65=a_churn_year,a_sticky*((cf_arr*(1+F$66)^J65)-((cf_arr*(1+F$66)^J65)*IF(J65>=a_churn_year,1-$B$69,1)))*(1-MIN(a_m0+a_mstep*J65,a_mcap)),0))-MAX(0,(((cf_arr*(1+F$66)^J65)*IF(J65>=a_churn_year,1-$B$69,1))*(MIN(a_m0+a_mstep*J65,a_mcap)-a_da)-IF(J65=a_churn_year,a_sticky*((cf_arr*(1+F$66)^J65)-((cf_arr*(1+F$66)^J65)*IF(J65>=a_churn_year,1-$B$69,1)))*(1-MIN(a_m0+a_mstep*J65,a_mcap)),0)))*a_tax+((cf_arr*(1+F$66)^J65)*IF(J65>=a_churn_year,1-$B$69,1))*a_da-((cf_arr*(1+F$66)^J65)*IF(J65>=a_churn_year,1-$B$69,1))*a_capex-a_wc*(((cf_arr*(1+F$66)^J65)*IF(J65>=a_churn_year,1-$B$69,1))-(cf_arr*(1+F$66)^I65*IF(I65>=a_churn_year,1-$B$69,1))) -> 132.4054 | K83: =(((cf_arr*(1+F$66)^K65)*IF(K65>=a_churn_year,1-$B$69,1))*(MIN(a_m0+a_mstep*K65,a_mcap)-a_da)-IF(K65=a_churn_year,a_sticky*((cf_arr*(1+F$66)^K65)-((cf_arr*(1+F$66)^K65)*IF(K65>=a_churn_year,1-$B$69,1)))*(1-MIN(a_m0+a_mstep*K65,a_mcap)),0))-MAX(0,(((cf_arr*(1+F$66)^K65)*IF(K65>=a_churn_year,1-$B$69,1))*(MIN(a_m0+a_mstep*K65,a_mcap)-a_da)-IF(K65=a_churn_year,a_sticky*((cf_arr*(1+F$66)^K65)-((cf_arr*(1+F$66)^K65)*IF(K65>=a_churn_year,1-$B$69,1)))*(1-MIN(a_m0+a_mstep*K65,a_mcap)),0)))*a_tax+((cf_arr*(1+F$66)^K65)*IF(K65>=a_churn_year,1-$B$69,1))*a_da-((cf_arr*(1+F$66)^K65)*IF(K65>=a_churn_year,1-$B$69,1))*a_capex-a_wc*(((cf_arr*(1+F$66)^K65)*IF(K65>=a_churn_year,1-$B$69,1))-(cf_arr*(1+F$66)^J65*IF(J65>=a_churn_year,1-$B$69,1))) -> 172.12703 | L83: =(((cf_arr*(1+F$66)^L65)*IF(L65>=a_churn_year,1-$B$69,1))*(MIN(a_m0+a_mstep*L65,a_mcap)-a_da)-IF(L65=a_churn_year,a_sticky*((cf_arr*(1+F$66)^L65)-((cf_arr*(1+F$66)^L65)*IF(L65>=a_churn_year,1-$B$69,1)))*(1-MIN(a_m0+a_mstep*L65,a_mcap)),0))-MAX(0,(((cf_arr*(1+F$66)^L65)*IF(L65>=a_churn_year,1-$B$69,1))*(MIN(a_m0+a_mstep*L65,a_mcap)-a_da)-IF(L65=a_churn_year,a_sticky*((cf_arr*(1+F$66)^L65)-((cf_arr*(1+F$66)^L65)*IF(L65>=a_churn_year,1-$B$69,1)))*(1-MIN(a_m0+a_mstep*L65,a_mcap)),0)))*a_tax+((cf_arr*(1+F$66)^L65)*IF(L65>=a_churn_year,1-$B$69,1))*a_da-((cf_arr*(1+F$66)^L65)*IF(L65>=a_churn_year,1-$B$69,1))*a_capex-a_wc*(((cf_arr*(1+F$66)^L65)*IF(L65>=a_churn_year,1-$B$69,1))-(cf_arr*(1+F$66)^K65*IF(K65>=a_churn_year,1-$B$69,1))) -> 223.76513 | M83: =(((cf_arr*(1+F$66)^M65)*IF(M65>=a_churn_year,1-$B$69,1))*(MIN(a_m0+a_mstep*M65,a_mcap)-a_da)-IF(M65=a_churn_year,a_sticky*((cf_arr*(1+F$66)^M65)-((cf_arr*(1+F$66)^M65)*IF(M65>=a_churn_year,1-$B$69,1)))*(1-MIN(a_m0+a_mstep*M65,a_mcap)),0))-MAX(0,(((cf_arr*(1+F$66)^M65)*IF(M65>=a_churn_year,1-$B$69,1))*(MIN(a_m0+a_mstep*M65,a_mcap)-a_da)-IF(M65=a_churn_year,a_sticky*((cf_arr*(1+F$66)^M65)-((cf_arr*(1+F$66)^M65)*IF(M65>=a_churn_year,1-$B$69,1)))*(1-MIN(a_m0+a_mstep*M65,a_mcap)),0)))*a_tax+((cf_arr*(1+F$66)^M65)*IF(M65>=a_churn_year,1-$B$69,1))*a_da-((cf_arr*(1+F$66)^M65)*IF(M65>=a_churn_year,1-$B$69,1))*a_capex-a_wc*(((cf_arr*(1+F$66)^M65)*IF(M65>=a_churn_year,1-$B$69,1))-(cf_arr*(1+F$66)^L65*IF(L65>=a_churn_year,1-$B$69,1))) -> 290.89467
